Workbook

Sheet 目录
A1: 目录及链接 | D1: 各交易所交易规则链接
A2: 1 | B2: 目录 | D2: 中国金融期货交易所 | E2: http://www.cffex.com.cn/jysgz/
A3: 2 | B3: 交易时间表 | D3: 上海期货交易所 | E3: https://www.shfe.com.cn/regulation/
A4: 3 | B4: 期货合约要素 | D4: 上海国际能源交易中心 | E4: https://www.ine.cn/regulation/ineregulation/rules/
A5: 4 | B5: 期权合约要素 | D5: 大连商品交易所 | E5: http://www.dce.com.cn/dalianshangpin/fgfz/index.html
A6: 5 | B6: 保证金及涨跌停板幅度表 | D6: 郑州商品交易所 | E6: https://www.czce.com.cn/cn/flfg/H077005index_1.htm
A7: 6 | B7: 限仓规则 | D7: 广州期货交易所 | E7: http://www.gfex.com.cn/gfex/jysgz/lists_notime.shtml
A8: 7 | B8: 交易限额 | D8: 上海证券交易所 | E8: http://www.sse.com.cn/lawandrules/sselawsrules/option/
A9: 8 | B9: 单笔最小开仓手数 | D9: 深圳证券交易所 | E9: https://www.szse.cn/lawrules/rule/derivative/index.html
A10: 9 | B10: 异常交易规则
A11: 10 | B11: 保证金优惠规则
A12: 11 | B12: 指令规则
A13: 12 | B13: 期权行权规则
A14: 13 | B14: 申报费规则
A15: 14 | B15: 修订记录
A16: 免责说明：本文件为国泰君安期货有限公司根据目前交易所规则汇编，供您参考，如有相关规则变动，则以交易所最新发布为准。

Sheet 交易时间表
A1: 点此返回目录
B2: 期货及期权各品种交易时间表
B3: 交易所 | C3: 品种名称 | D3: 品种代码 | E3: 是否有期权 | F3: 交易时间 | J3: QFII&RQFII | K3: 国际化品种
F4: 夜盘集合竞价 | G4: 夜盘连续竞价 | H4: 日盘集合竞价 | I4: 日盘连续竞价
B5: 上期所 | C5: 线材 | D5: wr | F5: 无夜盘 | H5: 申报阶段8:55-8:59 撮合阶段8:59-9:00 | I5: 上午9:00-10:15 10:30-11:30 下午13:30-15:00 | J5: =IFERROR(IF(VLOOKUP(D5,期货合约要素!$D:$Q,12,0)=0,"",VLOOKUP(D5,期货合约要素!$D:$Q,12,0)),IF(VLOOKUP(D5,期权合约要素!$D:$V,17,0)=0,"",VLOOKUP(D5,期权合约要素!$D:$V,17,0))) | K5: =IFERROR(IF(VLOOKUP(D5,期货合约要素!$D:$Q,14,0)=0,"",VLOOKUP(D5,期货合约要素!$D:$Q,14,0)),IF(VLOOKUP(D5,期权合约要素!$D:$V,19,0)=0,"",VLOOKUP(D5,期权合约要素!$D:$V,19,0)))
C6: 螺纹钢 | D6: rb | E6: 是 | F6: 申报阶段20:55-20:59 撮合阶段20:59-21:00 | G6: 21：00-23：00 | H6: 二次集合竞价： 申报阶段8:55-8:59 撮合阶段8:59-9:00 备注：未成交的交易指令自动参与日盘集合竞价，投资者可以在日盘集合竞价申报阶段对夜盘交易时段未成交的指令进行撤单。 | J6: =IFERROR(IF(VLOOKUP(D6,期货合约要素!$D:$Q,12,0)=0,"",VLOOKUP(D6,期货合约要素!$D:$Q,12,0)),IF(VLOOKUP(D6,期权合约要素!$D:$V,17,0)=0,"",VLOOKUP(D6,期权合约要素!$D:$V,17,0))) -> √ | K6: =IFERROR(IF(VLOOKUP(D6,期货合约要素!$D:$Q,14,0)=0,"",VLOOKUP(D6,期货合约要素!$D:$Q,14,0)),IF(VLOOKUP(D6,期权合约要素!$D:$V,19,0)=0,"",VLOOKUP(D6,期权合约要素!$D:$V,19,0)))
C7: 热轧卷板 | D7: hc | J7: =IFERROR(IF(VLOOKUP(D7,期货合约要素!$D:$Q,12,0)=0,"",VLOOKUP(D7,期货合约要素!$D:$Q,12,0)),IF(VLOOKUP(D7,期权合约要素!$D:$V,17,0)=0,"",VLOOKUP(D7,期权合约要素!$D:$V,17,0))) -> √ | K7: =IFERROR(IF(VLOOKUP(D7,期货合约要素!$D:$Q,14,0)=0,"",VLOOKUP(D7,期货合约要素!$D:$Q,14,0)),IF(VLOOKUP(D7,期权合约要素!$D:$V,19,0)=0,"",VLOOKUP(D7,期权合约要素!$D:$V,19,0)))
C8: 燃料油 | D8: fu | E8: 是 | J8: =IFERROR(IF(VLOOKUP(D8,期货合约要素!$D:$Q,12,0)=0,"",VLOOKUP(D8,期货合约要素!$D:$Q,12,0)),IF(VLOOKUP(D8,期权合约要素!$D:$V,17,0)=0,"",VLOOKUP(D8,期权合约要素!$D:$V,17,0))) -> √ | K8: =IFERROR(IF(VLOOKUP(D8,期货合约要素!$D:$Q,14,0)=0,"",VLOOKUP(D8,期货合约要素!$D:$Q,14,0)),IF(VLOOKUP(D8,期权合约要素!$D:$V,19,0)=0,"",VLOOKUP(D8,期权合约要素!$D:$V,19,0)))
C9: 石油沥青 | D9: bu | E9: 是 | J9: =IFERROR(IF(VLOOKUP(D9,期货合约要素!$D:$Q,12,0)=0,"",VLOOKUP(D9,期货合约要素!$D:$Q,12,0)),IF(VLOOKUP(D9,期权合约要素!$D:$V,17,0)=0,"",VLOOKUP(D9,期权合约要素!$D:$V,17,0))) -> √ | K9: =IFERROR(IF(VLOOKUP(D9,期货合约要素!$D:$Q,14,0)=0,"",VLOOKUP(D9,期货合约要素!$D:$Q,14,0)),IF(VLOOKUP(D9,期权合约要素!$D:$V,19,0)=0,"",VLOOKUP(D9,期权合约要素!$D:$V,19,0)))
C10: 天然橡胶 | D10: ru | E10: 是 | J10: =IFERROR(IF(VLOOKUP(D10,期货合约要素!$D:$Q,12,0)=0,"",VLOOKUP(D10,期货合约要素!$D:$Q,12,0)),IF(VLOOKUP(D10,期权合约要素!$D:$V,17,0)=0,"",VLOOKUP(D10,期权合约要素!$D:$V,17,0))) -> √ | K10: =IFERROR(IF(VLOOKUP(D10,期货合约要素!$D:$Q,14,0)=0,"",VLOOKUP(D10,期货合约要素!$D:$Q,14,0)),IF(VLOOKUP(D10,期权合约要素!$D:$V,19,0)=0,"",VLOOKUP(D10,期权合约要素!$D:$V,19,0)))
C11: 丁二烯橡胶 | D11: br | E11: 是 | J11: =IFERROR(IF(VLOOKUP(D11,期货合约要素!$D:$Q,12,0)=0,"",VLOOKUP(D11,期货合约要素!$D:$Q,12,0)),IF(VLOOKUP(D11,期权合约要素!$D:$V,17,0)=0,"",VLOOKUP(D11,期权合约要素!$D:$V,17,0))) | K11: =IFERROR(IF(VLOOKUP(D11,期货合约要素!$D:$Q,14,0)=0,"",VLOOKUP(D11,期货合约要素!$D:$Q,14,0)),IF(VLOOKUP(D11,期权合约要素!$D:$V,19,0)=0,"",VLOOKUP(D11,期权合约要素!$D:$V,19,0)))
C12: 漂针浆 | D12: sp | E12: 是 | J12: =IFERROR(IF(VLOOKUP(D12,期货合约要素!$D:$Q,12,0)=0,"",VLOOKUP(D12,期货合约要素!$D:$Q,12,0)),IF(VLOOKUP(D12,期权合约要素!$D:$V,17,0)=0,"",VLOOKUP(D12,期权合约要素!$D:$V,17,0))) -> √ | K12: =IFERROR(IF(VLOOKUP(D12,期货合约要素!$D:$Q,14,0)=0,"",VLOOKUP(D12,期货合约要素!$D:$Q,14,0)),IF(VLOOKUP(D12,期权合约要素!$D:$V,19,0)=0,"",VLOOKUP(D12,期权合约要素!$D:$V,19,0)))
C13: 胶版印刷纸 | D13: op | E13: 是 | J13: =IFERROR(IF(VLOOKUP(D13,期货合约要素!$D:$Q,12,0)=0,"",VLOOKUP(D13,期货合约要素!$D:$Q,12,0)),IF(VLOOKUP(D13,期权合约要素!$D:$V,17,0)=0,"",VLOOKUP(D13,期权合约要素!$D:$V,17,0))) | K13: =IFERROR(IF(VLOOKUP(D13,期货合约要素!$D:$Q,14,0)=0,"",VLOOKUP(D13,期货合约要素!$D:$Q,14,0)),IF(VLOOKUP(D13,期权合约要素!$D:$V,19,0)=0,"",VLOOKUP(D13,期权合约要素!$D:$V,19,0)))
C14: 铝 | D14: al | E14: 是 | F14: 申报阶段20:55-20:59 撮合阶段20:59-21:00 | G14: 21：00-次日01：00 | J14: =IFERROR(IF(VLOOKUP(D14,期货合约要素!$D:$Q,12,0)=0,"",VLOOKUP(D14,期货合约要素!$D:$Q,12,0)),IF(VLOOKUP(D14,期权合约要素!$D:$V,17,0)=0,"",VLOOKUP(D14,期权合约要素!$D:$V,17,0))) -> √ | K14: =IFERROR(IF(VLOOKUP(D14,期货合约要素!$D:$Q,14,0)=0,"",VLOOKUP(D14,期货合约要素!$D:$Q,14,0)),IF(VLOOKUP(D14,期权合约要素!$D:$V,19,0)=0,"",VLOOKUP(D14,期权合约要素!$D:$V,19,0)))
C15: 铜 | D15: cu | E15: 是 | J15: =IFERROR(IF(VLOOKUP(D15,期货合约要素!$D:$Q,12,0)=0,"",VLOOKUP(D15,期货合约要素!$D:$Q,12,0)),IF(VLOOKUP(D15,期权合约要素!$D:$V,17,0)=0,"",VLOOKUP(D15,期权合约要素!$D:$V,17,0))) -> √ | K15: =IFERROR(IF(VLOOKUP(D15,期货合约要素!$D:$Q,14,0)=0,"",VLOOKUP(D15,期货合约要素!$D:$Q,14,0)),IF(VLOOKUP(D15,期权合约要素!$D:$V,19,0)=0,"",VLOOKUP(D15,期权合约要素!$D:$V,19,0)))
C16: 不锈钢 | D16: ss | J16: =IFERROR(IF(VLOOKUP(D16,期货合约要素!$D:$Q,12,0)=0,"",VLOOKUP(D16,期货合约要素!$D:$Q,12,0)),IF(VLOOKUP(D16,期权合约要素!$D:$V,17,0)=0,"",VLOOKUP(D16,期权合约要素!$D:$V,17,0))) -> √ | K16: =IFERROR(IF(VLOOKUP(D16,期货合约要素!$D:$Q,14,0)=0,"",VLOOKUP(D16,期货合约要素!$D:$Q,14,0)),IF(VLOOKUP(D16,期权合约要素!$D:$V,19,0)=0,"",VLOOKUP(D16,期权合约要素!$D:$V,19,0)))
C17: 锌 | D17: zn | E17: 是 | J17: =IFERROR(IF(VLOOKUP(D17,期货合约要素!$D:$Q,12,0)=0,"",VLOOKUP(D17,期货合约要素!$D:$Q,12,0)),IF(VLOOKUP(D17,期权合约要素!$D:$V,17,0)=0,"",VLOOKUP(D17,期权合约要素!$D:$V,17,0))) -> √ | K17: =IFERROR(IF(VLOOKUP(D17,期货合约要素!$D:$Q,14,0)=0,"",VLOOKUP(D17,期货合约要素!$D:$Q,14,0)),IF(VLOOKUP(D17,期权合约要素!$D:$V,19,0)=0,"",VLOOKUP(D17,期权合约要素!$D:$V,19,0)))
C18: 铅 | D18: pb | E18: 是 | J18: =IFERROR(IF(VLOOKUP(D18,期货合约要素!$D:$Q,12,0)=0,"",VLOOKUP(D18,期货合约要素!$D:$Q,12,0)),IF(VLOOKUP(D18,期权合约要素!$D:$V,17,0)=0,"",VLOOKUP(D18,期权合约要素!$D:$V,17,0))) -> √ | K18: =IFERROR(IF(VLOOKUP(D18,期货合约要素!$D:$Q,14,0)=0,"",VLOOKUP(D18,期货合约要素!$D:$Q,14,0)),IF(VLOOKUP(D18,期权合约要素!$D:$V,19,0)=0,"",VLOOKUP(D18,期权合约要素!$D:$V,19,0)))
C19: 镍 | D19: ni | E19: 是 | J19: =IFERROR(IF(VLOOKUP(D19,期货合约要素!$D:$Q,12,0)=0,"",VLOOKUP(D19,期货合约要素!$D:$Q,12,0)),IF(VLOOKUP(D19,期权合约要素!$D:$V,17,0)=0,"",VLOOKUP(D19,期权合约要素!$D:$V,17,0))) -> √ | K19: =IFERROR(IF(VLOOKUP(D19,期货合约要素!$D:$Q,14,0)=0,"",VLOOKUP(D19,期货合约要素!$D:$Q,14,0)),IF(VLOOKUP(D19,期权合约要素!$D:$V,19,0)=0,"",VLOOKUP(D19,期权合约要素!$D:$V,19,0))) -> √
C20: 锡 | D20: sn | E20: 是 | J20: =IFERROR(IF(VLOOKUP(D20,期货合约要素!$D:$Q,12,0)=0,"",VLOOKUP(D20,期货合约要素!$D:$Q,12,0)),IF(VLOOKUP(D20,期权合约要素!$D:$V,17,0)=0,"",VLOOKUP(D20,期权合约要素!$D:$V,17,0))) -> √ | K20: =IFERROR(IF(VLOOKUP(D20,期货合约要素!$D:$Q,14,0)=0,"",VLOOKUP(D20,期货合约要素!$D:$Q,14,0)),IF(VLOOKUP(D20,期权合约要素!$D:$V,19,0)=0,"",VLOOKUP(D20,期权合约要素!$D:$V,19,0)))
C21: 氧化铝 | D21: ao | E21: 是 | J21: =IFERROR(IF(VLOOKUP(D21,期货合约要素!$D:$Q,12,0)=0,"",VLOOKUP(D21,期货合约要素!$D:$Q,12,0)),IF(VLOOKUP(D21,期权合约要素!$D:$V,17,0)=0,"",VLOOKUP(D21,期权合约要素!$D:$V,17,0))) | K21: =IFERROR(IF(VLOOKUP(D21,期货合约要素!$D:$Q,14,0)=0,"",VLOOKUP(D21,期货合约要素!$D:$Q,14,0)),IF(VLOOKUP(D21,期权合约要素!$D:$V,19,0)=0,"",VLOOKUP(D21,期权合约要素!$D:$V,19,0)))
C22: 铸造铝合金 | D22: ad | E22: 是 | J22: =IFERROR(IF(VLOOKUP(D22,期货合约要素!$D:$Q,12,0)=0,"",VLOOKUP(D22,期货合约要素!$D:$Q,12,0)),IF(VLOOKUP(D22,期权合约要素!$D:$V,17,0)=0,"",VLOOKUP(D22,期权合约要素!$D:$V,17,0))) | K22: =IFERROR(IF(VLOOKUP(D22,期货合约要素!$D:$Q,14,0)=0,"",VLOOKUP(D22,期货合约要素!$D:$Q,14,0)),IF(VLOOKUP(D22,期权合约要素!$D:$V,19,0)=0,"",VLOOKUP(D22,期权合约要素!$D:$V,19,0)))
C23: 黄金 | D23: au | E23: 是 | F23: 申报阶段20:55-20:59 撮合阶段20:59-21:00 | G23: 21：00-次日02：30 | J23: =IFERROR(IF(VLOOKUP(D23,期货合约要素!$D:$Q,12,0)=0,"",VLOOKUP(D23,期货合约要素!$D:$Q,12,0)),IF(VLOOKUP(D23,期权合约要素!$D:$V,17,0)=0,"",VLOOKUP(D23,期权合约要素!$D:$V,17,0))) -> √ | K23: =IFERROR(IF(VLOOKUP(D23,期货合约要素!$D:$Q,14,0)=0,"",VLOOKUP(D23,期货合约要素!$D:$Q,14,0)),IF(VLOOKUP(D23,期权合约要素!$D:$V,19,0)=0,"",VLOOKUP(D23,期权合约要素!$D:$V,19,0)))
C24: 白银 | D24: ag | E24: 是 | J24: =IFERROR(IF(VLOOKUP(D24,期货合约要素!$D:$Q,12,0)=0,"",VLOOKUP(D24,期货合约要素!$D:$Q,12,0)),IF(VLOOKUP(D24,期权合约要素!$D:$V,17,0)=0,"",VLOOKUP(D24,期权合约要素!$D:$V,17,0))) -> √ | K24: =IFERROR(IF(VLOOKUP(D24,期货合约要素!$D:$Q,14,0)=0,"",VLOOKUP(D24,期货合约要素!$D:$Q,14,0)),IF(VLOOKUP(D24,期权合约要素!$D:$V,19,0)=0,"",VLOOKUP(D24,期权合约要素!$D:$V,19,0)))
B25: 能源中心 | C25: 原油 | D25: sc | E25: 是 | J25: =IFERROR(IF(VLOOKUP(D25,期货合约要素!$D:$Q,12,0)=0,"",VLOOKUP(D25,期货合约要素!$D:$Q,12,0)),IF(VLOOKUP(D25,期权合约要素!$D:$V,17,0)=0,"",VLOOKUP(D25,期权合约要素!$D:$V,17,0))) -> √ | K25: =IFERROR(IF(VLOOKUP(D25,期货合约要素!$D:$Q,14,0)=0,"",VLOOKUP(D25,期货合约要素!$D:$Q,14,0)),IF(VLOOKUP(D25,期权合约要素!$D:$V,19,0)=0,"",VLOOKUP(D25,期权合约要素!$D:$V,19,0))) -> √
C26: 低硫燃料油 | D26: lu | F26: 申报阶段20:55-20:59 撮合阶段20:59-21:00 | G26: 21：00-23：00 | J26: =IFERROR(IF(VLOOKUP(D26,期货合约要素!$D:$Q,12,0)=0,"",VLOOKUP(D26,期货合约要素!$D:$Q,12,0)),IF(VLOOKUP(D26,期权合约要素!$D:$V,17,0)=0,"",VLOOKUP(D26,期权合约要素!$D:$V,17,0))) -> √ | K26: =IFERROR(IF(VLOOKUP(D26,期货合约要素!$D:$Q,14,0)=0,"",VLOOKUP(D26,期货合约要素!$D:$Q,14,0)),IF(VLOOKUP(D26,期权合约要素!$D:$V,19,0)=0,"",VLOOKUP(D26,期权合约要素!$D:$V,19,0))) -> √
C27: 20号胶 | D27: nr | E27: 是 | J27: =IFERROR(IF(VLOOKUP(D27,期货合约要素!$D:$Q,12,0)=0,"",VLOOKUP(D27,期货合约要素!$D:$Q,12,0)),IF(VLOOKUP(D27,期权合约要素!$D:$V,17,0)=0,"",VLOOKUP(D27,期权合约要素!$D:$V,17,0))) -> √ | K27: =IFERROR(IF(VLOOKUP(D27,期货合约要素!$D:$Q,14,0)=0,"",VLOOKUP(D27,期货合约要素!$D:$Q,14,0)),IF(VLOOKUP(D27,期权合约要素!$D:$V,19,0)=0,"",VLOOKUP(D27,期权合约要素!$D:$V,19,0))) -> √
C28: 国际铜 | D28: bc | E28: 是 | F28: 申报阶段20:55-20:59 撮合阶段20:59-21:00 | G28: 21：00-次日01：00 | J28: =IFERROR(IF(VLOOKUP(D28,期货合约要素!$D:$Q,12,0)=0,"",VLOOKUP(D28,期货合约要素!$D:$Q,12,0)),IF(VLOOKUP(D28,期权合约要素!$D:$V,17,0)=0,"",VLOOKUP(D28,期权合约要素!$D:$V,17,0))) -> √ | K28: =IFERROR(IF(VLOOKUP(D28,期货合约要素!$D:$Q,14,0)=0,"",VLOOKUP(D28,期货合约要素!$D:$Q,14,0)),IF(VLOOKUP(D28,期权合约要素!$D:$V,19,0)=0,"",VLOOKUP(D28,期权合约要素!$D:$V,19,0))) -> √
C29: 集运指数（欧线） | D29: ec | F29: 无夜盘 | H29: 申报阶段8:55-8:59 撮合阶段8:59-9:00 | J29: =IFERROR(IF(VLOOKUP(D29,期货合约要素!$D:$Q,12,0)=0,"",VLOOKUP(D29,期货合约要素!$D:$Q,12,0)),IF(VLOOKUP(D29,期权合约要素!$D:$V,17,0)=0,"",VLOOKUP(D29,期权合约要素!$D:$V,17,0))) -> √ | K29: =IFERROR(IF(VLOOKUP(D29,期货合约要素!$D:$Q,14,0)=0,"",VLOOKUP(D29,期货合约要素!$D:$Q,14,0)),IF(VLOOKUP(D29,期权合约要素!$D:$V,19,0)=0,"",VLOOKUP(D29,期权合约要素!$D:$V,19,0))) -> √
B30: 大商所 | C30: 黄大豆1号 | D30: a | E30: 是 | F30: 申报阶段20:55-20:59 撮合阶段20:59-21:00 | G30: 21：00-23：00 | H30: 二次集合竞价： 申报阶段8:55-8:59 撮合阶段8:59-9:00 备注：未成交的交易指令自动参与日盘集合竞价，投资者可以在日盘集合竞价申报阶段对夜盘交易时段未成交的指令进行撤单。未触发的止损（盈）指令和套利交易指令不参与集合竞价撮合。 | I30: 上午9:00-10:15 10:30-11:30 下午13:30-15:00 | J30: =IFERROR(IF(VLOOKUP(D30,期货合约要素!$D:$Q,12,0)=0,"",VLOOKUP(D30,期货合约要素!$D:$Q,12,0)),IF(VLOOKUP(D30,期权合约要素!$D:$V,17,0)=0,"",VLOOKUP(D30,期权合约要素!$D:$V,17,0))) -> √ | K30: =IFERROR(IF(VLOOKUP(D30,期货合约要素!$D:$Q,14,0)=0,"",VLOOKUP(D30,期货合约要素!$D:$Q,14,0)),IF(VLOOKUP(D30,期权合约要素!$D:$V,19,0)=0,"",VLOOKUP(D30,期权合约要素!$D:$V,19,0))) -> √
C31: 黄大豆2号 | D31: b | E31: 是 | J31: =IFERROR(IF(VLOOKUP(D31,期货合约要素!$D:$Q,12,0)=0,"",VLOOKUP(D31,期货合约要素!$D:$Q,12,0)),IF(VLOOKUP(D31,期权合约要素!$D:$V,17,0)=0,"",VLOOKUP(D31,期权合约要素!$D:$V,17,0))) -> √ | K31: =IFERROR(IF(VLOOKUP(D31,期货合约要素!$D:$Q,14,0)=0,"",VLOOKUP(D31,期货合约要素!$D:$Q,14,0)),IF(VLOOKUP(D31,期权合约要素!$D:$V,19,0)=0,"",VLOOKUP(D31,期权合约要素!$D:$V,19,0))) -> √
C32: 豆粕 | D32: m | E32: 是 | J32: =IFERROR(IF(VLOOKUP(D32,期货合约要素!$D:$Q,12,0)=0,"",VLOOKUP(D32,期货合约要素!$D:$Q,12,0)),IF(VLOOKUP(D32,期权合约要素!$D:$V,17,0)=0,"",VLOOKUP(D32,期权合约要素!$D:$V,17,0))) -> √ | K32: =IFERROR(IF(VLOOKUP(D32,期货合约要素!$D:$Q,14,0)=0,"",VLOOKUP(D32,期货合约要素!$D:$Q,14,0)),IF(VLOOKUP(D32,期权合约要素!$D:$V,19,0)=0,"",VLOOKUP(D32,期权合约要素!$D:$V,19,0))) -> √
C33: 豆油 | D33: y | E33: 是 | J33: =IFERROR(IF(VLOOKUP(D33,期货合约要素!$D:$Q,12,0)=0,"",VLOOKUP(D33,期货合约要素!$D:$Q,12,0)),IF(VLOOKUP(D33,期权合约要素!$D:$V,17,0)=0,"",VLOOKUP(D33,期权合约要素!$D:$V,17,0))) -> √ | K33: =IFERROR(IF(VLOOKUP(D33,期货合约要素!$D:$Q,14,0)=0,"",VLOOKUP(D33,期货合约要素!$D:$Q,14,0)),IF(VLOOKUP(D33,期权合约要素!$D:$V,19,0)=0,"",VLOOKUP(D33,期权合约要素!$D:$V,19,0))) -> √
C34: 棕榈油 | D34: p | E34: 是 | J34: =IFERROR(IF(VLOOKUP(D34,期货合约要素!$D:$Q,12,0)=0,"",VLOOKUP(D34,期货合约要素!$D:$Q,12,0)),IF(VLOOKUP(D34,期权合约要素!$D:$V,17,0)=0,"",VLOOKUP(D34,期权合约要素!$D:$V,17,0))) -> √ | K34: =IFERROR(IF(VLOOKUP(D34,期货合约要素!$D:$Q,14,0)=0,"",VLOOKUP(D34,期货合约要素!$D:$Q,14,0)),IF(VLOOKUP(D34,期权合约要素!$D:$V,19,0)=0,"",VLOOKUP(D34,期权合约要素!$D:$V,19,0))) -> √
C35: 玉米 | D35: c | E35: 是 | J35: =IFERROR(IF(VLOOKUP(D35,期货合约要素!$D:$Q,12,0)=0,"",VLOOKUP(D35,期货合约要素!$D:$Q,12,0)),IF(VLOOKUP(D35,期权合约要素!$D:$V,17,0)=0,"",VLOOKUP(D35,期权合约要素!$D:$V,17,0))) | K35: =IFERROR(IF(VLOOKUP(D35,期货合约要素!$D:$Q,14,0)=0,"",VLOOKUP(D35,期货合约要素!$D:$Q,14,0)),IF(VLOOKUP(D35,期权合约要素!$D:$V,19,0)=0,"",VLOOKUP(D35,期权合约要素!$D:$V,19,0)))
C36: 玉米淀粉 | D36: cs | E36: 是 | J36: =IFERROR(IF(VLOOKUP(D36,期货合约要素!$D:$Q,12,0)=0,"",VLOOKUP(D36,期货合约要素!$D:$Q,12,0)),IF(VLOOKUP(D36,期权合约要素!$D:$V,17,0)=0,"",VLOOKUP(D36,期权合约要素!$D:$V,17,0))) | K36: =IFERROR(IF(VLOOKUP(D36,期货合约要素!$D:$Q,14,0)=0,"",VLOOKUP(D36,期货合约要素!$D:$Q,14,0)),IF(VLOOKUP(D36,期权合约要素!$D:$V,19,0)=0,"",VLOOKUP(D36,期权合约要素!$D:$V,19,0)))
C37: 聚氯乙烯 | D37: v | E37: 是 | J37: =IFERROR(IF(VLOOKUP(D37,期货合约要素!$D:$Q,12,0)=0,"",VLOOKUP(D37,期货合约要素!$D:$Q,12,0)),IF(VLOOKUP(D37,期权合约要素!$D:$V,17,0)=0,"",VLOOKUP(D37,期权合约要素!$D:$V,17,0))) -> √ | K37: =IFERROR(IF(VLOOKUP(D37,期货合约要素!$D:$Q,14,0)=0,"",VLOOKUP(D37,期货合约要素!$D:$Q,14,0)),IF(VLOOKUP(D37,期权合约要素!$D:$V,19,0)=0,"",VLOOKUP(D37,期权合约要素!$D:$V,19,0)))
C38: 聚氯乙烯月均价 | D38: v_f | J38: =IFERROR(IF(VLOOKUP(D38,期货合约要素!$D:$Q,12,0)=0,"",VLOOKUP(D38,期货合约要素!$D:$Q,12,0)),IF(VLOOKUP(D38,期权合约要素!$D:$V,17,0)=0,"",VLOOKUP(D38,期权合约要素!$D:$V,17,0))) -> √ | K38: =IFERROR(IF(VLOOKUP(D38,期货合约要素!$D:$Q,14,0)=0,"",VLOOKUP(D38,期货合约要素!$D:$Q,14,0)),IF(VLOOKUP(D38,期权合约要素!$D:$V,19,0)=0,"",VLOOKUP(D38,期权合约要素!$D:$V,19,0)))
C39: 聚丙烯 | D39: pp | E39: 是 | J39: =IFERROR(IF(VLOOKUP(D39,期货合约要素!$D:$Q,12,0)=0,"",VLOOKUP(D39,期货合约要素!$D:$Q,12,0)),IF(VLOOKUP(D39,期权合约要素!$D:$V,17,0)=0,"",VLOOKUP(D39,期权合约要素!$D:$V,17,0))) -> √ | K39: =IFERROR(IF(VLOOKUP(D39,期货合约要素!$D:$Q,14,0)=0,"",VLOOKUP(D39,期货合约要素!$D:$Q,14,0)),IF(VLOOKUP(D39,期权合约要素!$D:$V,19,0)=0,"",VLOOKUP(D39,期权合约要素!$D:$V,19,0)))
C40: 聚丙烯月均价 | D40: pp_f | J40: =IFERROR(IF(VLOOKUP(D40,期货合约要素!$D:$Q,12,0)=0,"",VLOOKUP(D40,期货合约要素!$D:$Q,12,0)),IF(VLOOKUP(D40,期权合约要素!$D:$V,17,0)=0,"",VLOOKUP(D40,期权合约要素!$D:$V,17,0))) -> √ | K40: =IFERROR(IF(VLOOKUP(D40,期货合约要素!$D:$Q,14,0)=0,"",VLOOKUP(D40,期货合约要素!$D:$Q,14,0)),IF(VLOOKUP(D40,期权合约要素!$D:$V,19,0)=0,"",VLOOKUP(D40,期权合约要素!$D:$V,19,0)))
C41: 聚乙烯 | D41: l | E41: 是 | J41: =IFERROR(IF(VLOOKUP(D41,期货合约要素!$D:$Q,12,0)=0,"",VLOOKUP(D41,期货合约要素!$D:$Q,12,0)),IF(VLOOKUP(D41,期权合约要素!$D:$V,17,0)=0,"",VLOOKUP(D41,期权合约要素!$D:$V,17,0))) -> √ | K41: =IFERROR(IF(VLOOKUP(D41,期货合约要素!$D:$Q,14,0)=0,"",VLOOKUP(D41,期货合约要素!$D:$Q,14,0)),IF(VLOOKUP(D41,期权合约要素!$D:$V,19,0)=0,"",VLOOKUP(D41,期权合约要素!$D:$V,19,0)))
C42: 聚乙烯月均价 | D42: l_f | J42: =IFERROR(IF(VLOOKUP(D42,期货合约要素!$D:$Q,12,0)=0,"",VLOOKUP(D42,期货合约要素!$D:$Q,12,0)),IF(VLOOKUP(D42,期权合约要素!$D:$V,17,0)=0,"",VLOOKUP(D42,期权合约要素!$D:$V,17,0))) -> √ | K42: =IFERROR(IF(VLOOKUP(D42,期货合约要素!$D:$Q,14,0)=0,"",VLOOKUP(D42,期货合约要素!$D:$Q,14,0)),IF(VLOOKUP(D42,期权合约要素!$D:$V,19,0)=0,"",VLOOKUP(D42,期权合约要素!$D:$V,19,0)))
C43: 液化石油气 | D43: pg | E43: 是 | J43: =IFERROR(IF(VLOOKUP(D43,期货合约要素!$D:$Q,12,0)=0,"",VLOOKUP(D43,期货合约要素!$D:$Q,12,0)),IF(VLOOKUP(D43,期权合约要素!$D:$V,17,0)=0,"",VLOOKUP(D43,期权合约要素!$D:$V,17,0))) -> √ | K43: =IFERROR(IF(VLOOKUP(D43,期货合约要素!$D:$Q,14,0)=0,"",VLOOKUP(D43,期货合约要素!$D:$Q,14,0)),IF(VLOOKUP(D43,期权合约要素!$D:$V,19,0)=0,"",VLOOKUP(D43,期权合约要素!$D:$V,19,0)))
C44: 乙二醇 | D44: eg | E44: 是 | J44: =IFERROR(IF(VLOOKUP(D44,期货合约要素!$D:$Q,12,0)=0,"",VLOOKUP(D44,期货合约要素!$D:$Q,12,0)),IF(VLOOKUP(D44,期权合约要素!$D:$V,17,0)=0,"",VLOOKUP(D44,期权合约要素!$D:$V,17,0))) -> √ | K44: =IFERROR(IF(VLOOKUP(D44,期货合约要素!$D:$Q,14,0)=0,"",VLOOKUP(D44,期货合约要素!$D:$Q,14,0)),IF(VLOOKUP(D44,期权合约要素!$D:$V,19,0)=0,"",VLOOKUP(D44,期权合约要素!$D:$V,19,0)))
C45: 焦炭 | D45: j | J45: =IFERROR(IF(VLOOKUP(D45,期货合约要素!$D:$Q,12,0)=0,"",VLOOKUP(D45,期货合约要素!$D:$Q,12,0)),IF(VLOOKUP(D45,期权合约要素!$D:$V,17,0)=0,"",VLOOKUP(D45,期权合约要素!$D:$V,17,0))) | K45: =IFERROR(IF(VLOOKUP(D45,期货合约要素!$D:$Q,14,0)=0,"",VLOOKUP(D45,期货合约要素!$D:$Q,14,0)),IF(VLOOKUP(D45,期权合约要素!$D:$V,19,0)=0,"",VLOOKUP(D45,期权合约要素!$D:$V,19,0)))
C46: 焦煤 | D46: jm | E46: 是 | J46: =IFERROR(IF(VLOOKUP(D46,期货合约要素!$D:$Q,12,0)=0,"",VLOOKUP(D46,期货合约要素!$D:$Q,12,0)),IF(VLOOKUP(D46,期权合约要素!$D:$V,17,0)=0,"",VLOOKUP(D46,期权合约要素!$D:$V,17,0))) | K46: =IFERROR(IF(VLOOKUP(D46,期货合约要素!$D:$Q,14,0)=0,"",VLOOKUP(D46,期货合约要素!$D:$Q,14,0)),IF(VLOOKUP(D46,期权合约要素!$D:$V,19,0)=0,"",VLOOKUP(D46,期权合约要素!$D:$V,19,0)))
C47: 粳米 | D47: rr | J47: =IFERROR(IF(VLOOKUP(D47,期货合约要素!$D:$Q,12,0)=0,"",VLOOKUP(D47,期货合约要素!$D:$Q,12,0)),IF(VLOOKUP(D47,期权合约要素!$D:$V,17,0)=0,"",VLOOKUP(D47,期权合约要素!$D:$V,17,0))) | K47: =IFERROR(IF(VLOOKUP(D47,期货合约要素!$D:$Q,14,0)=0,"",VLOOKUP(D47,期货合约要素!$D:$Q,14,0)),IF(VLOOKUP(D47,期权合约要素!$D:$V,19,0)=0,"",VLOOKUP(D47,期权合约要素!$D:$V,19,0)))
C48: 苯乙烯 | D48: eb | E48: 是 | J48: =IFERROR(IF(VLOOKUP(D48,期货合约要素!$D:$Q,12,0)=0,"",VLOOKUP(D48,期货合约要素!$D:$Q,12,0)),IF(VLOOKUP(D48,期权合约要素!$D:$V,17,0)=0,"",VLOOKUP(D48,期权合约要素!$D:$V,17,0))) -> √ | K48: =IFERROR(IF(VLOOKUP(D48,期货合约要素!$D:$Q,14,0)=0,"",VLOOKUP(D48,期货合约要素!$D:$Q,14,0)),IF(VLOOKUP(D48,期权合约要素!$D:$V,19,0)=0,"",VLOOKUP(D48,期权合约要素!$D:$V,19,0)))
C49: 铁矿石 | D49: i | E49: 是 | J49: =IFERROR(IF(VLOOKUP(D49,期货合约要素!$D:$Q,12,0)=0,"",VLOOKUP(D49,期货合约要素!$D:$Q,12,0)),IF(VLOOKUP(D49,期权合约要素!$D:$V,17,0)=0,"",VLOOKUP(D49,期权合约要素!$D:$V,17,0))) -> √ | K49: =IFERROR(IF(VLOOKUP(D49,期货合约要素!$D:$Q,14,0)=0,"",VLOOKUP(D49,期货合约要素!$D:$Q,14,0)),IF(VLOOKUP(D49,期权合约要素!$D:$V,19,0)=0,"",VLOOKUP(D49,期权合约要素!$D:$V,19,0))) -> √
C50: 纯苯 | D50: bz | E50: 是 | J50: =IFERROR(IF(VLOOKUP(D50,期货合约要素!$D:$Q,12,0)=0,"",VLOOKUP(D50,期货合约要素!$D:$Q,12,0)),IF(VLOOKUP(D50,期权合约要素!$D:$V,17,0)=0,"",VLOOKUP(D50,期权合约要素!$D:$V,17,0))) | K50: =IFERROR(IF(VLOOKUP(D50,期货合约要素!$D:$Q,14,0)=0,"",VLOOKUP(D50,期货合约要素!$D:$Q,14,0)),IF(VLOOKUP(D50,期权合约要素!$D:$V,19,0)=0,"",VLOOKUP(D50,期权合约要素!$D:$V,19,0)))
C51: 鸡蛋 | D51: jd | E51: 是 | F51: 无夜盘 | H51: 申报阶段8:55-8:59 撮合阶段8:59-9:00 | J51: =IFERROR(IF(VLOOKUP(D51,期货合约要素!$D:$Q,12,0)=0,"",VLOOKUP(D51,期货合约要素!$D:$Q,12,0)),IF(VLOOKUP(D51,期权合约要素!$D:$V,17,0)=0,"",VLOOKUP(D51,期权合约要素!$D:$V,17,0))) | K51: =IFERROR(IF(VLOOKUP(D51,期货合约要素!$D:$Q,14,0)=0,"",VLOOKUP(D51,期货合约要素!$D:$Q,14,0)),IF(VLOOKUP(D51,期权合约要素!$D:$V,19,0)=0,"",VLOOKUP(D51,期权合约要素!$D:$V,19,0)))
C52: 生猪 | D52: lh | E52: 是 | J52: =IFERROR(IF(VLOOKUP(D52,期货合约要素!$D:$Q,12,0)=0,"",VLOOKUP(D52,期货合约要素!$D:$Q,12,0)),IF(VLOOKUP(D52,期权合约要素!$D:$V,17,0)=0,"",VLOOKUP(D52,期权合约要素!$D:$V,17,0))) | K52: =IFERROR(IF(VLOOKUP(D52,期货合约要素!$D:$Q,14,0)=0,"",VLOOKUP(D52,期货合约要素!$D:$Q,14,0)),IF(VLOOKUP(D52,期权合约要素!$D:$V,19,0)=0,"",VLOOKUP(D52,期权合约要素!$D:$V,19,0)))
C53: 胶合板 | D53: bb | J53: =IFERROR(IF(VLOOKUP(D53,期货合约要素!$D:$Q,12,0)=0,"",VLOOKUP(D53,期货合约要素!$D:$Q,12,0)),IF(VLOOKUP(D53,期权合约要素!$D:$V,17,0)=0,"",VLOOKUP(D53,期权合约要素!$D:$V,17,0))) | K53: =IFERROR(IF(VLOOKUP(D53,期货合约要素!$D:$Q,14,0)=0,"",VLOOKUP(D53,期货合约要素!$D:$Q,14,0)),IF(VLOOKUP(D53,期权合约要素!$D:$V,19,0)=0,"",VLOOKUP(D53,期权合约要素!$D:$V,19,0)))
C54: 纤维板 | D54: fb | J54: =IFERROR(IF(VLOOKUP(D54,期货合约要素!$D:$Q,12,0)=0,"",VLOOKUP(D54,期货合约要素!$D:$Q,12,0)),IF(VLOOKUP(D54,期权合约要素!$D:$V,17,0)=0,"",VLOOKUP(D54,期权合约要素!$D:$V,17,0))) | K54: =IFERROR(IF(VLOOKUP(D54,期货合约要素!$D:$Q,14,0)=0,"",VLOOKUP(D54,期货合约要素!$D:$Q,14,0)),IF(VLOOKUP(D54,期权合约要素!$D:$V,19,0)=0,"",VLOOKUP(D54,期权合约要素!$D:$V,19,0)))
C55: 原木 | D55: lg | E55: 是 | J55: =IFERROR(IF(VLOOKUP(D55,期货合约要素!$D:$Q,12,0)=0,"",VLOOKUP(D55,期货合约要素!$D:$Q,12,0)),IF(VLOOKUP(D55,期权合约要素!$D:$V,17,0)=0,"",VLOOKUP(D55,期权合约要素!$D:$V,17,0))) | K55: =IFERROR(IF(VLOOKUP(D55,期货合约要素!$D:$Q,14,0)=0,"",VLOOKUP(D55,期货合约要素!$D:$Q,14,0)),IF(VLOOKUP(D55,期权合约要素!$D:$V,19,0)=0,"",VLOOKUP(D55,期权合约要素!$D:$V,19,0)))
B56: 郑商所 | C56: 棉花 | D56: CF | E56: 是 | F56: 申报阶段20:55-20:59 撮合阶段20:59-21:00 | G56: 21：00-23：00 | H56: 夜盘品种不实行日盘集合竞价（夜盘交易中的未成交申报单，可以在同一交易日上午8：55至8：59之间撤单）。 | I56: 上午9:00-10:15 10:30-11:30 下午13:30-15:00 | J56: =IFERROR(IF(VLOOKUP(D56,期货合约要素!$D:$Q,12,0)=0,"",VLOOKUP(D56,期货合约要素!$D:$Q,12,0)),IF(VLOOKUP(D56,期权合约要素!$D:$V,17,0)=0,"",VLOOKUP(D56,期权合约要素!$D:$V,17,0))) | K56: =IFERROR(IF(VLOOKUP(D56,期货合约要素!$D:$Q,14,0)=0,"",VLOOKUP(D56,期货合约要素!$D:$Q,14,0)),IF(VLOOKUP(D56,期权合约要素!$D:$V,19,0)=0,"",VLOOKUP(D56,期权合约要素!$D:$V,19,0)))
C57: 棉纱 | D57: CY | J57: =IFERROR(IF(VLOOKUP(D57,期货合约要素!$D:$Q,12,0)=0,"",VLOOKUP(D57,期货合约要素!$D:$Q,12,0)),IF(VLOOKUP(D57,期权合约要素!$D:$V,17,0)=0,"",VLOOKUP(D57,期权合约要素!$D:$V,17,0))) | K57: =IFERROR(IF(VLOOKUP(D57,期货合约要素!$D:$Q,14,0)=0,"",VLOOKUP(D57,期货合约要素!$D:$Q,14,0)),IF(VLOOKUP(D57,期权合约要素!$D:$V,19,0)=0,"",VLOOKUP(D57,期权合约要素!$D:$V,19,0)))
C58: 白糖 | D58: SR | E58: 是 | J58: =IFERROR(IF(VLOOKUP(D58,期货合约要素!$D:$Q,12,0)=0,"",VLOOKUP(D58,期货合约要素!$D:$Q,12,0)),IF(VLOOKUP(D58,期权合约要素!$D:$V,17,0)=0,"",VLOOKUP(D58,期权合约要素!$D:$V,17,0))) -> √ | K58: =IFERROR(IF(VLOOKUP(D58,期货合约要素!$D:$Q,14,0)=0,"",VLOOKUP(D58,期货合约要素!$D:$Q,14,0)),IF(VLOOKUP(D58,期权合约要素!$D:$V,19,0)=0,"",VLOOKUP(D58,期权合约要素!$D:$V,19,0)))
C59: 玻璃 | D59: FG | E59: 是 | J59: =IFERROR(IF(VLOOKUP(D59,期货合约要素!$D:$Q,12,0)=0,"",VLOOKUP(D59,期货合约要素!$D:$Q,12,0)),IF(VLOOKUP(D59,期权合约要素!$D:$V,17,0)=0,"",VLOOKUP(D59,期权合约要素!$D:$V,17,0))) -> √ | K59: =IFERROR(IF(VLOOKUP(D59,期货合约要素!$D:$Q,14,0)=0,"",VLOOKUP(D59,期货合约要素!$D:$Q,14,0)),IF(VLOOKUP(D59,期权合约要素!$D:$V,19,0)=0,"",VLOOKUP(D59,期权合约要素!$D:$V,19,0)))
C60: 纯碱 | D60: SA | E60: 是 | J60: =IFERROR(IF(VLOOKUP(D60,期货合约要素!$D:$Q,12,0)=0,"",VLOOKUP(D60,期货合约要素!$D:$Q,12,0)),IF(VLOOKUP(D60,期权合约要素!$D:$V,17,0)=0,"",VLOOKUP(D60,期权合约要素!$D:$V,17,0))) -> √ | K60: =IFERROR(IF(VLOOKUP(D60,期货合约要素!$D:$Q,14,0)=0,"",VLOOKUP(D60,期货合约要素!$D:$Q,14,0)),IF(VLOOKUP(D60,期权合约要素!$D:$V,19,0)=0,"",VLOOKUP(D60,期权合约要素!$D:$V,19,0)))
C61: 甲醇 | D61: MA | E61: 是 | J61: =IFERROR(IF(VLOOKUP(D61,期货合约要素!$D:$Q,12,0)=0,"",VLOOKUP(D61,期货合约要素!$D:$Q,12,0)),IF(VLOOKUP(D61,期权合约要素!$D:$V,17,0)=0,"",VLOOKUP(D61,期权合约要素!$D:$V,17,0))) -> √ | K61: =IFERROR(IF(VLOOKUP(D61,期货合约要素!$D:$Q,14,0)=0,"",VLOOKUP(D61,期货合约要素!$D:$Q,14,0)),IF(VLOOKUP(D61,期权合约要素!$D:$V,19,0)=0,"",VLOOKUP(D61,期权合约要素!$D:$V,19,0)))
C62: PTA | D62: TA | E62: 是 | J62: =IFERROR(IF(VLOOKUP(D62,期货合约要素!$D:$Q,12,0)=0,"",VLOOKUP(D62,期货合约要素!$D:$Q,12,0)),IF(VLOOKUP(D62,期权合约要素!$D:$V,17,0)=0,"",VLOOKUP(D62,期权合约要素!$D:$V,17,0))) -> √ | K62: =IFERROR(IF(VLOOKUP(D62,期货合约要素!$D:$Q,14,0)=0,"",VLOOKUP(D62,期货合约要素!$D:$Q,14,0)),IF(VLOOKUP(D62,期权合约要素!$D:$V,19,0)=0,"",VLOOKUP(D62,期权合约要素!$D:$V,19,0))) -> √
C63: 短纤 | D63: PF | E63: 是 | J63: =IFERROR(IF(VLOOKUP(D63,期货合约要素!$D:$Q,12,0)=0,"",VLOOKUP(D63,期货合约要素!$D:$Q,12,0)),IF(VLOOKUP(D63,期权合约要素!$D:$V,17,0)=0,"",VLOOKUP(D63,期权合约要素!$D:$V,17,0))) -> √ | K63: =IFERROR(IF(VLOOKUP(D63,期货合约要素!$D:$Q,14,0)=0,"",VLOOKUP(D63,期货合约要素!$D:$Q,14,0)),IF(VLOOKUP(D63,期权合约要素!$D:$V,19,0)=0,"",VLOOKUP(D63,期权合约要素!$D:$V,19,0))) -> √
C64: 菜油 | D64: OI | E64: 是 | J64: =IFERROR(IF(VLOOKUP(D64,期货合约要素!$D:$Q,12,0)=0,"",VLOOKUP(D64,期货合约要素!$D:$Q,12,0)),IF(VLOOKUP(D64,期权合约要素!$D:$V,17,0)=0,"",VLOOKUP(D64,期权合约要素!$D:$V,17,0))) -> √ | K64: =IFERROR(IF(VLOOKUP(D64,期货合约要素!$D:$Q,14,0)=0,"",VLOOKUP(D64,期货合约要素!$D:$Q,14,0)),IF(VLOOKUP(D64,期权合约要素!$D:$V,19,0)=0,"",VLOOKUP(D64,期权合约要素!$D:$V,19,0))) -> √
C65: 菜籽粕 | D65: RM | E65: 是 | J65: =IFERROR(IF(VLOOKUP(D65,期货合约要素!$D:$Q,12,0)=0,"",VLOOKUP(D65,期货合约要素!$D:$Q,12,0)),IF(VLOOKUP(D65,期权合约要素!$D:$V,17,0)=0,"",VLOOKUP(D65,期权合约要素!$D:$V,17,0))) -> √ | K65: =IFERROR(IF(VLOOKUP(D65,期货合约要素!$D:$Q,14,0)=0,"",VLOOKUP(D65,期货合约要素!$D:$Q,14,0)),IF(VLOOKUP(D65,期权合约要素!$D:$V,19,0)=0,"",VLOOKUP(D65,期权合约要素!$D:$V,19,0))) -> √
C66: 对二甲苯 | D66: PX | E66: 是 | J66: =IFERROR(IF(VLOOKUP(D66,期货合约要素!$D:$Q,12,0)=0,"",VLOOKUP(D66,期货合约要素!$D:$Q,12,0)),IF(VLOOKUP(D66,期权合约要素!$D:$V,17,0)=0,"",VLOOKUP(D66,期权合约要素!$D:$V,17,0))) -> √ | K66: =IFERROR(IF(VLOOKUP(D66,期货合约要素!$D:$Q,14,0)=0,"",VLOOKUP(D66,期货合约要素!$D:$Q,14,0)),IF(VLOOKUP(D66,期权合约要素!$D:$V,19,0)=0,"",VLOOKUP(D66,期权合约要素!$D:$V,19,0))) -> √
C67: 烧碱 | D67: SH | E67: 是 | J67: =IFERROR(IF(VLOOKUP(D67,期货合约要素!$D:$Q,12,0)=0,"",VLOOKUP(D67,期货合约要素!$D:$Q,12,0)),IF(VLOOKUP(D67,期权合约要素!$D:$V,17,0)=0,"",VLOOKUP(D67,期权合约要素!$D:$V,17,0))) | K67: =IFERROR(IF(VLOOKUP(D67,期货合约要素!$D:$Q,14,0)=0,"",VLOOKUP(D67,期货合约要素!$D:$Q,14,0)),IF(VLOOKUP(D67,期权合约要素!$D:$V,19,0)=0,"",VLOOKUP(D67,期权合约要素!$D:$V,19,0)))
C68: 瓶片 | D68: PR | E68: 是 | J68: =IFERROR(IF(VLOOKUP(D68,期货合约要素!$D:$Q,12,0)=0,"",VLOOKUP(D68,期货合约要素!$D:$Q,12,0)),IF(VLOOKUP(D68,期权合约要素!$D:$V,17,0)=0,"",VLOOKUP(D68,期权合约要素!$D:$V,17,0))) -> √ | K68: =IFERROR(IF(VLOOKUP(D68,期货合约要素!$D:$Q,14,0)=0,"",VLOOKUP(D68,期货合约要素!$D:$Q,14,0)),IF(VLOOKUP(D68,期权合约要素!$D:$V,19,0)=0,"",VLOOKUP(D68,期权合约要素!$D:$V,19,0))) -> √
C69: 动力煤 | D69: ZC | E69: 是 | J69: =IFERROR(IF(VLOOKUP(D69,期货合约要素!$D:$Q,12,0)=0,"",VLOOKUP(D69,期货合约要素!$D:$Q,12,0)),IF(VLOOKUP(D69,期权合约要素!$D:$V,17,0)=0,"",VLOOKUP(D69,期权合约要素!$D:$V,17,0))) | K69: =IFERROR(IF(VLOOKUP(D69,期货合约要素!$D:$Q,14,0)=0,"",VLOOKUP(D69,期货合约要素!$D:$Q,14,0)),IF(VLOOKUP(D69,期权合约要素!$D:$V,19,0)=0,"",VLOOKUP(D69,期权合约要素!$D:$V,19,0)))
C70: 丙烯 | D70: PL | E70: 是 | J70: =IFERROR(IF(VLOOKUP(D70,期货合约要素!$D:$Q,12,0)=0,"",VLOOKUP(D70,期货合约要素!$D:$Q,12,0)),IF(VLOOKUP(D70,期权合约要素!$D:$V,17,0)=0,"",VLOOKUP(D70,期权合约要素!$D:$V,17,0))) | K70: =IFERROR(IF(VLOOKUP(D70,期货合约要素!$D:$Q,14,0)=0,"",VLOOKUP(D70,期货合约要素!$D:$Q,14,0)),IF(VLOOKUP(D70,期权合约要素!$D:$V,19,0)=0,"",VLOOKUP(D70,期权合约要素!$D:$V,19,0)))
C71: 锰硅 | D71: SM | E71: 是 | F71: 无夜盘 | H71: 申报阶段8:55-8:59 撮合阶段8:59-9:00 | J71: =IFERROR(IF(VLOOKUP(D71,期货合约要素!$D:$Q,12,0)=0,"",VLOOKUP(D71,期货合约要素!$D:$Q,12,0)),IF(VLOOKUP(D71,期权合约要素!$D:$V,17,0)=0,"",VLOOKUP(D71,期权合约要素!$D:$V,17,0))) -> √ | K71: =IFERROR(IF(VLOOKUP(D71,期货合约要素!$D:$Q,14,0)=0,"",VLOOKUP(D71,期货合约要素!$D:$Q,14,0)),IF(VLOOKUP(D71,期权合约要素!$D:$V,19,0)=0,"",VLOOKUP(D71,期权合约要素!$D:$V,19,0)))
C72: 普麦 | D72: PM | J72: =IFERROR(IF(VLOOKUP(D72,期货合约要素!$D:$Q,12,0)=0,"",VLOOKUP(D72,期货合约要素!$D:$Q,12,0)),IF(VLOOKUP(D72,期权合约要素!$D:$V,17,0)=0,"",VLOOKUP(D72,期权合约要素!$D:$V,17,0))) | K72: =IFERROR(IF(VLOOKUP(D72,期货合约要素!$D:$Q,14,0)=0,"",VLOOKUP(D72,期货合约要素!$D:$Q,14,0)),IF(VLOOKUP(D72,期权合约要素!$D:$V,19,0)=0,"",VLOOKUP(D72,期权合约要素!$D:$V,19,0)))
C73: 粳稻 | D73: JR | J73: =IFERROR(IF(VLOOKUP(D73,期货合约要素!$D:$Q,12,0)=0,"",VLOOKUP(D73,期货合约要素!$D:$Q,12,0)),IF(VLOOKUP(D73,期权合约要素!$D:$V,17,0)=0,"",VLOOKUP(D73,期权合约要素!$D:$V,17,0))) | K73: =IFERROR(IF(VLOOKUP(D73,期货合约要素!$D:$Q,14,0)=0,"",VLOOKUP(D73,期货合约要素!$D:$Q,14,0)),IF(VLOOKUP(D73,期权合约要素!$D:$V,19,0)=0,"",VLOOKUP(D73,期权合约要素!$D:$V,19,0)))
C74: 硅铁 | D74: SF | E74: 是 | J74: =IFERROR(IF(VLOOKUP(D74,期货合约要素!$D:$Q,12,0)=0,"",VLOOKUP(D74,期货合约要素!$D:$Q,12,0)),IF(VLOOKUP(D74,期权合约要素!$D:$V,17,0)=0,"",VLOOKUP(D74,期权合约要素!$D:$V,17,0))) -> √ | K74: =IFERROR(IF(VLOOKUP(D74,期货合约要素!$D:$Q,14,0)=0,"",VLOOKUP(D74,期货合约要素!$D:$Q,14,0)),IF(VLOOKUP(D74,期权合约要素!$D:$V,19,0)=0,"",VLOOKUP(D74,期权合约要素!$D:$V,19,0)))
C75: 苹果 | D75: AP | E75: 是 | J75: =IFERROR(IF(VLOOKUP(D75,期货合约要素!$D:$Q,12,0)=0,"",VLOOKUP(D75,期货合约要素!$D:$Q,12,0)),IF(VLOOKUP(D75,期权合约要素!$D:$V,17,0)=0,"",VLOOKUP(D75,期权合约要素!$D:$V,17,0))) | K75: =IFERROR(IF(VLOOKUP(D75,期货合约要素!$D:$Q,14,0)=0,"",VLOOKUP(D75,期货合约要素!$D:$Q,14,0)),IF(VLOOKUP(D75,期权合约要素!$D:$V,19,0)=0,"",VLOOKUP(D75,期权合约要素!$D:$V,19,0)))
C76: 油菜籽 | D76: RS | J76: =IFERROR(IF(VLOOKUP(D76,期货合约要素!$D:$Q,12,0)=0,"",VLOOKUP(D76,期货合约要素!$D:$Q,12,0)),IF(VLOOKUP(D76,期权合约要素!$D:$V,17,0)=0,"",VLOOKUP(D76,期权合约要素!$D:$V,17,0))) | K76: =IFERROR(IF(VLOOKUP(D76,期货合约要素!$D:$Q,14,0)=0,"",VLOOKUP(D76,期货合约要素!$D:$Q,14,0)),IF(VLOOKUP(D76,期权合约要素!$D:$V,19,0)=0,"",VLOOKUP(D76,期权合约要素!$D:$V,19,0)))
C77: 红枣 | D77: CJ | E77: 是 | J77: =IFERROR(IF(VLOOKUP(D77,期货合约要素!$D:$Q,12,0)=0,"",VLOOKUP(D77,期货合约要素!$D:$Q,12,0)),IF(VLOOKUP(D77,期权合约要素!$D:$V,17,0)=0,"",VLOOKUP(D77,期权合约要素!$D:$V,17,0))) | K77: =IFERROR(IF(VLOOKUP(D77,期货合约要素!$D:$Q,14,0)=0,"",VLOOKUP(D77,期货合约要素!$D:$Q,14,0)),IF(VLOOKUP(D77,期权合约要素!$D:$V,19,0)=0,"",VLOOKUP(D77,期权合约要素!$D:$V,19,0)))
C78: 强麦 | D78: WH | J78: =IFERROR(IF(VLOOKUP(D78,期货合约要素!$D:$Q,12,0)=0,"",VLOOKUP(D78,期货合约要素!$D:$Q,12,0)),IF(VLOOKUP(D78,期权合约要素!$D:$V,17,0)=0,"",VLOOKUP(D78,期权合约要素!$D:$V,17,0))) | K78: =IFERROR(IF(VLOOKUP(D78,期货合约要素!$D:$Q,14,0)=0,"",VLOOKUP(D78,期货合约要素!$D:$Q,14,0)),IF(VLOOKUP(D78,期权合约要素!$D:$V,19,0)=0,"",VLOOKUP(D78,期权合约要素!$D:$V,19,0)))
C79: 尿素 | D79: UR | E79: 是 | J79: =IFERROR(IF(VLOOKUP(D79,期货合约要素!$D:$Q,12,0)=0,"",VLOOKUP(D79,期货合约要素!$D:$Q,12,0)),IF(VLOOKUP(D79,期权合约要素!$D:$V,17,0)=0,"",VLOOKUP(D79,期权合约要素!$D:$V,17,0))) | K79: =IFERROR(IF(VLOOKUP(D79,期货合约要素!$D:$Q,14,0)=0,"",VLOOKUP(D79,期货合约要素!$D:$Q,14,0)),IF(VLOOKUP(D79,期权合约要素!$D:$V,19,0)=0,"",VLOOKUP(D79,期权合约要素!$D:$V,19,0)))
C80: 花生 | D80: PK | E80: 是 | J80: =IFERROR(IF(VLOOKUP(D80,期货合约要素!$D:$Q,12,0)=0,"",VLOOKUP(D80,期货合约要素!$D:$Q,12,0)),IF(VLOOKUP(D80,期权合约要素!$D:$V,17,0)=0,"",VLOOKUP(D80,期权合约要素!$D:$V,17,0))) -> √ | K80: =IFERROR(IF(VLOOKUP(D80,期货合约要素!$D:$Q,14,0)=0,"",VLOOKUP(D80,期货合约要素!$D:$Q,14,0)),IF(VLOOKUP(D80,期权合约要素!$D:$V,19,0)=0,"",VLOOKUP(D80,期权合约要素!$D:$V,19,0))) -> √
C81: 晚籼稻 | D81: LR | J81: =IFERROR(IF(VLOOKUP(D81,期货合约要素!$D:$Q,12,0)=0,"",VLOOKUP(D81,期货合约要素!$D:$Q,12,0)),IF(VLOOKUP(D81,期权合约要素!$D:$V,17,0)=0,"",VLOOKUP(D81,期权合约要素!$D:$V,17,0))) | K81: =IFERROR(IF(VLOOKUP(D81,期货合约要素!$D:$Q,14,0)=0,"",VLOOKUP(D81,期货合约要素!$D:$Q,14,0)),IF(VLOOKUP(D81,期权合约要素!$D:$V,19,0)=0,"",VLOOKUP(D81,期权合约要素!$D:$V,19,0)))
C82: 早籼稻 | D82: RI | J82: =IFERROR(IF(VLOOKUP(D82,期货合约要素!$D:$Q,12,0)=0,"",VLOOKUP(D82,期货合约要素!$D:$Q,12,0)),IF(VLOOKUP(D82,期权合约要素!$D:$V,17,0)=0,"",VLOOKUP(D82,期权合约要素!$D:$V,17,0))) | K82: =IFERROR(IF(VLOOKUP(D82,期货合约要素!$D:$Q,14,0)=0,"",VLOOKUP(D82,期货合约要素!$D:$Q,14,0)),IF(VLOOKUP(D82,期权合约要素!$D:$V,19,0)=0,"",VLOOKUP(D82,期权合约要素!$D:$V,19,0)))
B83: 广期所 | C83: 工业硅 | D83: si | E83: 是 | F83: 无夜盘 | H83: 申报阶段8:55-8:59 撮合阶段8:59-9:00 | I83: 上午9:00-10:15 10:30-11:30 下午13:30-15:00 | J83: =IFERROR(IF(VLOOKUP(D83,期货合约要素!$D:$Q,12,0)=0,"",VLOOKUP(D83,期货合约要素!$D:$Q,12,0)),IF(VLOOKUP(D83,期权合约要素!$D:$V,17,0)=0,"",VLOOKUP(D83,期权合约要素!$D:$V,17,0))) -> √ | K83: =IFERROR(IF(VLOOKUP(D83,期货合约要素!$D:$Q,14,0)=0,"",VLOOKUP(D83,期货合约要素!$D:$Q,14,0)),IF(VLOOKUP(D83,期权合约要素!$D:$V,19,0)=0,"",VLOOKUP(D83,期权合约要素!$D:$V,19,0)))
C84: 碳酸锂 | D84: lc | E84: 是 | J84: =IFERROR(IF(VLOOKUP(D84,期货合约要素!$D:$Q,12,0)=0,"",VLOOKUP(D84,期货合约要素!$D:$Q,12,0)),IF(VLOOKUP(D84,期权合约要素!$D:$V,17,0)=0,"",VLOOKUP(D84,期权合约要素!$D:$V,17,0))) -> √ | K84: =IFERROR(IF(VLOOKUP(D84,期货合约要素!$D:$Q,14,0)=0,"",VLOOKUP(D84,期货合约要素!$D:$Q,14,0)),IF(VLOOKUP(D84,期权合约要素!$D:$V,19,0)=0,"",VLOOKUP(D84,期权合约要素!$D:$V,19,0))) -> √
C85: 多晶硅 | D85: ps | E85: 是 | J85: =IFERROR(IF(VLOOKUP(D85,期货合约要素!$D:$Q,12,0)=0,"",VLOOKUP(D85,期货合约要素!$D:$Q,12,0)),IF(VLOOKUP(D85,期权合约要素!$D:$V,17,0)=0,"",VLOOKUP(D85,期权合约要素!$D:$V,17,0))) -> √ | K85: =IFERROR(IF(VLOOKUP(D85,期货合约要素!$D:$Q,14,0)=0,"",VLOOKUP(D85,期货合约要素!$D:$Q,14,0)),IF(VLOOKUP(D85,期权合约要素!$D:$V,19,0)=0,"",VLOOKUP(D85,期权合约要素!$D:$V,19,0)))
C86: 铂 | D86: pt | E86: 是 | J86: =IFERROR(IF(VLOOKUP(D86,期货合约要素!$D:$Q,12,0)=0,"",VLOOKUP(D86,期货合约要素!$D:$Q,12,0)),IF(VLOOKUP(D86,期权合约要素!$D:$V,17,0)=0,"",VLOOKUP(D86,期权合约要素!$D:$V,17,0))) | K86: =IFERROR(IF(VLOOKUP(D86,期货合约要素!$D:$Q,14,0)=0,"",VLOOKUP(D86,期货合约要素!$D:$Q,14,0)),IF(VLOOKUP(D86,期权合约要素!$D:$V,19,0)=0,"",VLOOKUP(D86,期权合约要素!$D:$V,19,0)))
C87: 钯 | D87: pd | E87: 是 | J87: =IFERROR(IF(VLOOKUP(D87,期货合约要素!$D:$Q,12,0)=0,"",VLOOKUP(D87,期货合约要素!$D:$Q,12,0)),IF(VLOOKUP(D87,期权合约要素!$D:$V,17,0)=0,"",VLOOKUP(D87,期权合约要素!$D:$V,17,0))) | K87: =IFERROR(IF(VLOOKUP(D87,期货合约要素!$D:$Q,14,0)=0,"",VLOOKUP(D87,期货合约要素!$D:$Q,14,0)),IF(VLOOKUP(D87,期权合约要素!$D:$V,19,0)=0,"",VLOOKUP(D87,期权合约要素!$D:$V,19,0)))
B88: 中金所 | C88: 2年期国债 | D88: TS | F88: 无夜盘 | H88: 申报阶段9:25-9:29 撮合阶段9:29-9:30 | I88: 上午9:30-11:30 下午13:00-15:15 （最后交易日为09：30-11：30） | J88: =IFERROR(IF(VLOOKUP(D88,期货合约要素!$D:$Q,12,0)=0,"",VLOOKUP(D88,期货合约要素!$D:$Q,12,0)),IF(VLOOKUP(D88,期权合约要素!$D:$V,17,0)=0,"",VLOOKUP(D88,期权合约要素!$D:$V,17,0))) -> √ | K88: =IFERROR(IF(VLOOKUP(D88,期货合约要素!$D:$Q,14,0)=0,"",VLOOKUP(D88,期货合约要素!$D:$Q,14,0)),IF(VLOOKUP(D88,期权合约要素!$D:$V,19,0)=0,"",VLOOKUP(D88,期权合约要素!$D:$V,19,0)))
C89: 5年期国债 | D89: TF | J89: =IFERROR(IF(VLOOKUP(D89,期货合约要素!$D:$Q,12,0)=0,"",VLOOKUP(D89,期货合约要素!$D:$Q,12,0)),IF(VLOOKUP(D89,期权合约要素!$D:$V,17,0)=0,"",VLOOKUP(D89,期权合约要素!$D:$V,17,0))) -> √ | K89: =IFERROR(IF(VLOOKUP(D89,期货合约要素!$D:$Q,14,0)=0,"",VLOOKUP(D89,期货合约要素!$D:$Q,14,0)),IF(VLOOKUP(D89,期权合约要素!$D:$V,19,0)=0,"",VLOOKUP(D89,期权合约要素!$D:$V,19,0)))
C90: 10年期国债 | D90: T | J90: =IFERROR(IF(VLOOKUP(D90,期货合约要素!$D:$Q,12,0)=0,"",VLOOKUP(D90,期货合约要素!$D:$Q,12,0)),IF(VLOOKUP(D90,期权合约要素!$D:$V,17,0)=0,"",VLOOKUP(D90,期权合约要素!$D:$V,17,0))) -> √ | K90: =IFERROR(IF(VLOOKUP(D90,期货合约要素!$D:$Q,14,0)=0,"",VLOOKUP(D90,期货合约要素!$D:$Q,14,0)),IF(VLOOKUP(D90,期权合约要素!$D:$V,19,0)=0,"",VLOOKUP(D90,期权合约要素!$D:$V,19,0)))
C91: 30年期国债 | D91: TL | J91: =IFERROR(IF(VLOOKUP(D91,期货合约要素!$D:$Q,12,0)=0,"",VLOOKUP(D91,期货合约要素!$D:$Q,12,0)),IF(VLOOKUP(D91,期权合约要素!$D:$V,17,0)=0,"",VLOOKUP(D91,期权合约要素!$D:$V,17,0))) -> √ | K91: =IFERROR(IF(VLOOKUP(D91,期货合约要素!$D:$Q,14,0)=0,"",VLOOKUP(D91,期货合约要素!$D:$Q,14,0)),IF(VLOOKUP(D91,期权合约要素!$D:$V,19,0)=0,"",VLOOKUP(D91,期权合约要素!$D:$V,19,0)))
C92: 沪深300股指期货 | D92: IF | I92: 上午9:30-11:30 下午13:00-15:00 | J92: =IFERROR(IF(VLOOKUP(D92,期货合约要素!$D:$Q,12,0)=0,"",VLOOKUP(D92,期货合约要素!$D:$Q,12,0)),IF(VLOOKUP(D92,期权合约要素!$D:$V,17,0)=0,"",VLOOKUP(D92,期权合约要素!$D:$V,17,0))) -> √ | K92: =IFERROR(IF(VLOOKUP(D92,期货合约要素!$D:$Q,14,0)=0,"",VLOOKUP(D92,期货合约要素!$D:$Q,14,0)),IF(VLOOKUP(D92,期权合约要素!$D:$V,19,0)=0,"",VLOOKUP(D92,期权合约要素!$D:$V,19,0)))
C93: 上证50股指期货 | D93: IH | J93: =IFERROR(IF(VLOOKUP(D93,期货合约要素!$D:$Q,12,0)=0,"",VLOOKUP(D93,期货合约要素!$D:$Q,12,0)),IF(VLOOKUP(D93,期权合约要素!$D:$V,17,0)=0,"",VLOOKUP(D93,期权合约要素!$D:$V,17,0))) -> √ | K93: =IFERROR(IF(VLOOKUP(D93,期货合约要素!$D:$Q,14,0)=0,"",VLOOKUP(D93,期货合约要素!$D:$Q,14,0)),IF(VLOOKUP(D93,期权合约要素!$D:$V,19,0)=0,"",VLOOKUP(D93,期权合约要素!$D:$V,19,0)))
C94: 中证500股指期货 | D94: IC | J94: =IFERROR(IF(VLOOKUP(D94,期货合约要素!$D:$Q,12,0)=0,"",VLOOKUP(D94,期货合约要素!$D:$Q,12,0)),IF(VLOOKUP(D94,期权合约要素!$D:$V,17,0)=0,"",VLOOKUP(D94,期权合约要素!$D:$V,17,0))) -> √ | K94: =IFERROR(IF(VLOOKUP(D94,期货合约要素!$D:$Q,14,0)=0,"",VLOOKUP(D94,期货合约要素!$D:$Q,14,0)),IF(VLOOKUP(D94,期权合约要素!$D:$V,19,0)=0,"",VLOOKUP(D94,期权合约要素!$D:$V,19,0)))
C95: 中证1000股指期货 | D95: IM | J95: =IFERROR(IF(VLOOKUP(D95,期货合约要素!$D:$Q,12,0)=0,"",VLOOKUP(D95,期货合约要素!$D:$Q,12,0)),IF(VLOOKUP(D95,期权合约要素!$D:$V,17,0)=0,"",VLOOKUP(D95,期权合约要素!$D:$V,17,0))) -> √ | K95: =IFERROR(IF(VLOOKUP(D95,期货合约要素!$D:$Q,14,0)=0,"",VLOOKUP(D95,期货合约要素!$D:$Q,14,0)),IF(VLOOKUP(D95,期权合约要素!$D:$V,19,0)=0,"",VLOOKUP(D95,期权合约要素!$D:$V,19,0)))
C96: 沪深300股指期权 | D96: IO | H96: 开盘集合竞价 申报阶段9:25-9:29 撮合阶段9:29-9:30 收盘集合竞价 14:57-15:00 | I96: 上午9:30-11:30 下午13:00-14:57 | J96: =IFERROR(IF(VLOOKUP(D96,期货合约要素!$D:$Q,12,0)=0,"",VLOOKUP(D96,期货合约要素!$D:$Q,12,0)),IF(VLOOKUP(D96,期权合约要素!$D:$V,17,0)=0,"",VLOOKUP(D96,期权合约要素!$D:$V,17,0))) -> √ | K96: =IFERROR(IF(VLOOKUP(D96,期货合约要素!$D:$Q,14,0)=0,"",VLOOKUP(D96,期货合约要素!$D:$Q,14,0)),IF(VLOOKUP(D96,期权合约要素!$D:$V,19,0)=0,"",VLOOKUP(D96,期权合约要素!$D:$V,19,0)))
C97: 中证1000股指期权 | D97: MO | J97: =IFERROR(IF(VLOOKUP(D97,期货合约要素!$D:$Q,12,0)=0,"",VLOOKUP(D97,期货合约要素!$D:$Q,12,0)),IF(VLOOKUP(D97,期权合约要素!$D:$V,17,0)=0,"",VLOOKUP(D97,期权合约要素!$D:$V,17,0))) -> √ | K97: =IFERROR(IF(VLOOKUP(D97,期货合约要素!$D:$Q,14,0)=0,"",VLOOKUP(D97,期货合约要素!$D:$Q,14,0)),IF(VLOOKUP(D97,期权合约要素!$D:$V,19,0)=0,"",VLOOKUP(D97,期权合约要素!$D:$V,19,0)))
C98: 上证50股指期权 | D98: HO | J98: =IFERROR(IF(VLOOKUP(D98,期货合约要素!$D:$Q,12,0)=0,"",VLOOKUP(D98,期货合约要素!$D:$Q,12,0)),IF(VLOOKUP(D98,期权合约要素!$D:$V,17,0)=0,"",VLOOKUP(D98,期权合约要素!$D:$V,17,0))) -> √ | K98: =IFERROR(IF(VLOOKUP(D98,期货合约要素!$D:$Q,14,0)=0,"",VLOOKUP(D98,期货合约要素!$D:$Q,14,0)),IF(VLOOKUP(D98,期权合约要素!$D:$V,19,0)=0,"",VLOOKUP(D98,期权合约要素!$D:$V,19,0)))
B99: 注： | C99: 集合竞价时间分为两个阶段，申报阶段为期货、期权合约买、卖指令申报时间，只能挂单、撤单且不进行撮合成交；撮合阶段为集合竞价撮合成交时间，交易所交易系统将不接受挂单、撤单等指令。

Sheet 期货合约要素
A1: 点此返回目录
B2: 期货品种合约要素
B3: 交易所 | C3: 品种名称 | D3: 品种代码 | E3: 交易单位(每手) | F3: 最小变动价位 | G3: 限价指令每次最大下单数量(手) | H3: 市价指令每次最大下单数量(手) | I3: 合约月份 | J3: 最小交割单位(手) | K3: 临近交割月调整要求 | L3: 最后交易日 | M3: 自然人最后退出日 | N3: 上市时间 | O3: QFII&RQFII | P3: QFII&RQFII可交易日期 | Q3: 国际化品种
B4: 中国金融期货交易所 | C4: 沪深300指数期货 | D4: IF | E4: 每点300元 | F4: 0.2点 | G4: 20 | H4: 10 （仅当月、下月合约支持） | I4: 当月、下月及随后两个季月 | J4: 1 | K4: 无需调整 | L4: 合约到期月份第三个周五 | M4: 无 | N4: 40284 | O4: √ | P4: 2011.05.04
C5: 上证50指数期货 | D5: IH | E5: 每点300元 | F5: 0.2点 | G5: 20 | H5: 10 （仅当月、下月合约支持） | I5: 当月、下月及随后两个季月 | J5: 1 | K5: 无需调整 | L5: 合约到期月份第三个周五 | M5: 无 | N5: 42110 | O5: √ | P5: 2015.04.16
C6: 中证500指数期货 | D6: IC | E6: 每点200元 | F6: 0.2点 | G6: 20 | H6: 10 （仅当月、下月合约支持） | I6: 当月、下月及随后两个季月 | J6: 1 | K6: 无需调整 | L6: 合约到期月份第三个周五 | M6: 无 | N6: 42110 | O6: √ | P6: 2015.04.16
C7: 中证1000指数期货 | D7: IM | E7: 每点200元 | F7: 0.2点 | G7: 20 | H7: 10 （仅当月、下月合约支持） | I7: 当月、下月及随后两个季月 | J7: 1 | K7: 无需调整 | L7: 合约到期月份第三个周五 | M7: 无 | N7: 44764 | O7: √ | P7: 2022.07.22
C8: 2年期国债期货 | D8: TS | E8: 合约乘数为20000 | F8: 0.002元 | G8: 50 | H8: 30 （ 仅最近的季月合约支持） | I8: 最近的三个季月（3月、6月、9月、12月中的最近三个月循环 | J8: 1 | K8: 未通过我司向交易所进行国债托管账户报备的客户需要在交割月前两个交易日收盘时将净持仓调整为0 | L8: 合约到期月份第二个周五 | M8: 未通过我司向交易所进行国债托管账户报备的客户需要在交割月前两个交易日收盘时将净持仓调整为0 | N8: 43329 | O8: √ | P8: 2026.04.24
C9: 5年期国债期货 | D9: TF | E9: 合约乘数为10000 | F9: 0.005元 | G9: 50 | H9: 30 （ 仅最近的季月合约支持） | I9: 最近的三个季月（3月、6月、9月、12月中的最近三个月循环 | J9: 1 | K9: 未通过我司向交易所进行国债托管账户报备的客户需要在交割月前两个交易日收盘时将净持仓调整为0 | L9: 合约到期月份第二个周五 | M9: 未通过我司向交易所进行国债托管账户报备的客户需要在交割月前两个交易日收盘时将净持仓调整为0 | N9: 41523 | O9: √ | P9: 2026.04.24
C10: 10年期国债期货 | D10: T | E10: 合约乘数为10000 | F10: 0.005元 | G10: 50 | H10: 30 （ 仅最近的季月合约支持） | I10: 最近的三个季月（3月、6月、9月、12月中的最近三个月循环 | J10: 1 | K10: 未通过我司向交易所进行国债托管账户报备的客户需要在交割月前两个交易日收盘时将净持仓调整为0 | L10: 合约到期月份第二个周五 | M10: 未通过我司向交易所进行国债托管账户报备的客户需要在交割月前两个交易日收盘时将净持仓调整为0 | N10: 42083 | O10: √ | P10: 2026.04.24
C11: 30年期国债期货 | D11: TL | E11: 合约乘数为10000 | F11: 0.01元 | G11: 50 | H11: 30 （ 仅最近的季月合约支持） | I11: 最近的三个季月（3月、6月、9月、12月中的最近三个月循环 | J11: 1 | K11: 未通过我司向交易所进行国债托管账户报备的客户需要在交割月前两个交易日收盘时将净持仓调整为0 | L11: 合约到期月份第二个周五 | M11: 未通过我司向交易所进行国债托管账户报备的客户需要在交割月前两个交易日收盘时将净持仓调整为0 | N11: 45037 | O11: √ | P11: 2026.04.24
B12: 上海国际能源交易中心 | C12: 原油 | D12: sc | E12: 1000桶 | F12: 0.1元/桶 | G12: 500 | H12: 60 | I12: 最近1-12个月为连续月份以及随后八个季月 | J12: 1 | K12: 无需调整 | L12: 交割月份前第一月的最后一个交易日 | M12: 最后交易日前第8个交易日收盘时调整为0手 | N12: 43185 | O12: √ | P12: 2022.09.05 | Q12: √
C13: 20号胶 | D13: nr | E13: 10吨 | F13: 5元/吨 | G13: 500 | H13: 60 | I13: 1-12月 | J13: 10 | K13: 10手整数倍 | L13: 合约交割月份的15日 | M13: 最后交易日前第5个交易日收盘时调整为0手 | N13: 43689 | O13: √ | P13: 2022.09.05 | Q13: √
C14: 低硫燃料油 | D14: lu | E14: 10吨 | F14: 1元/吨 | G14: 500 | H14: 60 | I14: 1-12月 | J14: 1 | K14: 无需调整 | L14: 交割月份前第一月的最后一个交易日 | M14: 最后交易日前第5个交易日收盘时调整为0手 | N14: 44004 | O14: √ | P14: 2022.09.05 | Q14: √
C15: 国际铜 | D15: bc | E15: 5吨 | F15: 10元/吨 | G15: 500 | H15: 60 | I15: 1-12月 | J15: 5 | K15: 5手整数倍 | L15: 合约交割月份的15日 | M15: 最后交易日前第5个交易日收盘时调整为0手 | N15: 44154 | O15: √ | P15: 2022.09.05 | Q15: √
C16: 集运指数（欧线） | D16: ec | E16: 每点50元 | F16: 0.5点 | G16: 500 | H16: 60 | I16: 1、3、4、5、6、7、8、9、10、11、12月份中的最近6个月内连续月份及随后的两个季月 | J16: 1 | K16: 无需调整 | L16: 合约交割月份最后一个开展期货交易的周一 | M16: 无需调整 | N16: 45156 | O16: √ | P16: 2025.03.04 | Q16: √
B17: 上海期货交易所 | C17: 螺纹钢 | D17: rb | E17: 10 吨 | F17: 1元/吨 | G17: 500 | H17: 60 | I17: 1-12月 | J17: 30 | K17: 30手整数倍 | L17: 合约交割月份的15日 | M17: 最后交易日前第5个交易日收盘时调整为0手 | N17: 39899 | O17: √ | P17: 2022.09.05
C18: 热轧卷板 | D18: hc | E18: 10 吨 | F18: 1元/吨 | G18: 500 | H18: 60 | I18: 1-12月 | J18: 30 | K18: 30手整数倍 | L18: 合约交割月份的15日 | M18: 最后交易日前第5个交易日收盘时调整为0手 | N18: 41719 | O18: √ | P18: 2022.09.05
C19: 线材 | D19: wr | E19: 10 吨 | F19: 1元/吨 | G19: 500 | H19: 60 | I19: 1-12月 | J19: 30 | K19: 30手整数倍 | L19: 合约交割月份的15日 | M19: 最后交易日前第5个交易日收盘时调整为0手 | N19: 39899 | P19: ——
C20: 铜 | D20: cu | E20: 5 吨 | F20: 10元/吨 | G20: 500 | H20: 60 | I20: 1-12月 | J20: 5 | K20: 5手整数倍 | L20: 合约交割月份的15日 | M20: 最后交易日前第5个交易日收盘时调整为0手 | N20: 34029 | O20: √ | P20: 2022.09.05
C21: 铝 | D21: al | E21: 5 吨 | F21: 5元/吨 | G21: 500 | H21: 60 | I21: 1-12月 | J21: 5 | K21: 5手整数倍 | L21: 合约交割月份的15日 | M21: 最后交易日前第5个交易日收盘时调整为0手 | N21: 33752 | O21: √ | P21: 2022.09.05
C22: 锌 | D22: zn | E22: 5 吨 | F22: 5元/吨 | G22: 500 | H22: 60 | I22: 1-12月 | J22: 5 | K22: 5手整数倍 | L22: 合约交割月份的15日 | M22: 最后交易日前第5个交易日收盘时调整为0手 | N22: 39167 | O22: √ | P22: 2022.09.05
C23: 铅 | D23: pb | E23: 5 吨 | F23: 5元/吨 | G23: 500 | H23: 60 | I23: 1-12月 | J23: 5 | K23: 5手整数倍 | L23: 合约交割月份的15日 | M23: 最后交易日前第5个交易日收盘时调整为0手 | N23: 40626 | O23: √ | P23: 2025.06.20
C24: 氧化铝 | D24: ao | E24: 20吨 | F24: 1元/吨 | G24: 500 | H24: 60 | I24: 1-12月 | J24: 15 | K24: 15手的整数倍 | L24: 合约交割月份的15日 | M24: 最后交易日前第5个交易日收盘时调整为0手 | N24: 45096 | P24: ——
C25: 不锈钢 | D25: ss | E25: 5吨 | F25: 5元/吨 | G25: 500 | H25: 60 | I25: 1-12月 | J25: 12 | K25: 12手的整数倍 | L25: 合约交割月份的15日 | M25: 最后交易日前第5个交易日收盘时调整为0手 | N25: 43733 | O25: √ | P25: 2025.03.04
C26: 镍 | D26: ni | E26: 1吨 | F26: 10元/吨 | G26: 500 | H26: 60 | I26: 1-12月 | J26: 6 | K26: 6手的整数倍 | L26: 合约交割月份的15日 | M26: 最后交易日前第5个交易日收盘时调整为0手 | N26: 42090 | O26: √ | P26: 2026.04.22 | Q26: √
C27: 锡 | D27: sn | E27: 1吨 | F27: 10元/吨 | G27: 500 | H27: 60 | I27: 1-12月 | J27: 2 | K27: 2手的整数倍 | L27: 合约交割月份的15日 | M27: 最后交易日前第5个交易日收盘时调整为0手 | N27: 42090 | O27: √ | P27: 2025.06.20
C28: 黄金 | D28: au | E28: 1000 克 | F28: 0.02元/克 | G28: 500 | H28: 60 | I28: 最近三个连续月份以及最近13个月以内的双月合约 | J28: 3 | K28: 3手整数倍 | L28: 合约交割月份的15日 | M28: 最后交易日前第5个交易日收盘时调整为0手 | N28: 39456 | O28: √ | P28: 2022.09.05
C29: 白银 | D29: ag | E29: 15千克 | F29: 1元/千克 | G29: 500 | H29: 60 | I29: 1-12月 | J29: 2 | K29: 2手整数倍 | L29: 合约交割月份的15日 | M29: 最后交易日前第5个交易日收盘时调整为0手 | N29: 41039 | O29: √ | P29: 2022.09.05
C30: 天然橡胶 | D30: ru | E30: 10吨 | F30: 5元/吨 | G30: 500 | H30: 60 | I30: 1、3-11月 | J30: 1 | K30: 无需调整 | L30: 合约交割月份的15日 | M30: 最后交易日前第5个交易日收盘时调整为0手 | N30: 34055 | O30: √ | P30: 2025.06.20
C31: 石油沥青 | D31: bu | E31: 10吨 | F31: 1元/吨 | G31: 500 | H31: 60 | I31: 最近1~12个月为连续月份以及随后四个季月 | J31: 1 | K31: 无需调整 | L31: 合约交割月份的15日 | M31: 最后交易日前第5个交易日收盘时调整为0手 | N31: 41556 | O31: √ | P31: 2025.09.10
C32: 纸浆 | D32: sp | E32: 10吨 | F32: 2元/吨 | G32: 500 | H32: 60 | I32: 1-12月 | J32: 2 | K32: 2手整数倍 | L32: 合约交割月份的15日 | M32: 最后交易日前第5个交易日收盘时调整为0手 | N32: 43431 | O32: √ | P32: 2025.03.04
C33: 保税380燃料油 | D33: fu | E33: 10吨 | F33: 1元/吨 | G33: 500 | H33: 60 | I33: 1-12月 | J33: 1 | K33: 无需调整 | L33: 交割月前一月的最后一个交易日 | M33: 最后交易日前第5个交易日收盘时调整为0手 | N33: 38224 | O33: √ | P33: 2025.03.04
C34: 合成橡胶 | D34: br | E34: 5吨 | F34: 5元/吨 | G34: 500 | H34: 60 | I34: 1-12月 | J34: 2 | K34: 2手整数倍 | L34: 合约交割月份的15日 | M34: 最后交易日前第5个交易日收盘时调整为0手 | N34: 45135 | P34: ——
C35: 铸造铝合金 | D35: ad | E35: 10吨 | F35: 5元/吨 | G35: 500 | H35: 60 | I35: 1-12月 | J35: 3 | K35: 3手整数倍 | L35: 合约交割月份的15日 | M35: 最后交易日前第5个交易日收盘时调整为0手 | N35: 45818 | P35: ——
C36: 胶版印刷纸 | D36: op | E36: 40吨 | F36: 2元/吨 | G36: 500 | H36: 60 | I36: 1-12月 | J36: 1 | K36: 无需调整 | L36: 合约交割月份的15日 | M36: 最后交易日前第5个交易日收盘时调整为0手 | N36: 45910 | P36: ——
B37: 大连商品交易所 | C37: 黄大豆一号 | D37: a | E37: 10 吨 | F37: 1 元/吨 | G37: 1000 | H37: 1000 | I37: 1、3、5、7、9、11 月 | J37: 1 | K37: 自然人不能持仓进入交割月 | L37: 合约月份第 10 个交易日 | M37: 自然人不能持仓进入交割月 | N37: 37330 | O37: √ | P37: 2022.09.05 | Q37: √
C38: 黄大豆二号 | D38: b | E38: 10 吨 | F38: 1 元/吨 | G38: 1000 | H38: 1000 | I38: 1-12月 | J38: 100 | K38: 自然人不能持仓进入交割月 | L38: 合约月份第 10 个交易日 | M38: 自然人不能持仓进入交割月 | N38: 38343 | O38: √ | P38: 2022.09.05 | Q38: √
C39: 豆粕 | D39: m | E39: 10 吨 | F39: 1 元/吨 | G39: 1000 | H39: 1000 | I39: 1、3、5、7、8、9、11、12月 | J39: 1 | K39: 自然人不能持仓进入交割月 | L39: 合约月份第 10 个交易日 | M39: 自然人不能持仓进入交割月 | N39: 36724 | O39: √ | P39: 2022.09.05 | Q39: √
C40: 豆油 | D40: y | E40: 10 吨 | F40: 1 元/吨 （20260410交易时起生效） | G40: 1000 | H40: 1000 | I40: 1、3、5、7、8、9、11、12月 | J40: 1 | K40: 自然人不能持仓进入交割月 | L40: 合约月份第 10 个交易日 | M40: 自然人不能持仓进入交割月 | N40: 38726 | O40: √ | P40: 2022.09.05 | Q40: √
C41: 棕榈油 | D41: p | E41: 10 吨 | F41: 1 元/吨 （20260410交易时起生效） | G41: 1000 | H41: 1000 | I41: 1-12月 | J41: 1 | K41: 自然人不能持仓进入交割月 | L41: 合约月份第 10 个交易日 | M41: 自然人不能持仓进入交割月 | N41: 39384 | O41: √ | P41: 2022.09.05 | Q41: √
C42: 焦煤 | D42: jm | E42: 60吨 | F42: 0.5 元/吨 | G42: 1000 | H42: 1000 | I42: 1-12月 | J42: 100； 1（2604及后续合约） | K42: 自然人不能持仓进入交割月 | L42: 合约月份第 10 个交易日 | M42: 自然人不能持仓进入交割月 | N42: 41355 | P42: ——
C43: 冶金焦炭 | D43: j | E43: 100吨 | F43: 0.5 元/吨 | G43: 500 | H43: 500 | I43: 1-12月 | J43: 10； 1（2604及后续合约） | K43: 自然人不能持仓进入交割月 | L43: 合约月份第 10 个交易日 | M43: 自然人不能持仓进入交割月 | N43: 40648 | P43: ——
C44: 铁矿石 | D44: i | E44: 100吨 | F44: 0.5 元/吨 | G44: 1000 | H44: 1000 | I44: 1-12月 | J44: 100； 50（2604及后续合约） | K44: 自然人不能持仓进入交割月 | L44: 合约月份第 10 个交易日 | M44: 自然人不能持仓进入交割月 | N44: 41565 | O44: √ | P44: 2022.09.05 | Q44: √
C45: 玉米 | D45: c | E45: 10 吨 | F45: 1 元/吨 | G45: 2000 | H45: 2000 | I45: 1、3、5、7、9、11 月 | J45: 1 | K45: 自然人不能持仓进入交割月 | L45: 合约月份第 10 个交易日 | M45: 自然人不能持仓进入交割月 | N45: 38252 | P45: ——
C46: 玉米淀粉 | D46: cs | E46: 10 吨 | F46: 1 元/吨 | G46: 1000 | H46: 1000 | I46: 1、3、5、7、9、11 月 | J46: 1 | K46: 自然人不能持仓进入交割月 | L46: 合约月份第 10 个交易日 | M46: 自然人不能持仓进入交割月 | N46: 41992 | P46: ——
C47: 聚乙烯 | D47: l | E47: 5 吨 | F47: 1 元/吨 | G47: 1000 | H47: 1000 | I47: 1-12月 | J47: 1 | K47: 自然人不能持仓进入交割月 | L47: 合约月份第 10 个交易日 | M47: 自然人不能持仓进入交割月 | N47: 39294 | O47: √ | P47: 2022.09.05
C48: 聚乙烯月均价 | D48: l_f | E48: 5 吨 | F48: 1 元/吨 | G48: 1000 | H48: 1000 | I48: 1-12月 | J48: 1 | K48: 无需调整 | L48: 合约月份前一个月的最后1个交易日 | M48: —— | N48: 45959 | O48: √ | P48: 2025.10.29
C49: 聚氯乙烯 | D49: v | E49: 5 吨 | F49: 1 元/吨 | G49: 1000 | H49: 1000 | I49: 1-12月 | J49: 1 | K49: 自然人不能持仓进入交割月 | L49: 合约月份第 10 个交易日 | M49: 自然人不能持仓进入交割月 | N49: 39958 | O49: √ | P49: 2025.03.04
C50: 聚氯乙烯月均价 | D50: v_f | E50: 5 吨 | F50: 1 元/吨 | G50: 1000 | H50: 1000 | I50: 1-12月 | J50: 1 | K50: 无需调整 | L50: 合约月份前一个月的最后1个交易日 | M50: —— | N50: 45959 | O50: √ | P50: 2025.10.29
C51: 聚丙烯 | D51: pp | E51: 5 吨 | F51: 1 元/吨 | G51: 1000 | H51: 1000 | I51: 1-12月 | J51: 1 | K51: 自然人不能持仓进入交割月 | L51: 合约月份第 10 个交易日 | M51: 自然人不能持仓进入交割月 | N51: 41698 | O51: √ | P51: 2025.03.04
C52: 聚丙烯月均价 | D52: pp_f | E52: 5 吨 | F52: 1 元/吨 | G52: 1000 | H52: 1000 | I52: 1-12月 | J52: 1 | K52: 无需调整 | L52: 合约月份前一个月的最后1个交易日 | M52: —— | N52: 45959 | O52: √ | P52: 2025.10.29
C53: 乙二醇 | D53: eg | E53: 10吨 | F53: 1 元/吨 | G53: 1000 | H53: 1000 | I53: 1-12月 | J53: 1 | K53: 自然人不能持仓进入交割月 | L53: 合约月份倒数第4个交易日 | M53: 自然人不能持仓进入交割月 | N53: 43444 | O53: √ | P53: 2025.06.20
C54: 苯乙烯 | D54: eb | E54: 5 吨 | F54: 1 元/吨 | G54: 1000 | H54: 1000 | I54: 1-12月 | J54: 1 | K54: 自然人不能持仓进入交割月 | L54: 合约月份倒数第4个交易日 | M54: 自然人不能持仓进入交割月 | N54: 43734 | O54: √ | P54: 2025.03.04
C55: 液化石油气 | D55: pg | E55: 20吨 | F55: 1 元/吨 | G55: 1000 | H55: 1000 | I55: 1-12月 | J55: 1 | K55: 自然人不能持仓进入交割月 | L55: 合约月份倒数第4个交易日 | M55: 自然人不能持仓进入交割月 | N55: 43920 | O55: √ | P55: 2025.06.20
C56: 粳米 | D56: rr | E56: 10吨 | F56: 1 元/吨 | G56: 1000 | H56: 1000 | I56: 1-12月 | J56: 1 | K56: 自然人不能持仓进入交割月 | L56: 合约月份第 10 个交易日 | M56: 自然人不能持仓进入交割月 | N56: 43693 | P56: ——
C57: 胶合板 | D57: bb | E57: 500张 | F57: 0.05元/张 | G57: 1000 | H57: 1000 | I57: 1-12月， bb2509及后续合约：1,3,5,7,9,11月 | J57: 1 | K57: 自然人不能持仓进入交割月 | L57: 合约月份第 10 个交易日 | M57: 自然人不能持仓进入交割月 | N57: 41614 | P57: ——
C58: 纤维板 | D58: fb | E58: 10立方米 | F58: 0.5元/立方米 | G58: 1000 | H58: 1000 | I58: 1-12月 | J58: 1 | K58: 自然人不能持仓进入交割月 | L58: 合约月份第 10 个交易日 | M58: 自然人不能持仓进入交割月 | N58: 41614 | P58: ——
C59: 原木 | D59: lg | E59: 90立方米 | F59: 0.5元/立方米 | G59: 1000 | H59: 1000 | I59: 1、3、5、7、9、11 月 | J59: 1 | K59: 自然人不能持仓进入交割月 | L59: 合约月份倒数第4个交易日 | M59: 自然人不能持仓进入交割月 | N59: 45614 | P59: ——
C60: 纯苯 | D60: bz | E60: 30吨 | F60: 1 元/吨 | G60: 1000 | H60: 1000 | I60: 1-12月 | J60: 1 | K60: 自然人不能持仓进入交割月 | L60: 合约月份倒数第4个交易日 | M60: 自然人不能持仓进入交割月 | N60: 45846 | P60: ——
C61: 鸡蛋 | D61: jd | E61: 5吨 | F61: 1元/500千克 | G61: 300 | H61: 300 | I61: 1-12月 | J61: 1 | K61: 自然人不能持仓进入交割月 | L61: 合约月份倒数第4个交易日 | M61: 自然人不能持仓进入交割月 | N61: 41586 | P61: ——
C62: 生猪 | D62: lh | E62: 16吨 | F62: 5元/吨 | G62: 50 | H62: 50 | I62: 1、3、5、7、9、11月 | J62: 1 | K62: 自然人不能持仓进入交割月 | L62: 合约月份倒数第4个交易日 | M62: 自然人不能持仓进入交割月 | N62: 44204 | P62: ——
B63: 郑州商品交易所 | C63: 棉花 | D63: CF | E63: 5 吨 | F63: 5元/吨 | G63: 1000 | H63: 200 | I63: 1、3、5、7、9、11月 | J63: 8 | K63: 自然人不能持仓进入交割月 | L63: 合约月份第 10 个交易日 | M63: 自然人不能持仓进入交割月 | N63: 38139 | P63: ——
C64: 棉纱 | D64: CY | E64: 5吨 | F64: 5元/吨 | G64: 1000 | H64: 200 | I64: 1-12月 | J64: 6 | K64: 自然人不能持仓进入交割月 | L64: 合约月份第 10 个交易日 | M64: 自然人不能持仓进入交割月 | N64: 42965 | P64: ——
C65: 白糖 | D65: SR | E65: 10 吨 | F65: 1 元 / 吨 | G65: 1000 | H65: 200 | I65: 1、3、5、7、9、11月 | J65: 1 | K65: 自然人不能持仓进入交割月 | L65: 合约月份第 10 个交易日 | M65: 自然人不能持仓进入交割月 | N65: 38723 | O65: √ | P65: 2022.09.05
C66: PTA | D66: TA | E66: 5 吨 | F66: 2元/吨 | G66: 1000 | H66: 200 | I66: 1-12月 | J66: 1 | K66: 自然人不能持仓进入交割月 | L66: 合约月份第 10 个交易日 | M66: 自然人不能持仓进入交割月 | N66: 39069 | O66: √ | P66: 2022.09.05 | Q66: √
C67: 短纤 | D67: PF | E67: 5 吨 | F67: 2元/吨 | G67: 1000 | H67: 200 | I67: 1-12月 | J67: 1 | K67: 自然人不能持仓进入交割月 | L67: 合约月份第 10 个交易日 | M67: 自然人不能持仓进入交割月 | N67: 44116 | O67: √ | P67: 2022.09.05 | Q67: √
C68: 玻璃 | D68: FG | E68: 20吨 | F68: 1 元/吨 | G68: 1000 | H68: 200 | I68: 1-12月 | J68: 1 | K68: 自然人不能持仓进入交割月 | L68: 合约月份第 10 个交易日 | M68: 自然人不能持仓进入交割月 | N68: 41246 | O68: √ | P68: 2025.06.20
C69: 甲醇 | D69: MA | E69: 10吨 | F69: 1 元/吨 | G69: 1000 | H69: 200 | I69: 1-12月 | J69: 1 | K69: 自然人不能持仓进入交割月 | L69: 合约月份第 10 个交易日 | M69: 自然人不能持仓进入交割月 | N69: 40844 | O69: √ | P69: 2022.09.05
C70: 纯碱 | D70: SA | E70: 20吨 | F70: 1元/吨 | G70: 1000 | H70: 200 | I70: 1-12月 | J70: 1 | K70: 自然人不能持仓进入交割月 | L70: 合约月份第 10 个交易日 | M70: 自然人不能持仓进入交割月 | N70: 43805 | O70: √ | P70: 2025.06.20
C71: 菜籽粕 | D71: RM | E71: 10吨 | F71: 1 元/吨 | G71: 1000 | H71: 200 | I71: 1、3、5、7、8、9、11月 | J71: 1 | K71: 自然人不能持仓进入交割月 | L71: 合约月份第 10 个交易日 | M71: 自然人不能持仓进入交割月 | N71: 41271 | O71: √ | P71: 2025.03.04 | Q71: √
C72: 菜籽油 | D72: OI | E72: 10 吨 | F72: 1元/吨 | G72: 1000 | H72: 200 | I72: 1、3、5、7、9、11月 | J72: 1 | K72: 自然人不能持仓进入交割月 | L72: 合约月份第 10 个交易日 | M72: 自然人不能持仓进入交割月 | N72: 39241 | O72: √ | P72: 2022.09.05 | Q72: √
C73: 动力煤 | D73: ZC | E73: 100吨 | F73: 0.2元/吨 | G73: 50 | H73: 10 | I73: 1-12月 | J73: 200 | K73: 自然人不能持仓进入交割月 | L73: 合约月份第5个交易日 | M73: 自然人不能持仓进入交割月 | N73: 41543 | P73: ——
C74: 强麦 | D74: WH | E74: 20 吨 | F74: 1 元/吨 | G74: 1000 | H74: 200 | I74: 1、3、5、7、9、11月 | J74: 1 | K74: 自然人不能持仓进入交割月 | L74: 合约月份第 10 个交易日 | M74: 自然人不能持仓进入交割月 | N74: 37708 | P74: ——
C75: 普麦 | D75: PM | E75: 50吨 | F75: 1元/吨 | G75: 1000 | H75: 200 | I75: 1、3、5、7、9、11月 | J75: 1 | K75: 自然人不能持仓进入交割月 | L75: 合约月份第 10 个交易日 | M75: 自然人不能持仓进入交割月 | N75: 40925 | P75: ——
C76: 早籼稻 | D76: RI | E76: 20 吨 | F76: 1 元/吨 | G76: 1000 | H76: 200 | I76: 1、3、5、7、9、11月 | J76: 1 | K76: 自然人不能持仓进入交割月 | L76: 合约月份第 10 个交易日 | M76: 自然人不能持仓进入交割月 | N76: 39923 | P76: ——
C77: 晚籼稻 | D77: LR | E77: 20 吨 | F77: 1 元/吨 | G77: 1000 | H77: 200 | I77: 1、3、5、7、9、11月 | J77: 1 | K77: 自然人不能持仓进入交割月 | L77: 合约月份第 10 个交易日 | M77: 自然人不能持仓进入交割月 | N77: 41828 | P77: ——
C78: 粳稻 | D78: JR | E78: 20 吨 | F78: 1 元/吨 | G78: 1000 | H78: 200 | I78: 1、3、5、7、9、11月 | J78: 1 | K78: 自然人不能持仓进入交割月 | L78: 合约月份第 10 个交易日 | M78: 自然人不能持仓进入交割月 | N78: 41596 | P78: ——
C79: 苹果 | D79: AP | E79: 10吨 | F79: 1元/吨 | G79: 1000 | H79: 200 | I79: 1、3、4、5、10、11、12月 | J79: 2 | K79: 自然人不能持仓进入交割月 | L79: 合约月份第 10 个交易日 | M79: 自然人不能持仓进入交割月 | N79: 43091 | P79: ——
C80: 红枣 | D80: CJ | E80: 5吨 | F80: 5元/吨 | G80: 100 | H80: 20 | I80: 1、3、5、7、9、12月 | J80: 1 | K80: 自然人不能持仓进入交割月 | L80: 合约月份第 10 个交易日 | M80: 自然人不能持仓进入交割月 | N80: 43585 | P80: ——
C81: 尿素 | D81: UR | E81: 20吨 | F81: 1元/吨 | G81: 1000 | H81: 200 | I81: 1-12月 | J81: 1 | K81: 自然人不能持仓进入交割月 | L81: 合约月份第 10 个交易日 | M81: 自然人不能持仓进入交割月 | N81: 43686 | P81: ——
C82: 花生 | D82: PK | E82: 5吨 | F82: 2元/吨 | G82: 1000 | H82: 200 | I82: 1、3、4、5、10、11、12月 | J82: 1 | K82: 自然人不能持仓进入交割月 | L82: 合约月份第 10 个交易日 | M82: 自然人不能持仓进入交割月 | N82: 44228 | O82: √ | P82: 2025.03.04 | Q82: √
C83: 油菜籽 | D83: RS | E83: 10吨 | F83: 1 元/吨 | G83: 1000 | H83: 200 | I83: 7、8、9、11月 | J83: 1 | K83: 自然人不能持仓进入交割月 | L83: 合约月份第 10 个交易日 | M83: 自然人不能持仓进入交割月 | N83: 41271 | P83: ——
C84: 锰硅 | D84: SM | E84: 5吨 | F84: 2元/吨 | G84: 1000 | H84: 200 | I84: 1-12月 | J84: 1 | K84: 自然人不能持仓进入交割月 | L84: 合约月份第 10 个交易日 | M84: 自然人不能持仓进入交割月 | N84: 41859 | O84: √ | P84: 2025.03.04
C85: 硅铁 | D85: SF | E85: 5吨 | F85: 2元/吨 | G85: 1000 | H85: 200 | I85: 1-12月 | J85: 1 | K85: 自然人不能持仓进入交割月 | L85: 合约月份第 10 个交易日 | M85: 自然人不能持仓进入交割月 | N85: 41859 | O85: √ | P85: 2025.06.20
C86: 对二甲苯 | D86: PX | E86: 5吨 | F86: 2元/吨 | G86: 1000 | H86: 200 | I86: 1-12月 | J86: 1 | K86: 自然人不能持仓进入交割月 | L86: 合约月份第 10 个交易日 | M86: 自然人不能持仓进入交割月 | N86: 45184 | O86: √ | P86: 2025.03.04 | Q86: √
C87: 烧碱 | D87: SH | E87: 30吨 | F87: 1元/吨 | G87: 1000 | H87: 200 | I87: 1-12月 | J87: 1 | K87: 自然人不能持仓进入交割月 | L87: 合约月份第 10 个交易日 | M87: 自然人不能持仓进入交割月 | N87: 45184 | P87: ——
C88: 瓶片 | D88: PR | E88: 15吨 | F88: 2元/吨 | G88: 1000 | H88: 200 | I88: 1-12月 | J88: 1 | K88: 自然人不能持仓进入交割月 | L88: 合约月份第 10 个交易日 | M88: 自然人不能持仓进入交割月 | N88: 45534 | O88: √ | P88: 2025.03.04 | Q88: √
C89: 丙烯 | D89: PL | E89: 20吨 | F89: 1元/吨 | G89: 1000 | H89: 200 | I89: 1-12月 | J89: 1 | K89: 自然人不能持仓进入交割月 | L89: 合约月份第 10 个交易日 | M89: 自然人不能持仓进入交割月 | N89: 45860 | P89: ——
B90: 广州期货交易所 | C90: 工业硅 | D90: si | E90: 5吨 | F90: 5元/吨 | G90: 1000 | H90: 1000 | I90: 1-12月 | J90: 1 | K90: 自然人不能持仓进入交割月 | L90: 合约月份的第10个交易日 | M90: 自然人不能持仓进入交割月 | N90: 44917 | O90: √ | P90: 2025.03.04
C91: 碳酸锂 | D91: lc | E91: 1吨 | F91: 20元/吨 | G91: 1000 | H91: 1000 | I91: 1-12月 | J91: 1 | K91: 自然人不能持仓进入交割月 | L91: 合约月份的第10个交易日 | M91: 自然人不能持仓进入交割月 | N91: 45128 | O91: √ | P91: 2025.03.04 | Q91: √
C92: 多晶硅 | D92: ps | E92: 3吨 | F92: 5元/吨 | G92: 1000 | H92: 1000 | I92: 1-12月 | J92: 10 | K92: 自然人不能持仓进入交割月 | L92: 合约月份的第10个交易日 | M92: 自然人不能持仓进入交割月 | N92: 45652 | O92: √ | P92: 2025.03.04
C93: 铂 | D93: pt | E93: 1000克 | F93: 0.05元/克 | G93: 1000 | H93: 1000 | I93: 2、4、6、8、10、12月 | J93: 1 | K93: 自然人不能持仓进入交割月 | L93: 合约月份的第10个交易日 | M93: 自然人不能持仓进入交割月 | N93: 45988 | P93: ——
C94: 钯 | D94: pd | E94: 1000克 | F94: 0.05元/克 | G94: 1000 | H94: 1000 | I94: 2、4、6、8、10、12月 | J94: 1 | K94: 自然人不能持仓进入交割月 | L94: 合约月份的第10个交易日 | M94: 自然人不能持仓进入交割月 | N94: 45988 | P94: ——
B95: 小结：截至目前，共91个期货品种，其中8个金融期货品种，1个服务型指数期货品种，82个商品期货品种；各交易所品种分布：中金所：8个；能源中心5个（夜盘4个），上期所20个（夜盘19个）；大商所26个（夜盘21个）；郑商所27个（夜盘15个）；广期所5个。夜盘交易的品种54个。

Sheet 期权合约要素
A1: 点此返回目录
B2: 期权品种合约要素
B3: 交易所 | C3: 品种名称 | D3: 品种代码 | E3: 合约标的 | F3: 夜盘交易时间 | G3: 总保证金比例 | H3: 保证金计算公式 | I3: 涨跌幅度 (标准) | J3: 交易单位 (每手) | K3: 最小变动价位 | L3: 限价指令每次最大下单数量(手) | M3: 市价指令每次最大下单数量(手) | N3: 合约月份 | O3: 最后交易日 | P3: 交收日 | Q3: 行权方式 | R3: 交割方式 | S3: 上市时间 | T3: QFII&RQFII | U3: QFII&RQFII可交易日期 | V3: 国际化品种
B4: 中金所 | C4: 沪深300指数期权 | D4: IO | E4: 沪深300指数 | F4: 无 | G4: 期权卖方交易保证金中涉及的合约保证金调整系数为14%，最低保障系数为0.5 | H4: 看涨期权：（合约结算价×合约乘数）+MAX（标的指数收盘价×合约乘数×12%-虚值额，0.5×标的指数收盘价×合约乘数×12%）； 看跌期权：（合约结算价×合约乘数）+MAX（标的指数收盘价×合约乘数×12%-虚值额，0.5×合约行权价格×合约乘数×12%） | I4: 上一交易日标的指数收盘价的±10% | J4: 100 | K4: 0.2点 | L4: 20 | M4: 无市价 | N4: 当月、下2个月及随后3个季月 | O4: 合约到期月份的第三个星期五 | P4: 同最后交易日 | Q4: 欧式 | R4: 现金 | S4: 43822 | T4: √ | U4: 2022.09.05
C5: 中证1000指数期权 | D5: MO | E5: 中证1000指数 | F5: 无 | J5: 100 | K5: 0.2点 | L5: 20 | M5: 无市价 | N5: 当月、下2个月及随后3个季月 | S5: 44764 | T5: √ | U5: 2022.09.05
C6: 上证50指数期权 | D6: HO | E6: 上证50指数 | F6: 无 | J6: 100 | K6: 0.2点 | L6: 20 | M6: 无市价 | N6: 当月、下2个月及随后3个季月 | S6: 44914 | T6: √ | U6: 2022.12.19
B7: 能源中心 | C7: 原油期权 | D7: sc_o | E7: 原油期货合约 | F7: 21:00-02:30 | G7: 期权卖方交易保证金中涉及标的期货合约的公司交易保证金收取标准为同期货保证金率 | H7: 期权合约结算价×标的期货合约交易单位+MAX[标的期货合约交易所保证金－（1/2）×期权虚值额，（1/2）×标的期货合约交易所保证金] | I7: 与期货合约涨跌停板幅度相同 | J7: 1000桶 | K7: 0.05元/桶 | L7: 100 | M7: 30 | N7: 最近两个连续月份合约，其后月份在标的期货合约结算后持仓量达到一定数值之后的第二个交易日挂牌。具体数值交易所另行发布。 | O7: 标的期货合约交割月前第一月的倒数第13个交易日 | P7: 同最后交易日 | Q7: 美式 | R7: 实物 | S7: 44368 | T7: √ | U7: 2022.09.05 | V7: √
C8: 20号胶期权 | D8: nr_o | E8: 20号胶期货合约 | F8: 21:00-23:00 | J8: 10吨 | K8: 1元/吨 | L8: 100 | M8: 30 | N8: 最近两个连续月份合约，其后月份在标的期货合约结算后持仓量达到一定数值之后的第二个交易日挂盘，具体数值交易所另行发布。 | O8: 标的期货合约交割月前第一月的倒数第五个交易日 | P8: 同最后交易日 | Q8: 美式 | R8: 实物 | S8: 46134 | T8: √ | U8: 2026.4.22 | V8: √
C9: 国际铜期权 | D9: bc_o | E9: 国际铜期货合约 | F9: 21:00-01:00 | J9: 5吨 | K9: 2元/吨 | L9: 100 | M9: 30 | N9: 最近两个连续月份合约，其后月份在标的期货合约结算后持仓量达到一定数值之后的第二个交易日挂盘，具体数值交易所另行发布。 | P9: 同最后交易日 | Q9: 美式 | R9: 实物 | S9: 46134 | T9: √ | U9: 2026.4.22 | V9: √
B10: 上期所 | C10: 铜期权 | D10: cu_o | E10: 铜期货合约 | F10: 21:00-01:00 | J10: 5 吨 | K10: 2元/吨 | L10: 100 | M10: 30 | N10: 1-12月；最近两个连续月份合约，其后月份在标的期货合约结算后持仓量达到一定数值之后的第二个交易日挂牌。具体数值交易所另行发布。 | O10: 标的期货合约交割月份前一个月的倒数第五个交易日 | P10: 同最后交易日 | Q10: 美式 | R10: 实物 | S10: 43364 | T10: √ | U10: 2022.09.05
C11: 天然橡胶期权 | D11: ru_o | E11: 天然橡胶期货合约 | F11: 21:00-23:00 | J11: 10吨 | K11: 1 元/吨 | L11: 100 | M11: 30 | N11: 1、3—11月；最近两个连续月份合约，其后月份在标的期货合约结算后持仓量达到一定数值之后的第二个交易日挂牌。具体数值交易所另行发布。 | S11: 43493 | T11: √ | U11: 2025.06.20
C12: 黄金期权 | D12: au_o | E12: 黄金期货合约 | F12: 21:00-02:30 | J12: 1000 克 | K12: 0.02元/克 | L12: 100 | M12: 30 | N12: 最近两个连续月份合约，其后月份在标的期货合约结算后持仓量达到一定数值之后的第二个交易日挂牌。具体数值交易所另行发布。 | S12: 43819 | T12: √ | U12: 2022.09.05
C13: 铝期权 | D13: al_o | E13: 铝期货合约 | F13: 21:00-01:00 | J13: 5 吨 | K13: 1元/吨 | L13: 100 | M13: 30 | N13: 最近两个连续月份合约，其后月份在标的期货合约结算后持仓量达到一定数值之后的第二个交易日挂牌。合约月份涉及的标的期货持仓量阈值为15000手（单边） | S13: 44053 | T13: √ | U13: 2022.09.05
C14: 锌期权 | D14: zn_o | E14: 锌期货合约 | F14: 21:00-01:00 | J14: 5 吨 | K14: 1元/吨 | L14: 100 | M14: 30 | N14: 最近两个连续月份合约，其后月份在标的期货合约结算后持仓量达到一定数值之后的第二个交易日挂牌。合约月份涉及的标的期货持仓量阈值为10000手（单边） | S14: 44053 | T14: √ | U14: 2022.09.05
C15: 螺纹钢期权 | D15: rb_o | E15: 螺纹钢期货合约 | F15: 21:00-23:00 | J15: 10吨 | K15: 0.5元/吨 | L15: 100 | M15: 30 | N15: 最近两个连续月份合约，其后月份在标的期货合约结算后持仓量达到一定数值之后的第二个交易日挂牌。合约月份涉及的标的期货持仓量阈值为100000手（单边） | S15: 44921 | T15: √ | U15: 2025.03.04
C16: 白银期权 | D16: ag_o | E16: 白银期货合约 | F16: 21:00-02:30 | J16: 15千克 | K16: 0.5元/千克 | L16: 100 | M16: 30 | N16: 最近两个连续月份合约，其后月份在标的期货合约结算后持仓量达到一定数值之后的第二个交易日挂牌。合约月份涉及的标的期货持仓量阈值为20000手（单边） | S16: 44921 | T16: √ | U16: 2025.03.04
C17: 合成橡胶期权 | D17: br_o | E17: 合成橡胶期货合约 | F17: 21:00-23:00 | J17: 5吨 | K17: 1元/吨 | L17: 100 | M17: 30 | N17: 最近两个连续月份合约，其后月份在标的期货合约结算后持仓量达到一定数值之后的第二个交易日挂牌。合约月份涉及的标的期货持仓量阈值为10000手（单边） | S17: 45138 | U17: ——
C18: 铅期权 | D18: pb_o | E18: 铅期货合约 | F18: 21:00-01:00 | J18: 5吨 | K18: 1元/吨 | L18: 100 | M18: 30 | N18: 最近两个连续月份合约，其后月份在标的期货合约结算后持仓量达到一定数值之后的第二个交易日挂牌。合约月份涉及的标的期货持仓量阈值均为10000手（单边） | S18: 45537 | T18: √ | U18: 2025.06.20
C19: 镍期权 | D19: ni_o | E19: 镍期货合约 | F19: 21:00-01:00 | J19: 1吨 | K19: 2元/吨 | L19: 100 | M19: 30 | N19: 最近两个连续月份合约，其后月份在标的期货合约结算后持仓量达到一定数值之后的第二个交易日挂牌。合约月份涉及的标的期货持仓量阈值均为10000手（单边） | S19: 45537 | T19: √ | U19: 2026.04.22 | V19: √
C20: 锡期权 | D20: sn_o | E20: 锡期货合约 | F20: 21:00-01:00 | J20: 1吨 | K20: 2元/吨 | L20: 100 | M20: 30 | N20: 最近两个连续月份合约，其后月份在标的期货合约结算后持仓量达到一定数值之后的第二个交易日挂牌。合约月份涉及的标的期货持仓量阈值均为10000手（单边） | S20: 45537 | T20: √ | U20: 2025.06.20
C21: 氧化铝期权 | D21: ao_o | E21: 氧化铝期货合约 | F21: 21:00-01:00 | J21: 20吨 | K21: 0.5元/吨 | L21: 100 | M21: 30 | N21: 最近两个连续月份合约，其后月份在标的期货合约结算后持仓量达到一定数值之后的第二个交易日挂牌。合约月份涉及的标的期货持仓量阈值均为10000手（单边） | S21: 45537 | U21: ——
C22: 铸造铝合金期权 | D22: ad_o | E22: 铸造铝合金期货合约 | F22: 21:00-01:00 | J22: 10吨 | K22: 1元/吨 | L22: 100 | M22: 30 | N22: 最近两个连续月份合约，其后月份在标的期货合约结算后持仓量达到一定数值之后的第二个交易日挂牌。合约月份涉及的标的期货持仓量阈值均为10000手（单边） | S22: 45819 | U22: ——
C23: 石油沥青期权 | D23: bu_o | E23: 石油沥青期货合约 | F23: 21:00-23:00 | J23: 10吨 | K23: 0.5元/吨 | L23: 100 | M23: 30 | N23: 最近两个连续月份合约，其后月份在标的期货合约结算后持仓量达到一定数值之后的第二个交易日挂牌。合约月份涉及的标的期货持仓量阈值均为50000手（单边） | S23: 45910 | T23: √ | U23: 2025.09.10
C24: 纸浆期权 | D24: sp_o | E24: 纸浆期货合约 | F24: 21:00-23:00 | J24: 10吨 | K24: 1元/吨 | L24: 100 | M24: 30 | N24: 最近两个连续月份合约，其后月份在标的期货合约结算后持仓量达到一定数值之后的第二个交易日挂牌。合约月份涉及的标的期货持仓量阈值均为20000手（单边） | S24: 45910 | T24: √ | U24: 2025.09.10
C25: 胶版印刷纸期权 | D25: op_o | E25: 胶版印刷纸期货合约 | F25: 21:00-23:00 | J25: 40吨 | K25: 1元/吨 | L25: 100 | M25: 30 | N25: 最近两个连续月份合约，其后月份在标的期货合约结算后持仓量达到一定数值之后的第二个交易日挂牌。合约月份涉及的标的期货持仓量阈值均为5000手（单边） | S25: 45910 | U25: ——
C26: 燃料油期权 | D26: fu_o | E26: 燃料油期货合约 | F26: 21:00-23:00 | J26: 10吨 | K26: 0.5元/吨 | L26: 100 | M26: 30 | N26: 最近两个连续月份合约，其后月份在标的期货合约结算后持仓量达到一定数值之后的第二个交易日挂牌。合约月份涉及的标的期货持仓量阈值均为30000手（单边） | O26: 标的期货合约交割月份前一个月的倒数第十个交易日 | S26: 45910 | T26: √ | U26: 2025.09.10
B27: 大商所 | C27: 豆粕期权 | D27: 常规期权：m_o 系列期权： m_MS_o | E27: 豆粕期货合约 | F27: 21:00-23:00 | G27: 期权卖方交易保证金中涉及标的期货合约的公司交易保证金收取标准为同期货保证金率 | H27: 期权合约结算价×标的期货合约交易单位+MAX[标的期货合约交易所保证金－（1/2）×期权虚值额，（1/2）×标的期货合约交易所保证金] | I27: 与期货合约涨跌停板幅度相同 | J27: 10 吨 | K27: 0.5元/吨 | L27: 1000 | M27: 无市价 | N27: 1、3、5、7、8、9、11、12月 | O27: 常规期权：标的期货合约交割月份前一个月的第12个交易日； 系列期权：标的期货合约交割月份前两个月的第12个交易日 | P27: 同最后交易日 | Q27: 美式 | R27: 实物 | S27: 常规期权：2017/3/31 系列期权： 2026/2/2 | T27: √ | U27: 2022.09.05 | V27: √
C28: 玉米期权 | D28: 常规期权：c_o 系列期权：c_MS_o | E28: 玉米期货合约 | F28: 21:00-23:00 | J28: 10 吨 | K28: 0.5元/吨 | L28: 2000 | M28: 无市价 | N28: 1、3、5、7、9、11月 | S28: 常规期权：2019/1/28 系列期权： 2026/2/2 | U28: ——
C29: 铁矿石期权 | D29: i_o | E29: 铁矿石期货合约 | F29: 21:00-23:00 | J29: 100吨 | K29: 0.1元/吨 | L29: 1000 | M29: 无市价 | N29: 1-12月 | O29: 标的期货合约交割月份前一个月的第12个交易日 | S29: 43808 | T29: √ | U29: 2022.09.05
C30: 液化石油气期权 | D30: pg_o | E30: 液化石油气期货合约 | F30: 21:00-23:00 | J30: 20吨 | K30: 0.2元/吨 | L30: 1000 | M30: 无市价 | N30: 1-12月 | S30: 43920 | T30: √ | U30: 2025.06.20
C31: 聚丙烯期权 | D31: pp_o | E31: 聚丙烯期货合约 | F31: 21:00-23:00 | J31: 5吨 | K31: 0.5元/吨 | L31: 1000 | M31: 无市价 | N31: 1-12月 | S31: 44018 | T31: √ | U31: 2025.03.04
C32: 聚氯乙烯期权 | D32: v_o | E32: 聚氯乙烯期货合约 | F32: 21:00-23:00 | J32: 5吨 | K32: 0.5元/吨 | L32: 1000 | M32: 无市价 | N32: 1-12月 | S32: 44018 | T32: √ | U32: 2025.03.04
C33: 聚乙烯期权 | D33: l_o | E33: 聚乙烯期货合约 | F33: 21:00-23:00 | J33: 5吨 | K33: 0.5元/吨 | L33: 1000 | M33: 无市价 | N33: 1-12月 | S33: 44018 | T33: √ | U33: 2022.09.05
C34: 棕榈油期权 | D34: p_o | E34: 棕榈油期货合约 | F34: 21:00-23:00 | J34: 10吨 | K34: 0.5元/吨 | L34: 1000 | M34: 无市价 | N34: 1-12月 | S34: 44365 | T34: √ | U34: 2022.09.05 | V34: √
C35: 黄大豆1号期权 | D35: 常规期权：a_o 系列期权：a_MS_o | E35: 黄大豆1号期货合约 | F35: 21:00-23:00 | J35: 10吨 | K35: 0.5元/吨 | L35: 1000 | M35: 无市价 | N35: 1、3、5、7、9、11 月 | O35: 常规期权：标的期货合约交割月份前一个月的第12个交易日； 系列期权：标的期货合约交割月份前两个月的第12个交易日。 | S35: 44781 | T35: √ | U35: 2022.09.05 | V35: √
C36: 黄大豆2号期权 | D36: b_o | E36: 黄大豆2号期货合约 | F36: 21:00-23:00 | J36: 10吨 | K36: 0.5元/吨 | L36: 1000 | M36: 无市价 | N36: 1-12月 | O36: 标的期货合约交割月份前一个月的第12个交易日 | S36: 44781 | T36: √ | U36: 2022.09.05 | V36: √
C37: 豆油期权 | D37: 常规期权：y_o 系列期权：y_MS_o | E37: 豆油期货合约 | F37: 21:00-23:00 | J37: 10吨 | K37: 0.5元/吨 | L37: 1000 | M37: 无市价 | N37: 常规期权：1、3、5、7、8、9、11、12月 系列期权：3、5、7、11月 | O37: 常规期权：标的期货合约交割月份前一个月的第12个交易日； 系列期权：标的期货合约交割月份前两个月的第12个交易日 | S37: 44781 | T37: √ | U37: 2022.09.05 | V37: √
C38: 乙二醇期权 | D38: eg_o | E38: 乙二醇期货合约 | F38: 21:00-23:00 | J38: 10吨 | K38: 0.5元/吨 | L38: 1000 | M38: 无市价 | N38: 1-12月 | O38: 标的期货合约交割月份前一个月的第12个交易日 | S38: 45061 | T38: √ | U38: 2025.06.20
C39: 苯乙烯期权 | D39: eb_o | E39: 苯乙烯期货合约 | F39: 21:00-23:00 | J39: 5吨 | K39: 0.5元/吨 | L39: 1000 | M39: 无市价 | N39: 1-12月 | S39: 45061 | T39: √ | U39: 2025.03.04
C40: 鸡蛋期权 | D40: jd_o | E40: 鸡蛋期货合约 | F40: 无 | J40: 5吨 | K40: 0.5元/500千克 | L40: 300 | M40: 无市价 | N40: 1-12月 | S40: 45527 | U40: ——
C41: 生猪期权 | D41: lh_o | E41: 生猪期货合约 | F41: 无 | J41: 16吨 | K41: 2.5元/吨 | L41: 50 | M41: 无市价 | N41: 1、3、5、7、9、11月 | S41: 45527 | U41: ——
C42: 玉米淀粉期权 | D42: cs_o | E42: 玉米淀粉期货合约 | F42: 21:00-23:00 | J42: 10吨 | K42: 0.5元/吨 | L42: 1000 | M42: 无市价 | N42: 1、3、5、7、9、11月 | S42: 45527 | U42: ——
C43: 原木期权 | D43: lg_o | E43: 原木期货合约 | F43: 无 | J43: 90立方米 | K43: 0.25元/立方米 | L43: 1000 | M43: 无市价 | N43: 1、3、5、7、9、11月 | S43: 45615 | U43: ——
C44: 纯苯期权 | D44: bz_o | E44: 纯苯期货合约 | F44: 21:00-23:00 | J44: 30吨 | K44: 0.5元/吨 | L44: 1000 | M44: 无市价 | N44: 1-12月 | S44: 45847 | U44: ——
C45: 焦煤期权 | D45: jm_o | E45: 焦煤期货合约 | F45: 21:00-23:00 | J45: 60吨 | K45: 0.1元/吨 | L45: 1000 | M45: 无市价 | N45: 1-12月 | S45: 46038 | U45: ——
B46: 郑商所 | C46: 白糖期权 | D46: 常规期权：SRC/SRP 系列期权： SRMSC/SRMSP | E46: 白糖期货合约 | F46: 21:00-23:00 | G46: 期权卖方交易保证金中涉及标的期货合约的公司交易保证金收取标准为同期货保证金率 | H46: 期权合约结算价×标的期货合约交易单位+MAX[标的期货合约交易所保证金－（1/2）×期权虚值额，（1/2）×标的期货合约交易所保证金] | I46: 与期货合约涨跌停板幅度相同 | J46: 10 吨 | K46: 0.5元/吨 | L46: 200 | M46: 5 | N46: 标的期货合约中常规期权：标的期货合约中的连续两个近月，其后月份在标的期货合约结算后持仓量达到5000手（单边）之后的第二个交易日挂牌 系列期权：在标的期货合约交割月份前四个月第一个交易日挂牌的连续两个近月，其后月份在标的期货合约结算后持仓量达到 5000 手（单边）之后的第二个交易日挂牌 | O46: 常规期权：标的期货合约交割月份前一个月第15个日历日之前（含该日）的倒数第3个交易日，以及交易所规定的其他日期 系列期权：标的期货合约交割月份前两个月第15个日历日之前（含该日）的倒数第3个交易日，以及交易所规定的其他日期 | P46: 同最后交易日 | Q46: 美式 | R46: 实物 | S46: 常规期权：2017/4/19 系列期权： 2025/3/3 | T46: √ | U46: 2022.09.05
C47: 棉花期权 | D47: CFC/CFP | E47: 棉花期货合约 | F47: 21:00-23:00 | J47: 5吨 | K47: 1元/吨 | L47: 200 | M47: 5 | N47: 标的期货合约中的连续两个近月，其后月份在标的期货合约结算后持仓量达到5000手（单边）之后的第二个交易日挂牌 | O47: 标的期货合约交割月份前一个月第15个日历日之前（含该日）的倒数第3个交易日 | S47: 43493 | U47: ——
C48: PTA期权 | D48: TAC/TAP | E48: PTA期货合约 | F48: 21:00-23:00 | J48: 5吨 | K48: 0.5元/吨 | L48: 200 | M48: 5 | N48: 标的期货合约中的连续两个近月，其后月份在标的期货合约结算后持仓量达到10000手（单边）之后的第二个交易日挂牌 | S48: 43815 | T48: √ | U48: 2022.09.05 | V48: √
C49: 甲醇期权 | D49: MAC/MAP | E49: 甲醇期货合约 | F49: 21:00-23:00 | J49: 10吨 | K49: 0.5元/吨 | L49: 200 | M49: 5 | N49: 标的期货合约中的连续两个近月，其后月份在标的期货合约结算后持仓量达到10000手（单边）之后的第二个交易日挂牌 | S49: 43815 | T49: √ | U49: 2022.09.05
C50: 菜籽粕期权 | D50: RMC/RMP | E50: 菜籽粕期货合约 | F50: 21:00-23:00 | J50: 10吨 | K50: 0.5元/吨 | L50: 200 | M50: 5 | N50: 标的期货合约中的连续两个近月，其后月份在标的期货合约结算后持仓量达到5000手（单边）之后的第二个交易日挂牌 | S50: 43846 | T50: √ | U50: 2025.03.04 | V50: √
C51: 菜籽油期权 | D51: OIC/OIP | E51: 菜籽油期货合约 | F51: 21:00-23:00 | J51: 10吨 | K51: 0.5元/吨 | L51: 200 | M51: 5 | N51: 标的期货合约中的连续两个近月，其后月份在标的期货合约结算后持仓量达到5000手（单边）之后的第二个交易日挂牌 | S51: 44799 | T51: √ | U51: 2022.09.05 | V51: √
C52: 花生期权 | D52: PKC/PKP | E52: 花生期货合约 | F52: 无夜盘 | J52: 5吨 | K52: 0.5元/吨 | L52: 200 | M52: 5 | N52: 标的期货合约中的连续两个近月，其后月份在标的期货合约结算后持仓量达到5000手（单边）之后的第二个交易日挂牌 | S52: 44799 | T52: √ | U52: 2025.03.04 | V52: √
C53: 动力煤期权 | D53: ZCC/ZCP | E53: 动力煤期货合约 | F53: 21:00-23:00 | J53: 100吨 | K53: 0.1元/吨 | L53: 200 | M53: 5 | N53: 标的期货合约中的连续两个近月，其后月份在标的期货合约结算后持仓量达到10000手（单边）之后的第二个交易日挂牌 | S53: 44012 | U53: ——
C54: 烧碱期权 | D54: SHC/SHP | E54: 烧碱期货合约 | F54: 21:00-23:00 | J54: 30吨 | K54: 0.5元/吨 | L54: 200 | M54: 5 | N54: 标的期货合约中的连续两个近月，其后月份在标的期货合约结算后持仓量达到10000手（单边）之后的第二个交易日挂牌 | S54: 45187 | U54: ——
C55: 短纤期权 | D55: PFC/PFP | E55: 短纤期货合约 | F55: 21:00-23:00 | J55: 5吨 | K55: 0.5元/吨 | L55: 200 | M55: 5 | N55: 标的期货合约中的连续两个近月，其后月份在标的期货合约结算后持仓量达到10000手（单边）之后的第二个交易日挂牌 | S55: 45219 | T55: √ | U55: 2025.03.04 | V55: √
C56: 纯碱期权 | D56: SAC/SAP | E56: 纯碱期货合约 | F56: 21:00-23:00 | J56: 20吨 | K56: 0.5元/吨 | L56: 200 | M56: 5 | N56: 标的期货合约中的连续两个近月，其后月份在标的期货合约结算后持仓量达到10000手（单边）之后的第二个交易日挂牌 | S56: 45219 | T56: √ | U56: 2025.06.20
C57: 锰硅期权 | D57: SMC/SMP | E57: 锰硅期货合约 | F57: 无夜盘 | J57: 5吨 | K57: 1元/吨 | L57: 200 | M57: 5 | N57: 标的期货合约中的连续两个近月，其后月份在标的期货合约结算后持仓量达到5000手（单边）之后的第二个交易日挂牌 | S57: 45219 | T57: √ | U57: 2025.03.04
C58: 硅铁期权 | D58: SFC/SFP | E58: 硅铁期货合约 | F58: 无夜盘 | J58: 5吨 | K58: 1元/吨 | L58: 200 | M58: 5 | N58: 标的期货合约中的连续两个近月，其后月份在标的期货合约结算后持仓量达到5000手（单边）之后的第二个交易日挂牌 | S58: 45219 | T58: √ | U58: 2025.06.20
C59: 尿素期权 | D59: URC/URP | E59: 尿素期货合约 | F59: 无夜盘 | J59: 20吨 | K59: 0.5元/吨 | L59: 200 | M59: 5 | N59: 标的期货合约中的连续两个近月，其后月份在标的期货合约结算后持仓量达到10000手（单边）之后的第二个交易日挂牌 | S59: 45219 | U59: ——
C60: 玻璃期权 | D60: FGC/FGP | E60: 玻璃期货合约 | F60: 21:00-23:00 | J60: 20吨 | K60: 0.5元/吨 | L60: 200 | M60: 5 | N60: 标的期货合约中的连续两个近月，其后月份在标的期货合约结算后持仓量达到10000手（单边）之后的第二个交易日挂牌 | S60: 45464 | T60: √ | U60: 2025.06.20
C61: 瓶片期权 | D61: PRC/PRP | E61: 瓶片期货合约 | F61: 21:00-23:00 | J61: 15吨 | K61: 0.5元/吨 | L61: 200 | M61: 5 | N61: 标的期货合约中的连续两个近月，其后月份在标的期货合约结算后持仓量达到3000手（单边）之后的第二个交易日挂牌 | S61: 45653 | T61: √ | U61: 2025.03.04 | V61: √
C62: 丙烯期权 | D62: PLC/PLP | E62: 丙烯期货合约 | F62: 21:00-23:00 | J62: 20吨 | K62: 0.5元/吨 | L62: 200 | M62: 5 | N62: 标的期货合约中的连续两个近月，其后月份在标的期货合约结算后持仓量达到10000手（单边）之后的第二个交易日挂牌 | S62: 45861 | U62: ——
C63: 对二甲苯期权 | D63: PXC/PXP | E63: 对二甲苯期货合约 | F63: 21:00-23:00 | J63: 5吨 | K63: 0.5元/吨 | L63: 200 | M63: 5 | N63: 标的期货合约中的连续两个近月，其后月份在标的期货合约结算后持仓量达到10000手（单边）之后的第二个交易日挂牌 | O63: 标的期货合约交割月份前两个月最后一个日历日之前(含该日)的倒数第3个交易日 | S63: 45187 | T63: √ | U63: 2025.03.04 | V63: √
C64: 苹果期权 | D64: APC/APP | E64: 苹果期货合约 | F64: 无夜盘 | J64: 10吨 | K64: 0.5元/吨 | L64: 200 | M64: 5 | N64: 标的期货合约中的连续两个近月，其后月份在标的期货合约结算后持仓量达到5000手（单边）之后的第二个交易日挂牌 | S64: 45219 | U64: ——
C65: 红枣期权 | D65: CJC/CJP | E65: 红枣期货合约 | F65: 无夜盘 | J65: 5吨 | K65: 1元/吨 | L65: 200 | M65: 5 | N65: 标的期货合约中的连续两个近月，其后月份在标的期货合约结算后持仓量达到5000手（单边）之后的第二个交易日挂牌 | S65: 45464 | U65: ——
B66: 广期所 | C66: 工业硅期权 | D66: si_o | E66: 工业硅期货合约 | F66: 无 | G66: 期权卖方交易保证金中涉及标的期货合约的公司交易保证金收取标准为同期货保证金率 | H66: 期权合约结算价×标的期货合约交易单位+MAX[标的期货合约交易所保证金－（1/2）×期权虚值额，（1/2）×标的期货合约交易所保证金] | I66: 与期货合约涨跌停板幅度相同 | J66: 5吨 | K66: 1元/吨 | L66: 100 | M66: 无市价 | N66: 1-12月 | O66: 标的期货合约交割月份前一个月的第5个交易日 | P66: 同最后交易日 | Q66: 美式 | R66: 实物 | S66: 44918 | T66: √ | U66: 2025.03.04
C67: 碳酸锂期权 | D67: lc_o | E67: 碳酸锂期货合约 | J67: 1吨 | K67: 10元/吨 | L67: 100 | M67: 无市价 | N67: 1-12月 | S67: 45131 | T67: √ | U67: 2025.03.04 | V67: √
C68: 多晶硅期权 | D68: ps_o | E68: 多晶硅期货合约 | J68: 3吨 | K68: 1元/吨 | L68: 100 | M68: 无市价 | N68: 1-12月 | S68: 45653 | T68: √ | U68: 2025.03.04
C69: 铂期权 | D69: pt_o | E69: 铂期货合约 | J69: 1000 克 | K69: 0.05元/克 | L69: 100 | M69: 无市价 | N69: 2、4、6、8、10、12月 | S69: 45989
C70: 钯期权 | D70: pd_o | E70: 钯期货合约 | J70: 1000 克 | K70: 0.05元/克 | L70: 100 | M70: 无市价 | N70: 2、4、6、8、10、12月 | S70: 45989
B71: 上交所 | C71: 上证50ETF期权 | E71: 510050 | F71: 无 | G71: 1.2*交易所保证金 | H71: 认购期权：[合约结算价+Max（12%×合约标的收盘价-认购期权虚值，7%×合约标的收盘价）]×合约单位； 认沽期权：Min[合约结算价+Max（12%×合约标的收盘价-认沽期权虚值，7%×行权价格），行权价格] ×合约单位 | I71: 见交易所网站 | J71: 10000份 | K71: 0.0001 | L71: 50 | M71: 10 | N71: 当月、下月及随后两个季月 | O71: 到期月份的第四个星期三（遇法定节假日顺延） | P71: 行权日次一交易日 | Q71: 欧式 | R71: 实物 | S71: 42044
C72: 沪深300ETF期权 | E72: 510300 | J72: 10000份 | K72: 0.0001 | L72: 50 | M72: 10 | N72: 当月、下月及随后两个季月 | S72: 43822
C73: 中证500ETF期权 | E73: 510500 | J73: 10000份 | K73: 0.0001 | L73: 50 | M73: 10 | N73: 当月、下月及随后两个季月 | S73: 44823
C74: 华夏科创50ETF期权 | E74: 588000 | J74: 10000份 | K74: 0.0001 | L74: 50 | M74: 10 | N74: 当月、下月及随后两个季月 | S74: 45082
C75: 易方达科创50ETF期权 | E75: 588080 | J75: 10000份 | K75: 0.0001 | L75: 50 | M75: 10 | N75: 当月、下月及随后两个季月 | S75: 45082
B76: 深交所 | C76: 沪深300ETF期权 | E76: 159919 | F76: 无 | G76: 1.2*交易所保证金 | J76: 10000份 | K76: 0.0001 | L76: 50 | M76: 10 | N76: 当月、下月及随后两个季月 | O76: 到期月份的第四个星期三（遇法定节假日顺延） | P76: 行权日次一交易日 | Q76: 欧式 | R76: 实物 | S76: 43822
C77: 创业板ETF期权 | E77: 159915 | J77: 10000份 | K77: 0.0001 | L77: 50 | M77: 10 | N77: 当月、下月及随后两个季月 | S77: 44823
C78: 中证500ETF期权 | E78: 159922 | J78: 10000份 | K78: 0.0001 | L78: 50 | M78: 10 | N78: 当月、下月及随后两个季月 | S78: 44823
C79: 深证100ETF期权 | E79: 159901 | J79: 10000份 | K79: 0.0001 | L79: 50 | M79: 10 | N79: 当月、下月及随后两个季月 | S79: 44907
B80: 小结：截至目前，共74个期权品种，其中3个金融指数期权品种，61个商品期货期权品种，9个ETF期权品种；各交易所品种分布：中金所：3个；能源中心1个（夜盘1个），上期所17个（夜盘17个），大商所18个（夜盘15个），郑商所20个（夜盘14个），广期所5个，上交所5个，深交所4个。夜盘交易的品种合计47个。

Sheet 保证金及涨跌停板幅度表
A1: 点此返回目录
B2: 期货品种保证金标准及涨跌停板幅度表
B3: 交易所 | C3: 品种名称 | D3: 品种代码 | E3: 合约单位 | F3: 公司加收 | G3: 按连续单边市调整的交易所保证金率 | M3: 连续单边市涨跌停板 | P3: 按时间梯度调整的交易所保证金率 | V3: QFII&RQFII | W3: 国际化品种
G4: 投机 | J4: 套保 | P4: 交割月前1个月 | R4: 交割月份
G5: 一般月份 | H5: 第一个单边市结算时 | I5: 第二个同方向单边市结算时 | J5: 一般月份 | K5: 第一个单边市结算时 | L5: 第二个同方向单边市结算时 | M5: 一般月份 | N5: 第一个单边市结算后 | O5: 第二个同方向单边市结算后 | P5: 第1个交易日起 （投机） | Q5: 第1个交易日起 （套保） | R5: 第1个交易日起 （投机） | S5: 第1个交易日起 （套保） | T5: 最后交易日前2个交易日起 （投机） | U5: 最后交易日前2个交易日起 （套保）
B6: 上海期货交易所 | C6: 螺纹钢 | D6: rb | E6: 10吨 | F6: 0.06 | G6: 0.07 | H6: =MAX(G6,N6+2%) -> 0.1 | I6: =MAX(G6,O6+2%) -> 0.12 | J6: 0.06 | K6: =MAX(J6,N6+2%) -> 0.1 | L6: =MAX(J6,O6+2%) -> 0.12 | M6: 0.05 | N6: =M6+3% -> 0.08 | O6: =N6+2% -> 0.1 | P6: =MAX(10%,G6) -> 0.1 | Q6: =MAX(10%,J6) -> 0.1 | R6: =MAX(15%,G6) -> 0.15 | S6: =MAX(15%,J6) -> 0.15 | T6: =MAX(20%,G6) -> 0.2 | U6: =MAX(J6,20%) -> 0.2 | V6: =IFERROR(IF(VLOOKUP(D6,期货合约要素!$D:$Q,12,0)=0,"",VLOOKUP(D6,期货合约要素!$D:$Q,12,0)),IF(VLOOKUP(D6,期权合约要素!$D:$V,17,0)=0,"",VLOOKUP(D6,期权合约要素!$D:$V,17,0))) -> √ | W6: =IFERROR(IF(VLOOKUP(D6,期货合约要素!$D:$Q,14,0)=0,"",VLOOKUP(D6,期货合约要素!$D:$Q,14,0)),IF(VLOOKUP(D6,期权合约要素!$D:$V,19,0)=0,"",VLOOKUP(D6,期权合约要素!$D:$V,19,0)))
C7: 热轧卷板 | D7: hc | E7: 10吨 | F7: 0.06 | G7: 0.07 | H7: =MAX(G7,N7+2%) -> 0.1 | I7: =MAX(G7,O7+2%) -> 0.12 | J7: 0.06 | K7: =MAX(J7,N7+2%) -> 0.1 | L7: =MAX(J7,O7+2%) -> 0.12 | M7: 0.05 | N7: =M7+3% -> 0.08 | O7: =N7+2% -> 0.1 | P7: =MAX(10%,G7) -> 0.1 | Q7: =MAX(10%,J7) -> 0.1 | R7: =MAX(15%,G7) -> 0.15 | S7: =MAX(15%,J7) -> 0.15 | T7: =MAX(20%,G7) -> 0.2 | U7: =MAX(J7,20%) -> 0.2 | V7: =IFERROR(IF(VLOOKUP(D7,期货合约要素!$D:$Q,12,0)=0,"",VLOOKUP(D7,期货合约要素!$D:$Q,12,0)),IF(VLOOKUP(D7,期权合约要素!$D:$V,17,0)=0,"",VLOOKUP(D7,期权合约要素!$D:$V,17,0))) -> √ | W7: =IFERROR(IF(VLOOKUP(D7,期货合约要素!$D:$Q,14,0)=0,"",VLOOKUP(D7,期货合约要素!$D:$Q,14,0)),IF(VLOOKUP(D7,期权合约要素!$D:$V,19,0)=0,"",VLOOKUP(D7,期权合约要素!$D:$V,19,0)))
C8: 线材 | D8: wr | E8: 10吨 | F8: 0.06 | G8: 0.09 | H8: =MAX(G8,N8+2%) -> 0.12 | I8: =MAX(G8,O8+2%) -> 0.14 | J8: 0.08 | K8: =MAX(J8,N8+2%) -> 0.12 | L8: =MAX(J8,O8+2%) -> 0.14 | M8: 0.07 | N8: =M8+3% -> 0.1 | O8: =N8+2% -> 0.12 | P8: =MAX(10%,G8) -> 0.1 | Q8: =MAX(10%,J8) -> 0.1 | R8: =MAX(15%,G8) -> 0.15 | S8: =MAX(15%,J8) -> 0.15 | T8: =MAX(20%,G8) -> 0.2 | U8: =MAX(J8,20%) -> 0.2 | V8: =IFERROR(IF(VLOOKUP(D8,期货合约要素!$D:$Q,12,0)=0,"",VLOOKUP(D8,期货合约要素!$D:$Q,12,0)),IF(VLOOKUP(D8,期权合约要素!$D:$V,17,0)=0,"",VLOOKUP(D8,期权合约要素!$D:$V,17,0))) | W8: =IFERROR(IF(VLOOKUP(D8,期货合约要素!$D:$Q,14,0)=0,"",VLOOKUP(D8,期货合约要素!$D:$Q,14,0)),IF(VLOOKUP(D8,期权合约要素!$D:$V,19,0)=0,"",VLOOKUP(D8,期权合约要素!$D:$V,19,0)))
C9: 线材 wr2607-wr2702合约 | G9: 0.1 | H9: =MAX(G9,N9+2%) -> 0.13 | I9: =MAX(G9,O9+2%) -> 0.15 | J9: 0.09 | K9: =MAX(J9,N9+2%) -> 0.13 | L9: =MAX(J9,O9+2%) -> 0.15 | M9: 0.08 | N9: =M9+3% -> 0.11 | O9: =N9+2% -> 0.13 | P9: =MAX(10%,G9) -> 0.1 | Q9: =MAX(10%,J9) -> 0.1 | R9: =MAX(15%,G9) -> 0.15 | S9: =MAX(15%,J9) -> 0.15 | T9: =MAX(20%,G9) -> 0.2 | U9: =MAX(J9,20%) -> 0.2
C10: 铜 | D10: cu | E10: 5吨 | F10: 0.07 | G10: 0.09 | H10: =MAX(G10,N10+2%) -> 0.12 | I10: =MAX(G10,O10+2%) -> 0.14 | J10: 0.08 | K10: =MAX(J10,N10+2%) -> 0.12 | L10: =MAX(J10,O10+2%) -> 0.14 | M10: 0.07 | N10: =M10+3% -> 0.1 | O10: =N10+2% -> 0.12 | P10: =MAX(10%,G10) -> 0.1 | Q10: =MAX(10%,J10) -> 0.1 | R10: =MAX(15%,G10) -> 0.15 | S10: =MAX(15%,J10) -> 0.15 | T10: =MAX(20%,G10) -> 0.2 | U10: =MAX(J10,20%) -> 0.2 | V10: =IFERROR(IF(VLOOKUP(D10,期货合约要素!$D:$Q,12,0)=0,"",VLOOKUP(D10,期货合约要素!$D:$Q,12,0)),IF(VLOOKUP(D10,期权合约要素!$D:$V,17,0)=0,"",VLOOKUP(D10,期权合约要素!$D:$V,17,0))) -> √ | W10: =IFERROR(IF(VLOOKUP(D10,期货合约要素!$D:$Q,14,0)=0,"",VLOOKUP(D10,期货合约要素!$D:$Q,14,0)),IF(VLOOKUP(D10,期权合约要素!$D:$V,19,0)=0,"",VLOOKUP(D10,期权合约要素!$D:$V,19,0)))
C11: 铜 cu2607-cu2702合约 | G11: 0.11 | H11: =MAX(G11,N11+2%) -> 0.14 | I11: =MAX(G11,O11+2%) -> 0.16 | J11: 0.1 | K11: =MAX(J11,N11+2%) -> 0.14 | L11: =MAX(J11,O11+2%) -> 0.16 | M11: 0.09 | N11: =M11+3% -> 0.12 | O11: =N11+2% -> 0.14 | P11: =MAX(10%,G11) -> 0.11 | Q11: =MAX(10%,J11) -> 0.1 | R11: =MAX(15%,G11) -> 0.15 | S11: =MAX(15%,J11) -> 0.15 | T11: =MAX(20%,G11) -> 0.2 | U11: =MAX(J11,20%) -> 0.2
C12: 铝 | D12: al | E12: 5吨 | F12: 0.07 | G12: 0.09 | H12: =MAX(G12,N12+2%) -> 0.12 | I12: =MAX(G12,O12+2%) -> 0.14 | J12: 0.08 | K12: =MAX(J12,N12+2%) -> 0.12 | L12: =MAX(J12,O12+2%) -> 0.14 | M12: 0.07 | N12: =M12+3% -> 0.1 | O12: =N12+2% -> 0.12 | P12: =MAX(10%,G12) -> 0.1 | Q12: =MAX(10%,J12) -> 0.1 | R12: =MAX(15%,G12) -> 0.15 | S12: =MAX(15%,J12) -> 0.15 | T12: =MAX(20%,G12) -> 0.2 | U12: =MAX(J12,20%) -> 0.2 | V12: =IFERROR(IF(VLOOKUP(D12,期货合约要素!$D:$Q,12,0)=0,"",VLOOKUP(D12,期货合约要素!$D:$Q,12,0)),IF(VLOOKUP(D12,期权合约要素!$D:$V,17,0)=0,"",VLOOKUP(D12,期权合约要素!$D:$V,17,0))) -> √ | W12: =IFERROR(IF(VLOOKUP(D12,期货合约要素!$D:$Q,14,0)=0,"",VLOOKUP(D12,期货合约要素!$D:$Q,14,0)),IF(VLOOKUP(D12,期权合约要素!$D:$V,19,0)=0,"",VLOOKUP(D12,期权合约要素!$D:$V,19,0)))
C13: 铝 al2607-al2702合约 | G13: 0.11 | H13: =MAX(G13,N13+2%) -> 0.14 | I13: =MAX(G13,O13+2%) -> 0.16 | J13: 0.1 | K13: =MAX(J13,N13+2%) -> 0.14 | L13: =MAX(J13,O13+2%) -> 0.16 | M13: 0.09 | N13: =M13+3% -> 0.12 | O13: =N13+2% -> 0.14 | P13: =MAX(10%,G13) -> 0.11 | Q13: =MAX(10%,J13) -> 0.1 | R13: =MAX(15%,G13) -> 0.15 | S13: =MAX(15%,J13) -> 0.15 | T13: =MAX(20%,G13) -> 0.2 | U13: =MAX(J13,20%) -> 0.2
C14: 锌 | D14: zn | E14: 5吨 | F14: 0.07 | G14: 0.09 | H14: =MAX(G14,N14+2%) -> 0.12 | I14: =MAX(G14,O14+2%) -> 0.14 | J14: 0.08 | K14: =MAX(J14,N14+2%) -> 0.12 | L14: =MAX(J14,O14+2%) -> 0.14 | M14: 0.07 | N14: =M14+3% -> 0.1 | O14: =N14+2% -> 0.12 | P14: =MAX(10%,G14) -> 0.1 | Q14: =MAX(10%,J14) -> 0.1 | R14: =MAX(15%,G14) -> 0.15 | S14: =MAX(15%,J14) -> 0.15 | T14: =MAX(20%,G14) -> 0.2 | U14: =MAX(J14,20%) -> 0.2 | V14: =IFERROR(IF(VLOOKUP(D14,期货合约要素!$D:$Q,12,0)=0,"",VLOOKUP(D14,期货合约要素!$D:$Q,12,0)),IF(VLOOKUP(D14,期权合约要素!$D:$V,17,0)=0,"",VLOOKUP(D14,期权合约要素!$D:$V,17,0))) -> √ | W14: =IFERROR(IF(VLOOKUP(D14,期货合约要素!$D:$Q,14,0)=0,"",VLOOKUP(D14,期货合约要素!$D:$Q,14,0)),IF(VLOOKUP(D14,期权合约要素!$D:$V,19,0)=0,"",VLOOKUP(D14,期权合约要素!$D:$V,19,0)))
C15: 锌 zn2607-zn2702合约 | G15: 0.11 | H15: =MAX(G15,N15+2%) -> 0.14 | I15: =MAX(G15,O15+2%) -> 0.16 | J15: 0.1 | K15: =MAX(J15,N15+2%) -> 0.14 | L15: =MAX(J15,O15+2%) -> 0.16 | M15: 0.09 | N15: =M15+3% -> 0.12 | O15: =N15+2% -> 0.14 | P15: =MAX(10%,G15) -> 0.11 | Q15: =MAX(10%,J15) -> 0.1 | R15: =MAX(15%,G15) -> 0.15 | S15: =MAX(15%,J15) -> 0.15 | T15: =MAX(20%,G15) -> 0.2 | U15: =MAX(J15,20%) -> 0.2
C16: 铅 | D16: pb | E16: 5吨 | F16: 0.07 | G16: 0.09 | H16: =MAX(G16,N16+2%) -> 0.12 | I16: =MAX(G16,O16+2%) -> 0.14 | J16: 0.08 | K16: =MAX(J16,N16+2%) -> 0.12 | L16: =MAX(J16,O16+2%) -> 0.14 | M16: 0.07 | N16: =M16+3% -> 0.1 | O16: =N16+2% -> 0.12 | P16: =MAX(10%,G16) -> 0.1 | Q16: =MAX(10%,J16) -> 0.1 | R16: =MAX(15%,G16) -> 0.15 | S16: =MAX(15%,J16) -> 0.15 | T16: =MAX(20%,G16) -> 0.2 | U16: =MAX(J16,20%) -> 0.2 | V16: =IFERROR(IF(VLOOKUP(D16,期货合约要素!$D:$Q,12,0)=0,"",VLOOKUP(D16,期货合约要素!$D:$Q,12,0)),IF(VLOOKUP(D16,期权合约要素!$D:$V,17,0)=0,"",VLOOKUP(D16,期权合约要素!$D:$V,17,0))) -> √ | W16: =IFERROR(IF(VLOOKUP(D16,期货合约要素!$D:$Q,14,0)=0,"",VLOOKUP(D16,期货合约要素!$D:$Q,14,0)),IF(VLOOKUP(D16,期权合约要素!$D:$V,19,0)=0,"",VLOOKUP(D16,期权合约要素!$D:$V,19,0)))
C17: 铅 pb2607-pb2702合约 | G17: 0.11 | H17: =MAX(G17,N17+2%) -> 0.14 | I17: =MAX(G17,O17+2%) -> 0.16 | J17: 0.1 | K17: =MAX(J17,N17+2%) -> 0.14 | L17: =MAX(J17,O17+2%) -> 0.16 | M17: 0.09 | N17: =M17+3% -> 0.12 | O17: =N17+2% -> 0.14 | P17: =MAX(10%,G17) -> 0.11 | Q17: =MAX(10%,J17) -> 0.1 | R17: =MAX(15%,G17) -> 0.15 | S17: =MAX(15%,J17) -> 0.15 | T17: =MAX(20%,G17) -> 0.2 | U17: =MAX(J17,20%) -> 0.2
C18: 氧化铝 | D18: ao | E18: 20吨 | F18: 0.07 | G18: 0.09 | H18: =MAX(G18,N18+2%) -> 0.12 | I18: =MAX(G18,O18+2%) -> 0.14 | J18: 0.08 | K18: =MAX(J18,N18+2%) -> 0.12 | L18: =MAX(J18,O18+2%) -> 0.14 | M18: 0.07 | N18: =M18+3% -> 0.1 | O18: =N18+2% -> 0.12 | P18: =MAX(10%,G18) -> 0.1 | Q18: =MAX(10%,J18) -> 0.1 | R18: =MAX(15%,G18) -> 0.15 | S18: =MAX(15%,J18) -> 0.15 | T18: =MAX(20%,G18) -> 0.2 | U18: =MAX(J18,20%) -> 0.2 | V18: =IFERROR(IF(VLOOKUP(D18,期货合约要素!$D:$Q,12,0)=0,"",VLOOKUP(D18,期货合约要素!$D:$Q,12,0)),IF(VLOOKUP(D18,期权合约要素!$D:$V,17,0)=0,"",VLOOKUP(D18,期权合约要素!$D:$V,17,0))) | W18: =IFERROR(IF(VLOOKUP(D18,期货合约要素!$D:$Q,14,0)=0,"",VLOOKUP(D18,期货合约要素!$D:$Q,14,0)),IF(VLOOKUP(D18,期权合约要素!$D:$V,19,0)=0,"",VLOOKUP(D18,期权合约要素!$D:$V,19,0)))
C19: 氧化铝 ao2607-ao2702合约 | G19: 0.11 | H19: =MAX(G19,N19+2%) -> 0.14 | I19: =MAX(G19,O19+2%) -> 0.16 | J19: 0.1 | K19: =MAX(J19,N19+2%) -> 0.14 | L19: =MAX(J19,O19+2%) -> 0.16 | M19: 0.09 | N19: =M19+3% -> 0.12 | O19: =N19+2% -> 0.14 | P19: =MAX(10%,G19) -> 0.11 | Q19: =MAX(10%,J19) -> 0.1 | R19: =MAX(15%,G19) -> 0.15 | S19: =MAX(15%,J19) -> 0.15 | T19: =MAX(20%,G19) -> 0.2 | U19: =MAX(J19,20%) -> 0.2
C20: 不锈钢 | D20: ss | E20: 5吨 | F20: 0.06 | G20: 0.07 | H20: =MAX(G20,N20+2%) -> 0.1 | I20: =MAX(G20,O20+2%) -> 0.12 | J20: 0.06 | K20: =MAX(J20,N20+2%) -> 0.1 | L20: =MAX(J20,O20+2%) -> 0.12 | M20: 0.05 | N20: =M20+3% -> 0.08 | O20: =N20+2% -> 0.1 | P20: =MAX(10%,G20) -> 0.1 | Q20: =MAX(10%,J20) -> 0.1 | R20: =MAX(15%,G20) -> 0.15 | S20: =MAX(15%,J20) -> 0.15 | T20: =MAX(20%,G20) -> 0.2 | U20: =MAX(J20,20%) -> 0.2 | V20: =IFERROR(IF(VLOOKUP(D20,期货合约要素!$D:$Q,12,0)=0,"",VLOOKUP(D20,期货合约要素!$D:$Q,12,0)),IF(VLOOKUP(D20,期权合约要素!$D:$V,17,0)=0,"",VLOOKUP(D20,期权合约要素!$D:$V,17,0))) -> √ | W20: =IFERROR(IF(VLOOKUP(D20,期货合约要素!$D:$Q,14,0)=0,"",VLOOKUP(D20,期货合约要素!$D:$Q,14,0)),IF(VLOOKUP(D20,期权合约要素!$D:$V,19,0)=0,"",VLOOKUP(D20,期权合约要素!$D:$V,19,0)))
C21: 镍 | D21: ni | E21: 1吨 | F21: 0.08 | G21: 0.1 | H21: =MAX(G21,N21+2%) -> 0.13 | I21: =MAX(G21,O21+2%) -> 0.15 | J21: 0.09 | K21: =MAX(J21,N21+2%) -> 0.13 | L21: =MAX(J21,O21+2%) -> 0.15 | M21: 0.08 | N21: =M21+3% -> 0.11 | O21: =N21+2% -> 0.13 | P21: =MAX(10%,G21) -> 0.1 | Q21: =MAX(10%,J21) -> 0.1 | R21: =MAX(15%,G21) -> 0.15 | S21: =MAX(15%,J21) -> 0.15 | T21: =MAX(20%,G21) -> 0.2 | U21: =MAX(J21,20%) -> 0.2 | V21: =IFERROR(IF(VLOOKUP(D21,期货合约要素!$D:$Q,12,0)=0,"",VLOOKUP(D21,期货合约要素!$D:$Q,12,0)),IF(VLOOKUP(D21,期权合约要素!$D:$V,17,0)=0,"",VLOOKUP(D21,期权合约要素!$D:$V,17,0))) -> √ | W21: =IFERROR(IF(VLOOKUP(D21,期货合约要素!$D:$Q,14,0)=0,"",VLOOKUP(D21,期货合约要素!$D:$Q,14,0)),IF(VLOOKUP(D21,期权合约要素!$D:$V,19,0)=0,"",VLOOKUP(D21,期权合约要素!$D:$V,19,0))) -> √
C22: 镍 ni2607-ni2703合约 | G22: 0.12 | H22: =MAX(G22,N22+2%) -> 0.15 | I22: =MAX(G22,O22+2%) -> 0.17 | J22: 0.11 | K22: =MAX(J22,N22+2%) -> 0.15 | L22: =MAX(J22,O22+2%) -> 0.17 | M22: 0.1 | N22: =M22+3% -> 0.13 | O22: =N22+2% -> 0.15 | P22: =MAX(10%,G22) -> 0.12 | Q22: =MAX(10%,J22) -> 0.11 | R22: =MAX(15%,G22) -> 0.15 | S22: =MAX(15%,J22) -> 0.15 | T22: =MAX(20%,G22) -> 0.2 | U22: =MAX(J22,20%) -> 0.2
C23: 锡 | D23: sn | E23: 1吨 | F23: 0.1 | G23: 0.13 | H23: =MAX(G23,N23+2%) -> 0.16 | I23: =MAX(G23,O23+2%) -> 0.18 | J23: 0.12 | K23: =MAX(J23,N23+2%) -> 0.16 | L23: =MAX(J23,O23+2%) -> 0.18 | M23: 0.11 | N23: =M23+3% -> 0.14 | O23: =N23+2% -> 0.16 | P23: =MAX(10%,G23) -> 0.13 | Q23: =MAX(10%,J23) -> 0.12 | R23: =MAX(15%,G23) -> 0.15 | S23: =MAX(15%,J23) -> 0.15 | T23: =MAX(20%,G23) -> 0.2 | U23: =MAX(J23,20%) -> 0.2 | V23: =IFERROR(IF(VLOOKUP(D23,期货合约要素!$D:$Q,12,0)=0,"",VLOOKUP(D23,期货合约要素!$D:$Q,12,0)),IF(VLOOKUP(D23,期权合约要素!$D:$V,17,0)=0,"",VLOOKUP(D23,期权合约要素!$D:$V,17,0))) -> √ | W23: =IFERROR(IF(VLOOKUP(D23,期货合约要素!$D:$Q,14,0)=0,"",VLOOKUP(D23,期货合约要素!$D:$Q,14,0)),IF(VLOOKUP(D23,期权合约要素!$D:$V,19,0)=0,"",VLOOKUP(D23,期权合约要素!$D:$V,19,0)))
C24: 锡 sn2607-sn2703合约 | G24: 0.14 | H24: =MAX(G24,N24+2%) -> 0.17 | I24: =MAX(G24,O24+2%) -> 0.19 | J24: 0.13 | K24: =MAX(J24,N24+2%) -> 0.17 | L24: =MAX(J24,O24+2%) -> 0.19 | M24: 0.12 | N24: =M24+3% -> 0.15 | O24: =N24+2% -> 0.17 | P24: =MAX(10%,G24) -> 0.14 | Q24: =MAX(10%,J24) -> 0.13 | R24: =MAX(15%,G24) -> 0.15 | S24: =MAX(15%,J24) -> 0.15 | T24: =MAX(20%,G24) -> 0.2 | U24: =MAX(J24,20%) -> 0.2
C25: 黄金 | D25: au | E25: 1000克 | F25: 0.12 | G25: 0.16 | H25: =MAX(G25,N25+2%) -> 0.19 | I25: =MAX(G25,O25+2%) -> 0.21 | J25: 0.15 | K25: =MAX(J25,N25+2%) -> 0.19 | L25: =MAX(J25,O25+2%) -> 0.21 | M25: 0.14 | N25: =M25+3% -> 0.17 | O25: =N25+2% -> 0.19 | P25: =MAX(10%,G25) -> 0.16 | Q25: =MAX(10%,J25) -> 0.15 | R25: =MAX(15%,G25) -> 0.16 | S25: =MAX(15%,J25) -> 0.15 | T25: =MAX(20%,G25) -> 0.2 | U25: =MAX(J25,20%) -> 0.2 | V25: =IFERROR(IF(VLOOKUP(D25,期货合约要素!$D:$Q,12,0)=0,"",VLOOKUP(D25,期货合约要素!$D:$Q,12,0)),IF(VLOOKUP(D25,期权合约要素!$D:$V,17,0)=0,"",VLOOKUP(D25,期权合约要素!$D:$V,17,0))) -> √ | W25: =IFERROR(IF(VLOOKUP(D25,期货合约要素!$D:$Q,14,0)=0,"",VLOOKUP(D25,期货合约要素!$D:$Q,14,0)),IF(VLOOKUP(D25,期权合约要素!$D:$V,19,0)=0,"",VLOOKUP(D25,期权合约要素!$D:$V,19,0)))
C26: 白银 | D26: ag | E26: 15千克 | F26: 0.16 | G26: 0.16 | H26: =MAX(G26,N26+2%) -> 0.19 | I26: =MAX(G26,O26+2%) -> 0.21 | J26: 0.15 | K26: =MAX(J26,N26+2%) -> 0.19 | L26: =MAX(J26,O26+2%) -> 0.21 | M26: 0.14 | N26: =M26+3% -> 0.17 | O26: =N26+2% -> 0.19 | P26: =MAX(10%,G26) -> 0.16 | Q26: =MAX(10%,J26) -> 0.15 | R26: =MAX(15%,G26) -> 0.16 | S26: =MAX(15%,J26) -> 0.15 | T26: =MAX(20%,G26) -> 0.2 | U26: =MAX(J26,20%) -> 0.2 | V26: =IFERROR(IF(VLOOKUP(D26,期货合约要素!$D:$Q,12,0)=0,"",VLOOKUP(D26,期货合约要素!$D:$Q,12,0)),IF(VLOOKUP(D26,期权合约要素!$D:$V,17,0)=0,"",VLOOKUP(D26,期权合约要素!$D:$V,17,0))) -> √ | W26: =IFERROR(IF(VLOOKUP(D26,期货合约要素!$D:$Q,14,0)=0,"",VLOOKUP(D26,期货合约要素!$D:$Q,14,0)),IF(VLOOKUP(D26,期权合约要素!$D:$V,19,0)=0,"",VLOOKUP(D26,期权合约要素!$D:$V,19,0)))
C27: 白银 ag2607-ag2704合约 | G27: 0.22 | H27: =MAX(G27,N27+2%) -> 0.25 | I27: =MAX(G27,O27+2%) -> 0.27 | J27: 0.21 | K27: =MAX(J27,N27+2%) -> 0.25 | L27: =MAX(J27,O27+2%) -> 0.27 | M27: 0.2 | N27: =M27+3% -> 0.23 | O27: =N27+2% -> 0.25 | P27: =MAX(10%,G27) -> 0.22 | Q27: =MAX(10%,J27) -> 0.21 | R27: =MAX(15%,G27) -> 0.22 | S27: =MAX(15%,J27) -> 0.21 | T27: =MAX(20%,G27) -> 0.22 | U27: =MAX(J27,20%) -> 0.21
C28: 白银 ag2705-ag2706合约 | G28: 0.19 | H28: =MAX(G28,N28+2%) -> 0.22 | I28: =MAX(G28,O28+2%) -> 0.24 | J28: 0.18 | K28: =MAX(J28,N28+2%) -> 0.22 | L28: =MAX(J28,O28+2%) -> 0.24 | M28: 0.17 | N28: =M28+3% -> 0.2 | O28: =N28+2% -> 0.22 | P28: =MAX(10%,G28) -> 0.19 | Q28: =MAX(10%,J28) -> 0.18 | R28: =MAX(15%,G28) -> 0.19 | S28: =MAX(15%,J28) -> 0.18 | T28: =MAX(20%,G28) -> 0.2 | U28: =MAX(J28,20%) -> 0.2
C29: 天然橡胶 | D29: ru | E29: 10吨 | F29: 0.06 | G29: 0.09 | H29: =MAX(G29,N29+2%) -> 0.12 | I29: =MAX(G29,O29+2%) -> 0.14 | J29: 0.08 | K29: =MAX(J29,N29+2%) -> 0.12 | L29: =MAX(J29,O29+2%) -> 0.14 | M29: 0.07 | N29: =M29+3% -> 0.1 | O29: =N29+2% -> 0.12 | P29: =MAX(10%,G29) -> 0.1 | Q29: =MAX(10%,J29) -> 0.1 | R29: =MAX(15%,G29) -> 0.15 | S29: =MAX(15%,J29) -> 0.15 | T29: =MAX(20%,G29) -> 0.2 | U29: =MAX(J29,20%) -> 0.2 | V29: =IFERROR(IF(VLOOKUP(D29,期货合约要素!$D:$Q,12,0)=0,"",VLOOKUP(D29,期货合约要素!$D:$Q,12,0)),IF(VLOOKUP(D29,期权合约要素!$D:$V,17,0)=0,"",VLOOKUP(D29,期权合约要素!$D:$V,17,0))) -> √ | W29: =IFERROR(IF(VLOOKUP(D29,期货合约要素!$D:$Q,14,0)=0,"",VLOOKUP(D29,期货合约要素!$D:$Q,14,0)),IF(VLOOKUP(D29,期权合约要素!$D:$V,19,0)=0,"",VLOOKUP(D29,期权合约要素!$D:$V,19,0)))
C30: 石油沥青 | D30: bu | E30: 10吨 | F30: 0.1 | G30: 0.12 | H30: =MAX(G30,N30+2%) -> 0.15 | I30: =MAX(G30,O30+2%) -> 0.17 | J30: 0.11 | K30: =MAX(J30,N30+2%) -> 0.15 | L30: =MAX(J30,O30+2%) -> 0.17 | M30: 0.1 | N30: =M30+3% -> 0.13 | O30: =N30+2% -> 0.15 | P30: =MAX(10%,G30) -> 0.12 | Q30: =MAX(10%,J30) -> 0.11 | R30: =MAX(15%,G30) -> 0.15 | S30: =MAX(15%,J30) -> 0.15 | T30: =MAX(20%,G30) -> 0.2 | U30: =MAX(J30,20%) -> 0.2 | V30: =IFERROR(IF(VLOOKUP(D30,期货合约要素!$D:$Q,12,0)=0,"",VLOOKUP(D30,期货合约要素!$D:$Q,12,0)),IF(VLOOKUP(D30,期权合约要素!$D:$V,17,0)=0,"",VLOOKUP(D30,期权合约要素!$D:$V,17,0))) -> √ | W30: =IFERROR(IF(VLOOKUP(D30,期货合约要素!$D:$Q,14,0)=0,"",VLOOKUP(D30,期货合约要素!$D:$Q,14,0)),IF(VLOOKUP(D30,期权合约要素!$D:$V,19,0)=0,"",VLOOKUP(D30,期权合约要素!$D:$V,19,0)))
C31: 纸浆 | D31: sp | E31: 10吨 | F31: 0.06 | G31: 0.07 | H31: =MAX(G31,N31+2%) -> 0.1 | I31: =MAX(G31,O31+2%) -> 0.12 | J31: 0.06 | K31: =MAX(J31,N31+2%) -> 0.1 | L31: =MAX(J31,O31+2%) -> 0.12 | M31: 0.05 | N31: =M31+3% -> 0.08 | O31: =N31+2% -> 0.1 | P31: =MAX(10%,G31) -> 0.1 | Q31: =MAX(10%,J31) -> 0.1 | R31: =MAX(15%,G31) -> 0.15 | S31: =MAX(15%,J31) -> 0.15 | T31: =MAX(20%,G31) -> 0.2 | U31: =MAX(J31,20%) -> 0.2 | V31: =IFERROR(IF(VLOOKUP(D31,期货合约要素!$D:$Q,12,0)=0,"",VLOOKUP(D31,期货合约要素!$D:$Q,12,0)),IF(VLOOKUP(D31,期权合约要素!$D:$V,17,0)=0,"",VLOOKUP(D31,期权合约要素!$D:$V,17,0))) -> √ | W31: =IFERROR(IF(VLOOKUP(D31,期货合约要素!$D:$Q,14,0)=0,"",VLOOKUP(D31,期货合约要素!$D:$Q,14,0)),IF(VLOOKUP(D31,期权合约要素!$D:$V,19,0)=0,"",VLOOKUP(D31,期权合约要素!$D:$V,19,0)))
C32: 合成橡胶 | D32: br | E32: 5吨 | F32: 0.1 | G32: 0.12 | H32: =MAX(G32,N32+2%) -> 0.15 | I32: =MAX(G32,O32+2%) -> 0.17 | J32: 0.11 | K32: =MAX(J32,N32+2%) -> 0.15 | L32: =MAX(J32,O32+2%) -> 0.17 | M32: 0.1 | N32: =M32+3% -> 0.13 | O32: =N32+2% -> 0.15 | P32: =MAX(10%,G32) -> 0.12 | Q32: =MAX(10%,J32) -> 0.11 | R32: =MAX(15%,G32) -> 0.15 | S32: =MAX(15%,J32) -> 0.15 | T32: =MAX(20%,G32) -> 0.2 | U32: =MAX(J32,20%) -> 0.2 | V32: =IFERROR(IF(VLOOKUP(D32,期货合约要素!$D:$Q,12,0)=0,"",VLOOKUP(D32,期货合约要素!$D:$Q,12,0)),IF(VLOOKUP(D32,期权合约要素!$D:$V,17,0)=0,"",VLOOKUP(D32,期权合约要素!$D:$V,17,0))) | W32: =IFERROR(IF(VLOOKUP(D32,期货合约要素!$D:$Q,14,0)=0,"",VLOOKUP(D32,期货合约要素!$D:$Q,14,0)),IF(VLOOKUP(D32,期权合约要素!$D:$V,19,0)=0,"",VLOOKUP(D32,期权合约要素!$D:$V,19,0)))
C33: 铸造铝合金 | D33: ad | E33: 10吨 | F33: 0.07 | G33: 0.07 | H33: =MAX(G33,N33+2%) -> 0.1 | I33: =MAX(G33,O33+2%) -> 0.12 | J33: 0.06 | K33: =MAX(J33,N33+2%) -> 0.1 | L33: =MAX(J33,O33+2%) -> 0.12 | M33: 0.05 | N33: =M33+3% -> 0.08 | O33: =N33+2% -> 0.1 | P33: =MAX(10%,G33) -> 0.1 | Q33: =MAX(10%,J33) -> 0.1 | R33: =MAX(15%,G33) -> 0.15 | S33: =MAX(15%,J33) -> 0.15 | T33: =MAX(20%,G33) -> 0.2 | U33: =MAX(J33,20%) -> 0.2 | V33: =IFERROR(IF(VLOOKUP(D33,期货合约要素!$D:$Q,12,0)=0,"",VLOOKUP(D33,期货合约要素!$D:$Q,12,0)),IF(VLOOKUP(D33,期权合约要素!$D:$V,17,0)=0,"",VLOOKUP(D33,期权合约要素!$D:$V,17,0))) | W33: =IFERROR(IF(VLOOKUP(D33,期货合约要素!$D:$Q,14,0)=0,"",VLOOKUP(D33,期货合约要素!$D:$Q,14,0)),IF(VLOOKUP(D33,期权合约要素!$D:$V,19,0)=0,"",VLOOKUP(D33,期权合约要素!$D:$V,19,0)))
C34: 铸造铝合金 ad2607-ad2702合约 | G34: 0.1 | H34: =MAX(G34,N34+2%) -> 0.13 | I34: =MAX(G34,O34+2%) -> 0.15 | J34: 0.09 | K34: =MAX(J34,N34+2%) -> 0.13 | L34: =MAX(J34,O34+2%) -> 0.15 | M34: 0.08 | N34: =M34+3% -> 0.11 | O34: =N34+2% -> 0.13 | P34: =MAX(10%,G34) -> 0.1 | Q34: =MAX(10%,J34) -> 0.1 | R34: =MAX(15%,G34) -> 0.15 | S34: =MAX(15%,J34) -> 0.15 | T34: =MAX(20%,G34) -> 0.2 | U34: =MAX(J34,20%) -> 0.2
C35: 胶版印刷纸 | D35: op | E35: 40吨 | F35: 0.05 | G35: 0.07 | H35: =MAX(G35,N35+2%) -> 0.1 | I35: =MAX(G35,O35+2%) -> 0.12 | J35: 0.06 | K35: =MAX(J35,N35+2%) -> 0.1 | L35: =MAX(J35,O35+2%) -> 0.12 | M35: 0.05 | N35: =M35+3% -> 0.08 | O35: =N35+2% -> 0.1 | P35: =MAX(10%,G35) -> 0.1 | Q35: =MAX(10%,J35) -> 0.1 | R35: =MAX(15%,G35) -> 0.15 | S35: =MAX(15%,J35) -> 0.15 | T35: =MAX(20%,G35) -> 0.2 | U35: =MAX(J35,20%) -> 0.2 | V35: =IFERROR(IF(VLOOKUP(D35,期货合约要素!$D:$Q,12,0)=0,"",VLOOKUP(D35,期货合约要素!$D:$Q,12,0)),IF(VLOOKUP(D35,期权合约要素!$D:$V,17,0)=0,"",VLOOKUP(D35,期权合约要素!$D:$V,17,0))) | W35: =IFERROR(IF(VLOOKUP(D35,期货合约要素!$D:$Q,14,0)=0,"",VLOOKUP(D35,期货合约要素!$D:$Q,14,0)),IF(VLOOKUP(D35,期权合约要素!$D:$V,19,0)=0,"",VLOOKUP(D35,期权合约要素!$D:$V,19,0)))
C36: 保税380燃料油 | D36: fu | E36: 10吨 | F36: 0.13 | G36: 0.16 | H36: =MAX(G36,N36+2%) -> 0.19 | I36: =O36+2% -> 0.21 | J36: 0.15 | K36: =MAX(J36,N36+2%) -> 0.19 | L36: =MAX(J36,O36+2%) -> 0.21 | M36: 0.14 | N36: =M36+3% -> 0.17 | O36: =N36+2% -> 0.19 | P36: 交割月前2月第10个交易日起 （投机） | Q36: 交割月前2月第10个交易日起 （套保） | R36: 交割月前1月第10个交易日起 （投机） | S36: 交割月前1月第10个交易日起 （套保） | T36: 最后交易日前2个交易日起 （投机） | U36: 最后交易日前2个交易日起 （套保） | V36: =IFERROR(IF(VLOOKUP(D36,期货合约要素!$D:$Q,12,0)=0,"",VLOOKUP(D36,期货合约要素!$D:$Q,12,0)),IF(VLOOKUP(D36,期权合约要素!$D:$V,17,0)=0,"",VLOOKUP(D36,期权合约要素!$D:$V,17,0))) -> √ | W36: =IFERROR(IF(VLOOKUP(D36,期货合约要素!$D:$Q,14,0)=0,"",VLOOKUP(D36,期货合约要素!$D:$Q,14,0)),IF(VLOOKUP(D36,期权合约要素!$D:$V,19,0)=0,"",VLOOKUP(D36,期权合约要素!$D:$V,19,0)))
P37: =MAX(10%,G36) -> 0.16 | Q37: =MAX(10%,J36) -> 0.15 | R37: =MAX(15%,G36) -> 0.16 | S37: =MAX(15%,J36) -> 0.15 | T37: =MAX(20%,G36) -> 0.2 | U37: =MAX(J36,20%) -> 0.2
C38: 保税380燃料油 fu2607 | G38: 0.19 | H38: =MAX(G38,N38+2%) -> 0.22 | I38: =O38+2% -> 0.24 | J38: 0.18 | K38: =MAX(J38,N38+2%) -> 0.22 | L38: =MAX(J38,O38+2%) -> 0.24 | M38: 0.17 | N38: =M38+3% -> 0.2 | O38: =N38+2% -> 0.22 | P38: =MAX(10%,G38) -> 0.19 | Q38: =MAX(10%,J38) -> 0.18 | R38: =MAX(15%,G38) -> 0.19 | S38: =MAX(15%,J38) -> 0.18 | T38: =MAX(20%,G38) -> 0.2 | U38: =MAX(J38,20%) -> 0.2
B39: 上海国际能源交易中心 | C39: 20号胶 | D39: nr | E39: 10吨 | F39: 0.06 | G39: 0.09 | H39: =MAX(G39,N39+2%) -> 0.12 | I39: =MAX(G39,O39+2%) -> 0.14 | J39: 0.08 | K39: =MAX(J39,N39+2%) -> 0.12 | L39: =MAX(J39,O39+2%) -> 0.14 | M39: 0.07 | N39: =M39+3% -> 0.1 | O39: =N39+2% -> 0.12 | P39: 交割月前1月第1个交易日起 （投机） | Q39: 交割月前1月第1个交易日起 （套保） | R39: 交割月第1个交易日起 （投机） | S39: 交割月第1个交易日起 （套保） | T39: 最后交易日前2个交易日起 （投机） | U39: 最后交易日前2个交易日起 （套保） | V39: =IFERROR(IF(VLOOKUP(D39,期货合约要素!$D:$Q,12,0)=0,"",VLOOKUP(D39,期货合约要素!$D:$Q,12,0)),IF(VLOOKUP(D39,期权合约要素!$D:$V,17,0)=0,"",VLOOKUP(D39,期权合约要素!$D:$V,17,0))) -> √ | W39: =IFERROR(IF(VLOOKUP(D39,期货合约要素!$D:$Q,14,0)=0,"",VLOOKUP(D39,期货合约要素!$D:$Q,14,0)),IF(VLOOKUP(D39,期权合约要素!$D:$V,19,0)=0,"",VLOOKUP(D39,期权合约要素!$D:$V,19,0))) -> √
P40: =MAX(10%,G39) -> 0.1 | Q40: =MAX(10%,J39) -> 0.1 | R40: =MAX(15%,G39) -> 0.15 | S40: =MAX(15%,J40) -> 0.15 | T40: =MAX(20%,G39) -> 0.2 | U40: =MAX(J39,20%) -> 0.2
C41: 国际铜 | D41: bc | E41: 5吨 | F41: 0.07 | G41: 0.09 | H41: =MAX(G41,N41+2%) -> 0.12 | I41: =MAX(G41,O41+2%) -> 0.14 | J41: 0.08 | K41: =MAX(J41,N41+2%) -> 0.12 | L41: =MAX(J41,O41+2%) -> 0.14 | M41: 0.07 | N41: =M41+3% -> 0.1 | O41: =N41+2% -> 0.12 | P41: =MAX(10%,G41) -> 0.1 | Q41: =MAX(10%,J41) -> 0.1 | R41: =MAX(15%,G41) -> 0.15 | S41: =MAX(15%,J41) -> 0.15 | T41: =MAX(20%,G40) -> 0.2 | U41: =MAX(J41,20%) -> 0.2 | V41: =IFERROR(IF(VLOOKUP(D41,期货合约要素!$D:$Q,12,0)=0,"",VLOOKUP(D41,期货合约要素!$D:$Q,12,0)),IF(VLOOKUP(D41,期权合约要素!$D:$V,17,0)=0,"",VLOOKUP(D41,期权合约要素!$D:$V,17,0))) -> √ | W41: =IFERROR(IF(VLOOKUP(D41,期货合约要素!$D:$Q,14,0)=0,"",VLOOKUP(D41,期货合约要素!$D:$Q,14,0)),IF(VLOOKUP(D41,期权合约要素!$D:$V,19,0)=0,"",VLOOKUP(D41,期权合约要素!$D:$V,19,0))) -> √
C42: 国际铜 bc2607-bc2702合约 | G42: 0.11 | H42: =MAX(G42,N42+2%) -> 0.14 | I42: =MAX(G42,O42+2%) -> 0.16 | J42: 0.1 | K42: =MAX(J42,N42+2%) -> 0.14 | L42: =MAX(J42,O42+2%) -> 0.16 | M42: 0.09 | N42: =M42+3% -> 0.12 | O42: =N42+2% -> 0.14 | P42: =MAX(10%,G42) -> 0.11 | Q42: =MAX(10%,J42) -> 0.1 | R42: =MAX(15%,G42) -> 0.15 | S42: =MAX(15%,J42) -> 0.15 | T42: =MAX(20%,G40) -> 0.2 | U42: =MAX(J42,20%) -> 0.2
C43: 原油 | D43: sc | E43: 1000桶 | F43: 0.13 | G43: 0.16 | H43: =MAX(G43,N43+2%) -> 0.19 | I43: =O43+2% -> 0.21 | J43: 0.15 | K43: =MAX(J43,N43+2%) -> 0.19 | L43: =MAX(J43,O43+2%) -> 0.21 | M43: 0.14 | N43: =M43+3% -> 0.17 | O43: =N43+2% -> 0.19 | P43: 交割月前1月第1个交易日起 （投机） | Q43: 交割月前1月第1个交易日起 （套保） | R43: 最后交易日前2个交易日起 （投机） | T43: 最后交易日前2个交易日起 （套保） | V43: =IFERROR(IF(VLOOKUP(D43,期货合约要素!$D:$Q,12,0)=0,"",VLOOKUP(D43,期货合约要素!$D:$Q,12,0)),IF(VLOOKUP(D43,期权合约要素!$D:$V,17,0)=0,"",VLOOKUP(D43,期权合约要素!$D:$V,17,0))) -> √ | W43: =IFERROR(IF(VLOOKUP(D43,期货合约要素!$D:$Q,14,0)=0,"",VLOOKUP(D43,期货合约要素!$D:$Q,14,0)),IF(VLOOKUP(D43,期权合约要素!$D:$V,19,0)=0,"",VLOOKUP(D43,期权合约要素!$D:$V,19,0))) -> √
P44: =MAX(10%,G43) -> 0.16 | Q44: =MAX(10%,J43) -> 0.15 | R44: =MAX(G43,20%) -> 0.2 | T44: =MAX(J43,20%) -> 0.2
C45: 原油 sc2607 | G45: 0.19 | H45: =MAX(G45,N45+2%) -> 0.22 | I45: =O45+2% -> 0.24 | J45: 0.18 | K45: =MAX(J45,N45+2%) -> 0.22 | L45: =MAX(J45,O45+2%) -> 0.24 | M45: 0.17 | N45: =M45+3% -> 0.2 | O45: =N45+2% -> 0.22 | P45: =MAX(10%,G44) -> 0.1 | Q45: =MAX(10%,J44) -> 0.1 | R45: =MAX(G44,20%) -> 0.2 | T45: =MAX(J44,20%) -> 0.2
C46: 低硫燃料油 | D46: lu | E46: 10吨 | F46: 0.13 | G46: 0.16 | H46: =MAX(G46,N46+2%) -> 0.19 | I46: =O46+2% -> 0.21 | J46: 0.15 | K46: =MAX(J46,N46+2%) -> 0.19 | L46: =MAX(J46,O46+2%) -> 0.21 | M46: 0.14 | N46: =M46+3% -> 0.17 | O46: =N46+2% -> 0.19 | P46: =MAX(10%,G46) -> 0.16 | Q46: =MAX(10%,J46) -> 0.15 | R46: =MAX(G46,20%) -> 0.2 | T46: =MAX(J46,20%) -> 0.2 | V46: =IFERROR(IF(VLOOKUP(D46,期货合约要素!$D:$Q,12,0)=0,"",VLOOKUP(D46,期货合约要素!$D:$Q,12,0)),IF(VLOOKUP(D46,期权合约要素!$D:$V,17,0)=0,"",VLOOKUP(D46,期权合约要素!$D:$V,17,0))) -> √ | W46: =IFERROR(IF(VLOOKUP(D46,期货合约要素!$D:$Q,14,0)=0,"",VLOOKUP(D46,期货合约要素!$D:$Q,14,0)),IF(VLOOKUP(D46,期权合约要素!$D:$V,19,0)=0,"",VLOOKUP(D46,期权合约要素!$D:$V,19,0))) -> √
C47: 低硫燃料油 lu2607 | G47: 0.19 | H47: =MAX(G47,N47+2%) -> 0.22 | I47: =O47+2% -> 0.24 | J47: 0.18 | K47: =MAX(J47,N47+2%) -> 0.22 | L47: =MAX(J47,O47+2%) -> 0.24 | M47: 0.17 | N47: =M47+3% -> 0.2 | O47: =N47+2% -> 0.22 | P47: =MAX(10%,G47) -> 0.19 | Q47: =MAX(10%,J47) -> 0.18 | R47: =MAX(G47,20%) -> 0.2 | T47: =MAX(J47,20%) -> 0.2
C48: 集运指数 （欧线） | D48: ec | E48: 50元 | F48: 0.17 | G48: 0.17 | H48: =MAX(G48,N48+2%) -> 0.2 | I48: =O48+2% -> 0.22 | J48: 0.17 | K48: =MAX(J48,N48+2%) -> 0.2 | L48: =MAX(J48,O48+2%) -> 0.22 | M48: 0.15 | N48: =M48+3% -> 0.18 | O48: =N48+2% -> 0.2 | P48: 最后交易日前7个交易日起 （投机） | Q48: 最后交易日前7个交易日起 （套保） | R48: 最后交易日前2个交易日起 （投机） | T48: 最后交易日前2个交易日起 （套保） | V48: =IFERROR(IF(VLOOKUP(D48,期货合约要素!$D:$Q,12,0)=0,"",VLOOKUP(D48,期货合约要素!$D:$Q,12,0)),IF(VLOOKUP(D48,期权合约要素!$D:$V,17,0)=0,"",VLOOKUP(D48,期权合约要素!$D:$V,17,0))) -> √ | W48: =IFERROR(IF(VLOOKUP(D48,期货合约要素!$D:$Q,14,0)=0,"",VLOOKUP(D48,期货合约要素!$D:$Q,14,0)),IF(VLOOKUP(D48,期权合约要素!$D:$V,19,0)=0,"",VLOOKUP(D48,期权合约要素!$D:$V,19,0))) -> √
P49: =MAX(G48,20%) -> 0.2 | Q49: =MAX(J48,20%) -> 0.2 | R49: =MAX(G48,30%) -> 0.3 | T49: =MAX(J48,30%) -> 0.3
C50: 集运指数 （欧线） ec2607-ec2610,ec2612,ec2703 | G50: 0.22 | H50: =MAX(G50,N50+2%) -> 0.25 | I50: =O50+2% -> 0.27 | J50: 0.22 | K50: =MAX(J50,N50+2%) -> 0.25 | L50: =MAX(J50,O50+2%) -> 0.27 | M50: 0.2 | N50: =M50+3% -> 0.23 | O50: =N50+2% -> 0.25 | P50: =MAX(G50,20%) -> 0.22 | Q50: =MAX(J50,20%) -> 0.22 | R50: =MAX(G50,30%) -> 0.3 | T50: =MAX(J50,30%) -> 0.3
B53: 交易所 | C53: 品种名称 | D53: 品种代码 | E53: 合约单位 | F53: 公司加收 | G53: 按连续单边市调整的交易所保证金率 | M53: 连续单边市涨跌停板 | P53: 交易所时间梯度保证金 | V53: QFII&RQFII | W53: 国际化品种
G54: 投机 | J54: 套保 | P54: 交割月前1个月 | T54: 交割月份
G55: 一般月份 | H55: 第一个单边市结算时 | I55: 第二个同方向单边市结算时 | J55: 一般月份 | K55: 第一个单边市结算时 | L55: 第二个同方向单边市结算时 | M55: 一般月份 | N55: 第一个单边市结算后 | O55: 第二个同方向单边市结算后 | P55: 第16个日历日起 （投机） | R55: 第16个日历日起 （套保） | T55: 第1个日历日起 （投机） | U55: 第1个日历日起 （套保）
B56: 郑州 商品 交易所 | C56: 棉花 | D56: CF | E56: 5吨 | F56: 0.06 | G56: 0.07 | H56: =MAX(G56,N56+2%) -> 0.11 | I56: =MAX(G56,O56+2%) -> 0.14 | J56: 0.07 | K56: =MAX(J56,N56+2%) -> 0.11 | L56: =MAX(J56,O56+2%) -> 0.14 | M56: 0.06 | N56: =M56+3% -> 0.09 | O56: =N56+3% -> 0.12 | P56: =MAX(G56,10%) -> 0.1 | R56: =MAX(J56,10%) -> 0.1 | T56: =MAX(20%,G56) -> 0.2 | U56: =MAX(J56,20%) -> 0.2 | V56: =IFERROR(IF(VLOOKUP(D56,期货合约要素!$D:$Q,12,0)=0,"",VLOOKUP(D56,期货合约要素!$D:$Q,12,0)),IF(VLOOKUP(D56,期权合约要素!$D:$V,17,0)=0,"",VLOOKUP(D56,期权合约要素!$D:$V,17,0))) | W56: =IFERROR(IF(VLOOKUP(D56,期货合约要素!$D:$Q,14,0)=0,"",VLOOKUP(D56,期货合约要素!$D:$Q,14,0)),IF(VLOOKUP(D56,期权合约要素!$D:$V,19,0)=0,"",VLOOKUP(D56,期权合约要素!$D:$V,19,0)))
C57: 棉纱 | D57: CY | E57: 5吨 | F57: 0.06 | G57: 0.05 | H57: =MAX(G57,N57+2%) -> 0.09 | I57: =MAX(G57,O57+2%) -> 0.12 | J57: 0.05 | K57: =MAX(J57,N57+2%) -> 0.09 | L57: =MAX(J57,O57+2%) -> 0.12 | M57: 0.04 | N57: =M57+3% -> 0.07 | O57: =N57+3% -> 0.1 | P57: =MAX(G57,10%) -> 0.1 | R57: =MAX(J57,10%) -> 0.1 | T57: =MAX(20%,G57) -> 0.2 | U57: =MAX(J57,20%) -> 0.2 | V57: =IFERROR(IF(VLOOKUP(D57,期货合约要素!$D:$Q,12,0)=0,"",VLOOKUP(D57,期货合约要素!$D:$Q,12,0)),IF(VLOOKUP(D57,期权合约要素!$D:$V,17,0)=0,"",VLOOKUP(D57,期权合约要素!$D:$V,17,0))) | W57: =IFERROR(IF(VLOOKUP(D57,期货合约要素!$D:$Q,14,0)=0,"",VLOOKUP(D57,期货合约要素!$D:$Q,14,0)),IF(VLOOKUP(D57,期权合约要素!$D:$V,19,0)=0,"",VLOOKUP(D57,期权合约要素!$D:$V,19,0)))
C58: 白糖 | D58: SR | E58: 10吨 | F58: 0.06 | G58: 0.06 | H58: =MAX(G58,N58+2%) -> 0.1 | I58: =MAX(G58,O58+2%) -> 0.13 | J58: 0.06 | K58: =MAX(J58,N58+2%) -> 0.1 | L58: =MAX(J58,O58+2%) -> 0.13 | M58: 0.05 | N58: =M58+3% -> 0.08 | O58: =N58+3% -> 0.11 | P58: =MAX(G58,10%) -> 0.1 | R58: =MAX(J58,10%) -> 0.1 | T58: =MAX(20%,G58) -> 0.2 | U58: =MAX(J58,20%) -> 0.2 | V58: =IFERROR(IF(VLOOKUP(D58,期货合约要素!$D:$Q,12,0)=0,"",VLOOKUP(D58,期货合约要素!$D:$Q,12,0)),IF(VLOOKUP(D58,期权合约要素!$D:$V,17,0)=0,"",VLOOKUP(D58,期权合约要素!$D:$V,17,0))) -> √ | W58: =IFERROR(IF(VLOOKUP(D58,期货合约要素!$D:$Q,14,0)=0,"",VLOOKUP(D58,期货合约要素!$D:$Q,14,0)),IF(VLOOKUP(D58,期权合约要素!$D:$V,19,0)=0,"",VLOOKUP(D58,期权合约要素!$D:$V,19,0)))
C59: PTA | D59: TA | E59: 5吨 | F59: 0.1 | G59: 0.07 | H59: =MAX(G59,N59+2%) -> 0.11 | I59: =MAX(G59,O59+2%) -> 0.14 | J59: 0.07 | K59: =MAX(J59,N59+2%) -> 0.11 | L59: =MAX(J59,O59+2%) -> 0.14 | M59: 0.06 | N59: =M59+3% -> 0.09 | O59: =N59+3% -> 0.12 | P59: =MAX(G59,10%) -> 0.1 | R59: =MAX(J59,10%) -> 0.1 | T59: =MAX(20%,G59) -> 0.2 | U59: =MAX(J59,20%) -> 0.2 | V59: =IFERROR(IF(VLOOKUP(D59,期货合约要素!$D:$Q,12,0)=0,"",VLOOKUP(D59,期货合约要素!$D:$Q,12,0)),IF(VLOOKUP(D59,期权合约要素!$D:$V,17,0)=0,"",VLOOKUP(D59,期权合约要素!$D:$V,17,0))) -> √ | W59: =IFERROR(IF(VLOOKUP(D59,期货合约要素!$D:$Q,14,0)=0,"",VLOOKUP(D59,期货合约要素!$D:$Q,14,0)),IF(VLOOKUP(D59,期权合约要素!$D:$V,19,0)=0,"",VLOOKUP(D59,期权合约要素!$D:$V,19,0))) -> √
C60: PTA TA607 | G60: 0.13 | H60: =MAX(G60,N60+2%) -> 0.16 | I60: =MAX(G60,O60+2%) -> 0.19 | J60: 0.13 | K60: =MAX(J60,N60+2%) -> 0.16 | L60: =MAX(J60,O60+2%) -> 0.19 | M60: 0.11 | N60: =M60+3% -> 0.14 | O60: =N60+3% -> 0.17 | P60: =MAX(G60,10%) -> 0.13 | R60: =MAX(J60,10%) -> 0.13 | T60: =MAX(20%,G60) -> 0.2 | U60: =MAX(J60,20%) -> 0.2
C61: PTA TA608-TA609 | G61: 0.1 | H61: =MAX(G61,N61+2%) -> 0.14 | I61: =MAX(G61,O61+2%) -> 0.17 | J61: 0.1 | K61: =MAX(J61,N61+2%) -> 0.14 | L61: =MAX(J61,O61+2%) -> 0.17 | M61: 0.09 | N61: =M61+3% -> 0.12 | O61: =N61+3% -> 0.15 | P61: =MAX(G61,10%) -> 0.1 | R61: =MAX(J61,10%) -> 0.1 | T61: =MAX(20%,G61) -> 0.2 | U61: =MAX(J61,20%) -> 0.2
C62: 短纤 | D62: PF | E62: 5吨 | F62: 0.1 | G62: 0.07 | H62: =MAX(G62,N62+2%) -> 0.11 | I62: =MAX(G62,O62+2%) -> 0.14 | J62: 0.07 | K62: =MAX(J62,N62+2%) -> 0.11 | L62: =MAX(J62,O62+2%) -> 0.14 | M62: 0.06 | N62: =M62+3% -> 0.09 | O62: =N62+3% -> 0.12 | P62: =MAX(G62,10%) -> 0.1 | R62: =MAX(J62,10%) -> 0.1 | T62: =MAX(20%,G62) -> 0.2 | U62: =MAX(J62,20%) -> 0.2 | V62: =IFERROR(IF(VLOOKUP(D62,期货合约要素!$D:$Q,12,0)=0,"",VLOOKUP(D62,期货合约要素!$D:$Q,12,0)),IF(VLOOKUP(D62,期权合约要素!$D:$V,17,0)=0,"",VLOOKUP(D62,期权合约要素!$D:$V,17,0))) -> √ | W62: =IFERROR(IF(VLOOKUP(D62,期货合约要素!$D:$Q,14,0)=0,"",VLOOKUP(D62,期货合约要素!$D:$Q,14,0)),IF(VLOOKUP(D62,期权合约要素!$D:$V,19,0)=0,"",VLOOKUP(D62,期权合约要素!$D:$V,19,0))) -> √
C63: 短纤 PF607 | G63: 0.13 | H63: =MAX(G63,N63+2%) -> 0.16 | I63: =MAX(G63,O63+2%) -> 0.19 | J63: 0.13 | K63: =MAX(J63,N63+2%) -> 0.16 | L63: =MAX(J63,O63+2%) -> 0.19 | M63: 0.11 | N63: =M63+3% -> 0.14 | O63: =N63+3% -> 0.17 | P63: =MAX(G63,10%) -> 0.13 | R63: =MAX(J63,10%) -> 0.13 | T63: =MAX(20%,G63) -> 0.2 | U63: =MAX(J63,20%) -> 0.2
C64: 短纤 PF608-PF609 | G64: 0.1 | H64: =MAX(G64,N64+2%) -> 0.14 | I64: =MAX(G64,O64+2%) -> 0.17 | J64: 0.1 | K64: =MAX(J64,N64+2%) -> 0.14 | L64: =MAX(J64,O64+2%) -> 0.17 | M64: 0.09 | N64: =M64+3% -> 0.12 | O64: =N64+3% -> 0.15 | P64: =MAX(G64,10%) -> 0.1 | R64: =MAX(J64,10%) -> 0.1 | T64: =MAX(20%,G64) -> 0.2 | U64: =MAX(J64,20%) -> 0.2
C65: 玻璃 | D65: FG | E65: 20吨 | F65: 0.08 | G65: 0.09 | H65: =MAX(G65,N65+2%) -> 0.13 | I65: =MAX(G65,O65+2%) -> 0.16 | J65: 0.09 | K65: =MAX(J65,N65+2%) -> 0.13 | L65: =MAX(J65,O65+2%) -> 0.16 | M65: 0.08 | N65: =M65+3% -> 0.11 | O65: =N65+3% -> 0.14 | P65: =MAX(G65,10%) -> 0.1 | R65: =MAX(J65,10%) -> 0.1 | T65: =MAX(20%,G65) -> 0.2 | U65: =MAX(J65,20%) -> 0.2 | V65: =IFERROR(IF(VLOOKUP(D65,期货合约要素!$D:$Q,12,0)=0,"",VLOOKUP(D65,期货合约要素!$D:$Q,12,0)),IF(VLOOKUP(D65,期权合约要素!$D:$V,17,0)=0,"",VLOOKUP(D65,期权合约要素!$D:$V,17,0))) -> √ | W65: =IFERROR(IF(VLOOKUP(D65,期货合约要素!$D:$Q,14,0)=0,"",VLOOKUP(D65,期货合约要素!$D:$Q,14,0)),IF(VLOOKUP(D65,期权合约要素!$D:$V,19,0)=0,"",VLOOKUP(D65,期权合约要素!$D:$V,19,0)))
C66: 甲醇 | D66: MA | E66: 10吨 | F66: 0.09 | G66: 0.07 | H66: =MAX(G66,N66+2%) -> 0.11 | I66: =MAX(G66,O66+2%) -> 0.14 | J66: 0.07 | K66: =MAX(J66,N66+2%) -> 0.11 | L66: =MAX(J66,O66+2%) -> 0.14 | M66: 0.06 | N66: =M66+3% -> 0.09 | O66: =N66+3% -> 0.12 | P66: =MAX(G66,10%) -> 0.1 | R66: =MAX(J66,10%) -> 0.1 | T66: =MAX(20%,G66) -> 0.2 | U66: =MAX(J66,20%) -> 0.2 | V66: =IFERROR(IF(VLOOKUP(D66,期货合约要素!$D:$Q,12,0)=0,"",VLOOKUP(D66,期货合约要素!$D:$Q,12,0)),IF(VLOOKUP(D66,期权合约要素!$D:$V,17,0)=0,"",VLOOKUP(D66,期权合约要素!$D:$V,17,0))) -> √ | W66: =IFERROR(IF(VLOOKUP(D66,期货合约要素!$D:$Q,14,0)=0,"",VLOOKUP(D66,期货合约要素!$D:$Q,14,0)),IF(VLOOKUP(D66,期权合约要素!$D:$V,19,0)=0,"",VLOOKUP(D66,期权合约要素!$D:$V,19,0)))
C67: 甲醇 MA607 | G67: 0.13 | H67: =MAX(G67,N67+2%) -> 0.16 | I67: =MAX(G67,O67+2%) -> 0.19 | J67: 0.13 | K67: =MAX(J67,N67+2%) -> 0.16 | L67: =MAX(J67,O67+2%) -> 0.19 | M67: 0.11 | N67: =M67+3% -> 0.14 | O67: =N67+3% -> 0.17 | P67: =MAX(G67,10%) -> 0.13 | R67: =MAX(J67,10%) -> 0.13 | T67: =MAX(20%,G67) -> 0.2 | U67: =MAX(J67,20%) -> 0.2
C68: 甲醇 MA608-MA609 | G68: 0.1 | H68: =MAX(G68,N68+2%) -> 0.14 | I68: =MAX(G68,O68+2%) -> 0.17 | J68: 0.1 | K68: =MAX(J68,N68+2%) -> 0.14 | L68: =MAX(J68,O68+2%) -> 0.17 | M68: 0.09 | N68: =M68+3% -> 0.12 | O68: =N68+3% -> 0.15 | P68: =MAX(G68,10%) -> 0.1 | R68: =MAX(J68,10%) -> 0.1 | T68: =MAX(20%,G68) -> 0.2 | U68: =MAX(J68,20%) -> 0.2
C69: 纯碱 | D69: SA | E69: 20吨 | F69: 0.06 | G69: 0.08 | H69: =MAX(G69,N69+2%) -> 0.12 | I69: =MAX(G69,O69+2%) -> 0.15 | J69: 0.08 | K69: =MAX(J69,N69+2%) -> 0.12 | L69: =MAX(J69,O69+2%) -> 0.15 | M69: 0.07 | N69: =M69+3% -> 0.1 | O69: =N69+3% -> 0.13 | P69: =MAX(G69,10%) -> 0.1 | R69: =MAX(J69,10%) -> 0.1 | T69: =MAX(20%,G69) -> 0.2 | U69: =MAX(J69,20%) -> 0.2 | V69: =IFERROR(IF(VLOOKUP(D69,期货合约要素!$D:$Q,12,0)=0,"",VLOOKUP(D69,期货合约要素!$D:$Q,12,0)),IF(VLOOKUP(D69,期权合约要素!$D:$V,17,0)=0,"",VLOOKUP(D69,期权合约要素!$D:$V,17,0))) -> √ | W69: =IFERROR(IF(VLOOKUP(D69,期货合约要素!$D:$Q,14,0)=0,"",VLOOKUP(D69,期货合约要素!$D:$Q,14,0)),IF(VLOOKUP(D69,期权合约要素!$D:$V,19,0)=0,"",VLOOKUP(D69,期权合约要素!$D:$V,19,0)))
C70: 菜籽粕 | D70: RM | E70: 10吨 | F70: 0.07 | G70: 0.07 | H70: =MAX(G70,N70+2%) -> 0.11 | I70: =MAX(G70,O70+2%) -> 0.14 | J70: 0.07 | K70: =MAX(J70,N70+2%) -> 0.11 | L70: =MAX(J70,O70+2%) -> 0.14 | M70: 0.06 | N70: =M70+3% -> 0.09 | O70: =N70+3% -> 0.12 | P70: =MAX(G70,10%) -> 0.1 | R70: =MAX(J70,10%) -> 0.1 | T70: =MAX(20%,G70) -> 0.2 | U70: =MAX(J70,20%) -> 0.2 | V70: =IFERROR(IF(VLOOKUP(D70,期货合约要素!$D:$Q,12,0)=0,"",VLOOKUP(D70,期货合约要素!$D:$Q,12,0)),IF(VLOOKUP(D70,期权合约要素!$D:$V,17,0)=0,"",VLOOKUP(D70,期权合约要素!$D:$V,17,0))) -> √ | W70: =IFERROR(IF(VLOOKUP(D70,期货合约要素!$D:$Q,14,0)=0,"",VLOOKUP(D70,期货合约要素!$D:$Q,14,0)),IF(VLOOKUP(D70,期权合约要素!$D:$V,19,0)=0,"",VLOOKUP(D70,期权合约要素!$D:$V,19,0))) -> √
C71: 菜籽油 | D71: OI | E71: 10吨 | F71: 0.08 | G71: 0.07 | H71: =MAX(G71,N71+2%) -> 0.11 | I71: =MAX(G71,O71+2%) -> 0.14 | J71: 0.07 | K71: =MAX(J71,N71+2%) -> 0.11 | L71: =MAX(J71,O71+2%) -> 0.14 | M71: 0.06 | N71: =M71+3% -> 0.09 | O71: =N71+3% -> 0.12 | P71: =MAX(G71,10%) -> 0.1 | R71: =MAX(J71,10%) -> 0.1 | T71: =MAX(20%,G71) -> 0.2 | U71: =MAX(J71,20%) -> 0.2 | V71: =IFERROR(IF(VLOOKUP(D71,期货合约要素!$D:$Q,12,0)=0,"",VLOOKUP(D71,期货合约要素!$D:$Q,12,0)),IF(VLOOKUP(D71,期权合约要素!$D:$V,17,0)=0,"",VLOOKUP(D71,期权合约要素!$D:$V,17,0))) -> √ | W71: =IFERROR(IF(VLOOKUP(D71,期货合约要素!$D:$Q,14,0)=0,"",VLOOKUP(D71,期货合约要素!$D:$Q,14,0)),IF(VLOOKUP(D71,期权合约要素!$D:$V,19,0)=0,"",VLOOKUP(D71,期权合约要素!$D:$V,19,0))) -> √
C72: 动力煤 | D72: ZC | E72: 100吨 | F72: 0.5 | G72: 0.5 | H72: =MAX(G72,N72+2%) -> 0.5 | I72: =MAX(G72,O72+2%) -> 0.5 | J72: 0.5 | K72: =MAX(J72,N72+2%) -> 0.5 | L72: =MAX(J72,O72+2%) -> 0.5 | M72: 0.1 | N72: =M72+3% -> 0.13 | O72: =N72+3% -> 0.16 | P72: =MAX(G72,10%) -> 0.5 | R72: =MAX(J72,10%) -> 0.5 | T72: =MAX(20%,G72) -> 0.5 | U72: =MAX(J72,20%) -> 0.5 | V72: =IFERROR(IF(VLOOKUP(D72,期货合约要素!$D:$Q,12,0)=0,"",VLOOKUP(D72,期货合约要素!$D:$Q,12,0)),IF(VLOOKUP(D72,期权合约要素!$D:$V,17,0)=0,"",VLOOKUP(D72,期权合约要素!$D:$V,17,0))) | W72: =IFERROR(IF(VLOOKUP(D72,期货合约要素!$D:$Q,14,0)=0,"",VLOOKUP(D72,期货合约要素!$D:$Q,14,0)),IF(VLOOKUP(D72,期权合约要素!$D:$V,19,0)=0,"",VLOOKUP(D72,期权合约要素!$D:$V,19,0)))
C73: 强麦 | D73: WH | E73: 20吨 | F73: 0.45 | G73: 0.15 | H73: =MAX(G73,N73+2%) -> 0.15 | I73: =MAX(G73,O73+2%) -> 0.15 | J73: 0.15 | K73: =MAX(J73,N73+2%) -> 0.15 | L73: =MAX(J73,O73+2%) -> 0.15 | M73: 0.07 | N73: =M73+3% -> 0.1 | O73: =N73+3% -> 0.13 | P73: =MAX(G73,10%) -> 0.15 | R73: =MAX(J73,10%) -> 0.15 | T73: =MAX(20%,G73) -> 0.2 | U73: =MAX(J73,20%) -> 0.2 | V73: =IFERROR(IF(VLOOKUP(D73,期货合约要素!$D:$Q,12,0)=0,"",VLOOKUP(D73,期货合约要素!$D:$Q,12,0)),IF(VLOOKUP(D73,期权合约要素!$D:$V,17,0)=0,"",VLOOKUP(D73,期权合约要素!$D:$V,17,0))) | W73: =IFERROR(IF(VLOOKUP(D73,期货合约要素!$D:$Q,14,0)=0,"",VLOOKUP(D73,期货合约要素!$D:$Q,14,0)),IF(VLOOKUP(D73,期权合约要素!$D:$V,19,0)=0,"",VLOOKUP(D73,期权合约要素!$D:$V,19,0)))
C74: 普麦 | D74: PM | E74: 50吨 | F74: 0.45 | G74: 0.15 | H74: =MAX(G74,N74+2%) -> 0.15 | I74: =MAX(G74,O74+2%) -> 0.15 | J74: 0.15 | K74: =MAX(J74,N74+2%) -> 0.15 | L74: =MAX(J74,O74+2%) -> 0.15 | M74: 0.07 | N74: =M74+3% -> 0.1 | O74: =N74+3% -> 0.13 | P74: =MAX(G74,10%) -> 0.15 | R74: =MAX(J74,10%) -> 0.15 | T74: =MAX(20%,G74) -> 0.2 | U74: =MAX(J74,20%) -> 0.2 | V74: =IFERROR(IF(VLOOKUP(D74,期货合约要素!$D:$Q,12,0)=0,"",VLOOKUP(D74,期货合约要素!$D:$Q,12,0)),IF(VLOOKUP(D74,期权合约要素!$D:$V,17,0)=0,"",VLOOKUP(D74,期权合约要素!$D:$V,17,0))) | W74: =IFERROR(IF(VLOOKUP(D74,期货合约要素!$D:$Q,14,0)=0,"",VLOOKUP(D74,期货合约要素!$D:$Q,14,0)),IF(VLOOKUP(D74,期权合约要素!$D:$V,19,0)=0,"",VLOOKUP(D74,期权合约要素!$D:$V,19,0)))
C75: 早籼稻 | D75: RI | E75: 20吨 | F75: 0.45 | G75: 0.15 | H75: =MAX(G75,N75+2%) -> 0.15 | I75: =MAX(G75,O75+2%) -> 0.15 | J75: 0.15 | K75: =MAX(J75,N75+2%) -> 0.15 | L75: =MAX(J75,O75+2%) -> 0.15 | M75: 0.07 | N75: =M75+3% -> 0.1 | O75: =N75+3% -> 0.13 | P75: =MAX(G75,10%) -> 0.15 | R75: =MAX(J75,10%) -> 0.15 | T75: =MAX(20%,G75) -> 0.2 | U75: =MAX(J75,20%) -> 0.2 | V75: =IFERROR(IF(VLOOKUP(D75,期货合约要素!$D:$Q,12,0)=0,"",VLOOKUP(D75,期货合约要素!$D:$Q,12,0)),IF(VLOOKUP(D75,期权合约要素!$D:$V,17,0)=0,"",VLOOKUP(D75,期权合约要素!$D:$V,17,0))) | W75: =IFERROR(IF(VLOOKUP(D75,期货合约要素!$D:$Q,14,0)=0,"",VLOOKUP(D75,期货合约要素!$D:$Q,14,0)),IF(VLOOKUP(D75,期权合约要素!$D:$V,19,0)=0,"",VLOOKUP(D75,期权合约要素!$D:$V,19,0)))
C76: 晚籼稻 | D76: LR | E76: 20吨 | F76: 0.45 | G76: 0.15 | H76: =MAX(G76,N76+2%) -> 0.15 | I76: =MAX(G76,O76+2%) -> 0.15 | J76: 0.15 | K76: =MAX(J76,N76+2%) -> 0.15 | L76: =MAX(J76,O76+2%) -> 0.15 | M76: 0.07 | N76: =M76+3% -> 0.1 | O76: =N76+3% -> 0.13 | P76: =MAX(G76,10%) -> 0.15 | R76: =MAX(J76,10%) -> 0.15 | T76: =MAX(20%,G76) -> 0.2 | U76: =MAX(J76,20%) -> 0.2 | V76: =IFERROR(IF(VLOOKUP(D76,期货合约要素!$D:$Q,12,0)=0,"",VLOOKUP(D76,期货合约要素!$D:$Q,12,0)),IF(VLOOKUP(D76,期权合约要素!$D:$V,17,0)=0,"",VLOOKUP(D76,期权合约要素!$D:$V,17,0))) | W76: =IFERROR(IF(VLOOKUP(D76,期货合约要素!$D:$Q,14,0)=0,"",VLOOKUP(D76,期货合约要素!$D:$Q,14,0)),IF(VLOOKUP(D76,期权合约要素!$D:$V,19,0)=0,"",VLOOKUP(D76,期权合约要素!$D:$V,19,0)))
C77: 粳稻 | D77: JR | E77: 20吨 | F77: 0.45 | G77: 0.15 | H77: =MAX(G77,N77+2%) -> 0.15 | I77: =MAX(G77,O77+2%) -> 0.15 | J77: 0.15 | K77: =MAX(J77,N77+2%) -> 0.15 | L77: =MAX(J77,O77+2%) -> 0.15 | M77: 0.07 | N77: =M77+3% -> 0.1 | O77: =N77+3% -> 0.13 | P77: =MAX(G77,10%) -> 0.15 | R77: =MAX(J77,10%) -> 0.15 | T77: =MAX(20%,G77) -> 0.2 | U77: =MAX(J77,20%) -> 0.2 | V77: =IFERROR(IF(VLOOKUP(D77,期货合约要素!$D:$Q,12,0)=0,"",VLOOKUP(D77,期货合约要素!$D:$Q,12,0)),IF(VLOOKUP(D77,期权合约要素!$D:$V,17,0)=0,"",VLOOKUP(D77,期权合约要素!$D:$V,17,0))) | W77: =IFERROR(IF(VLOOKUP(D77,期货合约要素!$D:$Q,14,0)=0,"",VLOOKUP(D77,期货合约要素!$D:$Q,14,0)),IF(VLOOKUP(D77,期权合约要素!$D:$V,19,0)=0,"",VLOOKUP(D77,期权合约要素!$D:$V,19,0)))
C78: 苹果 | D78: AP | E78: 10吨 | F78: 0.07 | G78: 0.09 | H78: =MAX(G78,N78+2%) -> 0.13 | I78: =MAX(G78,O78+2%) -> 0.16 | J78: 0.09 | K78: =MAX(J78,N78+2%) -> 0.13 | L78: =MAX(J78,O78+2%) -> 0.16 | M78: 0.08 | N78: =M78+3% -> 0.11 | O78: =N78+3% -> 0.14 | P78: =MAX(G78,10%) -> 0.1 | R78: =MAX(J78,10%) -> 0.1 | T78: =MAX(20%,G78) -> 0.2 | U78: =MAX(J78,20%) -> 0.2 | V78: =IFERROR(IF(VLOOKUP(D78,期货合约要素!$D:$Q,12,0)=0,"",VLOOKUP(D78,期货合约要素!$D:$Q,12,0)),IF(VLOOKUP(D78,期权合约要素!$D:$V,17,0)=0,"",VLOOKUP(D78,期权合约要素!$D:$V,17,0))) | W78: =IFERROR(IF(VLOOKUP(D78,期货合约要素!$D:$Q,14,0)=0,"",VLOOKUP(D78,期货合约要素!$D:$Q,14,0)),IF(VLOOKUP(D78,期权合约要素!$D:$V,19,0)=0,"",VLOOKUP(D78,期权合约要素!$D:$V,19,0)))
C79: 尿素 | D79: UR | E79: 20吨 | F79: 0.07 | G79: 0.08 | H79: =MAX(G79,N79+2%) -> 0.12 | I79: =MAX(G79,O79+2%) -> 0.15 | J79: 0.08 | K79: =MAX(J79,N79+2%) -> 0.12 | L79: =MAX(J79,O79+2%) -> 0.15 | M79: 0.07 | N79: =M79+3% -> 0.1 | O79: =N79+3% -> 0.13 | P79: =MAX(G79,10%) -> 0.1 | R79: =MAX(J79,10%) -> 0.1 | T79: =MAX(20%,G79) -> 0.2 | U79: =MAX(J79,20%) -> 0.2 | V79: =IFERROR(IF(VLOOKUP(D79,期货合约要素!$D:$Q,12,0)=0,"",VLOOKUP(D79,期货合约要素!$D:$Q,12,0)),IF(VLOOKUP(D79,期权合约要素!$D:$V,17,0)=0,"",VLOOKUP(D79,期权合约要素!$D:$V,17,0))) | W79: =IFERROR(IF(VLOOKUP(D79,期货合约要素!$D:$Q,14,0)=0,"",VLOOKUP(D79,期货合约要素!$D:$Q,14,0)),IF(VLOOKUP(D79,期权合约要素!$D:$V,19,0)=0,"",VLOOKUP(D79,期权合约要素!$D:$V,19,0)))
C80: 花生 | D80: PK | E80: 5吨 | F80: 0.05 | G80: 0.07 | H80: =MAX(G80,N80+2%) -> 0.11 | I80: =MAX(G80,O80+2%) -> 0.14 | J80: 0.07 | K80: =MAX(J80,N80+2%) -> 0.11 | L80: =MAX(J80,O80+2%) -> 0.14 | M80: 0.06 | N80: =M80+3% -> 0.09 | O80: =N80+3% -> 0.12 | P80: =MAX(G80,10%) -> 0.1 | R80: =MAX(J80,10%) -> 0.1 | T80: =MAX(20%,G80) -> 0.2 | U80: =MAX(J80,20%) -> 0.2 | V80: =IFERROR(IF(VLOOKUP(D80,期货合约要素!$D:$Q,12,0)=0,"",VLOOKUP(D80,期货合约要素!$D:$Q,12,0)),IF(VLOOKUP(D80,期权合约要素!$D:$V,17,0)=0,"",VLOOKUP(D80,期权合约要素!$D:$V,17,0))) -> √ | W80: =IFERROR(IF(VLOOKUP(D80,期货合约要素!$D:$Q,14,0)=0,"",VLOOKUP(D80,期货合约要素!$D:$Q,14,0)),IF(VLOOKUP(D80,期权合约要素!$D:$V,19,0)=0,"",VLOOKUP(D80,期权合约要素!$D:$V,19,0))) -> √
... C84: 烧碱 | D84: SH | E84: 30吨 | F84: 0.08 | G84: 0.08 | H84: =MAX(G84,N84+2%) -> 0.12 | I84: =MAX(G84,O84+2%) -> 0.15 | J84: 0.08 | K84: =MAX(J84,N84+2%) -> 0.12 | L84: =MAX(J84,O84+2%) -> 0.15 | M84: 0.07 | N84: =M84+3% -> 0.1 | O84: =N84+3% -> 0.13 | P84: =MAX(G84,10%) -> 0.1 | R84: =MAX(J84,10%) -> 0.1 | T84: =MAX(20%,G84) -> 0.2 | U84: =MAX(J84,20%) -> 0.2 | V84: =IFERROR(IF(VLOOKUP(D84,期货合约要素!$D:$Q,12,0)=0,"",VLOOKUP(D84,期货合约要素!$D:$Q,12,0)),IF(VLOOKUP(D84,期权合约要素!$D:$V,17,0)=0,"",VLOOKUP(D84,期权合约要素!$D:$V,17,0))) | W84: =IFERROR(IF(VLOOKUP(D84,期货合约要素!$D:$Q,14,0)=0,"",VLOOKUP(D84,期货合约要素!$D:$Q,14,0)),IF(VLOOKUP(D84,期权合约要素!$D:$V,19,0)=0,"",VLOOKUP(D84,期权合约要素!$D:$V,19,0)))
C85: 烧碱 SH607 | G85: 0.12 | H85: =MAX(G85,N85+2%) -> 0.15 | I85: =MAX(G85,O85+2%) -> 0.18 | J85: 0.12 | K85: =MAX(J85,N85+2%) -> 0.15 | L85: =MAX(J85,O85+2%) -> 0.18 | M85: 0.1 | N85: =M85+3% -> 0.13 | O85: =N85+3% -> 0.16 | P85: =MAX(G85,10%) -> 0.12 | R85: =MAX(J85,10%) -> 0.12 | T85: =MAX(20%,G85) -> 0.2 | U85: =MAX(J85,20%) -> 0.2
C86: 瓶片 | D86: PR | E86: 15吨 | F86: 0.09 | G86: 0.07 | H86: =MAX(G86,N86+2%) -> 0.11 | I86: =MAX(G86,O86+2%) -> 0.14 | J86: 0.07 | K86: =MAX(J86,N86+2%) -> 0.11 | L86: =MAX(J86,O86+2%) -> 0.14 | M86: 0.06 | N86: =M86+3% -> 0.09 | O86: =N86+3% -> 0.12 | P86: =MAX(G86,10%) -> 0.1 | R86: =MAX(J86,10%) -> 0.1 | T86: =MAX(20%,G86) -> 0.2 | U86: =MAX(J86,20%) -> 0.2 | V86: =IFERROR(IF(VLOOKUP(D86,期货合约要素!$D:$Q,12,0)=0,"",VLOOKUP(D86,期货合约要素!$D:$Q,12,0)),IF(VLOOKUP(D86,期权合约要素!$D:$V,17,0)=0,"",VLOOKUP(D86,期权合约要素!$D:$V,17,0))) -> √ | W86: =IFERROR(IF(VLOOKUP(D86,期货合约要素!$D:$Q,14,0)=0,"",VLOOKUP(D86,期货合约要素!$D:$Q,14,0)),IF(VLOOKUP(D86,期权合约要素!$D:$V,19,0)=0,"",VLOOKUP(D86,期权合约要素!$D:$V,19,0))) -> √
C87: 瓶片 PR607 | G87: 0.13 | H87: =MAX(G87,N87+2%) -> 0.16 | I87: =MAX(G87,O87+2%) -> 0.19 | J87: 0.13 | K87: =MAX(J87,N87+2%) -> 0.16 | L87: =MAX(J87,O87+2%) -> 0.19 | M87: 0.11 | N87: =M87+3% -> 0.14 | O87: =N87+3% -> 0.17 | P87: =MAX(G87,10%) -> 0.13 | R87: =MAX(J87,10%) -> 0.13 | T87: =MAX(20%,G87) -> 0.2 | U87: =MAX(J87,20%) -> 0.2
C88: 瓶片 PR608-PR609 | G88: 0.1 | H88: =MAX(G88,N88+2%) -> 0.14 | I88: =MAX(G88,O88+2%) -> 0.17 | J88: 0.1 | K88: =MAX(J88,N88+2%) -> 0.14 | L88: =MAX(J88,O88+2%) -> 0.17 | M88: 0.09 | N88: =M88+3% -> 0.12 | O88: =N88+3% -> 0.15 | P88: =MAX(G88,10%) -> 0.1 | R88: =MAX(J88,10%) -> 0.1 | T88: =MAX(20%,G88) -> 0.2 | U88: =MAX(J88,20%) -> 0.2
C89: 丙烯 | D89: PL | E89: 20吨 | F89: 0.09 | G89: 0.07 | H89: =MAX(G89,N89+2%) -> 0.11 | I89: =MAX(G89,O89+2%) -> 0.14 | J89: 0.07 | K89: =MAX(J89,N89+2%) -> 0.11 | L89: =MAX(J89,O89+2%) -> 0.14 | M89: 0.06 | N89: =M89+3% -> 0.09 | O89: =N89+3% -> 0.12 | P89: =MAX(G89,10%) -> 0.1 | R89: =MAX(J89,10%) -> 0.1 | T89: =MAX(20%,G89) -> 0.2 | U89: =MAX(J89,20%) -> 0.2 | V89: =IFERROR(IF(VLOOKUP(D89,期货合约要素!$D:$Q,12,0)=0,"",VLOOKUP(D89,期货合约要素!$D:$Q,12,0)),IF(VLOOKUP(D89,期权合约要素!$D:$V,17,0)=0,"",VLOOKUP(D89,期权合约要素!$D:$V,17,0))) | W89: =IFERROR(IF(VLOOKUP(D89,期货合约要素!$D:$Q,14,0)=0,"",VLOOKUP(D89,期货合约要素!$D:$Q,14,0)),IF(VLOOKUP(D89,期权合约要素!$D:$V,19,0)=0,"",VLOOKUP(D89,期权合约要素!$D:$V,19,0)))
C90: 丙烯 PL607 | G90: 0.11 | H90: =MAX(G90,N90+2%) -> 0.14 | I90: =MAX(G90,O90+2%) -> 0.17 | J90: 0.11 | K90: =MAX(J90,N90+2%) -> 0.14 | L90: =MAX(J90,O90+2%) -> 0.17 | M90: 0.09 | N90: =M90+3% -> 0.12 | O90: =N90+3% -> 0.15 | P90: =MAX(G90,10%) -> 0.11 | R90: =MAX(J90,10%) -> 0.11 | T90: =MAX(20%,G90) -> 0.2 | U90: =MAX(J90,20%) -> 0.2
C91: 丙烯 PL608-PL609 | G91: 0.1 | H91: =MAX(G91,N91+2%) -> 0.14 | I91: =MAX(G91,O91+2%) -> 0.17 | J91: 0.1 | K91: =MAX(J91,N91+2%) -> 0.14 | L91: =MAX(J91,O91+2%) -> 0.17 | M91: 0.09 | N91: =M91+3% -> 0.12 | O91: =N91+3% -> 0.15 | P91: =MAX(G91,10%) -> 0.1 | R91: =MAX(J91,10%) -> 0.1 | T91: =MAX(20%,G91) -> 0.2 | U91: =MAX(J91,20%) -> 0.2
C92: 红枣 | D92: CJ | E92: 5吨 | F92: 0.06 | G92: 0.08 | H92: =MAX(G92,N92+2%) -> 0.12 | I92: =MAX(G92,O92+2%) -> 0.15 | J92: 0.08 | K92: =MAX(J92,N92+2%) -> 0.12 | L92: =MAX(J92,O92+2%) -> 0.15 | M92: 0.07 | N92: =M92+3% -> 0.1 | O92: =N92+3% -> 0.13 | P92: 第一个日历日至第15个日历日 （投机） | Q92: 第一个日历日至第15个日历日 （套保） | R92: 第16个日历日起 （投机） | S92: 第16个日历日起 （套保） | T92: 第1个日历日起 （投机） | U92: 第1个日历日起 （套保） | V92: =IFERROR(IF(VLOOKUP(D92,期货合约要素!$D:$Q,12,0)=0,"",VLOOKUP(D92,期货合约要素!$D:$Q,12,0)),IF(VLOOKUP(D92,期权合约要素!$D:$V,17,0)=0,"",VLOOKUP(D92,期权合约要素!$D:$V,17,0))) | W92: =IFERROR(IF(VLOOKUP(D92,期货合约要素!$D:$Q,14,0)=0,"",VLOOKUP(D92,期货合约要素!$D:$Q,14,0)),IF(VLOOKUP(D92,期权合约要素!$D:$V,19,0)=0,"",VLOOKUP(D92,期权合约要素!$D:$V,19,0)))
P93: =MAX(G92,10%) -> 0.1 | Q93: =MAX(J92,10%) -> 0.1 | R93: =MAX(G92,15%) -> 0.15 | S93: =MAX(J92,15%) -> 0.15 | T93: =MAX(G92,20%) -> 0.2 | U93: =MAX(J92,20%) -> 0.2
C94: 对二甲苯 | D94: PX | E94: 5吨 | F94: 0.1 | G94: 0.07 | H94: =MAX(G94,N94+2%) -> 0.11 | I94: =MAX(G94,O94+2%) -> 0.14 | J94: 0.07 | K94: =MAX(J94,N94+2%) -> 0.11 | L94: =MAX(J94,O94+2%) -> 0.14 | M94: 0.06 | N94: =M94+3% -> 0.09 | O94: =N94+3% -> 0.12 | P94: =MAX(G94,10%) -> 0.1 | Q94: =MAX(J94,10%) -> 0.1 | R94: =MAX(G94,15%) -> 0.15 | S94: =MAX(J94,15%) -> 0.15 | T94: =MAX(G94,20%) -> 0.2 | U94: =MAX(J94,20%) -> 0.2 | V94: =IFERROR(IF(VLOOKUP(D94,期货合约要素!$D:$Q,12,0)=0,"",VLOOKUP(D94,期货合约要素!$D:$Q,12,0)),IF(VLOOKUP(D94,期权合约要素!$D:$V,17,0)=0,"",VLOOKUP(D94,期权合约要素!$D:$V,17,0))) -> √ | W94: =IFERROR(IF(VLOOKUP(D94,期货合约要素!$D:$Q,14,0)=0,"",VLOOKUP(D94,期货合约要素!$D:$Q,14,0)),IF(VLOOKUP(D94,期权合约要素!$D:$V,19,0)=0,"",VLOOKUP(D94,期权合约要素!$D:$V,19,0))) -> √
C95: 对二甲苯 PX607 | G95: 0.13 | H95: =MAX(G95,N95+2%) -> 0.16 | I95: =MAX(G95,O95+2%) -> 0.19 | J95: 0.13 | K95: =MAX(J95,N95+2%) -> 0.16 | L95: =MAX(J95,O95+2%) -> 0.19 | M95: 0.11 | N95: =M95+3% -> 0.14 | O95: =N95+3% -> 0.17 | P95: =MAX(G95,10%) -> 0.13 | Q95: =MAX(J95,10%) -> 0.13 | R95: =MAX(G95,15%) -> 0.15 | S95: =MAX(J95,15%) -> 0.15 | T95: =MAX(G95,20%) -> 0.2 | U95: =MAX(J95,20%) -> 0.2
C96: 对二甲苯 PX608-PX609 | G96: 0.1 | H96: =MAX(G96,N96+2%) -> 0.14 | I96: =MAX(G96,O96+2%) -> 0.17 | J96: 0.1 | K96: =MAX(J96,N96+2%) -> 0.14 | L96: =MAX(J96,O96+2%) -> 0.17 | M96: 0.09 | N96: =M96+3% -> 0.12 | O96: =N96+3% -> 0.15 | P96: =MAX(G96,10%) -> 0.1 | Q96: =MAX(J96,10%) -> 0.1 | R96: =MAX(G96,15%) -> 0.15 | S96: =MAX(J96,15%) -> 0.15 | T96: =MAX(G96,20%) -> 0.2 | U96: =MAX(J96,20%) -> 0.2
B98: 交易所 | C98: 品种名称 | D98: 品种代码 | E98: 合约单位 | F98: 公司加收 | G98: 按连续单边市调整的交易所保证金率 | M98: 连续单边市涨跌停板 | P98: 交易所时间梯度保证金 | V98: QFII&RQFII | W98: 国际化品种
G99: 投机 | J99: 套保 | P99: 交割月前1个月 | T99: 交割月
G100: 一般月份 | H100: 第一个单边市结算时 | I100: 第二个同方向单边市结算时 | J100: 一般月份 | K100: 第一个单边市结算时 | L100: 第二个同方向单边市结算时 | M100: 一般月份 | N100: 第一个单边市结算后 | O100: 第二个同方向单边市结算后 | P100: 第15个交易日起 （投机） | R100: 第15个交易日起 （套保） | T100: 第1个交易日起 （投机） | U100: 第1个交易日起 （套保）
B101: 大连 商品 交易所 | C101: 黄大豆一号 | D101: a | E101: 10吨 | F101: 0.05 | G101: 0.07 | H101: =MAX(G101,N101+2%) -> 0.11 | I101: =MAX(G101,O101+2%) -> 0.13 | J101: 0.07 | K101: =MAX(J101,N101+2%) -> 0.11 | L101: =MAX(J101,O101+2%) -> 0.13 | M101: 0.06 | N101: =M101+3% -> 0.09 | O101: =N101+2% -> 0.11 | P101: =MAX(G101,10%) -> 0.1 | R101: =MAX(J101,10%) -> 0.1 | T101: =MAX(20%,G101) -> 0.2 | U101: =MAX(J101,20%) -> 0.2 | V101: =IFERROR(IF(VLOOKUP(D101,期货合约要素!$D:$Q,12,0)=0,"",VLOOKUP(D101,期货合约要素!$D:$Q,12,0)),IF(VLOOKUP(D101,期权合约要素!$D:$V,17,0)=0,"",VLOOKUP(D101,期权合约要素!$D:$V,17,0))) -> √ | W101: =IFERROR(IF(VLOOKUP(D101,期货合约要素!$D:$Q,14,0)=0,"",VLOOKUP(D101,期货合约要素!$D:$Q,14,0)),IF(VLOOKUP(D101,期权合约要素!$D:$V,19,0)=0,"",VLOOKUP(D101,期权合约要素!$D:$V,19,0))) -> √
C102: 黄大豆二号 | D102: b | E102: 10吨 | F102: 0.05 | G102: 0.07 | H102: =MAX(G102,N102+2%) -> 0.11 | I102: =MAX(G102,O102+2%) -> 0.13 | J102: 0.07 | K102: =MAX(J102,N102+2%) -> 0.11 | L102: =MAX(J102,O102+2%) -> 0.13 | M102: 0.06 | N102: =M102+3% -> 0.09 | O102: =N102+2% -> 0.11 | P102: =MAX(G102,10%) -> 0.1 | R102: =MAX(J102,10%) -> 0.1 | T102: =MAX(20%,G102) -> 0.2 | U102: =MAX(J102,20%) -> 0.2 | V102: =IFERROR(IF(VLOOKUP(D102,期货合约要素!$D:$Q,12,0)=0,"",VLOOKUP(D102,期货合约要素!$D:$Q,12,0)),IF(VLOOKUP(D102,期权合约要素!$D:$V,17,0)=0,"",VLOOKUP(D102,期权合约要素!$D:$V,17,0))) -> √ | W102: =IFERROR(IF(VLOOKUP(D102,期货合约要素!$D:$Q,14,0)=0,"",VLOOKUP(D102,期货合约要素!$D:$Q,14,0)),IF(VLOOKUP(D102,期权合约要素!$D:$V,19,0)=0,"",VLOOKUP(D102,期权合约要素!$D:$V,19,0))) -> √
C103: 豆粕 | D103: m | E103: 10吨 | F103: 0.06 | G103: 0.07 | H103: =MAX(G103,N103+2%) -> 0.11 | I103: =MAX(G103,O103+2%) -> 0.13 | J103: 0.07 | K103: =MAX(J103,N103+2%) -> 0.11 | L103: =MAX(J103,O103+2%) -> 0.13 | M103: 0.06 | N103: =M103+3% -> 0.09 | O103: =N103+2% -> 0.11 | P103: =MAX(G103,10%) -> 0.1 | R103: =MAX(J103,10%) -> 0.1 | T103: =MAX(20%,G103) -> 0.2 | U103: =MAX(J103,20%) -> 0.2 | V103: =IFERROR(IF(VLOOKUP(D103,期货合约要素!$D:$Q,12,0)=0,"",VLOOKUP(D103,期货合约要素!$D:$Q,12,0)),IF(VLOOKUP(D103,期权合约要素!$D:$V,17,0)=0,"",VLOOKUP(D103,期权合约要素!$D:$V,17,0))) -> √ | W103: =IFERROR(IF(VLOOKUP(D103,期货合约要素!$D:$Q,14,0)=0,"",VLOOKUP(D103,期货合约要素!$D:$Q,14,0)),IF(VLOOKUP(D103,期权合约要素!$D:$V,19,0)=0,"",VLOOKUP(D103,期权合约要素!$D:$V,19,0))) -> √
C104: 豆油 | D104: y | E104: 10吨 | F104: 0.08 | G104: 0.07 | H104: =MAX(G104,N104+2%) -> 0.11 | I104: =MAX(G104,O104+2%) -> 0.13 | J104: 0.07 | K104: =MAX(J104,N104+2%) -> 0.11 | L104: =MAX(J104,O104+2%) -> 0.13 | M104: 0.06 | N104: =M104+3% -> 0.09 | O104: =N104+2% -> 0.11 | P104: =MAX(G104,10%) -> 0.1 | R104: =MAX(J104,10%) -> 0.1 | T104: =MAX(20%,G104) -> 0.2 | U104: =MAX(J104,20%) -> 0.2 | V104: =IFERROR(IF(VLOOKUP(D104,期货合约要素!$D:$Q,12,0)=0,"",VLOOKUP(D104,期货合约要素!$D:$Q,12,0)),IF(VLOOKUP(D104,期权合约要素!$D:$V,17,0)=0,"",VLOOKUP(D104,期权合约要素!$D:$V,17,0))) -> √ | W104: =IFERROR(IF(VLOOKUP(D104,期货合约要素!$D:$Q,14,0)=0,"",VLOOKUP(D104,期货合约要素!$D:$Q,14,0)),IF(VLOOKUP(D104,期权合约要素!$D:$V,19,0)=0,"",VLOOKUP(D104,期权合约要素!$D:$V,19,0))) -> √
C105: 棕榈油 | D105: p | E105: 10吨 | F105: 0.08 | G105: 0.08 | H105: =MAX(G105,N105+2%) -> 0.12 | I105: =MAX(G105,O105+2%) -> 0.14 | J105: 0.08 | K105: =MAX(J105,N105+2%) -> 0.12 | L105: =MAX(J105,O105+2%) -> 0.14 | M105: 0.07 | N105: =M105+3% -> 0.1 | O105: =N105+2% -> 0.12 | P105: =MAX(G105,10%) -> 0.1 | R105: =MAX(J105,10%) -> 0.1 | T105: =MAX(20%,G105) -> 0.2 | U105: =MAX(J105,20%) -> 0.2 | V105: =IFERROR(IF(VLOOKUP(D105,期货合约要素!$D:$Q,12,0)=0,"",VLOOKUP(D105,期货合约要素!$D:$Q,12,0)),IF(VLOOKUP(D105,期权合约要素!$D:$V,17,0)=0,"",VLOOKUP(D105,期权合约要素!$D:$V,17,0))) -> √ | W105: =IFERROR(IF(VLOOKUP(D105,期货合约要素!$D:$Q,14,0)=0,"",VLOOKUP(D105,期货合约要素!$D:$Q,14,0)),IF(VLOOKUP(D105,期权合约要素!$D:$V,19,0)=0,"",VLOOKUP(D105,期权合约要素!$D:$V,19,0))) -> √
C106: 焦煤 | D106: jm | E106: 60吨 | F106: 0.1 | G106: 0.12 | H106: =MAX(G106,N106+2%) -> 0.13 | I106: =MAX(G106,O106+2%) -> 0.15 | J106: 0.12 | K106: =MAX(J106,N106+2%) -> 0.13 | L106: =MAX(J106,O106+2%) -> 0.15 | M106: 0.08 | N106: =M106+3% -> 0.11 | O106: =N106+2% -> 0.13 | P106: =MAX(G106,10%) -> 0.12 | R106: =MAX(J106,10%) -> 0.12 | T106: =MAX(20%,G106) -> 0.2 | U106: =MAX(J106,20%) -> 0.2 | V106: =IFERROR(IF(VLOOKUP(D106,期货合约要素!$D:$Q,12,0)=0,"",VLOOKUP(D106,期货合约要素!$D:$Q,12,0)),IF(VLOOKUP(D106,期权合约要素!$D:$V,17,0)=0,"",VLOOKUP(D106,期权合约要素!$D:$V,17,0))) | W106: =IFERROR(IF(VLOOKUP(D106,期货合约要素!$D:$Q,14,0)=0,"",VLOOKUP(D106,期货合约要素!$D:$Q,14,0)),IF(VLOOKUP(D106,期权合约要素!$D:$V,19,0)=0,"",VLOOKUP(D106,期权合约要素!$D:$V,19,0)))
...

Sheet 限仓规则
A1: 点此返回目录
B2: 各交易所投机限仓标准（单边计算） | M2: 上交所股票期权限仓表
B3: 交易所 | C3: 品种名称 | D3: 品种代码 | E3: 合约挂牌至交割月前第二月的最后一个交易日 | G3: 交割月前第一月 | H3: 交割月份 | I3: 备注 | J3: QFII&RQFII | K3: 国际化品种 | M3: 投资者满足的条件 | N3: 权利仓持仓限额（张） | O3: 总持仓限额（张） | P3: 单日买入开仓限额（张） | Q3: 备注
B4: 上期所 | C4: 铝 | D4: al | E4: 市场单边持仓量≥10万手， 限仓比例10% | G4: 3000 | H4: 1000 | I4: 需调整为5手整数倍进入交割月 | J4: =IFERROR(IF(VLOOKUP(D4,期货合约要素!$D:$Q,12,0)=0,"",VLOOKUP(D4,期货合约要素!$D:$Q,12,0)),IF(VLOOKUP(D4,期权合约要素!$D:$V,17,0)=0,"",VLOOKUP(D4,期权合约要素!$D:$V,17,0))) -> √ | K4: =IFERROR(IF(VLOOKUP(D4,期货合约要素!$D:$Q,14,0)=0,"",VLOOKUP(D4,期货合约要素!$D:$Q,14,0)),IF(VLOOKUP(D4,期权合约要素!$D:$V,19,0)=0,"",VLOOKUP(D4,期权合约要素!$D:$V,19,0))) | M4: 新开立合约账户 | N4: 100 | O4: 200 | P4: 400 | Q4: 客户在多家经纪商开户的，各经纪商单独控制持仓限额。
E5: 市场单边持仓量＜10万手， 限仓10000 | J5: =IFERROR(IF(VLOOKUP(D5,期货合约要素!$D:$Q,12,0)=0,"",VLOOKUP(D5,期货合约要素!$D:$Q,12,0)),IF(VLOOKUP(D5,期权合约要素!$D:$V,17,0)=0,"",VLOOKUP(D5,期权合约要素!$D:$V,17,0))) -> #N/A | K5: =IFERROR(IF(VLOOKUP(D5,期货合约要素!$D:$Q,14,0)=0,"",VLOOKUP(D5,期货合约要素!$D:$Q,14,0)),IF(VLOOKUP(D5,期权合约要素!$D:$V,19,0)=0,"",VLOOKUP(D5,期权合约要素!$D:$V,19,0))) -> #N/A
C6: 铜 | D6: cu | E6: 市场单边持仓量≥8万手， 限仓比例10% | G6: 3000 | H6: 1000 | J6: =IFERROR(IF(VLOOKUP(D6,期货合约要素!$D:$Q,12,0)=0,"",VLOOKUP(D6,期货合约要素!$D:$Q,12,0)),IF(VLOOKUP(D6,期权合约要素!$D:$V,17,0)=0,"",VLOOKUP(D6,期权合约要素!$D:$V,17,0))) -> √ | K6: =IFERROR(IF(VLOOKUP(D6,期货合约要素!$D:$Q,14,0)=0,"",VLOOKUP(D6,期货合约要素!$D:$Q,14,0)),IF(VLOOKUP(D6,期权合约要素!$D:$V,19,0)=0,"",VLOOKUP(D6,期权合约要素!$D:$V,19,0))) | M6: （1）三级投资者 （2）开户满10个交易日 （3）成交量达到100张 | N6: 1000 | O6: 2000 | P6: 4000
E7: 市场单边持仓量＜8万手，限仓8000 | J7: =IFERROR(IF(VLOOKUP(D7,期货合约要素!$D:$Q,12,0)=0,"",VLOOKUP(D7,期货合约要素!$D:$Q,12,0)),IF(VLOOKUP(D7,期权合约要素!$D:$V,17,0)=0,"",VLOOKUP(D7,期权合约要素!$D:$V,17,0))) -> #N/A | K7: =IFERROR(IF(VLOOKUP(D7,期货合约要素!$D:$Q,14,0)=0,"",VLOOKUP(D7,期货合约要素!$D:$Q,14,0)),IF(VLOOKUP(D7,期权合约要素!$D:$V,19,0)=0,"",VLOOKUP(D7,期权合约要素!$D:$V,19,0))) -> #N/A
C8: 锌 | D8: zn | E8: 市场单边持仓量≥6万手， 限仓比例10% | G8: 2400 | H8: 800 | J8: =IFERROR(IF(VLOOKUP(D8,期货合约要素!$D:$Q,12,0)=0,"",VLOOKUP(D8,期货合约要素!$D:$Q,12,0)),IF(VLOOKUP(D8,期权合约要素!$D:$V,17,0)=0,"",VLOOKUP(D8,期权合约要素!$D:$V,17,0))) -> √ | K8: =IFERROR(IF(VLOOKUP(D8,期货合约要素!$D:$Q,14,0)=0,"",VLOOKUP(D8,期货合约要素!$D:$Q,14,0)),IF(VLOOKUP(D8,期权合约要素!$D:$V,19,0)=0,"",VLOOKUP(D8,期权合约要素!$D:$V,19,0)))
E9: 市场单边持仓量＜6万手， 限仓6000 | J9: =IFERROR(IF(VLOOKUP(D9,期货合约要素!$D:$Q,12,0)=0,"",VLOOKUP(D9,期货合约要素!$D:$Q,12,0)),IF(VLOOKUP(D9,期权合约要素!$D:$V,17,0)=0,"",VLOOKUP(D9,期权合约要素!$D:$V,17,0))) -> #N/A | K9: =IFERROR(IF(VLOOKUP(D9,期货合约要素!$D:$Q,14,0)=0,"",VLOOKUP(D9,期货合约要素!$D:$Q,14,0)),IF(VLOOKUP(D9,期权合约要素!$D:$V,19,0)=0,"",VLOOKUP(D9,期权合约要素!$D:$V,19,0))) -> #N/A | M9: （1）三级投资者 （2）开户满10个交易日 （3）成交量达到500张 （4）在我司托管的自有资产余额超过100万 | N9: 2000 | O9: 4000 | P9: 8000
C10: 铅 | D10: pb | E10: 市场单边持仓量≥5万手， 限仓比例10% | G10: 1800 | H10: 600 | J10: =IFERROR(IF(VLOOKUP(D10,期货合约要素!$D:$Q,12,0)=0,"",VLOOKUP(D10,期货合约要素!$D:$Q,12,0)),IF(VLOOKUP(D10,期权合约要素!$D:$V,17,0)=0,"",VLOOKUP(D10,期权合约要素!$D:$V,17,0))) -> √ | K10: =IFERROR(IF(VLOOKUP(D10,期货合约要素!$D:$Q,14,0)=0,"",VLOOKUP(D10,期货合约要素!$D:$Q,14,0)),IF(VLOOKUP(D10,期权合约要素!$D:$V,19,0)=0,"",VLOOKUP(D10,期权合约要素!$D:$V,19,0)))
E11: 市场单边持仓量＜5万手，限仓5000 | J11: =IFERROR(IF(VLOOKUP(D11,期货合约要素!$D:$Q,12,0)=0,"",VLOOKUP(D11,期货合约要素!$D:$Q,12,0)),IF(VLOOKUP(D11,期权合约要素!$D:$V,17,0)=0,"",VLOOKUP(D11,期权合约要素!$D:$V,17,0))) -> #N/A | K11: =IFERROR(IF(VLOOKUP(D11,期货合约要素!$D:$Q,14,0)=0,"",VLOOKUP(D11,期货合约要素!$D:$Q,14,0)),IF(VLOOKUP(D11,期权合约要素!$D:$V,19,0)=0,"",VLOOKUP(D11,期权合约要素!$D:$V,19,0))) -> #N/A
C12: 螺纹钢 | D12: rb | E12: 市场单边持仓量≥90万手，限仓比例10% | G12: 4500 | H12: 900 | I12: 需调整为30手整数倍进入交割月 | J12: =IFERROR(IF(VLOOKUP(D12,期货合约要素!$D:$Q,12,0)=0,"",VLOOKUP(D12,期货合约要素!$D:$Q,12,0)),IF(VLOOKUP(D12,期权合约要素!$D:$V,17,0)=0,"",VLOOKUP(D12,期权合约要素!$D:$V,17,0))) -> √ | K12: =IFERROR(IF(VLOOKUP(D12,期货合约要素!$D:$Q,14,0)=0,"",VLOOKUP(D12,期货合约要素!$D:$Q,14,0)),IF(VLOOKUP(D12,期权合约要素!$D:$V,19,0)=0,"",VLOOKUP(D12,期权合约要素!$D:$V,19,0)))
E13: 市场单边持仓量＜90万手，限仓90000 | J13: =IFERROR(IF(VLOOKUP(D13,期货合约要素!$D:$Q,12,0)=0,"",VLOOKUP(D13,期货合约要素!$D:$Q,12,0)),IF(VLOOKUP(D13,期权合约要素!$D:$V,17,0)=0,"",VLOOKUP(D13,期权合约要素!$D:$V,17,0))) -> #N/A | K13: =IFERROR(IF(VLOOKUP(D13,期货合约要素!$D:$Q,14,0)=0,"",VLOOKUP(D13,期货合约要素!$D:$Q,14,0)),IF(VLOOKUP(D13,期权合约要素!$D:$V,19,0)=0,"",VLOOKUP(D13,期权合约要素!$D:$V,19,0))) -> #N/A | M13: （1）三级投资者 （2）开户满10个交易日 （3）成交量达到1000张 （4）在我司托管的自有资产余额超过300万 （须先向上交所报备，下一交易日设置） | N13: 5000 | O13: 10000 | P13: 10000
C14: 线材 | D14: wr | E14: 市场单边持仓量≥22.5万手， 限仓比例10% | G14: 1800 | H14: 360 | J14: =IFERROR(IF(VLOOKUP(D14,期货合约要素!$D:$Q,12,0)=0,"",VLOOKUP(D14,期货合约要素!$D:$Q,12,0)),IF(VLOOKUP(D14,期权合约要素!$D:$V,17,0)=0,"",VLOOKUP(D14,期权合约要素!$D:$V,17,0))) | K14: =IFERROR(IF(VLOOKUP(D14,期货合约要素!$D:$Q,14,0)=0,"",VLOOKUP(D14,期货合约要素!$D:$Q,14,0)),IF(VLOOKUP(D14,期权合约要素!$D:$V,19,0)=0,"",VLOOKUP(D14,期权合约要素!$D:$V,19,0)))
E15: 市场单边持仓量＜22.5万手，限仓22500 | J15: =IFERROR(IF(VLOOKUP(D15,期货合约要素!$D:$Q,12,0)=0,"",VLOOKUP(D15,期货合约要素!$D:$Q,12,0)),IF(VLOOKUP(D15,期权合约要素!$D:$V,17,0)=0,"",VLOOKUP(D15,期权合约要素!$D:$V,17,0))) -> #N/A | K15: =IFERROR(IF(VLOOKUP(D15,期货合约要素!$D:$Q,14,0)=0,"",VLOOKUP(D15,期货合约要素!$D:$Q,14,0)),IF(VLOOKUP(D15,期权合约要素!$D:$V,19,0)=0,"",VLOOKUP(D15,期权合约要素!$D:$V,19,0))) -> #N/A
C16: 热卷 | D16: hc | E16: 市场单边持仓量≥120万手， 限仓比例10% | G16: 9000 | H16: 1800 | J16: =IFERROR(IF(VLOOKUP(D16,期货合约要素!$D:$Q,12,0)=0,"",VLOOKUP(D16,期货合约要素!$D:$Q,12,0)),IF(VLOOKUP(D16,期权合约要素!$D:$V,17,0)=0,"",VLOOKUP(D16,期权合约要素!$D:$V,17,0))) -> √ | K16: =IFERROR(IF(VLOOKUP(D16,期货合约要素!$D:$Q,14,0)=0,"",VLOOKUP(D16,期货合约要素!$D:$Q,14,0)),IF(VLOOKUP(D16,期权合约要素!$D:$V,19,0)=0,"",VLOOKUP(D16,期权合约要素!$D:$V,19,0)))
E17: 市场单边持仓量＜120万手，限仓120000 | J17: =IFERROR(IF(VLOOKUP(D17,期货合约要素!$D:$Q,12,0)=0,"",VLOOKUP(D17,期货合约要素!$D:$Q,12,0)),IF(VLOOKUP(D17,期权合约要素!$D:$V,17,0)=0,"",VLOOKUP(D17,期权合约要素!$D:$V,17,0))) -> #N/A | K17: =IFERROR(IF(VLOOKUP(D17,期货合约要素!$D:$Q,14,0)=0,"",VLOOKUP(D17,期货合约要素!$D:$Q,14,0)),IF(VLOOKUP(D17,期权合约要素!$D:$V,19,0)=0,"",VLOOKUP(D17,期权合约要素!$D:$V,19,0))) -> #N/A
C18: 氧化铝 | D18: ao | E18: 8000 | G18: 900 | H18: 300 | I18: 需调整为15手整数倍进入交割月 | J18: =IFERROR(IF(VLOOKUP(D18,期货合约要素!$D:$Q,12,0)=0,"",VLOOKUP(D18,期货合约要素!$D:$Q,12,0)),IF(VLOOKUP(D18,期权合约要素!$D:$V,17,0)=0,"",VLOOKUP(D18,期权合约要素!$D:$V,17,0))) | K18: =IFERROR(IF(VLOOKUP(D18,期货合约要素!$D:$Q,14,0)=0,"",VLOOKUP(D18,期货合约要素!$D:$Q,14,0)),IF(VLOOKUP(D18,期权合约要素!$D:$V,19,0)=0,"",VLOOKUP(D18,期权合约要素!$D:$V,19,0)))
C19: 不锈钢 | D19: ss | E19: 市场单边持仓量≥7万手， 限仓比例10% | G19: 1800 | H19: 360 | I19: 需调整为12手整数倍进入交割月 | J19: =IFERROR(IF(VLOOKUP(D19,期货合约要素!$D:$Q,12,0)=0,"",VLOOKUP(D19,期货合约要素!$D:$Q,12,0)),IF(VLOOKUP(D19,期权合约要素!$D:$V,17,0)=0,"",VLOOKUP(D19,期权合约要素!$D:$V,17,0))) -> √ | K19: =IFERROR(IF(VLOOKUP(D19,期货合约要素!$D:$Q,14,0)=0,"",VLOOKUP(D19,期货合约要素!$D:$Q,14,0)),IF(VLOOKUP(D19,期权合约要素!$D:$V,19,0)=0,"",VLOOKUP(D19,期权合约要素!$D:$V,19,0)))
E20: 市场单边持仓量＜7万手，限仓7000 | J20: =IFERROR(IF(VLOOKUP(D20,期货合约要素!$D:$Q,12,0)=0,"",VLOOKUP(D20,期货合约要素!$D:$Q,12,0)),IF(VLOOKUP(D20,期权合约要素!$D:$V,17,0)=0,"",VLOOKUP(D20,期权合约要素!$D:$V,17,0))) -> #N/A | K20: =IFERROR(IF(VLOOKUP(D20,期货合约要素!$D:$Q,14,0)=0,"",VLOOKUP(D20,期货合约要素!$D:$Q,14,0)),IF(VLOOKUP(D20,期权合约要素!$D:$V,19,0)=0,"",VLOOKUP(D20,期权合约要素!$D:$V,19,0))) -> #N/A
C21: 镍 | D21: ni | E21: 市场单边持仓量≥6万手， 限仓比例10% | G21: 1800 | H21: 600 | I21: 需调整为6手整数倍进入交割月 | J21: =IFERROR(IF(VLOOKUP(D21,期货合约要素!$D:$Q,12,0)=0,"",VLOOKUP(D21,期货合约要素!$D:$Q,12,0)),IF(VLOOKUP(D21,期权合约要素!$D:$V,17,0)=0,"",VLOOKUP(D21,期权合约要素!$D:$V,17,0))) -> √ | K21: =IFERROR(IF(VLOOKUP(D21,期货合约要素!$D:$Q,14,0)=0,"",VLOOKUP(D21,期货合约要素!$D:$Q,14,0)),IF(VLOOKUP(D21,期权合约要素!$D:$V,19,0)=0,"",VLOOKUP(D21,期权合约要素!$D:$V,19,0))) -> √ | M21: 深交所股票期权限仓表
E22: 市场单边持仓量＜6万手，限仓6000 | J22: =IFERROR(IF(VLOOKUP(D22,期货合约要素!$D:$Q,12,0)=0,"",VLOOKUP(D22,期货合约要素!$D:$Q,12,0)),IF(VLOOKUP(D22,期权合约要素!$D:$V,17,0)=0,"",VLOOKUP(D22,期权合约要素!$D:$V,17,0))) -> #N/A | K22: =IFERROR(IF(VLOOKUP(D22,期货合约要素!$D:$Q,14,0)=0,"",VLOOKUP(D22,期货合约要素!$D:$Q,14,0)),IF(VLOOKUP(D22,期权合约要素!$D:$V,19,0)=0,"",VLOOKUP(D22,期权合约要素!$D:$V,19,0))) -> #N/A | M22: 投资者满足的条件 | N22: 权利仓持仓限额（张） | O22: 总持仓限额（张） | P22: 单日买入开仓限额（张） | Q22: 备注
C23: 锡 | D23: sn | E23: 市场单边持仓量≥1.5万手， 限仓比例10% | G23: 600 | H23: 200 | I23: 需调整为2手整数倍进入交割月 | J23: =IFERROR(IF(VLOOKUP(D23,期货合约要素!$D:$Q,12,0)=0,"",VLOOKUP(D23,期货合约要素!$D:$Q,12,0)),IF(VLOOKUP(D23,期权合约要素!$D:$V,17,0)=0,"",VLOOKUP(D23,期权合约要素!$D:$V,17,0))) -> √ | K23: =IFERROR(IF(VLOOKUP(D23,期货合约要素!$D:$Q,14,0)=0,"",VLOOKUP(D23,期货合约要素!$D:$Q,14,0)),IF(VLOOKUP(D23,期权合约要素!$D:$V,19,0)=0,"",VLOOKUP(D23,期权合约要素!$D:$V,19,0)))
E24: 市场单边持仓量＜1.5万手，限仓1500 | J24: =IFERROR(IF(VLOOKUP(D24,期货合约要素!$D:$Q,12,0)=0,"",VLOOKUP(D24,期货合约要素!$D:$Q,12,0)),IF(VLOOKUP(D24,期权合约要素!$D:$V,17,0)=0,"",VLOOKUP(D24,期权合约要素!$D:$V,17,0))) -> #N/A | K24: =IFERROR(IF(VLOOKUP(D24,期货合约要素!$D:$Q,14,0)=0,"",VLOOKUP(D24,期货合约要素!$D:$Q,14,0)),IF(VLOOKUP(D24,期权合约要素!$D:$V,19,0)=0,"",VLOOKUP(D24,期权合约要素!$D:$V,19,0))) -> #N/A | M24: 新开立合约账户 | N24: 100 | O24: 200 | P24: 400 | Q24: 客户在多家经纪商开户的，各经纪商单独控制持仓限额； 深交所对单一客户合并控制权利仓5000、总持仓10000、单日买入开仓限额10000；可能存在客户不超过在经纪商的持仓限额，但是合并后达到交易所持仓限额无法开仓的情况。
C25: 丁二烯橡胶 | D25: br | E25: 市场单边持仓量≥1万手， 限仓比例10% | G25: 300 | H25: 60 | J25: =IFERROR(IF(VLOOKUP(D25,期货合约要素!$D:$Q,12,0)=0,"",VLOOKUP(D25,期货合约要素!$D:$Q,12,0)),IF(VLOOKUP(D25,期权合约要素!$D:$V,17,0)=0,"",VLOOKUP(D25,期权合约要素!$D:$V,17,0))) | K25: =IFERROR(IF(VLOOKUP(D25,期货合约要素!$D:$Q,14,0)=0,"",VLOOKUP(D25,期货合约要素!$D:$Q,14,0)),IF(VLOOKUP(D25,期权合约要素!$D:$V,19,0)=0,"",VLOOKUP(D25,期权合约要素!$D:$V,19,0)))
E26: 市场单边持仓量＜1万手，限仓1000 | J26: =IFERROR(IF(VLOOKUP(D26,期货合约要素!$D:$Q,12,0)=0,"",VLOOKUP(D26,期货合约要素!$D:$Q,12,0)),IF(VLOOKUP(D26,期权合约要素!$D:$V,17,0)=0,"",VLOOKUP(D26,期权合约要素!$D:$V,17,0))) -> #N/A | K26: =IFERROR(IF(VLOOKUP(D26,期货合约要素!$D:$Q,14,0)=0,"",VLOOKUP(D26,期货合约要素!$D:$Q,14,0)),IF(VLOOKUP(D26,期权合约要素!$D:$V,19,0)=0,"",VLOOKUP(D26,期权合约要素!$D:$V,19,0))) -> #N/A | M26: （1）三级投资者 （2）开户满10个交易日 （3）成交量达到100张 | N26: 1000 | O26: 2000 | P26: 4000
C27: 白银 | D27: ag | E27: 9000 | G27: 2700 | H27: 900 | J27: =IFERROR(IF(VLOOKUP(D27,期货合约要素!$D:$Q,12,0)=0,"",VLOOKUP(D27,期货合约要素!$D:$Q,12,0)),IF(VLOOKUP(D27,期权合约要素!$D:$V,17,0)=0,"",VLOOKUP(D27,期权合约要素!$D:$V,17,0))) -> √ | K27: =IFERROR(IF(VLOOKUP(D27,期货合约要素!$D:$Q,14,0)=0,"",VLOOKUP(D27,期货合约要素!$D:$Q,14,0)),IF(VLOOKUP(D27,期权合约要素!$D:$V,19,0)=0,"",VLOOKUP(D27,期权合约要素!$D:$V,19,0)))
C28: 纸浆 | D28: sp | E28: 4500 | G28: 900 | H28: 300 | J28: =IFERROR(IF(VLOOKUP(D28,期货合约要素!$D:$Q,12,0)=0,"",VLOOKUP(D28,期货合约要素!$D:$Q,12,0)),IF(VLOOKUP(D28,期权合约要素!$D:$V,17,0)=0,"",VLOOKUP(D28,期权合约要素!$D:$V,17,0))) -> √ | K28: =IFERROR(IF(VLOOKUP(D28,期货合约要素!$D:$Q,14,0)=0,"",VLOOKUP(D28,期货合约要素!$D:$Q,14,0)),IF(VLOOKUP(D28,期权合约要素!$D:$V,19,0)=0,"",VLOOKUP(D28,期权合约要素!$D:$V,19,0)))
C29: 黄金 | D29: au | E29: 9000 | G29: 2700 | H29: 900 | I29: 需调整为3手整数倍进入交割月 | J29: =IFERROR(IF(VLOOKUP(D29,期货合约要素!$D:$Q,12,0)=0,"",VLOOKUP(D29,期货合约要素!$D:$Q,12,0)),IF(VLOOKUP(D29,期权合约要素!$D:$V,17,0)=0,"",VLOOKUP(D29,期权合约要素!$D:$V,17,0))) -> √ | K29: =IFERROR(IF(VLOOKUP(D29,期货合约要素!$D:$Q,14,0)=0,"",VLOOKUP(D29,期货合约要素!$D:$Q,14,0)),IF(VLOOKUP(D29,期权合约要素!$D:$V,19,0)=0,"",VLOOKUP(D29,期权合约要素!$D:$V,19,0))) | M29: （1）三级投资者 （2）开户满10个交易日 （3）成交量达到500张 （4）在我司托管的自有资产余额超过100万 | N29: 2000 | O29: 4000 | P29: 8000
C30: 铸造铝合金 | D30: ad | E30: 市场单边持仓量≥9000手， 限仓比例10% | G30: 300 | H30: 90 | J30: =IFERROR(IF(VLOOKUP(D30,期货合约要素!$D:$Q,12,0)=0,"",VLOOKUP(D30,期货合约要素!$D:$Q,12,0)),IF(VLOOKUP(D30,期权合约要素!$D:$V,17,0)=0,"",VLOOKUP(D30,期权合约要素!$D:$V,17,0))) | K30: =IFERROR(IF(VLOOKUP(D30,期货合约要素!$D:$Q,14,0)=0,"",VLOOKUP(D30,期货合约要素!$D:$Q,14,0)),IF(VLOOKUP(D30,期权合约要素!$D:$V,19,0)=0,"",VLOOKUP(D30,期权合约要素!$D:$V,19,0)))
E31: 市场单边持仓量＜9000手，限仓900 | J31: =IFERROR(IF(VLOOKUP(D31,期货合约要素!$D:$Q,12,0)=0,"",VLOOKUP(D31,期货合约要素!$D:$Q,12,0)),IF(VLOOKUP(D31,期权合约要素!$D:$V,17,0)=0,"",VLOOKUP(D31,期权合约要素!$D:$V,17,0))) -> #N/A | K31: =IFERROR(IF(VLOOKUP(D31,期货合约要素!$D:$Q,14,0)=0,"",VLOOKUP(D31,期货合约要素!$D:$Q,14,0)),IF(VLOOKUP(D31,期权合约要素!$D:$V,19,0)=0,"",VLOOKUP(D31,期权合约要素!$D:$V,19,0))) -> #N/A
C32: 沥青 | D32: bu | E32: 8000 | G32: 1500 | H32: 500 | J32: =IFERROR(IF(VLOOKUP(D32,期货合约要素!$D:$Q,12,0)=0,"",VLOOKUP(D32,期货合约要素!$D:$Q,12,0)),IF(VLOOKUP(D32,期权合约要素!$D:$V,17,0)=0,"",VLOOKUP(D32,期权合约要素!$D:$V,17,0))) -> √ | K32: =IFERROR(IF(VLOOKUP(D32,期货合约要素!$D:$Q,14,0)=0,"",VLOOKUP(D32,期货合约要素!$D:$Q,14,0)),IF(VLOOKUP(D32,期权合约要素!$D:$V,19,0)=0,"",VLOOKUP(D32,期权合约要素!$D:$V,19,0)))
C33: 橡胶 | D33: ru | E33: 1000 | G33: 300 | H33: 50 | J33: =IFERROR(IF(VLOOKUP(D33,期货合约要素!$D:$Q,12,0)=0,"",VLOOKUP(D33,期货合约要素!$D:$Q,12,0)),IF(VLOOKUP(D33,期权合约要素!$D:$V,17,0)=0,"",VLOOKUP(D33,期权合约要素!$D:$V,17,0))) -> √ | K33: =IFERROR(IF(VLOOKUP(D33,期货合约要素!$D:$Q,14,0)=0,"",VLOOKUP(D33,期货合约要素!$D:$Q,14,0)),IF(VLOOKUP(D33,期权合约要素!$D:$V,19,0)=0,"",VLOOKUP(D33,期权合约要素!$D:$V,19,0)))
C34: 胶版印刷纸 | D34: op | E34: 市场单边持仓量≥2.5万手， 限仓比例10% | G34: 500 | H34: 100 | J34: =IFERROR(IF(VLOOKUP(D34,期货合约要素!$D:$Q,12,0)=0,"",VLOOKUP(D34,期货合约要素!$D:$Q,12,0)),IF(VLOOKUP(D34,期权合约要素!$D:$V,17,0)=0,"",VLOOKUP(D34,期权合约要素!$D:$V,17,0))) | K34: =IFERROR(IF(VLOOKUP(D34,期货合约要素!$D:$Q,14,0)=0,"",VLOOKUP(D34,期货合约要素!$D:$Q,14,0)),IF(VLOOKUP(D34,期权合约要素!$D:$V,19,0)=0,"",VLOOKUP(D34,期权合约要素!$D:$V,19,0))) | M34: （1）三级投资者 （2）开户满10个交易日 （3）成交量达到1000张 （4）在我司托管的自有资产余额超过300万 | N34: 5000 | O34: 10000 | P34: 10000
C35: 胶版印刷纸 | D35: op | E35: 市场单边持仓量＜2.5万手，限仓2500 | G35: 150 | H35: 50 | J35: =IFERROR(IF(VLOOKUP(D35,期货合约要素!$D:$Q,12,0)=0,"",VLOOKUP(D35,期货合约要素!$D:$Q,12,0)),IF(VLOOKUP(D35,期权合约要素!$D:$V,17,0)=0,"",VLOOKUP(D35,期权合约要素!$D:$V,17,0))) | K35: =IFERROR(IF(VLOOKUP(D35,期货合约要素!$D:$Q,14,0)=0,"",VLOOKUP(D35,期货合约要素!$D:$Q,14,0)),IF(VLOOKUP(D35,期权合约要素!$D:$V,19,0)=0,"",VLOOKUP(D35,期权合约要素!$D:$V,19,0)))
C36: 品种名称 | D36: 品种代码 | E36: 合约挂牌至交割月前第三月的最后一个交易日 | G36: 交割月前第二月 | H36: 交割月前第一月 | I36: 备注 | J36: QFII&RQFII | K36: 国际化品种
C37: 保税380燃料油 | D37: fu | E37: 7500 | G37: 1500 | H37: 500 | J37: =IFERROR(IF(VLOOKUP(D37,期货合约要素!$D:$Q,12,0)=0,"",VLOOKUP(D37,期货合约要素!$D:$Q,12,0)),IF(VLOOKUP(D37,期权合约要素!$D:$V,17,0)=0,"",VLOOKUP(D37,期权合约要素!$D:$V,17,0))) -> √ | K37: =IFERROR(IF(VLOOKUP(D37,期货合约要素!$D:$Q,14,0)=0,"",VLOOKUP(D37,期货合约要素!$D:$Q,14,0)),IF(VLOOKUP(D37,期权合约要素!$D:$V,19,0)=0,"",VLOOKUP(D37,期权合约要素!$D:$V,19,0)))
C38: 品种名称 | D38: 品种代码 | E38: 标的期货合约挂牌至交割月前第二月的最后一个交易日 | G38: 标的期货合约交割月前第一个月 | I38: 备注 | J38: QFII&RQFII | K38: 国际化品种
C39: 铜期权 | D39: cu_o | E39: 8000 | G39: 3000 | I39: 期权持仓的计算方式如下： 买单边持仓量=同标的看涨期权的买持仓量+看跌期权的卖持仓量； 卖单边持仓量=同标的看涨期权的卖持仓量+看跌期权的买持仓量。 | J39: =IFERROR(IF(VLOOKUP(D39,期货合约要素!$D:$Q,12,0)=0,"",VLOOKUP(D39,期货合约要素!$D:$Q,12,0)),IF(VLOOKUP(D39,期权合约要素!$D:$V,17,0)=0,"",VLOOKUP(D39,期权合约要素!$D:$V,17,0))) -> √ | K39: =IFERROR(IF(VLOOKUP(D39,期货合约要素!$D:$Q,14,0)=0,"",VLOOKUP(D39,期货合约要素!$D:$Q,14,0)),IF(VLOOKUP(D39,期权合约要素!$D:$V,19,0)=0,"",VLOOKUP(D39,期权合约要素!$D:$V,19,0))) | M39: 股票期权限购表
C40: 橡胶期权 | D40: ru_o | E40: 1000 | G40: 300 | J40: =IFERROR(IF(VLOOKUP(D40,期货合约要素!$D:$Q,12,0)=0,"",VLOOKUP(D40,期货合约要素!$D:$Q,12,0)),IF(VLOOKUP(D40,期权合约要素!$D:$V,17,0)=0,"",VLOOKUP(D40,期权合约要素!$D:$V,17,0))) -> √ | K40: =IFERROR(IF(VLOOKUP(D40,期货合约要素!$D:$Q,14,0)=0,"",VLOOKUP(D40,期货合约要素!$D:$Q,14,0)),IF(VLOOKUP(D40,期权合约要素!$D:$V,19,0)=0,"",VLOOKUP(D40,期权合约要素!$D:$V,19,0))) | M40: 投资者满足的条件 | N40: 买入金额限额 (按万取整，仅限个人投资者，以下两者的最大值) | P40: 备注
C41: 黄金期权 | D41: au_o | E41: 9000 | G41: 2700 | J41: =IFERROR(IF(VLOOKUP(D41,期货合约要素!$D:$Q,12,0)=0,"",VLOOKUP(D41,期货合约要素!$D:$Q,12,0)),IF(VLOOKUP(D41,期权合约要素!$D:$V,17,0)=0,"",VLOOKUP(D41,期权合约要素!$D:$V,17,0))) -> √ | K41: =IFERROR(IF(VLOOKUP(D41,期货合约要素!$D:$Q,14,0)=0,"",VLOOKUP(D41,期货合约要素!$D:$Q,14,0)),IF(VLOOKUP(D41,期权合约要素!$D:$V,19,0)=0,"",VLOOKUP(D41,期权合约要素!$D:$V,19,0)))
C42: 铝期权 | D42: al_o | E42: 10000 | G42: 3000 | J42: =IFERROR(IF(VLOOKUP(D42,期货合约要素!$D:$Q,12,0)=0,"",VLOOKUP(D42,期货合约要素!$D:$Q,12,0)),IF(VLOOKUP(D42,期权合约要素!$D:$V,17,0)=0,"",VLOOKUP(D42,期权合约要素!$D:$V,17,0))) -> √ | K42: =IFERROR(IF(VLOOKUP(D42,期货合约要素!$D:$Q,14,0)=0,"",VLOOKUP(D42,期货合约要素!$D:$Q,14,0)),IF(VLOOKUP(D42,期权合约要素!$D:$V,19,0)=0,"",VLOOKUP(D42,期权合约要素!$D:$V,19,0))) | M42: 新开立合约账户 | N42: （1）投资者在我司托管的自有资产余额的10%； （2）前6个月日均持有证券市值的20%。 | P42: 1、自有资产余额，指投资者托管在我司的证券市值与资金账户可用余额（不含通过融资融券交易融入的证券和资金）。其中，证券市值包括期权合约市值，计算方法为：期权合约市值=∑期权合约实时成交价或最新结算价×合约单位×合约张数。当投资者持有权利仓时，期权合约市值计为正值；当投资者持有义务仓时，期权合约市值计为负值。
C43: 锌期权 | D43: zn_o | E43: 6000 | G43: 2400 | J43: =IFERROR(IF(VLOOKUP(D43,期货合约要素!$D:$Q,12,0)=0,"",VLOOKUP(D43,期货合约要素!$D:$Q,12,0)),IF(VLOOKUP(D43,期权合约要素!$D:$V,17,0)=0,"",VLOOKUP(D43,期权合约要素!$D:$V,17,0))) -> √ | K43: =IFERROR(IF(VLOOKUP(D43,期货合约要素!$D:$Q,14,0)=0,"",VLOOKUP(D43,期货合约要素!$D:$Q,14,0)),IF(VLOOKUP(D43,期权合约要素!$D:$V,19,0)=0,"",VLOOKUP(D43,期权合约要素!$D:$V,19,0)))
C44: 螺纹钢期权 | D44: rb_o | E44: 90000 | G44: 4500 | J44: =IFERROR(IF(VLOOKUP(D44,期货合约要素!$D:$Q,12,0)=0,"",VLOOKUP(D44,期货合约要素!$D:$Q,12,0)),IF(VLOOKUP(D44,期权合约要素!$D:$V,17,0)=0,"",VLOOKUP(D44,期权合约要素!$D:$V,17,0))) -> √ | K44: =IFERROR(IF(VLOOKUP(D44,期货合约要素!$D:$Q,14,0)=0,"",VLOOKUP(D44,期货合约要素!$D:$Q,14,0)),IF(VLOOKUP(D44,期权合约要素!$D:$V,19,0)=0,"",VLOOKUP(D44,期权合约要素!$D:$V,19,0)))
C45: 白银期权 | D45: ag_o | E45: 9000 | G45: 2700 | J45: =IFERROR(IF(VLOOKUP(D45,期货合约要素!$D:$Q,12,0)=0,"",VLOOKUP(D45,期货合约要素!$D:$Q,12,0)),IF(VLOOKUP(D45,期权合约要素!$D:$V,17,0)=0,"",VLOOKUP(D45,期权合约要素!$D:$V,17,0))) -> √ | K45: =IFERROR(IF(VLOOKUP(D45,期货合约要素!$D:$Q,14,0)=0,"",VLOOKUP(D45,期货合约要素!$D:$Q,14,0)),IF(VLOOKUP(D45,期权合约要素!$D:$V,19,0)=0,"",VLOOKUP(D45,期权合约要素!$D:$V,19,0))) | M45: 三级投资者 | N45: （1）投资者在我司托管的自有资产余额的20%； （2）前6个月日均持有证券市值的20%。
C46: 丁二烯橡胶期权 | D46: br_o | E46: 1000 | G46: 300 | J46: =IFERROR(IF(VLOOKUP(D46,期货合约要素!$D:$Q,12,0)=0,"",VLOOKUP(D46,期货合约要素!$D:$Q,12,0)),IF(VLOOKUP(D46,期权合约要素!$D:$V,17,0)=0,"",VLOOKUP(D46,期权合约要素!$D:$V,17,0))) | K46: =IFERROR(IF(VLOOKUP(D46,期货合约要素!$D:$Q,14,0)=0,"",VLOOKUP(D46,期货合约要素!$D:$Q,14,0)),IF(VLOOKUP(D46,期权合约要素!$D:$V,19,0)=0,"",VLOOKUP(D46,期权合约要素!$D:$V,19,0)))
C47: 铅期权 | D47: pb_o | E47: 5000 | G47: 1800 | J47: =IFERROR(IF(VLOOKUP(D47,期货合约要素!$D:$Q,12,0)=0,"",VLOOKUP(D47,期货合约要素!$D:$Q,12,0)),IF(VLOOKUP(D47,期权合约要素!$D:$V,17,0)=0,"",VLOOKUP(D47,期权合约要素!$D:$V,17,0))) -> √ | K47: =IFERROR(IF(VLOOKUP(D47,期货合约要素!$D:$Q,14,0)=0,"",VLOOKUP(D47,期货合约要素!$D:$Q,14,0)),IF(VLOOKUP(D47,期权合约要素!$D:$V,19,0)=0,"",VLOOKUP(D47,期权合约要素!$D:$V,19,0))) | M47: 权利仓持仓限额已达到2000张 | N47: （1）投资者在我司托管的自有资产余额的30%； （2）前6个月日均持有证券市值的20%。
C48: 镍期权 | D48: ni_o | E48: 6000 | G48: 1800 | J48: =IFERROR(IF(VLOOKUP(D48,期货合约要素!$D:$Q,12,0)=0,"",VLOOKUP(D48,期货合约要素!$D:$Q,12,0)),IF(VLOOKUP(D48,期权合约要素!$D:$V,17,0)=0,"",VLOOKUP(D48,期权合约要素!$D:$V,17,0))) -> √ | K48: =IFERROR(IF(VLOOKUP(D48,期货合约要素!$D:$Q,14,0)=0,"",VLOOKUP(D48,期货合约要素!$D:$Q,14,0)),IF(VLOOKUP(D48,期权合约要素!$D:$V,19,0)=0,"",VLOOKUP(D48,期权合约要素!$D:$V,19,0))) -> √
C49: 锡期权 | D49: sn_o | E49: 1500 | G49: 600 | J49: =IFERROR(IF(VLOOKUP(D49,期货合约要素!$D:$Q,12,0)=0,"",VLOOKUP(D49,期货合约要素!$D:$Q,12,0)),IF(VLOOKUP(D49,期权合约要素!$D:$V,17,0)=0,"",VLOOKUP(D49,期权合约要素!$D:$V,17,0))) -> √ | K49: =IFERROR(IF(VLOOKUP(D49,期货合约要素!$D:$Q,14,0)=0,"",VLOOKUP(D49,期货合约要素!$D:$Q,14,0)),IF(VLOOKUP(D49,期权合约要素!$D:$V,19,0)=0,"",VLOOKUP(D49,期权合约要素!$D:$V,19,0)))
C50: 氧化铝期权 | D50: ao_o | E50: 8000 | G50: 900 | J50: =IFERROR(IF(VLOOKUP(D50,期货合约要素!$D:$Q,12,0)=0,"",VLOOKUP(D50,期货合约要素!$D:$Q,12,0)),IF(VLOOKUP(D50,期权合约要素!$D:$V,17,0)=0,"",VLOOKUP(D50,期权合约要素!$D:$V,17,0))) | K50: =IFERROR(IF(VLOOKUP(D50,期货合约要素!$D:$Q,14,0)=0,"",VLOOKUP(D50,期货合约要素!$D:$Q,14,0)),IF(VLOOKUP(D50,期权合约要素!$D:$V,19,0)=0,"",VLOOKUP(D50,期权合约要素!$D:$V,19,0)))
C51: 铸造铝合金期权 | D51: ad_o | E51: 900 | G51: 300 | J51: =IFERROR(IF(VLOOKUP(D51,期货合约要素!$D:$Q,12,0)=0,"",VLOOKUP(D51,期货合约要素!$D:$Q,12,0)),IF(VLOOKUP(D51,期权合约要素!$D:$V,17,0)=0,"",VLOOKUP(D51,期权合约要素!$D:$V,17,0))) | K51: =IFERROR(IF(VLOOKUP(D51,期货合约要素!$D:$Q,14,0)=0,"",VLOOKUP(D51,期货合约要素!$D:$Q,14,0)),IF(VLOOKUP(D51,期权合约要素!$D:$V,19,0)=0,"",VLOOKUP(D51,期权合约要素!$D:$V,19,0)))
C52: 石油沥青期权 | D52: bu_o | E52: 8000 | G52: 1500 | J52: =IFERROR(IF(VLOOKUP(D52,期货合约要素!$D:$Q,12,0)=0,"",VLOOKUP(D52,期货合约要素!$D:$Q,12,0)),IF(VLOOKUP(D52,期权合约要素!$D:$V,17,0)=0,"",VLOOKUP(D52,期权合约要素!$D:$V,17,0))) -> √ | K52: =IFERROR(IF(VLOOKUP(D52,期货合约要素!$D:$Q,14,0)=0,"",VLOOKUP(D52,期货合约要素!$D:$Q,14,0)),IF(VLOOKUP(D52,期权合约要素!$D:$V,19,0)=0,"",VLOOKUP(D52,期权合约要素!$D:$V,19,0)))
C53: 纸浆期权 | D53: sp_o | E53: 4500 | G53: 900 | J53: =IFERROR(IF(VLOOKUP(D53,期货合约要素!$D:$Q,12,0)=0,"",VLOOKUP(D53,期货合约要素!$D:$Q,12,0)),IF(VLOOKUP(D53,期权合约要素!$D:$V,17,0)=0,"",VLOOKUP(D53,期权合约要素!$D:$V,17,0))) -> √ | K53: =IFERROR(IF(VLOOKUP(D53,期货合约要素!$D:$Q,14,0)=0,"",VLOOKUP(D53,期货合约要素!$D:$Q,14,0)),IF(VLOOKUP(D53,期权合约要素!$D:$V,19,0)=0,"",VLOOKUP(D53,期权合约要素!$D:$V,19,0)))
C54: 胶版印刷纸期权 | D54: op_o | E54: 2500 | G54: 500 | J54: =IFERROR(IF(VLOOKUP(D54,期货合约要素!$D:$Q,12,0)=0,"",VLOOKUP(D54,期货合约要素!$D:$Q,12,0)),IF(VLOOKUP(D54,期权合约要素!$D:$V,17,0)=0,"",VLOOKUP(D54,期权合约要素!$D:$V,17,0))) | K54: =IFERROR(IF(VLOOKUP(D54,期货合约要素!$D:$Q,14,0)=0,"",VLOOKUP(D54,期货合约要素!$D:$Q,14,0)),IF(VLOOKUP(D54,期权合约要素!$D:$V,19,0)=0,"",VLOOKUP(D54,期权合约要素!$D:$V,19,0)))
C55: 品种名称 | D55: 品种代码 | E55: 合约挂牌至交割月前第三月的最后一个交易日 | G55: 交割月前第二月 | H55: 交割月前第一月 | J55: QFII&RQFII | K55: 国际化品种
C56: 燃料油期权 | D56: fu_o | E56: 7500 | G56: 1500 | H56: 500 | J56: =IFERROR(IF(VLOOKUP(D56,期货合约要素!$D:$Q,12,0)=0,"",VLOOKUP(D56,期货合约要素!$D:$Q,12,0)),IF(VLOOKUP(D56,期权合约要素!$D:$V,17,0)=0,"",VLOOKUP(D56,期权合约要素!$D:$V,17,0))) -> √ | K56: =IFERROR(IF(VLOOKUP(D56,期货合约要素!$D:$Q,14,0)=0,"",VLOOKUP(D56,期货合约要素!$D:$Q,14,0)),IF(VLOOKUP(D56,期权合约要素!$D:$V,19,0)=0,"",VLOOKUP(D56,期权合约要素!$D:$V,19,0)))
B57: 能源中心 | C57: 品种名称 | D57: 品种代码 | E57: 合约挂牌至交割月前第三月的最后一个交易日 | G57: 交割月份前第二月 | H57: 交割月份前第一月 | I57: 备注 | J57: QFII&RQFII | K57: 国际化品种
C58: 原油 | D58: sc | E58: 3000 | G58: 1500 | H58: 500 | J58: =IFERROR(IF(VLOOKUP(D58,期货合约要素!$D:$Q,12,0)=0,"",VLOOKUP(D58,期货合约要素!$D:$Q,12,0)),IF(VLOOKUP(D58,期权合约要素!$D:$V,17,0)=0,"",VLOOKUP(D58,期权合约要素!$D:$V,17,0))) -> √ | K58: =IFERROR(IF(VLOOKUP(D58,期货合约要素!$D:$Q,14,0)=0,"",VLOOKUP(D58,期货合约要素!$D:$Q,14,0)),IF(VLOOKUP(D58,期权合约要素!$D:$V,19,0)=0,"",VLOOKUP(D58,期权合约要素!$D:$V,19,0))) -> √
C59: 低硫燃料油 | D59: lu | E59: 市场单边持仓量≥10万手， 限仓比例10% | G59: 1500 | H59: 500 | J59: =IFERROR(IF(VLOOKUP(D59,期货合约要素!$D:$Q,12,0)=0,"",VLOOKUP(D59,期货合约要素!$D:$Q,12,0)),IF(VLOOKUP(D59,期权合约要素!$D:$V,17,0)=0,"",VLOOKUP(D59,期权合约要素!$D:$V,17,0))) -> √ | K59: =IFERROR(IF(VLOOKUP(D59,期货合约要素!$D:$Q,14,0)=0,"",VLOOKUP(D59,期货合约要素!$D:$Q,14,0)),IF(VLOOKUP(D59,期权合约要素!$D:$V,19,0)=0,"",VLOOKUP(D59,期权合约要素!$D:$V,19,0))) -> √
E60: 市场单边持仓量＜10万手， 限仓10000
C61: 品种名称 | D61: 品种代码 | E61: 合约挂牌至交割月前第二月的最后一个交易日 | G61: 交割月份前第一月 | H61: 交割月份 | I61: 备注 | J61: QFII&RQFII | K61: 国际化品种
C62: 20号胶 | D62: nr | E62: 2000 | G62: 600 | H62: 200 | I62: 需调整为10手整数倍进入交割月 | J62: =IFERROR(IF(VLOOKUP(D62,期货合约要素!$D:$Q,12,0)=0,"",VLOOKUP(D62,期货合约要素!$D:$Q,12,0)),IF(VLOOKUP(D62,期权合约要素!$D:$V,17,0)=0,"",VLOOKUP(D62,期权合约要素!$D:$V,17,0))) -> √ | K62: =IFERROR(IF(VLOOKUP(D62,期货合约要素!$D:$Q,14,0)=0,"",VLOOKUP(D62,期货合约要素!$D:$Q,14,0)),IF(VLOOKUP(D62,期权合约要素!$D:$V,19,0)=0,"",VLOOKUP(D62,期权合约要素!$D:$V,19,0))) -> √
C63: 国际铜 | D63: bc | E63: 市场单边持仓量≥7万手， 限仓比例10% | G63: 3500 | H63: 700 | I63: 需调整为5手整数倍进入交割月 | J63: =IFERROR(IF(VLOOKUP(D63,期货合约要素!$D:$Q,12,0)=0,"",VLOOKUP(D63,期货合约要素!$D:$Q,12,0)),IF(VLOOKUP(D63,期权合约要素!$D:$V,17,0)=0,"",VLOOKUP(D63,期权合约要素!$D:$V,17,0))) -> √ | K63: =IFERROR(IF(VLOOKUP(D63,期货合约要素!$D:$Q,14,0)=0,"",VLOOKUP(D63,期货合约要素!$D:$Q,14,0)),IF(VLOOKUP(D63,期权合约要素!$D:$V,19,0)=0,"",VLOOKUP(D63,期权合约要素!$D:$V,19,0))) -> √
E64: 市场单边持仓量＜7万手， 限仓7000
C65: 品种名称 | D65: 品种代码 | E65: 合约挂盘至最后交易日前第八个交易日 | G65: 最后交易日前第七个交易日至最后交易日前第三个交易日 | H65: 最后交易日前第二个交易日至最后交易日 | I65: 备注 | J65: QFII&RQFII | K65: 国际化品种
C66: 集运指数（欧线） | D66: ec | E66: 1200 | G66: 360 | H66: 120 | J66: =IFERROR(IF(VLOOKUP(D66,期货合约要素!$D:$Q,12,0)=0,"",VLOOKUP(D66,期货合约要素!$D:$Q,12,0)),IF(VLOOKUP(D66,期权合约要素!$D:$V,17,0)=0,"",VLOOKUP(D66,期权合约要素!$D:$V,17,0))) -> √ | K66: =IFERROR(IF(VLOOKUP(D66,期货合约要素!$D:$Q,14,0)=0,"",VLOOKUP(D66,期货合约要素!$D:$Q,14,0)),IF(VLOOKUP(D66,期权合约要素!$D:$V,19,0)=0,"",VLOOKUP(D66,期权合约要素!$D:$V,19,0))) -> √
C67: 品种名称 | D67: 品种代码 | E67: 合约挂牌至交割月前第三月的最后一个交易日 | G67: 交割月份前第二月 | H67: 交割月份前第一月 | I67: 备注 | J67: QFII&RQFII | K67: 国际化品种
C68: 原油期权 | D68: sc_o | E68: 3000 | G68: 1500 | H68: 500 | I68: 期权持仓的计算方式如下： 买单边持仓量=同标的看涨期权的买持仓量+看跌期权的卖持仓量； 卖单边持仓量=同标的看涨期权的卖持仓量+看跌期权的买持仓量。 | J68: =IFERROR(IF(VLOOKUP(D68,期货合约要素!$D:$Q,12,0)=0,"",VLOOKUP(D68,期货合约要素!$D:$Q,12,0)),IF(VLOOKUP(D68,期权合约要素!$D:$V,17,0)=0,"",VLOOKUP(D68,期权合约要素!$D:$V,17,0))) -> √ | K68: =IFERROR(IF(VLOOKUP(D68,期货合约要素!$D:$Q,14,0)=0,"",VLOOKUP(D68,期货合约要素!$D:$Q,14,0)),IF(VLOOKUP(D68,期权合约要素!$D:$V,19,0)=0,"",VLOOKUP(D68,期权合约要素!$D:$V,19,0))) -> √
C69: 品种名称 | D69: 品种代码 | E69: 标的期货合约挂牌至交割月前第二月的最后一个交易日 | H69: 标的期货合约交割月前第一个月 | J69: QFII&RQFII | K69: 国际化品种
C70: 20号胶期权 | D70: nr_o | E70: 2000 | H70: 600 | J70: =IFERROR(IF(VLOOKUP(D70,期货合约要素!$D:$Q,12,0)=0,"",VLOOKUP(D70,期货合约要素!$D:$Q,12,0)),IF(VLOOKUP(D70,期权合约要素!$D:$V,17,0)=0,"",VLOOKUP(D70,期权合约要素!$D:$V,17,0))) -> √ | K70: =IFERROR(IF(VLOOKUP(D70,期货合约要素!$D:$Q,14,0)=0,"",VLOOKUP(D70,期货合约要素!$D:$Q,14,0)),IF(VLOOKUP(D70,期权合约要素!$D:$V,19,0)=0,"",VLOOKUP(D70,期权合约要素!$D:$V,19,0))) -> √
C71: 国际铜期权 | D71: bc_o | E71: 7000 | H71: 3500 | J71: =IFERROR(IF(VLOOKUP(D71,期货合约要素!$D:$Q,12,0)=0,"",VLOOKUP(D71,期货合约要素!$D:$Q,12,0)),IF(VLOOKUP(D71,期权合约要素!$D:$V,17,0)=0,"",VLOOKUP(D71,期权合约要素!$D:$V,17,0))) -> √ | K71: =IFERROR(IF(VLOOKUP(D71,期货合约要素!$D:$Q,14,0)=0,"",VLOOKUP(D71,期货合约要素!$D:$Q,14,0)),IF(VLOOKUP(D71,期权合约要素!$D:$V,19,0)=0,"",VLOOKUP(D71,期权合约要素!$D:$V,19,0))) -> √
B72: 大商所 | C72: 品种名称 | D72: 品种代码 | E72: 合约上市至交割月份前一个月第十四个交易日 （持仓量为单边计算） | G72: 交割月前一个月第十五个交易日起 | H72: 交割月份 （法人） | I72: 备注 | J72: QFII&RQFII | K72: 国际化品种
C73: 豆一 | D73: a | E73: 市场单边持仓量≤5万 | F73: 2500 | G73: 2000 | H73: 1000 | J73: =IFERROR(IF(VLOOKUP(D73,期货合约要素!$D:$Q,12,0)=0,"",VLOOKUP(D73,期货合约要素!$D:$Q,12,0)),IF(VLOOKUP(D73,期权合约要素!$D:$V,17,0)=0,"",VLOOKUP(D73,期权合约要素!$D:$V,17,0))) -> √ | K73: =IFERROR(IF(VLOOKUP(D73,期货合约要素!$D:$Q,14,0)=0,"",VLOOKUP(D73,期货合约要素!$D:$Q,14,0)),IF(VLOOKUP(D73,期权合约要素!$D:$V,19,0)=0,"",VLOOKUP(D73,期权合约要素!$D:$V,19,0))) -> √
E74: 市场单边持仓量＞5万 | F74: 市场单边持仓量×5% | J74: =IFERROR(IF(VLOOKUP(D74,期货合约要素!$D:$Q,12,0)=0,"",VLOOKUP(D74,期货合约要素!$D:$Q,12,0)),IF(VLOOKUP(D74,期权合约要素!$D:$V,17,0)=0,"",VLOOKUP(D74,期权合约要素!$D:$V,17,0))) -> #N/A | K74: =IFERROR(IF(VLOOKUP(D74,期货合约要素!$D:$Q,14,0)=0,"",VLOOKUP(D74,期货合约要素!$D:$Q,14,0)),IF(VLOOKUP(D74,期权合约要素!$D:$V,19,0)=0,"",VLOOKUP(D74,期权合约要素!$D:$V,19,0))) -> #N/A
C75: 豆二 | D75: b | E75: 市场单边持仓量≤10万 | F75: 5000 | G75: 3000 | H75: 1000 | J75: =IFERROR(IF(VLOOKUP(D75,期货合约要素!$D:$Q,12,0)=0,"",VLOOKUP(D75,期货合约要素!$D:$Q,12,0)),IF(VLOOKUP(D75,期权合约要素!$D:$V,17,0)=0,"",VLOOKUP(D75,期权合约要素!$D:$V,17,0))) -> √ | K75: =IFERROR(IF(VLOOKUP(D75,期货合约要素!$D:$Q,14,0)=0,"",VLOOKUP(D75,期货合约要素!$D:$Q,14,0)),IF(VLOOKUP(D75,期权合约要素!$D:$V,19,0)=0,"",VLOOKUP(D75,期权合约要素!$D:$V,19,0))) -> √
E76: 市场单边持仓量＞10万 | F76: 市场单边持仓量×5% | J76: =IFERROR(IF(VLOOKUP(D76,期货合约要素!$D:$Q,12,0)=0,"",VLOOKUP(D76,期货合约要素!$D:$Q,12,0)),IF(VLOOKUP(D76,期权合约要素!$D:$V,17,0)=0,"",VLOOKUP(D76,期权合约要素!$D:$V,17,0))) -> #N/A | K76: =IFERROR(IF(VLOOKUP(D76,期货合约要素!$D:$Q,14,0)=0,"",VLOOKUP(D76,期货合约要素!$D:$Q,14,0)),IF(VLOOKUP(D76,期权合约要素!$D:$V,19,0)=0,"",VLOOKUP(D76,期权合约要素!$D:$V,19,0))) -> #N/A
C77: 豆粕 | D77: m | E77: 市场单边持仓量≤40万 | F77: 2万 | G77: 7500 | H77: 2500 | J77: =IFERROR(IF(VLOOKUP(D77,期货合约要素!$D:$Q,12,0)=0,"",VLOOKUP(D77,期货合约要素!$D:$Q,12,0)),IF(VLOOKUP(D77,期权合约要素!$D:$V,17,0)=0,"",VLOOKUP(D77,期权合约要素!$D:$V,17,0))) -> √ | K77: =IFERROR(IF(VLOOKUP(D77,期货合约要素!$D:$Q,14,0)=0,"",VLOOKUP(D77,期货合约要素!$D:$Q,14,0)),IF(VLOOKUP(D77,期权合约要素!$D:$V,19,0)=0,"",VLOOKUP(D77,期权合约要素!$D:$V,19,0))) -> √
E78: 市场单边持仓量＞40万 | F78: 市场单边持仓量×5% | J78: =IFERROR(IF(VLOOKUP(D78,期货合约要素!$D:$Q,12,0)=0,"",VLOOKUP(D78,期货合约要素!$D:$Q,12,0)),IF(VLOOKUP(D78,期权合约要素!$D:$V,17,0)=0,"",VLOOKUP(D78,期权合约要素!$D:$V,17,0))) -> #N/A | K78: =IFERROR(IF(VLOOKUP(D78,期货合约要素!$D:$Q,14,0)=0,"",VLOOKUP(D78,期货合约要素!$D:$Q,14,0)),IF(VLOOKUP(D78,期权合约要素!$D:$V,19,0)=0,"",VLOOKUP(D78,期权合约要素!$D:$V,19,0))) -> #N/A
C79: 玉米 | D79: c | E79: 市场单边持仓量≤40万 | F79: 2万 | G79: 15000 | H79: 5000 | J79: =IFERROR(IF(VLOOKUP(D79,期货合约要素!$D:$Q,12,0)=0,"",VLOOKUP(D79,期货合约要素!$D:$Q,12,0)),IF(VLOOKUP(D79,期权合约要素!$D:$V,17,0)=0,"",VLOOKUP(D79,期权合约要素!$D:$V,17,0))) | K79: =IFERROR(IF(VLOOKUP(D79,期货合约要素!$D:$Q,14,0)=0,"",VLOOKUP(D79,期货合约要素!$D:$Q,14,0)),IF(VLOOKUP(D79,期权合约要素!$D:$V,19,0)=0,"",VLOOKUP(D79,期权合约要素!$D:$V,19,0)))
E80: 市场单边持仓量＞40万 | F80: 市场单边持仓量×5% | J80: =IFERROR(IF(VLOOKUP(D80,期货合约要素!$D:$Q,12,0)=0,"",VLOOKUP(D80,期货合约要素!$D:$Q,12,0)),IF(VLOOKUP(D80,期权合约要素!$D:$V,17,0)=0,"",VLOOKUP(D80,期权合约要素!$D:$V,17,0))) -> #N/A | K80: =IFERROR(IF(VLOOKUP(D80,期货合约要素!$D:$Q,14,0)=0,"",VLOOKUP(D80,期货合约要素!$D:$Q,14,0)),IF(VLOOKUP(D80,期权合约要素!$D:$V,19,0)=0,"",VLOOKUP(D80,期权合约要素!$D:$V,19,0))) -> #N/A
C81: 玉米淀粉 | D81: cs | E81: 市场单边持仓量≤15万 | F81: 15000 | G81: 4500 | H81: 1500 | J81: =IFERROR(IF(VLOOKUP(D81,期货合约要素!$D:$Q,12,0)=0,"",VLOOKUP(D81,期货合约要素!$D:$Q,12,0)),IF(VLOOKUP(D81,期权合约要素!$D:$V,17,0)=0,"",VLOOKUP(D81,期权合约要素!$D:$V,17,0))) | K81: =IFERROR(IF(VLOOKUP(D81,期货合约要素!$D:$Q,14,0)=0,"",VLOOKUP(D81,期货合约要素!$D:$Q,14,0)),IF(VLOOKUP(D81,期权合约要素!$D:$V,19,0)=0,"",VLOOKUP(D81,期权合约要素!$D:$V,19,0)))
E82: 市场单边持仓量＞15万 | F82: 市场单边持仓量×10% | J82: =IFERROR(IF(VLOOKUP(D82,期货合约要素!$D:$Q,12,0)=0,"",VLOOKUP(D82,期货合约要素!$D:$Q,12,0)),IF(VLOOKUP(D82,期权合约要素!$D:$V,17,0)=0,"",VLOOKUP(D82,期权合约要素!$D:$V,17,0))) -> #N/A | K82: =IFERROR(IF(VLOOKUP(D82,期货合约要素!$D:$Q,14,0)=0,"",VLOOKUP(D82,期货合约要素!$D:$Q,14,0)),IF(VLOOKUP(D82,期权合约要素!$D:$V,19,0)=0,"",VLOOKUP(D82,期权合约要素!$D:$V,19,0))) -> #N/A
C83: 豆油 | D83: y | E83: 市场单边持仓量≤20万 | F83: 1万 | G83: 3000 | H83: 1000 | J83: =IFERROR(IF(VLOOKUP(D83,期货合约要素!$D:$Q,12,0)=0,"",VLOOKUP(D83,期货合约要素!$D:$Q,12,0)),IF(VLOOKUP(D83,期权合约要素!$D:$V,17,0)=0,"",VLOOKUP(D83,期权合约要素!$D:$V,17,0))) -> √ | K83: =IFERROR(IF(VLOOKUP(D83,期货合约要素!$D:$Q,14,0)=0,"",VLOOKUP(D83,期货合约要素!$D:$Q,14,0)),IF(VLOOKUP(D83,期权合约要素!$D:$V,19,0)=0,"",VLOOKUP(D83,期权合约要素!$D:$V,19,0))) -> √
E84: 市场单边持仓量＞20万 | F84: 市场单边持仓量×5% | J84: =IFERROR(IF(VLOOKUP(D84,期货合约要素!$D:$Q,12,0)=0,"",VLOOKUP(D84,期货合约要素!$D:$Q,12,0)),IF(VLOOKUP(D84,期权合约要素!$D:$V,17,0)=0,"",VLOOKUP(D84,期权合约要素!$D:$V,17,0))) -> #N/A | K84: =IFERROR(IF(VLOOKUP(D84,期货合约要素!$D:$Q,14,0)=0,"",VLOOKUP(D84,期货合约要素!$D:$Q,14,0)),IF(VLOOKUP(D84,期权合约要素!$D:$V,19,0)=0,"",VLOOKUP(D84,期权合约要素!$D:$V,19,0))) -> #N/A
C85: 棕榈油 | D85: p | E85: 市场单边持仓量≤10万 | F85: 5000 | G85: 1500 | H85: 500 | J85: =IFERROR(IF(VLOOKUP(D85,期货合约要素!$D:$Q,12,0)=0,"",VLOOKUP(D85,期货合约要素!$D:$Q,12,0)),IF(VLOOKUP(D85,期权合约要素!$D:$V,17,0)=0,"",VLOOKUP(D85,期权合约要素!$D:$V,17,0))) -> √ | K85: =IFERROR(IF(VLOOKUP(D85,期货合约要素!$D:$Q,14,0)=0,"",VLOOKUP(D85,期货合约要素!$D:$Q,14,0)),IF(VLOOKUP(D85,期权合约要素!$D:$V,19,0)=0,"",VLOOKUP(D85,期权合约要素!$D:$V,19,0))) -> √
E86: 市场单边持仓量＞10万 | F86: 市场单边持仓量×5% | J86: =IFERROR(IF(VLOOKUP(D86,期货合约要素!$D:$Q,12,0)=0,"",VLOOKUP(D86,期货合约要素!$D:$Q,12,0)),IF(VLOOKUP(D86,期权合约要素!$D:$V,17,0)=0,"",VLOOKUP(D86,期权合约要素!$D:$V,17,0))) -> #N/A | K86: =IFERROR(IF(VLOOKUP(D86,期货合约要素!$D:$Q,14,0)=0,"",VLOOKUP(D86,期货合约要素!$D:$Q,14,0)),IF(VLOOKUP(D86,期权合约要素!$D:$V,19,0)=0,"",VLOOKUP(D86,期权合约要素!$D:$V,19,0))) -> #N/A
C87: 线型低密度聚乙烯 | D87: l | E87: 市场单边持仓量≤20万 | F87: 1.6万 | G87: 4000 | H87: 2500 | J87: =IFERROR(IF(VLOOKUP(D87,期货合约要素!$D:$Q,12,0)=0,"",VLOOKUP(D87,期货合约要素!$D:$Q,12,0)),IF(VLOOKUP(D87,期权合约要素!$D:$V,17,0)=0,"",VLOOKUP(D87,期权合约要素!$D:$V,17,0))) -> √ | K87: =IFERROR(IF(VLOOKUP(D87,期货合约要素!$D:$Q,14,0)=0,"",VLOOKUP(D87,期货合约要素!$D:$Q,14,0)),IF(VLOOKUP(D87,期权合约要素!$D:$V,19,0)=0,"",VLOOKUP(D87,期权合约要素!$D:$V,19,0)))
E88: 市场单边持仓量＞20万 | F88: 市场单边持仓量×8% | J88: =IFERROR(IF(VLOOKUP(D88,期货合约要素!$D:$Q,12,0)=0,"",VLOOKUP(D88,期货合约要素!$D:$Q,12,0)),IF(VLOOKUP(D88,期权合约要素!$D:$V,17,0)=0,"",VLOOKUP(D88,期权合约要素!$D:$V,17,0))) -> #N/A | K88: =IFERROR(IF(VLOOKUP(D88,期货合约要素!$D:$Q,14,0)=0,"",VLOOKUP(D88,期货合约要素!$D:$Q,14,0)),IF(VLOOKUP(D88,期权合约要素!$D:$V,19,0)=0,"",VLOOKUP(D88,期权合约要素!$D:$V,19,0))) -> #N/A
C89: 线型低密度聚乙烯月均价 | D89: l_f | E89: 市场单边持仓量≤20万 | F89: 4000 | G89: 1000 | H89: — — | J89: =IFERROR(IF(VLOOKUP(D89,期货合约要素!$D:$Q,12,0)=0,"",VLOOKUP(D89,期货合约要素!$D:$Q,12,0)),IF(VLOOKUP(D89,期权合约要素!$D:$V,17,0)=0,"",VLOOKUP(D89,期权合约要素!$D:$V,17,0))) -> √ | K89: =IFERROR(IF(VLOOKUP(D89,期货合约要素!$D:$Q,14,0)=0,"",VLOOKUP(D89,期货合约要素!$D:$Q,14,0)),IF(VLOOKUP(D89,期权合约要素!$D:$V,19,0)=0,"",VLOOKUP(D89,期权合约要素!$D:$V,19,0)))
E90: 市场单边持仓量＞20万 | F90: 市场单边持仓量×2%
C91: 聚氯乙烯 | D91: v | E91: 市场单边持仓量≤20万 | F91: 1.6万 | G91: 4000 | H91: 2500 | J91: =IFERROR(IF(VLOOKUP(D91,期货合约要素!$D:$Q,12,0)=0,"",VLOOKUP(D91,期货合约要素!$D:$Q,12,0)),IF(VLOOKUP(D91,期权合约要素!$D:$V,17,0)=0,"",VLOOKUP(D91,期权合约要素!$D:$V,17,0))) -> √ | K91: =IFERROR(IF(VLOOKUP(D91,期货合约要素!$D:$Q,14,0)=0,"",VLOOKUP(D91,期货合约要素!$D:$Q,14,0)),IF(VLOOKUP(D91,期权合约要素!$D:$V,19,0)=0,"",VLOOKUP(D91,期权合约要素!$D:$V,19,0)))
E92: 市场单边持仓量＞20万 | F92: 市场单边持仓量×8% | J92: =IFERROR(IF(VLOOKUP(D92,期货合约要素!$D:$Q,12,0)=0,"",VLOOKUP(D92,期货合约要素!$D:$Q,12,0)),IF(VLOOKUP(D92,期权合约要素!$D:$V,17,0)=0,"",VLOOKUP(D92,期权合约要素!$D:$V,17,0))) -> #N/A | K92: =IFERROR(IF(VLOOKUP(D92,期货合约要素!$D:$Q,14,0)=0,"",VLOOKUP(D92,期货合约要素!$D:$Q,14,0)),IF(VLOOKUP(D92,期权合约要素!$D:$V,19,0)=0,"",VLOOKUP(D92,期权合约要素!$D:$V,19,0))) -> #N/A
C93: 聚氯乙烯月均价 | D93: v_f | E93: 市场单边持仓量≤20万 | F93: 4000 | G93: 1000 | H93: — — | J93: =IFERROR(IF(VLOOKUP(D93,期货合约要素!$D:$Q,12,0)=0,"",VLOOKUP(D93,期货合约要素!$D:$Q,12,0)),IF(VLOOKUP(D93,期权合约要素!$D:$V,17,0)=0,"",VLOOKUP(D93,期权合约要素!$D:$V,17,0))) -> √ | K93: =IFERROR(IF(VLOOKUP(D93,期货合约要素!$D:$Q,14,0)=0,"",VLOOKUP(D93,期货合约要素!$D:$Q,14,0)),IF(VLOOKUP(D93,期权合约要素!$D:$V,19,0)=0,"",VLOOKUP(D93,期权合约要素!$D:$V,19,0)))
E94: 市场单边持仓量＞20万 | F94: 市场单边持仓量×2%
C95: 焦炭 | D95: j | E95: 市场单边持仓量≤5万 | F95: 5000 | G95: 300 | H95: 100 | J95: =IFERROR(IF(VLOOKUP(D95,期货合约要素!$D:$Q,12,0)=0,"",VLOOKUP(D95,期货合约要素!$D:$Q,12,0)),IF(VLOOKUP(D95,期权合约要素!$D:$V,17,0)=0,"",VLOOKUP(D95,期权合约要素!$D:$V,17,0))) | K95: =IFERROR(IF(VLOOKUP(D95,期货合约要素!$D:$Q,14,0)=0,"",VLOOKUP(D95,期货合约要素!$D:$Q,14,0)),IF(VLOOKUP(D95,期权合约要素!$D:$V,19,0)=0,"",VLOOKUP(D95,期权合约要素!$D:$V,19,0)))
E96: 市场单边持仓量＞5万 | F96: 市场单边持仓量×10% | J96: =IFERROR(IF(VLOOKUP(D96,期货合约要素!$D:$Q,12,0)=0,"",VLOOKUP(D96,期货合约要素!$D:$Q,12,0)),IF(VLOOKUP(D96,期权合约要素!$D:$V,17,0)=0,"",VLOOKUP(D96,期权合约要素!$D:$V,17,0))) -> #N/A | K96: =IFERROR(IF(VLOOKUP(D96,期货合约要素!$D:$Q,14,0)=0,"",VLOOKUP(D96,期货合约要素!$D:$Q,14,0)),IF(VLOOKUP(D96,期权合约要素!$D:$V,19,0)=0,"",VLOOKUP(D96,期权合约要素!$D:$V,19,0))) -> #N/A
C97: 焦煤 | D97: jm | E97: 市场单边持仓量≤8万 | F97: 8000 | G97: 500 | H97: 200 | J97: =IFERROR(IF(VLOOKUP(D97,期货合约要素!$D:$Q,12,0)=0,"",VLOOKUP(D97,期货合约要素!$D:$Q,12,0)),IF(VLOOKUP(D97,期权合约要素!$D:$V,17,0)=0,"",VLOOKUP(D97,期权合约要素!$D:$V,17,0))) | K97: =IFERROR(IF(VLOOKUP(D97,期货合约要素!$D:$Q,14,0)=0,"",VLOOKUP(D97,期货合约要素!$D:$Q,14,0)),IF(VLOOKUP(D97,期权合约要素!$D:$V,19,0)=0,"",VLOOKUP(D97,期权合约要素!$D:$V,19,0)))
E98: 市场单边持仓量＞8万 | F98: 市场单边持仓量×10% | J98: =IFERROR(IF(VLOOKUP(D98,期货合约要素!$D:$Q,12,0)=0,"",VLOOKUP(D98,期货合约要素!$D:$Q,12,0)),IF(VLOOKUP(D98,期权合约要素!$D:$V,17,0)=0,"",VLOOKUP(D98,期权合约要素!$D:$V,17,0))) -> #N/A | K98: =IFERROR(IF(VLOOKUP(D98,期货合约要素!$D:$Q,14,0)=0,"",VLOOKUP(D98,期货合约要素!$D:$Q,14,0)),IF(VLOOKUP(D98,期权合约要素!$D:$V,19,0)=0,"",VLOOKUP(D98,期权合约要素!$D:$V,19,0))) -> #N/A
C99: 纤维板 | D99: fb | E99: 市场单边持仓量≤30万 | F99: 30000 | G99: 800 | H99: 200 | J99: =IFERROR(IF(VLOOKUP(D99,期货合约要素!$D:$Q,12,0)=0,"",VLOOKUP(D99,期货合约要素!$D:$Q,12,0)),IF(VLOOKUP(D99,期权合约要素!$D:$V,17,0)=0,"",VLOOKUP(D99,期权合约要素!$D:$V,17,0))) | K99: =IFERROR(IF(VLOOKUP(D99,期货合约要素!$D:$Q,14,0)=0,"",VLOOKUP(D99,期货合约要素!$D:$Q,14,0)),IF(VLOOKUP(D99,期权合约要素!$D:$V,19,0)=0,"",VLOOKUP(D99,期权合约要素!$D:$V,19,0)))
E100: 市场单边持仓量＞30万 | F100: 市场单边持仓量×10% | J100: =IFERROR(IF(VLOOKUP(D100,期货合约要素!$D:$Q,12,0)=0,"",VLOOKUP(D100,期货合约要素!$D:$Q,12,0)),IF(VLOOKUP(D100,期权合约要素!$D:$V,17,0)=0,"",VLOOKUP(D100,期权合约要素!$D:$V,17,0))) -> #N/A | K100: =IFERROR(IF(VLOOKUP(D100,期货合约要素!$D:$Q,14,0)=0,"",VLOOKUP(D100,期货合约要素!$D:$Q,14,0)),IF(VLOOKUP(D100,期权合约要素!$D:$V,19,0)=0,"",VLOOKUP(D100,期权合约要素!$D:$V,19,0))) -> #N/A
...

Sheet 交易限额
A1: 点此返回目录
B2: 实施交易限额的品种汇总表
B3: 交易所 | C3: 品种名称 | D3: 品种代码 | E3: 特殊合约 | F3: 说明 | G3: 单合约 | H3: 单品种 | I3: 时间 | J3: 交易所是否前端控制 | K3: QFII&RQFII | L3: 国际化品种
B4: 中金所 | C4: 沪深300股指期货 | D4: IF | F4: 限制单合约 | G4: 500 | H4: / | I4: 44760 | J4: 是 （实控组没有前端控制） | K4: =IFERROR(IF(VLOOKUP(D4,期货合约要素!$D:$Q,12,0)=0,"",VLOOKUP(D4,期货合约要素!$D:$Q,12,0)),IF(VLOOKUP(D4,期权合约要素!$D:$V,17,0)=0,"",VLOOKUP(D4,期权合约要素!$D:$V,17,0))) -> √ | L4: =IFERROR(IF(VLOOKUP(D4,期货合约要素!$D:$Q,14,0)=0,"",VLOOKUP(D4,期货合约要素!$D:$Q,14,0)),IF(VLOOKUP(D4,期权合约要素!$D:$V,19,0)=0,"",VLOOKUP(D4,期权合约要素!$D:$V,19,0)))
C5: 上证50股指期货 | D5: IH | F5: 限制单合约 | G5: 500 | H5: / | I5: 44760 | K5: =IFERROR(IF(VLOOKUP(D5,期货合约要素!$D:$Q,12,0)=0,"",VLOOKUP(D5,期货合约要素!$D:$Q,12,0)),IF(VLOOKUP(D5,期权合约要素!$D:$V,17,0)=0,"",VLOOKUP(D5,期权合约要素!$D:$V,17,0))) -> √ | L5: =IFERROR(IF(VLOOKUP(D5,期货合约要素!$D:$Q,14,0)=0,"",VLOOKUP(D5,期货合约要素!$D:$Q,14,0)),IF(VLOOKUP(D5,期权合约要素!$D:$V,19,0)=0,"",VLOOKUP(D5,期权合约要素!$D:$V,19,0)))
C6: 中证500股指期货 | D6: IC | F6: 限制单合约 | G6: 500 | H6: / | I6: 44760 | K6: =IFERROR(IF(VLOOKUP(D6,期货合约要素!$D:$Q,12,0)=0,"",VLOOKUP(D6,期货合约要素!$D:$Q,12,0)),IF(VLOOKUP(D6,期权合约要素!$D:$V,17,0)=0,"",VLOOKUP(D6,期权合约要素!$D:$V,17,0))) -> √ | L6: =IFERROR(IF(VLOOKUP(D6,期货合约要素!$D:$Q,14,0)=0,"",VLOOKUP(D6,期货合约要素!$D:$Q,14,0)),IF(VLOOKUP(D6,期权合约要素!$D:$V,19,0)=0,"",VLOOKUP(D6,期权合约要素!$D:$V,19,0)))
C7: 中证1000股指期货 | D7: IM | F7: 限制单合约 | G7: 500 | H7: / | I7: 44760 | K7: =IFERROR(IF(VLOOKUP(D7,期货合约要素!$D:$Q,12,0)=0,"",VLOOKUP(D7,期货合约要素!$D:$Q,12,0)),IF(VLOOKUP(D7,期权合约要素!$D:$V,17,0)=0,"",VLOOKUP(D7,期权合约要素!$D:$V,17,0))) -> √ | L7: =IFERROR(IF(VLOOKUP(D7,期货合约要素!$D:$Q,14,0)=0,"",VLOOKUP(D7,期货合约要素!$D:$Q,14,0)),IF(VLOOKUP(D7,期权合约要素!$D:$V,19,0)=0,"",VLOOKUP(D7,期权合约要素!$D:$V,19,0)))
C8: 沪深300指数期权 | D8: IO | F8: 限制品种、单月份系列、深度虚值合约 | G8: 月份期权合约100 深度虚值合约 30 | H8: 200 | I8: 44909 | K8: =IFERROR(IF(VLOOKUP(D8,期货合约要素!$D:$Q,12,0)=0,"",VLOOKUP(D8,期货合约要素!$D:$Q,12,0)),IF(VLOOKUP(D8,期权合约要素!$D:$V,17,0)=0,"",VLOOKUP(D8,期权合约要素!$D:$V,17,0))) -> √ | L8: =IFERROR(IF(VLOOKUP(D8,期货合约要素!$D:$Q,14,0)=0,"",VLOOKUP(D8,期货合约要素!$D:$Q,14,0)),IF(VLOOKUP(D8,期权合约要素!$D:$V,19,0)=0,"",VLOOKUP(D8,期权合约要素!$D:$V,19,0)))
C9: 中证1000指数期权 | D9: MO | F9: 限制品种、单月份系列、深度虚值合约 | G9: 月份期权合约100 深度虚值合约 30 | H9: 200 | I9: 44909 | K9: =IFERROR(IF(VLOOKUP(D9,期货合约要素!$D:$Q,12,0)=0,"",VLOOKUP(D9,期货合约要素!$D:$Q,12,0)),IF(VLOOKUP(D9,期权合约要素!$D:$V,17,0)=0,"",VLOOKUP(D9,期权合约要素!$D:$V,17,0))) -> √ | L9: =IFERROR(IF(VLOOKUP(D9,期货合约要素!$D:$Q,14,0)=0,"",VLOOKUP(D9,期货合约要素!$D:$Q,14,0)),IF(VLOOKUP(D9,期权合约要素!$D:$V,19,0)=0,"",VLOOKUP(D9,期权合约要素!$D:$V,19,0)))
C10: 上证50指数期权 | D10: HO | F10: 限制品种、单月份系列、深度虚值合约 | G10: 月份期权合约100 深度虚值合约 30 | H10: 200 | I10: 44909 | K10: =IFERROR(IF(VLOOKUP(D10,期货合约要素!$D:$Q,12,0)=0,"",VLOOKUP(D10,期货合约要素!$D:$Q,12,0)),IF(VLOOKUP(D10,期权合约要素!$D:$V,17,0)=0,"",VLOOKUP(D10,期权合约要素!$D:$V,17,0))) -> √ | L10: =IFERROR(IF(VLOOKUP(D10,期货合约要素!$D:$Q,14,0)=0,"",VLOOKUP(D10,期货合约要素!$D:$Q,14,0)),IF(VLOOKUP(D10,期权合约要素!$D:$V,19,0)=0,"",VLOOKUP(D10,期权合约要素!$D:$V,19,0)))
B11: 大商所 | C11: 豆粕 | D11: m | F11: 限制单合约 | G11: 20000 | H11: / | I11: 45252 | J11: 是 | K11: =IFERROR(IF(VLOOKUP(D11,期货合约要素!$D:$Q,12,0)=0,"",VLOOKUP(D11,期货合约要素!$D:$Q,12,0)),IF(VLOOKUP(D11,期权合约要素!$D:$V,17,0)=0,"",VLOOKUP(D11,期权合约要素!$D:$V,17,0))) -> √ | L11: =IFERROR(IF(VLOOKUP(D11,期货合约要素!$D:$Q,14,0)=0,"",VLOOKUP(D11,期货合约要素!$D:$Q,14,0)),IF(VLOOKUP(D11,期权合约要素!$D:$V,19,0)=0,"",VLOOKUP(D11,期权合约要素!$D:$V,19,0))) -> √
C12: 聚氯乙烯 | D12: v | F12: 限制单合约 | G12: 18000 | H12: / | I12: 45252 | K12: =IFERROR(IF(VLOOKUP(D12,期货合约要素!$D:$Q,12,0)=0,"",VLOOKUP(D12,期货合约要素!$D:$Q,12,0)),IF(VLOOKUP(D12,期权合约要素!$D:$V,17,0)=0,"",VLOOKUP(D12,期权合约要素!$D:$V,17,0))) -> √ | L12: =IFERROR(IF(VLOOKUP(D12,期货合约要素!$D:$Q,14,0)=0,"",VLOOKUP(D12,期货合约要素!$D:$Q,14,0)),IF(VLOOKUP(D12,期权合约要素!$D:$V,19,0)=0,"",VLOOKUP(D12,期权合约要素!$D:$V,19,0)))
C13: 聚氯乙烯月均价 | D13: v_f | F13: 限制单合约 | G13: 18000 | H13: / | I13: 45959 | K13: =IFERROR(IF(VLOOKUP(D13,期货合约要素!$D:$Q,12,0)=0,"",VLOOKUP(D13,期货合约要素!$D:$Q,12,0)),IF(VLOOKUP(D13,期权合约要素!$D:$V,17,0)=0,"",VLOOKUP(D13,期权合约要素!$D:$V,17,0))) -> √ | L13: =IFERROR(IF(VLOOKUP(D13,期货合约要素!$D:$Q,14,0)=0,"",VLOOKUP(D13,期货合约要素!$D:$Q,14,0)),IF(VLOOKUP(D13,期权合约要素!$D:$V,19,0)=0,"",VLOOKUP(D13,期权合约要素!$D:$V,19,0)))
C14: 豆油 | D14: y | F14: 限制单合约 | G14: 15000 | H14: / | I14: 45252 | K14: =IFERROR(IF(VLOOKUP(D14,期货合约要素!$D:$Q,12,0)=0,"",VLOOKUP(D14,期货合约要素!$D:$Q,12,0)),IF(VLOOKUP(D14,期权合约要素!$D:$V,17,0)=0,"",VLOOKUP(D14,期权合约要素!$D:$V,17,0))) -> √ | L14: =IFERROR(IF(VLOOKUP(D14,期货合约要素!$D:$Q,14,0)=0,"",VLOOKUP(D14,期货合约要素!$D:$Q,14,0)),IF(VLOOKUP(D14,期权合约要素!$D:$V,19,0)=0,"",VLOOKUP(D14,期权合约要素!$D:$V,19,0))) -> √
C15: 聚丙烯 | D15: pp | F15: 限制单合约 | G15: 10000 | H15: / | I15: 45252 | K15: =IFERROR(IF(VLOOKUP(D15,期货合约要素!$D:$Q,12,0)=0,"",VLOOKUP(D15,期货合约要素!$D:$Q,12,0)),IF(VLOOKUP(D15,期权合约要素!$D:$V,17,0)=0,"",VLOOKUP(D15,期权合约要素!$D:$V,17,0))) -> √ | L15: =IFERROR(IF(VLOOKUP(D15,期货合约要素!$D:$Q,14,0)=0,"",VLOOKUP(D15,期货合约要素!$D:$Q,14,0)),IF(VLOOKUP(D15,期权合约要素!$D:$V,19,0)=0,"",VLOOKUP(D15,期权合约要素!$D:$V,19,0)))
C16: 聚丙烯月均价 | D16: pp_f | F16: 限制单合约 | G16: 10000 | H16: / | I16: 45959 | K16: =IFERROR(IF(VLOOKUP(D16,期货合约要素!$D:$Q,12,0)=0,"",VLOOKUP(D16,期货合约要素!$D:$Q,12,0)),IF(VLOOKUP(D16,期权合约要素!$D:$V,17,0)=0,"",VLOOKUP(D16,期权合约要素!$D:$V,17,0))) -> √ | L16: =IFERROR(IF(VLOOKUP(D16,期货合约要素!$D:$Q,14,0)=0,"",VLOOKUP(D16,期货合约要素!$D:$Q,14,0)),IF(VLOOKUP(D16,期权合约要素!$D:$V,19,0)=0,"",VLOOKUP(D16,期权合约要素!$D:$V,19,0)))
C17: 棕榈油 | D17: p | F17: 限制单合约 | G17: 10000 | H17: / | I17: 45064 | K17: =IFERROR(IF(VLOOKUP(D17,期货合约要素!$D:$Q,12,0)=0,"",VLOOKUP(D17,期货合约要素!$D:$Q,12,0)),IF(VLOOKUP(D17,期权合约要素!$D:$V,17,0)=0,"",VLOOKUP(D17,期权合约要素!$D:$V,17,0))) -> √ | L17: =IFERROR(IF(VLOOKUP(D17,期货合约要素!$D:$Q,14,0)=0,"",VLOOKUP(D17,期货合约要素!$D:$Q,14,0)),IF(VLOOKUP(D17,期权合约要素!$D:$V,19,0)=0,"",VLOOKUP(D17,期权合约要素!$D:$V,19,0))) -> √
C18: 液化石油气 | D18: pg | F18: 限制单合约 | G18: 10000 | H18: / | I18: 45064 | K18: =IFERROR(IF(VLOOKUP(D18,期货合约要素!$D:$Q,12,0)=0,"",VLOOKUP(D18,期货合约要素!$D:$Q,12,0)),IF(VLOOKUP(D18,期权合约要素!$D:$V,17,0)=0,"",VLOOKUP(D18,期权合约要素!$D:$V,17,0))) -> √ | L18: =IFERROR(IF(VLOOKUP(D18,期货合约要素!$D:$Q,14,0)=0,"",VLOOKUP(D18,期货合约要素!$D:$Q,14,0)),IF(VLOOKUP(D18,期权合约要素!$D:$V,19,0)=0,"",VLOOKUP(D18,期权合约要素!$D:$V,19,0)))
C19: 玉米 | D19: c | F19: 限制单合约 | G19: 8000 | H19: / | I19: 45252 | K19: =IFERROR(IF(VLOOKUP(D19,期货合约要素!$D:$Q,12,0)=0,"",VLOOKUP(D19,期货合约要素!$D:$Q,12,0)),IF(VLOOKUP(D19,期权合约要素!$D:$V,17,0)=0,"",VLOOKUP(D19,期权合约要素!$D:$V,17,0))) | L19: =IFERROR(IF(VLOOKUP(D19,期货合约要素!$D:$Q,14,0)=0,"",VLOOKUP(D19,期货合约要素!$D:$Q,14,0)),IF(VLOOKUP(D19,期权合约要素!$D:$V,19,0)=0,"",VLOOKUP(D19,期权合约要素!$D:$V,19,0)))
C20: 聚乙烯 | D20: l | F20: 限制单合约 | G20: 8000 | H20: / | I20: 45252 | K20: =IFERROR(IF(VLOOKUP(D20,期货合约要素!$D:$Q,12,0)=0,"",VLOOKUP(D20,期货合约要素!$D:$Q,12,0)),IF(VLOOKUP(D20,期权合约要素!$D:$V,17,0)=0,"",VLOOKUP(D20,期权合约要素!$D:$V,17,0))) -> √ | L20: =IFERROR(IF(VLOOKUP(D20,期货合约要素!$D:$Q,14,0)=0,"",VLOOKUP(D20,期货合约要素!$D:$Q,14,0)),IF(VLOOKUP(D20,期权合约要素!$D:$V,19,0)=0,"",VLOOKUP(D20,期权合约要素!$D:$V,19,0)))
C21: 聚乙烯月均价 | D21: l_f | F21: 限制单合约 | G21: 8000 | H21: / | I21: 45959 | K21: =IFERROR(IF(VLOOKUP(D21,期货合约要素!$D:$Q,12,0)=0,"",VLOOKUP(D21,期货合约要素!$D:$Q,12,0)),IF(VLOOKUP(D21,期权合约要素!$D:$V,17,0)=0,"",VLOOKUP(D21,期权合约要素!$D:$V,17,0))) -> √ | L21: =IFERROR(IF(VLOOKUP(D21,期货合约要素!$D:$Q,14,0)=0,"",VLOOKUP(D21,期货合约要素!$D:$Q,14,0)),IF(VLOOKUP(D21,期权合约要素!$D:$V,19,0)=0,"",VLOOKUP(D21,期权合约要素!$D:$V,19,0)))
C22: 生猪 | D22: lh | F22: 限制单合约 | G22: 1000 | H22: / | I22: 45188 | K22: =IFERROR(IF(VLOOKUP(D22,期货合约要素!$D:$Q,12,0)=0,"",VLOOKUP(D22,期货合约要素!$D:$Q,12,0)),IF(VLOOKUP(D22,期权合约要素!$D:$V,17,0)=0,"",VLOOKUP(D22,期权合约要素!$D:$V,17,0))) | L22: =IFERROR(IF(VLOOKUP(D22,期货合约要素!$D:$Q,14,0)=0,"",VLOOKUP(D22,期货合约要素!$D:$Q,14,0)),IF(VLOOKUP(D22,期权合约要素!$D:$V,19,0)=0,"",VLOOKUP(D22,期权合约要素!$D:$V,19,0)))
C23: 铁矿石 | D23: i | F23: 限制单合约 | G23: 2000 | H23: / | I23: 44978 | K23: =IFERROR(IF(VLOOKUP(D23,期货合约要素!$D:$Q,12,0)=0,"",VLOOKUP(D23,期货合约要素!$D:$Q,12,0)),IF(VLOOKUP(D23,期权合约要素!$D:$V,17,0)=0,"",VLOOKUP(D23,期权合约要素!$D:$V,17,0))) -> √ | L23: =IFERROR(IF(VLOOKUP(D23,期货合约要素!$D:$Q,14,0)=0,"",VLOOKUP(D23,期货合约要素!$D:$Q,14,0)),IF(VLOOKUP(D23,期权合约要素!$D:$V,19,0)=0,"",VLOOKUP(D23,期权合约要素!$D:$V,19,0))) -> √
... C25: 焦炭 | D25: j | F25: 限制单合约 | G25: 500 | H25: / | I25: 46185 | K25: =IFERROR(IF(VLOOKUP(D25,期货合约要素!$D:$Q,12,0)=0,"",VLOOKUP(D25,期货合约要素!$D:$Q,12,0)),IF(VLOOKUP(D25,期权合约要素!$D:$V,17,0)=0,"",VLOOKUP(D25,期权合约要素!$D:$V,17,0))) | L25: =IFERROR(IF(VLOOKUP(D25,期货合约要素!$D:$Q,14,0)=0,"",VLOOKUP(D25,期货合约要素!$D:$Q,14,0)),IF(VLOOKUP(D25,期权合约要素!$D:$V,19,0)=0,"",VLOOKUP(D25,期权合约要素!$D:$V,19,0)))
C26: 苯乙烯 | D26: eb | F26: / | G26: / | H26: / | I26: / | J26: / | K26: =IFERROR(IF(VLOOKUP(D26,期货合约要素!$D:$Q,12,0)=0,"",VLOOKUP(D26,期货合约要素!$D:$Q,12,0)),IF(VLOOKUP(D26,期权合约要素!$D:$V,17,0)=0,"",VLOOKUP(D26,期权合约要素!$D:$V,17,0))) -> √ | L26: =IFERROR(IF(VLOOKUP(D26,期货合约要素!$D:$Q,14,0)=0,"",VLOOKUP(D26,期货合约要素!$D:$Q,14,0)),IF(VLOOKUP(D26,期权合约要素!$D:$V,19,0)=0,"",VLOOKUP(D26,期权合约要素!$D:$V,19,0)))
C27: 乙二醇 | D27: eg | F27: / | G27: / | H27: / | I27: / | K27: =IFERROR(IF(VLOOKUP(D27,期货合约要素!$D:$Q,12,0)=0,"",VLOOKUP(D27,期货合约要素!$D:$Q,12,0)),IF(VLOOKUP(D27,期权合约要素!$D:$V,17,0)=0,"",VLOOKUP(D27,期权合约要素!$D:$V,17,0))) -> √ | L27: =IFERROR(IF(VLOOKUP(D27,期货合约要素!$D:$Q,14,0)=0,"",VLOOKUP(D27,期货合约要素!$D:$Q,14,0)),IF(VLOOKUP(D27,期权合约要素!$D:$V,19,0)=0,"",VLOOKUP(D27,期权合约要素!$D:$V,19,0)))
C28: 纯苯 | D28: bz | F28: / | G28: / | H28: / | I28: / | K28: =IFERROR(IF(VLOOKUP(D28,期货合约要素!$D:$Q,12,0)=0,"",VLOOKUP(D28,期货合约要素!$D:$Q,12,0)),IF(VLOOKUP(D28,期权合约要素!$D:$V,17,0)=0,"",VLOOKUP(D28,期权合约要素!$D:$V,17,0))) | L28: =IFERROR(IF(VLOOKUP(D28,期货合约要素!$D:$Q,14,0)=0,"",VLOOKUP(D28,期货合约要素!$D:$Q,14,0)),IF(VLOOKUP(D28,期权合约要素!$D:$V,19,0)=0,"",VLOOKUP(D28,期权合约要素!$D:$V,19,0)))
B29: 广期所 | C29: 工业硅 | D29: si | F29: 限制单合约 | G29: 10000 | H29: / | I29: 45744 | J29: 是 | K29: =IFERROR(IF(VLOOKUP(D29,期货合约要素!$D:$Q,12,0)=0,"",VLOOKUP(D29,期货合约要素!$D:$Q,12,0)),IF(VLOOKUP(D29,期权合约要素!$D:$V,17,0)=0,"",VLOOKUP(D29,期权合约要素!$D:$V,17,0))) -> √ | L29: =IFERROR(IF(VLOOKUP(D29,期货合约要素!$D:$Q,14,0)=0,"",VLOOKUP(D29,期货合约要素!$D:$Q,14,0)),IF(VLOOKUP(D29,期权合约要素!$D:$V,19,0)=0,"",VLOOKUP(D29,期权合约要素!$D:$V,19,0)))
C30: 多晶硅 | D30: ps | E30: ps2608-ps2707 | F30: 限制单合约 | G30: 200 | H30: / | I30: 46115 | K30: =IFERROR(IF(VLOOKUP(D30,期货合约要素!$D:$Q,12,0)=0,"",VLOOKUP(D30,期货合约要素!$D:$Q,12,0)),IF(VLOOKUP(D30,期权合约要素!$D:$V,17,0)=0,"",VLOOKUP(D30,期权合约要素!$D:$V,17,0))) -> √ | L30: =IFERROR(IF(VLOOKUP(D30,期货合约要素!$D:$Q,14,0)=0,"",VLOOKUP(D30,期货合约要素!$D:$Q,14,0)),IF(VLOOKUP(D30,期权合约要素!$D:$V,19,0)=0,"",VLOOKUP(D30,期权合约要素!$D:$V,19,0)))
E31: 其他月份合约 | F31: 限制单合约 | G31: 10000 | H31: / | I31: 45859
C32: 碳酸锂 | D32: lc | E32: lc2608-lc2707 | F32: 限制单合约 | G32: 400 | H32: / | I32: 2026/2/9发布 | K32: =IFERROR(IF(VLOOKUP(D32,期货合约要素!$D:$Q,12,0)=0,"",VLOOKUP(D32,期货合约要素!$D:$Q,12,0)),IF(VLOOKUP(D32,期权合约要素!$D:$V,17,0)=0,"",VLOOKUP(D32,期权合约要素!$D:$V,17,0))) -> √ | L32: =IFERROR(IF(VLOOKUP(D32,期货合约要素!$D:$Q,14,0)=0,"",VLOOKUP(D32,期货合约要素!$D:$Q,14,0)),IF(VLOOKUP(D32,期权合约要素!$D:$V,19,0)=0,"",VLOOKUP(D32,期权合约要素!$D:$V,19,0))) -> √
E33: 其他月份合约 | F33: 限制单合约 | G33: 10000 | H33: / | I33: 45258
C34: 铂 | D34: pt | E34: pt2607-pt2702 | F34: 限制单合约 | G34: 300 | H34: / | I34: 2026/2/9发布 | K34: =IFERROR(IF(VLOOKUP(D34,期货合约要素!$D:$Q,12,0)=0,"",VLOOKUP(D34,期货合约要素!$D:$Q,12,0)),IF(VLOOKUP(D34,期权合约要素!$D:$V,17,0)=0,"",VLOOKUP(D34,期权合约要素!$D:$V,17,0))) | L34: =IFERROR(IF(VLOOKUP(D34,期货合约要素!$D:$Q,14,0)=0,"",VLOOKUP(D34,期货合约要素!$D:$Q,14,0)),IF(VLOOKUP(D34,期权合约要素!$D:$V,19,0)=0,"",VLOOKUP(D34,期权合约要素!$D:$V,19,0)))
C35: 钯 | D35: pd | E35: pd2607-pd2702 | F35: 限制单合约 | G35: 300 | H35: / | I35: 2026/2/9发布 | K35: =IFERROR(IF(VLOOKUP(D35,期货合约要素!$D:$Q,12,0)=0,"",VLOOKUP(D35,期货合约要素!$D:$Q,12,0)),IF(VLOOKUP(D35,期权合约要素!$D:$V,17,0)=0,"",VLOOKUP(D35,期权合约要素!$D:$V,17,0))) | L35: =IFERROR(IF(VLOOKUP(D35,期货合约要素!$D:$Q,14,0)=0,"",VLOOKUP(D35,期货合约要素!$D:$Q,14,0)),IF(VLOOKUP(D35,期权合约要素!$D:$V,19,0)=0,"",VLOOKUP(D35,期权合约要素!$D:$V,19,0)))
B36: 郑商所 | C36: PTA | D36: TA | F36: 限制单合约 | G36: 30000 | H36: / | I36: 45257 | J36: 是 （实控组没有前端控制） | K36: =IFERROR(IF(VLOOKUP(D36,期货合约要素!$D:$Q,12,0)=0,"",VLOOKUP(D36,期货合约要素!$D:$Q,12,0)),IF(VLOOKUP(D36,期权合约要素!$D:$V,17,0)=0,"",VLOOKUP(D36,期权合约要素!$D:$V,17,0))) -> √ | L36: =IFERROR(IF(VLOOKUP(D36,期货合约要素!$D:$Q,14,0)=0,"",VLOOKUP(D36,期货合约要素!$D:$Q,14,0)),IF(VLOOKUP(D36,期权合约要素!$D:$V,19,0)=0,"",VLOOKUP(D36,期权合约要素!$D:$V,19,0))) -> √
C37: 甲醇 | D37: MA | F37: 限制单合约 | G37: 25000 | H37: / | I37: 45257 | K37: =IFERROR(IF(VLOOKUP(D37,期货合约要素!$D:$Q,12,0)=0,"",VLOOKUP(D37,期货合约要素!$D:$Q,12,0)),IF(VLOOKUP(D37,期权合约要素!$D:$V,17,0)=0,"",VLOOKUP(D37,期权合约要素!$D:$V,17,0))) -> √ | L37: =IFERROR(IF(VLOOKUP(D37,期货合约要素!$D:$Q,14,0)=0,"",VLOOKUP(D37,期货合约要素!$D:$Q,14,0)),IF(VLOOKUP(D37,期权合约要素!$D:$V,19,0)=0,"",VLOOKUP(D37,期权合约要素!$D:$V,19,0)))
C38: 玻璃 | D38: FG | F38: 限制单合约 | G38: 25000 | H38: / | K38: =IFERROR(IF(VLOOKUP(D38,期货合约要素!$D:$Q,12,0)=0,"",VLOOKUP(D38,期货合约要素!$D:$Q,12,0)),IF(VLOOKUP(D38,期权合约要素!$D:$V,17,0)=0,"",VLOOKUP(D38,期权合约要素!$D:$V,17,0))) -> √ | L38: =IFERROR(IF(VLOOKUP(D38,期货合约要素!$D:$Q,14,0)=0,"",VLOOKUP(D38,期货合约要素!$D:$Q,14,0)),IF(VLOOKUP(D38,期权合约要素!$D:$V,19,0)=0,"",VLOOKUP(D38,期权合约要素!$D:$V,19,0)))
C39: 菜油 | D39: OI | F39: 限制单合约 | G39: 10000 | H39: / | K39: =IFERROR(IF(VLOOKUP(D39,期货合约要素!$D:$Q,12,0)=0,"",VLOOKUP(D39,期货合约要素!$D:$Q,12,0)),IF(VLOOKUP(D39,期权合约要素!$D:$V,17,0)=0,"",VLOOKUP(D39,期权合约要素!$D:$V,17,0))) -> √ | L39: =IFERROR(IF(VLOOKUP(D39,期货合约要素!$D:$Q,14,0)=0,"",VLOOKUP(D39,期货合约要素!$D:$Q,14,0)),IF(VLOOKUP(D39,期权合约要素!$D:$V,19,0)=0,"",VLOOKUP(D39,期权合约要素!$D:$V,19,0))) -> √
C40: 白糖 | D40: SR | F40: 限制单合约 | G40: 10000 | H40: / | K40: =IFERROR(IF(VLOOKUP(D40,期货合约要素!$D:$Q,12,0)=0,"",VLOOKUP(D40,期货合约要素!$D:$Q,12,0)),IF(VLOOKUP(D40,期权合约要素!$D:$V,17,0)=0,"",VLOOKUP(D40,期权合约要素!$D:$V,17,0))) -> √ | L40: =IFERROR(IF(VLOOKUP(D40,期货合约要素!$D:$Q,14,0)=0,"",VLOOKUP(D40,期货合约要素!$D:$Q,14,0)),IF(VLOOKUP(D40,期权合约要素!$D:$V,19,0)=0,"",VLOOKUP(D40,期权合约要素!$D:$V,19,0)))
C41: 棉花 | D41: CF | F41: 限制单合约 | G41: 10000 | H41: / | K41: =IFERROR(IF(VLOOKUP(D41,期货合约要素!$D:$Q,12,0)=0,"",VLOOKUP(D41,期货合约要素!$D:$Q,12,0)),IF(VLOOKUP(D41,期权合约要素!$D:$V,17,0)=0,"",VLOOKUP(D41,期权合约要素!$D:$V,17,0))) | L41: =IFERROR(IF(VLOOKUP(D41,期货合约要素!$D:$Q,14,0)=0,"",VLOOKUP(D41,期货合约要素!$D:$Q,14,0)),IF(VLOOKUP(D41,期权合约要素!$D:$V,19,0)=0,"",VLOOKUP(D41,期权合约要素!$D:$V,19,0)))
C42: 纯碱 | D42: SA | F42: 限制单合约 | G42: 10000 | H42: / | K42: =IFERROR(IF(VLOOKUP(D42,期货合约要素!$D:$Q,12,0)=0,"",VLOOKUP(D42,期货合约要素!$D:$Q,12,0)),IF(VLOOKUP(D42,期权合约要素!$D:$V,17,0)=0,"",VLOOKUP(D42,期权合约要素!$D:$V,17,0))) -> √ | L42: =IFERROR(IF(VLOOKUP(D42,期货合约要素!$D:$Q,14,0)=0,"",VLOOKUP(D42,期货合约要素!$D:$Q,14,0)),IF(VLOOKUP(D42,期权合约要素!$D:$V,19,0)=0,"",VLOOKUP(D42,期权合约要素!$D:$V,19,0)))
C43: 锰硅 | D43: SM | F43: 限制单合约 | G43: 10000 | H43: / | I43: 45422 | K43: =IFERROR(IF(VLOOKUP(D43,期货合约要素!$D:$Q,12,0)=0,"",VLOOKUP(D43,期货合约要素!$D:$Q,12,0)),IF(VLOOKUP(D43,期权合约要素!$D:$V,17,0)=0,"",VLOOKUP(D43,期权合约要素!$D:$V,17,0))) -> √ | L43: =IFERROR(IF(VLOOKUP(D43,期货合约要素!$D:$Q,14,0)=0,"",VLOOKUP(D43,期货合约要素!$D:$Q,14,0)),IF(VLOOKUP(D43,期权合约要素!$D:$V,19,0)=0,"",VLOOKUP(D43,期权合约要素!$D:$V,19,0)))
C44: 菜粕 | D44: RM | F44: 限制单合约 | G44: 15000 | H44: / | I44: 45257 | K44: =IFERROR(IF(VLOOKUP(D44,期货合约要素!$D:$Q,12,0)=0,"",VLOOKUP(D44,期货合约要素!$D:$Q,12,0)),IF(VLOOKUP(D44,期权合约要素!$D:$V,17,0)=0,"",VLOOKUP(D44,期权合约要素!$D:$V,17,0))) -> √ | L44: =IFERROR(IF(VLOOKUP(D44,期货合约要素!$D:$Q,14,0)=0,"",VLOOKUP(D44,期货合约要素!$D:$Q,14,0)),IF(VLOOKUP(D44,期权合约要素!$D:$V,19,0)=0,"",VLOOKUP(D44,期权合约要素!$D:$V,19,0))) -> √
C45: 动力煤 | D45: ZC | F45: 限制单合约 | G45: 20 | H45: / | I45: 每月第6个交易日 | K45: =IFERROR(IF(VLOOKUP(D45,期货合约要素!$D:$Q,12,0)=0,"",VLOOKUP(D45,期货合约要素!$D:$Q,12,0)),IF(VLOOKUP(D45,期权合约要素!$D:$V,17,0)=0,"",VLOOKUP(D45,期权合约要素!$D:$V,17,0))) | L45: =IFERROR(IF(VLOOKUP(D45,期货合约要素!$D:$Q,14,0)=0,"",VLOOKUP(D45,期货合约要素!$D:$Q,14,0)),IF(VLOOKUP(D45,期权合约要素!$D:$V,19,0)=0,"",VLOOKUP(D45,期权合约要素!$D:$V,19,0)))
C46: 强麦 | D46: WH | F46: / | G46: / | H46: / | I46: / | J46: / | K46: =IFERROR(IF(VLOOKUP(D46,期货合约要素!$D:$Q,12,0)=0,"",VLOOKUP(D46,期货合约要素!$D:$Q,12,0)),IF(VLOOKUP(D46,期权合约要素!$D:$V,17,0)=0,"",VLOOKUP(D46,期权合约要素!$D:$V,17,0))) | L46: =IFERROR(IF(VLOOKUP(D46,期货合约要素!$D:$Q,14,0)=0,"",VLOOKUP(D46,期货合约要素!$D:$Q,14,0)),IF(VLOOKUP(D46,期权合约要素!$D:$V,19,0)=0,"",VLOOKUP(D46,期权合约要素!$D:$V,19,0)))
C47: 普麦 | D47: PM | F47: / | G47: / | H47: / | I47: / | K47: =IFERROR(IF(VLOOKUP(D47,期货合约要素!$D:$Q,12,0)=0,"",VLOOKUP(D47,期货合约要素!$D:$Q,12,0)),IF(VLOOKUP(D47,期权合约要素!$D:$V,17,0)=0,"",VLOOKUP(D47,期权合约要素!$D:$V,17,0))) | L47: =IFERROR(IF(VLOOKUP(D47,期货合约要素!$D:$Q,14,0)=0,"",VLOOKUP(D47,期货合约要素!$D:$Q,14,0)),IF(VLOOKUP(D47,期权合约要素!$D:$V,19,0)=0,"",VLOOKUP(D47,期权合约要素!$D:$V,19,0)))
C48: 早籼稻 | D48: RI | F48: / | G48: / | H48: / | I48: / | K48: =IFERROR(IF(VLOOKUP(D48,期货合约要素!$D:$Q,12,0)=0,"",VLOOKUP(D48,期货合约要素!$D:$Q,12,0)),IF(VLOOKUP(D48,期权合约要素!$D:$V,17,0)=0,"",VLOOKUP(D48,期权合约要素!$D:$V,17,0))) | L48: =IFERROR(IF(VLOOKUP(D48,期货合约要素!$D:$Q,14,0)=0,"",VLOOKUP(D48,期货合约要素!$D:$Q,14,0)),IF(VLOOKUP(D48,期权合约要素!$D:$V,19,0)=0,"",VLOOKUP(D48,期权合约要素!$D:$V,19,0)))
C49: 晚籼稻 | D49: LR | F49: / | G49: / | H49: / | I49: / | K49: =IFERROR(IF(VLOOKUP(D49,期货合约要素!$D:$Q,12,0)=0,"",VLOOKUP(D49,期货合约要素!$D:$Q,12,0)),IF(VLOOKUP(D49,期权合约要素!$D:$V,17,0)=0,"",VLOOKUP(D49,期权合约要素!$D:$V,17,0))) | L49: =IFERROR(IF(VLOOKUP(D49,期货合约要素!$D:$Q,14,0)=0,"",VLOOKUP(D49,期货合约要素!$D:$Q,14,0)),IF(VLOOKUP(D49,期权合约要素!$D:$V,19,0)=0,"",VLOOKUP(D49,期权合约要素!$D:$V,19,0)))
C50: 粳稻 | D50: JR | F50: / | G50: / | H50: / | I50: / | K50: =IFERROR(IF(VLOOKUP(D50,期货合约要素!$D:$Q,12,0)=0,"",VLOOKUP(D50,期货合约要素!$D:$Q,12,0)),IF(VLOOKUP(D50,期权合约要素!$D:$V,17,0)=0,"",VLOOKUP(D50,期权合约要素!$D:$V,17,0))) | L50: =IFERROR(IF(VLOOKUP(D50,期货合约要素!$D:$Q,14,0)=0,"",VLOOKUP(D50,期货合约要素!$D:$Q,14,0)),IF(VLOOKUP(D50,期权合约要素!$D:$V,19,0)=0,"",VLOOKUP(D50,期权合约要素!$D:$V,19,0)))
C51: 对二甲苯 | D51: PX | F51: / | G51: / | H51: / | I51: / | K51: =IFERROR(IF(VLOOKUP(D51,期货合约要素!$D:$Q,12,0)=0,"",VLOOKUP(D51,期货合约要素!$D:$Q,12,0)),IF(VLOOKUP(D51,期权合约要素!$D:$V,17,0)=0,"",VLOOKUP(D51,期权合约要素!$D:$V,17,0))) -> √ | L51: =IFERROR(IF(VLOOKUP(D51,期货合约要素!$D:$Q,14,0)=0,"",VLOOKUP(D51,期货合约要素!$D:$Q,14,0)),IF(VLOOKUP(D51,期权合约要素!$D:$V,19,0)=0,"",VLOOKUP(D51,期权合约要素!$D:$V,19,0))) -> √
C52: 短纤 | D52: PF | F52: / | G52: / | H52: / | I52: / | K52: =IFERROR(IF(VLOOKUP(D52,期货合约要素!$D:$Q,12,0)=0,"",VLOOKUP(D52,期货合约要素!$D:$Q,12,0)),IF(VLOOKUP(D52,期权合约要素!$D:$V,17,0)=0,"",VLOOKUP(D52,期权合约要素!$D:$V,17,0))) -> √ | L52: =IFERROR(IF(VLOOKUP(D52,期货合约要素!$D:$Q,14,0)=0,"",VLOOKUP(D52,期货合约要素!$D:$Q,14,0)),IF(VLOOKUP(D52,期权合约要素!$D:$V,19,0)=0,"",VLOOKUP(D52,期权合约要素!$D:$V,19,0))) -> √
C53: 瓶片 | D53: PR | F53: / | G53: / | H53: / | I53: / | K53: =IFERROR(IF(VLOOKUP(D53,期货合约要素!$D:$Q,12,0)=0,"",VLOOKUP(D53,期货合约要素!$D:$Q,12,0)),IF(VLOOKUP(D53,期权合约要素!$D:$V,17,0)=0,"",VLOOKUP(D53,期权合约要素!$D:$V,17,0))) -> √ | L53: =IFERROR(IF(VLOOKUP(D53,期货合约要素!$D:$Q,14,0)=0,"",VLOOKUP(D53,期货合约要素!$D:$Q,14,0)),IF(VLOOKUP(D53,期权合约要素!$D:$V,19,0)=0,"",VLOOKUP(D53,期权合约要素!$D:$V,19,0))) -> √
C54: 丙烯 | D54: PL | E54: / | F54: / | G54: / | H54: / | I54: / | K54: =IFERROR(IF(VLOOKUP(D54,期货合约要素!$D:$Q,12,0)=0,"",VLOOKUP(D54,期货合约要素!$D:$Q,12,0)),IF(VLOOKUP(D54,期权合约要素!$D:$V,17,0)=0,"",VLOOKUP(D54,期权合约要素!$D:$V,17,0))) | L54: =IFERROR(IF(VLOOKUP(D54,期货合约要素!$D:$Q,14,0)=0,"",VLOOKUP(D54,期货合约要素!$D:$Q,14,0)),IF(VLOOKUP(D54,期权合约要素!$D:$V,19,0)=0,"",VLOOKUP(D54,期权合约要素!$D:$V,19,0)))
C55: 苹果 | D55: AP | E55: / | F55: / | G55: / | H55: / | I55: / | K55: =IFERROR(IF(VLOOKUP(D55,期货合约要素!$D:$Q,12,0)=0,"",VLOOKUP(D55,期货合约要素!$D:$Q,12,0)),IF(VLOOKUP(D55,期权合约要素!$D:$V,17,0)=0,"",VLOOKUP(D55,期权合约要素!$D:$V,17,0))) | L55: =IFERROR(IF(VLOOKUP(D55,期货合约要素!$D:$Q,14,0)=0,"",VLOOKUP(D55,期货合约要素!$D:$Q,14,0)),IF(VLOOKUP(D55,期权合约要素!$D:$V,19,0)=0,"",VLOOKUP(D55,期权合约要素!$D:$V,19,0)))
B56: 能源中心 | C56: 原油 | D56: sc | E56: sc2607 | F56: 限制单合约 | G56: 400 | H56: / | I56: 46091 | J56: 是 （实控组没有前端控制） | K56: =IFERROR(IF(VLOOKUP(D56,期货合约要素!$D:$Q,12,0)=0,"",VLOOKUP(D56,期货合约要素!$D:$Q,12,0)),IF(VLOOKUP(D56,期权合约要素!$D:$V,17,0)=0,"",VLOOKUP(D56,期权合约要素!$D:$V,17,0))) -> √ | L56: =IFERROR(IF(VLOOKUP(D56,期货合约要素!$D:$Q,14,0)=0,"",VLOOKUP(D56,期货合约要素!$D:$Q,14,0)),IF(VLOOKUP(D56,期权合约要素!$D:$V,19,0)=0,"",VLOOKUP(D56,期权合约要素!$D:$V,19,0))) -> √
E57: 其他月份合约 | F57: 限制单合约 | G57: 1600 | H57: / | I57: 46198
C58: 集运指数（欧线） | D58: ec | E58: ec2607-2610、 ec2612、ec2703 | F58: 限制单合约 | G58: 50 | H58: / | I58: 46085 | K58: =IFERROR(IF(VLOOKUP(D58,期货合约要素!$D:$Q,12,0)=0,"",VLOOKUP(D58,期货合约要素!$D:$Q,12,0)),IF(VLOOKUP(D58,期权合约要素!$D:$V,17,0)=0,"",VLOOKUP(D58,期权合约要素!$D:$V,17,0))) -> √ | L58: =IFERROR(IF(VLOOKUP(D58,期货合约要素!$D:$Q,14,0)=0,"",VLOOKUP(D58,期货合约要素!$D:$Q,14,0)),IF(VLOOKUP(D58,期权合约要素!$D:$V,19,0)=0,"",VLOOKUP(D58,期权合约要素!$D:$V,19,0))) -> √
E59: 其他月份合约 | F59: 限制单合约 | G59: 200 | H59: / | I59: 45945
C60: 低硫燃料油 | D60: lu | E60: lu2607 | F60: 限制单合约 | G60: 1500 | H60: / | I60: 46091 | K60: =IFERROR(IF(VLOOKUP(D60,期货合约要素!$D:$Q,12,0)=0,"",VLOOKUP(D60,期货合约要素!$D:$Q,12,0)),IF(VLOOKUP(D60,期权合约要素!$D:$V,17,0)=0,"",VLOOKUP(D60,期权合约要素!$D:$V,17,0))) -> √ | L60: =IFERROR(IF(VLOOKUP(D60,期货合约要素!$D:$Q,14,0)=0,"",VLOOKUP(D60,期货合约要素!$D:$Q,14,0)),IF(VLOOKUP(D60,期权合约要素!$D:$V,19,0)=0,"",VLOOKUP(D60,期权合约要素!$D:$V,19,0))) -> √
E61: 其他月份合约 | F61: 限制单合约 | G61: 6000 | H61: / | I61: 46198
B62: 上期所 | C62: 螺纹钢 | D62: rb | F62: 限制单合约 | G62: 32000 | H62: / | I62: 45261 | J62: 是 （实控组没有前端控制） | K62: =IFERROR(IF(VLOOKUP(D62,期货合约要素!$D:$Q,12,0)=0,"",VLOOKUP(D62,期货合约要素!$D:$Q,12,0)),IF(VLOOKUP(D62,期权合约要素!$D:$V,17,0)=0,"",VLOOKUP(D62,期权合约要素!$D:$V,17,0))) -> √ | L62: =IFERROR(IF(VLOOKUP(D62,期货合约要素!$D:$Q,14,0)=0,"",VLOOKUP(D62,期货合约要素!$D:$Q,14,0)),IF(VLOOKUP(D62,期权合约要素!$D:$V,19,0)=0,"",VLOOKUP(D62,期权合约要素!$D:$V,19,0)))
C63: 燃料油 | D63: fu | E63: fu2607 | F63: 限制单合约 | G63: 1500 | H63: / | I63: 46091 | K63: =IFERROR(IF(VLOOKUP(D63,期货合约要素!$D:$Q,12,0)=0,"",VLOOKUP(D63,期货合约要素!$D:$Q,12,0)),IF(VLOOKUP(D63,期权合约要素!$D:$V,17,0)=0,"",VLOOKUP(D63,期权合约要素!$D:$V,17,0))) -> √ | L63: =IFERROR(IF(VLOOKUP(D63,期货合约要素!$D:$Q,14,0)=0,"",VLOOKUP(D63,期货合约要素!$D:$Q,14,0)),IF(VLOOKUP(D63,期权合约要素!$D:$V,19,0)=0,"",VLOOKUP(D63,期权合约要素!$D:$V,19,0)))
E64: 其他月份合约 | F64: 限制单合约 | G64: 6000 | H64: / | I64: 46198
C65: 热轧卷板 | D65: hc | F65: 限制单合约 | G65: 10000 | H65: / | I65: 45261 | K65: =IFERROR(IF(VLOOKUP(D65,期货合约要素!$D:$Q,12,0)=0,"",VLOOKUP(D65,期货合约要素!$D:$Q,12,0)),IF(VLOOKUP(D65,期权合约要素!$D:$V,17,0)=0,"",VLOOKUP(D65,期权合约要素!$D:$V,17,0))) -> √ | L65: =IFERROR(IF(VLOOKUP(D65,期货合约要素!$D:$Q,14,0)=0,"",VLOOKUP(D65,期货合约要素!$D:$Q,14,0)),IF(VLOOKUP(D65,期权合约要素!$D:$V,19,0)=0,"",VLOOKUP(D65,期权合约要素!$D:$V,19,0)))
C66: 纸浆 | D66: sp | F66: 限制单合约 | G66: 8000 | H66: / | K66: =IFERROR(IF(VLOOKUP(D66,期货合约要素!$D:$Q,12,0)=0,"",VLOOKUP(D66,期货合约要素!$D:$Q,12,0)),IF(VLOOKUP(D66,期权合约要素!$D:$V,17,0)=0,"",VLOOKUP(D66,期权合约要素!$D:$V,17,0))) -> √ | L66: =IFERROR(IF(VLOOKUP(D66,期货合约要素!$D:$Q,14,0)=0,"",VLOOKUP(D66,期货合约要素!$D:$Q,14,0)),IF(VLOOKUP(D66,期权合约要素!$D:$V,19,0)=0,"",VLOOKUP(D66,期权合约要素!$D:$V,19,0)))
C67: 天然橡胶 | D67: ru | F67: 限制单合约 | G67: 6000 | H67: / | K67: =IFERROR(IF(VLOOKUP(D67,期货合约要素!$D:$Q,12,0)=0,"",VLOOKUP(D67,期货合约要素!$D:$Q,12,0)),IF(VLOOKUP(D67,期权合约要素!$D:$V,17,0)=0,"",VLOOKUP(D67,期权合约要素!$D:$V,17,0))) -> √ | L67: =IFERROR(IF(VLOOKUP(D67,期货合约要素!$D:$Q,14,0)=0,"",VLOOKUP(D67,期货合约要素!$D:$Q,14,0)),IF(VLOOKUP(D67,期权合约要素!$D:$V,19,0)=0,"",VLOOKUP(D67,期权合约要素!$D:$V,19,0)))
C68: 铝 | D68: al | F68: 限制单合约 | G68: 4000 | H68: / | K68: =IFERROR(IF(VLOOKUP(D68,期货合约要素!$D:$Q,12,0)=0,"",VLOOKUP(D68,期货合约要素!$D:$Q,12,0)),IF(VLOOKUP(D68,期权合约要素!$D:$V,17,0)=0,"",VLOOKUP(D68,期权合约要素!$D:$V,17,0))) -> √ | L68: =IFERROR(IF(VLOOKUP(D68,期货合约要素!$D:$Q,14,0)=0,"",VLOOKUP(D68,期货合约要素!$D:$Q,14,0)),IF(VLOOKUP(D68,期权合约要素!$D:$V,19,0)=0,"",VLOOKUP(D68,期权合约要素!$D:$V,19,0)))
C69: 锌 | D69: zn | F69: 限制单合约 | G69: 3000 | H69: / | K69: =IFERROR(IF(VLOOKUP(D69,期货合约要素!$D:$Q,12,0)=0,"",VLOOKUP(D69,期货合约要素!$D:$Q,12,0)),IF(VLOOKUP(D69,期权合约要素!$D:$V,17,0)=0,"",VLOOKUP(D69,期权合约要素!$D:$V,17,0))) -> √ | L69: =IFERROR(IF(VLOOKUP(D69,期货合约要素!$D:$Q,14,0)=0,"",VLOOKUP(D69,期货合约要素!$D:$Q,14,0)),IF(VLOOKUP(D69,期权合约要素!$D:$V,19,0)=0,"",VLOOKUP(D69,期权合约要素!$D:$V,19,0)))
C70: 白银 | D70: ag | E70: ag2607-2701 | F70: 限制单合约 | G70: 800 | H70: / | I70: 46048 | K70: =IFERROR(IF(VLOOKUP(D70,期货合约要素!$D:$Q,12,0)=0,"",VLOOKUP(D70,期货合约要素!$D:$Q,12,0)),IF(VLOOKUP(D70,期权合约要素!$D:$V,17,0)=0,"",VLOOKUP(D70,期权合约要素!$D:$V,17,0))) -> √ | L70: =IFERROR(IF(VLOOKUP(D70,期货合约要素!$D:$Q,14,0)=0,"",VLOOKUP(D70,期货合约要素!$D:$Q,14,0)),IF(VLOOKUP(D70,期权合约要素!$D:$V,19,0)=0,"",VLOOKUP(D70,期权合约要素!$D:$V,19,0)))
E71: 其他月份合约 | F71: 限制单合约 | G71: 7000 | H71: / | I71: 46031
C72: 黄金 | D72: au | F72: 限制单合约 | G72: 2800 | H72: / | I72: 45394 | K72: =IFERROR(IF(VLOOKUP(D72,期货合约要素!$D:$Q,12,0)=0,"",VLOOKUP(D72,期货合约要素!$D:$Q,12,0)),IF(VLOOKUP(D72,期权合约要素!$D:$V,17,0)=0,"",VLOOKUP(D72,期权合约要素!$D:$V,17,0))) -> √ | L72: =IFERROR(IF(VLOOKUP(D72,期货合约要素!$D:$Q,14,0)=0,"",VLOOKUP(D72,期货合约要素!$D:$Q,14,0)),IF(VLOOKUP(D72,期权合约要素!$D:$V,19,0)=0,"",VLOOKUP(D72,期权合约要素!$D:$V,19,0)))
C73: 铜 | D73: cu | F73: 限制单合约 | G73: 2000 | H73: / | K73: =IFERROR(IF(VLOOKUP(D73,期货合约要素!$D:$Q,12,0)=0,"",VLOOKUP(D73,期货合约要素!$D:$Q,12,0)),IF(VLOOKUP(D73,期权合约要素!$D:$V,17,0)=0,"",VLOOKUP(D73,期权合约要素!$D:$V,17,0))) -> √ | L73: =IFERROR(IF(VLOOKUP(D73,期货合约要素!$D:$Q,14,0)=0,"",VLOOKUP(D73,期货合约要素!$D:$Q,14,0)),IF(VLOOKUP(D73,期权合约要素!$D:$V,19,0)=0,"",VLOOKUP(D73,期权合约要素!$D:$V,19,0)))
C74: 镍 | D74: ni | E74: ni2607-2701 | F74: 限制单合约 | G74: 2500 | H74: / | I74: 46042 | K74: =IFERROR(IF(VLOOKUP(D74,期货合约要素!$D:$Q,12,0)=0,"",VLOOKUP(D74,期货合约要素!$D:$Q,12,0)),IF(VLOOKUP(D74,期权合约要素!$D:$V,17,0)=0,"",VLOOKUP(D74,期权合约要素!$D:$V,17,0))) -> √ | L74: =IFERROR(IF(VLOOKUP(D74,期货合约要素!$D:$Q,14,0)=0,"",VLOOKUP(D74,期货合约要素!$D:$Q,14,0)),IF(VLOOKUP(D74,期权合约要素!$D:$V,19,0)=0,"",VLOOKUP(D74,期权合约要素!$D:$V,19,0))) -> √
C75: 锡 | D75: sn | E75: sn2607-2701 | F75: 限制单合约 | G75: 200 | H75: / | I75: 46048 | K75: =IFERROR(IF(VLOOKUP(D75,期货合约要素!$D:$Q,12,0)=0,"",VLOOKUP(D75,期货合约要素!$D:$Q,12,0)),IF(VLOOKUP(D75,期权合约要素!$D:$V,17,0)=0,"",VLOOKUP(D75,期权合约要素!$D:$V,17,0))) -> √ | L75: =IFERROR(IF(VLOOKUP(D75,期货合约要素!$D:$Q,14,0)=0,"",VLOOKUP(D75,期货合约要素!$D:$Q,14,0)),IF(VLOOKUP(D75,期权合约要素!$D:$V,19,0)=0,"",VLOOKUP(D75,期权合约要素!$D:$V,19,0)))
E76: 其他月份合约 | F76: 限制单合约 | G76: 800 | H76: / | I76: 46038

Sheet 单笔最小开仓手数
A1: 点此返回目录
B2: 单笔最小开仓手数汇总表
B3: 交易所 | C3: 品种名称 | D3: 品种代码 | E3: 具体合约 | F3: 单笔最小开仓量 | G3: QFII&RQFII | H3: 国际化品种
B4: 广期所 | C4: 多晶硅 | D4: ps | E4: ps2608-ps2707 | F4: 5手 | G4: =IFERROR(IF(VLOOKUP(D4,期货合约要素!$D:$Q,12,0)=0,"",VLOOKUP(D4,期货合约要素!$D:$Q,12,0)),IF(VLOOKUP(D4,期权合约要素!$D:$V,17,0)=0,"",VLOOKUP(D4,期权合约要素!$D:$V,17,0))) -> √ | H4: =IFERROR(IF(VLOOKUP(D4,期货合约要素!$D:$Q,14,0)=0,"",VLOOKUP(D4,期货合约要素!$D:$Q,14,0)),IF(VLOOKUP(D4,期权合约要素!$D:$V,19,0)=0,"",VLOOKUP(D4,期权合约要素!$D:$V,19,0)))
C5: 碳酸锂 | D5: lc | E5: lc2608-lc2707 | G5: =IFERROR(IF(VLOOKUP(D5,期货合约要素!$D:$Q,12,0)=0,"",VLOOKUP(D5,期货合约要素!$D:$Q,12,0)),IF(VLOOKUP(D5,期权合约要素!$D:$V,17,0)=0,"",VLOOKUP(D5,期权合约要素!$D:$V,17,0))) -> √ | H5: =IFERROR(IF(VLOOKUP(D5,期货合约要素!$D:$Q,14,0)=0,"",VLOOKUP(D5,期货合约要素!$D:$Q,14,0)),IF(VLOOKUP(D5,期权合约要素!$D:$V,19,0)=0,"",VLOOKUP(D5,期权合约要素!$D:$V,19,0))) -> √
C6: 其他 | D6: / | E6: 各合约 | F6: 1手
B7: 郑商所 | C7: 强麦 | D7: WH | E7: 限制单合约 | F7: 10手 | G7: =IFERROR(IF(VLOOKUP(D7,期货合约要素!$D:$Q,12,0)=0,"",VLOOKUP(D7,期货合约要素!$D:$Q,12,0)),IF(VLOOKUP(D7,期权合约要素!$D:$V,17,0)=0,"",VLOOKUP(D7,期权合约要素!$D:$V,17,0))) | H7: =IFERROR(IF(VLOOKUP(D7,期货合约要素!$D:$Q,14,0)=0,"",VLOOKUP(D7,期货合约要素!$D:$Q,14,0)),IF(VLOOKUP(D7,期权合约要素!$D:$V,19,0)=0,"",VLOOKUP(D7,期权合约要素!$D:$V,19,0)))
C8: 普麦 | D8: PM | E8: 限制单合约 | G8: =IFERROR(IF(VLOOKUP(D8,期货合约要素!$D:$Q,12,0)=0,"",VLOOKUP(D8,期货合约要素!$D:$Q,12,0)),IF(VLOOKUP(D8,期权合约要素!$D:$V,17,0)=0,"",VLOOKUP(D8,期权合约要素!$D:$V,17,0))) | H8: =IFERROR(IF(VLOOKUP(D8,期货合约要素!$D:$Q,14,0)=0,"",VLOOKUP(D8,期货合约要素!$D:$Q,14,0)),IF(VLOOKUP(D8,期权合约要素!$D:$V,19,0)=0,"",VLOOKUP(D8,期权合约要素!$D:$V,19,0)))
C9: 早籼稻 | D9: RI | E9: 限制单合约 | G9: =IFERROR(IF(VLOOKUP(D9,期货合约要素!$D:$Q,12,0)=0,"",VLOOKUP(D9,期货合约要素!$D:$Q,12,0)),IF(VLOOKUP(D9,期权合约要素!$D:$V,17,0)=0,"",VLOOKUP(D9,期权合约要素!$D:$V,17,0))) | H9: =IFERROR(IF(VLOOKUP(D9,期货合约要素!$D:$Q,14,0)=0,"",VLOOKUP(D9,期货合约要素!$D:$Q,14,0)),IF(VLOOKUP(D9,期权合约要素!$D:$V,19,0)=0,"",VLOOKUP(D9,期权合约要素!$D:$V,19,0)))
C10: 晚籼稻 | D10: LR | E10: 限制单合约 | G10: =IFERROR(IF(VLOOKUP(D10,期货合约要素!$D:$Q,12,0)=0,"",VLOOKUP(D10,期货合约要素!$D:$Q,12,0)),IF(VLOOKUP(D10,期权合约要素!$D:$V,17,0)=0,"",VLOOKUP(D10,期权合约要素!$D:$V,17,0))) | H10: =IFERROR(IF(VLOOKUP(D10,期货合约要素!$D:$Q,14,0)=0,"",VLOOKUP(D10,期货合约要素!$D:$Q,14,0)),IF(VLOOKUP(D10,期权合约要素!$D:$V,19,0)=0,"",VLOOKUP(D10,期权合约要素!$D:$V,19,0)))
C11: 粳稻 | D11: JR | E11: 限制单合约 | G11: =IFERROR(IF(VLOOKUP(D11,期货合约要素!$D:$Q,12,0)=0,"",VLOOKUP(D11,期货合约要素!$D:$Q,12,0)),IF(VLOOKUP(D11,期权合约要素!$D:$V,17,0)=0,"",VLOOKUP(D11,期权合约要素!$D:$V,17,0))) | H11: =IFERROR(IF(VLOOKUP(D11,期货合约要素!$D:$Q,14,0)=0,"",VLOOKUP(D11,期货合约要素!$D:$Q,14,0)),IF(VLOOKUP(D11,期权合约要素!$D:$V,19,0)=0,"",VLOOKUP(D11,期权合约要素!$D:$V,19,0)))
C12: 甲醇 | D12: MA | E12: MA607 | F12: 4手 | G12: =IFERROR(IF(VLOOKUP(D12,期货合约要素!$D:$Q,12,0)=0,"",VLOOKUP(D12,期货合约要素!$D:$Q,12,0)),IF(VLOOKUP(D12,期权合约要素!$D:$V,17,0)=0,"",VLOOKUP(D12,期权合约要素!$D:$V,17,0))) -> √ | H12: =IFERROR(IF(VLOOKUP(D12,期货合约要素!$D:$Q,14,0)=0,"",VLOOKUP(D12,期货合约要素!$D:$Q,14,0)),IF(VLOOKUP(D12,期权合约要素!$D:$V,19,0)=0,"",VLOOKUP(D12,期权合约要素!$D:$V,19,0)))
C13: 对二甲苯 | D13: PX | E13: PX607 | F13: 2手 | G13: =IFERROR(IF(VLOOKUP(D13,期货合约要素!$D:$Q,12,0)=0,"",VLOOKUP(D13,期货合约要素!$D:$Q,12,0)),IF(VLOOKUP(D13,期权合约要素!$D:$V,17,0)=0,"",VLOOKUP(D13,期权合约要素!$D:$V,17,0))) -> √ | H13: =IFERROR(IF(VLOOKUP(D13,期货合约要素!$D:$Q,14,0)=0,"",VLOOKUP(D13,期货合约要素!$D:$Q,14,0)),IF(VLOOKUP(D13,期权合约要素!$D:$V,19,0)=0,"",VLOOKUP(D13,期权合约要素!$D:$V,19,0))) -> √
C14: 动力煤 | D14: ZC | E14: 限制单合约 | F14: 4手 | G14: =IFERROR(IF(VLOOKUP(D14,期货合约要素!$D:$Q,12,0)=0,"",VLOOKUP(D14,期货合约要素!$D:$Q,12,0)),IF(VLOOKUP(D14,期权合约要素!$D:$V,17,0)=0,"",VLOOKUP(D14,期权合约要素!$D:$V,17,0))) | H14: =IFERROR(IF(VLOOKUP(D14,期货合约要素!$D:$Q,14,0)=0,"",VLOOKUP(D14,期货合约要素!$D:$Q,14,0)),IF(VLOOKUP(D14,期权合约要素!$D:$V,19,0)=0,"",VLOOKUP(D14,期权合约要素!$D:$V,19,0)))
C15: 其他 | D15: / | E15: 各合约 | F15: 1手
B16: 其他交易所 | C16: 所有品种 | D16: / | E16: 各合约 | F16: 1手
B17: 注：数据整理于各期货交易所，以交易所最新公告为准。 最小开仓手数仅针对开仓，平仓不受此限制。

Sheet 异常交易规则
B1: 点此返回目录
B2: ▷ 注意：以下异常交易行为的认定标准均以“单一合约”为基本对象
B4: 异常交易类型/交易所 | C4: 中金所 | D4: 上期所/上期能源 | E4: 大商所/广期所 | G4: 郑商所
B5: （一）自成交 | C5: ≥5次 | D5: ≥5次 | E5: ≥5次 | G5: ≥5次
B6: 同一笔委托拆成多笔成交形成自成交，自成交次数计算方式： | C6: 正常计算 | D6: 1次 | E6: 1次（大商所） | F6: 正常计算（广期所） | G6: 1次
B7: 集合竞价期间的自成交 | C7: 正常计算 | D7: 1次 | E7: 1次 | F7: 1次 | G7: 1次
B8: （二）频繁报撤单 | C8: 股指期货(IF IC IH IM)≥400次 国债期货(TS TF T TL)≥500次 股指期权(IO MO HO)≥500次 | D8: ≥500次 | E8: ≥500次 | G8: ≥500次
B9: （三）大额报撤单 | C9: 撤单次数≥100次，且单笔撤单量达到或超过交易所规定限价指令每次最大下单数量80% | D9: 撤单次数≥50次，且单笔撤单量≥300手 | E9: 撤单次数≥50次，且单笔撤单量超过合约最大下单手数的80% | G9: 撤单次数≥50次，且单笔撤单量≥800手
B10: 监管措施 （自成交、频繁报撤单、大额报撤单） | C10: 1. 股指期货：发生1次对客户采取限制开仓不少于1个月的自律管理措施 2. 其他期货品种： 第一次，对客户进行教育、引导、劝阻及制止 第二次，交易所将客户列入重点关注名单 第三次，对客户采取限制开仓不少于1个月的自律管理措施
B11: 豁免情形 | C11: 除国债期货：因（1）套期保值交易、（2）市价指令自动形成的自成交、频繁报撤单、大额报撤单行为不构成异常交易行为；（3）因其他限价指令形成的频繁报撤单行为。 国债期货：因（1）套期保值交易、市价指令自动形成的自成交、频繁报撤单、大额报撤单行为；（2）因其他限价指令形成的频繁报撤单行为；（3）套利交易所产生的频繁报撤单和大额报撤单行为, 不构成异常交易行为。 | D11: 因（1）套期保值交易 产生的自成交、频繁报撤单、大额报撤单行为不构成异常交易行为。 | E11: 因（1）套期保值交易（套期保值属性指令）、（2）市价指令、（3）止损（盈）指令、（4）套利指令 形成的自成交、频繁报撤单、大额报撤单行为不构成异常交易行为。 | G11: 因（1）套期保值交易、（2）市价指令、（3）套利指令 产生的自成交、频繁报撤单、大额报撤单行为不构成异常交易行为。
C12: 实施申报费收费的合约上产生的频繁报撤单行为不构成异常交易行为（由附加FOK和FAK属性的限价指令产生的频繁报撤单除外）
C13: 做市交易产生的频繁报撤单行为不构成异常交易行为
B14: （四）停板价位频繁报撤单 | C14: - | G14: ≥100次
B15: 监管措施 （停板价位频繁报撤单） | C15: - | G15: 1.一般情况下：同频繁报撤监管措施； 2.视为停板价位频繁报撤单情节严重的： （即，当某个交易日某一合约出现涨（跌）停板后，客户当日在涨（跌）停板价位买（卖）单撤销定单次数100次以上且撤销定单手数合计10000手以上的） 直接限制开仓，限制开仓时间不少于1个月
B16: （五）日内过度交易 | C16: 根据《中国金融期货交易所风险控制管理办法》相关规定： 1.股指期货（IF/IC/IH/IM)： 单个交易日单个合约的开仓交易量不得超500手 2.股指期权(IO/MO/HO)： 品种日内开仓交易最大数量：200手 单个月份期权合约日内开仓交易最大数量：100手 深度虚值合约日内开仓交易最大数量：30手 PS：中金所有前端风控，可保障单账户不超过开仓限额，实控组无法保障。 | D16: 一、上期所 1.螺纹钢：各月份合约上单个交易日开仓量不得超过32000手 2.燃料油：FU2607合约上单个交易日开仓量不得超过1500手，其他月份合约上单个交易日开仓量不得超过6000手 3.白银：AG2607-AG2701合约上单个交易日开仓量不得超过800手，其他月份合约上单个交易日开仓量不得超过7000手 4.热轧卷板：各月份合约上单个交易日开仓量不得超过10000手 5.纸浆：各月份合约上单个交易日开仓量不得超过8000手 6.天然橡胶：各月份合约上单个交易日开仓量不得超过6000手 7.铝：各月份合约上单个交易日开仓量不得超过4000手 8.锌：各月份合约上单个交易日开仓量不得超过3000手 9.黄金：各月份合约上单个交易日开仓量不得超过2800手 10.铜：各月份合约上单个交易日开仓量不得超过2000手 11.锡：SN2607-SN2701合约上单个交易日开仓量不得超过200手，其他月份合约上单个交易日开仓量不得超过800手 12.镍：NI2607-NI2701合约上单个交易日开仓量不得超过2500手 二、能源中心 1.原油：SC2607合约上单个交易日开仓量不得超过400手，其他月份合约上单个交易日开仓量不得超过1600手 2.集运指数（欧线）期货：EC2606-2610、EC2612、EC2703合约上单个交易日开仓量不得超过50手；其他月份合约上单个交易日开仓量不得超过200手 3.低硫燃料油：LU2607合约上单个交易日开仓量不得超过1500手，其他月份合约上单个交易日开仓量不得超过6000手 PS：上期所和能源中心有前端风控，可保障单账户不超过开仓限额，实控组无法保障。 | E16: 一、大商所 1.豆粕：各月份合约上单日开仓量不得超过20000手 2.聚氯乙烯/聚氯乙烯月均价：各月份合约上单日开仓量不得超过18000手 3.豆油：各月份合约上单日开仓量不得超过15000手 4.棕榈油/液化石油气/聚丙烯/聚丙烯月均价：各月份合约上单日开仓量不得超过10000手 5.玉米/聚乙烯/聚乙烯月均价：各月份合约上单日开仓量不得超过8000手 6.生猪：各月份合约上单日开仓量不得超过1000手 7.铁矿石：单日单合约开仓量不得超过2000手 8.焦煤：各月份合约上单日开仓量不得超过2000手 9.焦炭：各月份合约上单日开仓量不得超过500手 PS：大商所有前端风控，可保障单账户和实控组账户不超过开仓限额。 | G16: 1.PTA：单个交易日单个合约开仓量不得超过30000手 2.甲醇：单个交易日单个合约开仓量不得超过25000手 3.玻璃：单个交易日单个合约开仓量不得超过25000手 4.菜粕：单个交易日单个合约开仓量不得超过15000手 5.菜油/白糖/棉花/纯碱/锰硅：各月份合约上单日开仓交易的最大数量为10000手 6.动力煤（当前上市所有合约）：单个交易日单个合约开仓量不得超过20手 PS：郑商所有前端风控，可保障单账户不超过开仓限额，实控组无法保障。
E17: 二、广期所 1.工业硅期货：单个交易日，各月份合约单个合约开仓量不得超过10000手 2.多晶硅期货：单个交易日，PS2608-PS2707单个合约开仓量不得超过200手；其他月份合约单个合约开仓量不得超过10000手 3.碳酸锂期货：单个交易日，LC2608-LC2707单个合约开仓量不得超过400手；其他月份合约单个合约开仓量不得超过10000手 4.铂/钯期货：单个交易日，PT2607-PT2702、PD2607-PD2702单个合约开仓量不得超过300手 PS：广期所有前端风控，可保障单账户和实控组账户不超过开仓限额。
B18: 监管措施 （日内过度交易） | C18: 第一次，限制开仓5个交易日的措施； 第二次，限制开仓10个交易日的措施； 第三次及以上，限制开仓1个月的措施； 情节严重的，按《中国金融期货交易所风险控制管理办法》《中国金融期货交易所违规违约处理办法》的有关规定处理。 | D18: 第一次，限制开仓不少于5个交易日的措施； 第二次，限制开仓不少于1个月的措施； 第三次及以上，限制开仓不少于2个月的措施； 情节严重的，按《上海期货交易所违规处理办法》的有关规定处理。 | E18: - | G18: 对于超过交易限额的非期货公司会员或者客户，交易所要求客户报告相关情况并采取暂停客户开仓不低于5个交易日的监管措施。累计2个交易日超过交易限额的，交易所将采取暂停客户开仓不低于1个月的监管措施。 情节严重的，按照《郑州商品交易所违规处理办法》有关规定处理。
B19: （六）实际控制关系账户组合并持仓超限 | C19: 交易所对已认定的实际控制关系账户组视作同一客户，实际控制关系账户组中的客户持仓合并计算，合并计算后的持仓不得超过交易所规定的持仓限额。 | D19: -
B20: 监管措施 （实控账户组合并持仓超限） | C20: 第一次：交易所将该组实际控制关系账户列入重点关注名单。第二次：交易所对该组实际控制关系账户采取限制开仓不少于10个交易日的自律管理措施。第三次：交易所对该组实际控制关系账户采取限制开仓不少于6个月的自律管理措施。 客户应当在交易所规定的时限内自行平仓。逾期未处理完毕的，由交易所执行强行平仓，并对客户采取限制开仓不少于1个月的自律管理措施。 | D20: - | E20: - | G20: -
B21: 限制开仓方式 | C21: 各类异常交易行为次数分开统计； 限制开仓品种 | D21: 各类异常交易行为次数分开统计； 所有品种违规次数合并计算，对第三次违规合约的品种进行限制开仓 | E21: 各类异常交易行为次数分开统计； 所有品种违规次数合并计算，对第三次违规的合约进行限制开仓 | G21: 各类异常交易行为次数分开统计； 所有品种违规次数合并计算，日内过度交易类异常交易对违规品种进行限制开仓，其余类型的异常交易行为对违规的合约进行限制开仓
B23: 《…异常交易管理办法》部分内容 | C23: …单个交易日在单品种多个合约上因自成交、频繁报撤单、大额报撤单达到交易所处理标准的，按照一次认定。 | D23: …单个交易日在两个及以上期货合约或者两个及以上期权合约因自成交、频繁报撤单、大额报撤单达到交易所异常交易行为处理标准的，同一种异常交易行为按照发生一次异常交易行为认定。 | E23: …单个交易日在多个期货合约或者多个期权合约上自成交、频繁报撤单或大额报撤单行为达到交易所处理标准的，分别认定为出现一次自成交、频繁报撤单、大额报撤单行为达到交易所处理标准。 | G23: …单个交易日在两个以上合约因自成交、频繁报撤单、大额报撤单或者实际控制关系账户合并持仓超限达到异常交易行为处理标准的，同一种异常交易行为按照发生一次认定。

Sheet 保证金优惠规则
A1: 点此返回目录
B2: 各交易所保证金优惠规则
B3: 交易所 | C3: 保证金优惠政策 | D3: 优惠政策描述 | E3: 组合类型 | F3: 组合规则 | G3: 保证金收取规则 | H3: 盘中优惠方式 | I3: 结算后优惠方式 | J3: 备注
B4: 大商所 广期所 | C4: 组合策略保证金 | D4: 符合优惠规则的双边持仓按照规定比例组成持仓组合，组合中的持仓按照交易所规定的组合保证金收取 | E4: 期货对锁 | F4: 在同一期货品种同一月份合约上建立数量相等、方向相反的头寸 | G4: 期货高腿保证金 | H4: 1、部分组合盘中使用SP（期货跨期、期货不同交割方式套利）、SPC（期货跨品种）套利指令直接建立组合，实时优惠； 2、盘中先建立单腿合约，再通过交易端申请组合可以实时优惠，也可以申请组合解除实时拆散组合，解除优惠。 | I4: 1、结算时交易所根据公布的组合优先级自动进行组合优惠； 2、客户可通过会员申请保留组合资格，交易所审批通过后，结算时将保留客户的盘中组合持仓，且不将剩余单腿持仓进行自动组合。 | J4: 1、大商所组合规则详见交易所官网：首页 > 数据中心 > 业务数据 > 业务参数> 交易参数 ； 2、广期所组合规则详见交易所官网：首页 > 业务/服务 > 业务参数 > 交易参数\结算参数； 3、期权合约仅部分月份支持组合； 4、新合约上市首日盘中不参与组合，结算时参与组合。
E5: 期货跨期 | F5: 在同一期货品种的不同月份合约上建立数量相等、方向相反的头寸
E6: 期货不同交割方式套利 | F6: 在同一品种实物交割期货合约和月均价期货合约上建立数量相等、方向相反的头寸
E7: 期货跨品种 （广期所无） | F7: 在不同期货品种合约上建立数量相等、方向相反的头寸
E8: 卖出期权期货组合 | F8: 卖出看涨期权，同时买入标的期货合约 | G8: 期货保证金+期权权利金
F9: 卖出看跌期权，同时卖出标的期货合约
E10: 期权跨式 | F10: 卖出相同标的期货合约相同执行价格的看涨期权和看跌期权 | G10: max(看涨期权保证金，看跌期权保证金)+另一腿权利金
E11: 期权宽跨式 | F11: 卖出相同标的期货合约低执行价格的看跌期权和高执行价格的看涨期权
E12: 期权对锁 | F12: 在同一期权合约上建立数量相等、方向相反的头寸 | G12: 0.2*卖期权保证金
E13: 买入期权垂直价差 | F13: 买进低执行价格的看涨期权，同时卖出相同标的期货合约的高执行价格的看涨期权 | G13: 0.2*卖期权保证金
F14: 买进高执行价格的看跌期权，同时卖出相同标的期货合约的低执行价格的看跌期权
E15: 卖出期权垂直价差 | F15: 卖出低执行价格的看涨期权，同时买进相同标的期货合约的高执行价格的看涨期权 | G15: min(执行价格之差，卖期权保证金)
F16: 卖出高执行价格的看跌期权，同时买进相同标的期货合约的低执行价格的看跌期权
E17: 买入期权期货组合（广期所无） | F17: 买入看涨期权，同时卖出标的期货合约 | G17: 0.8*期货保证金
F18: 买入看跌期权，同时买入标的期货合约
B19: 郑商所 | C19: 组合策略保证金 | D19: 符合优惠规则的双边持仓按照规定比例组成持仓组合，组合中的持仓按照交易所规定的组合保证金收取 | E19: 期货对锁 | F19: 在同一期货品种同一月份合约上建立数量相等、方向相反的头寸 | G19: 期货高腿保证金 | H19: 1、期货对锁持仓盘中自动实时优惠； 2、部分组合盘中使用SPD（期货跨期）、IPS（期货跨品种）、STD（期权跨式，需附加FOK、FAK使用）、STG（期权宽跨式，需附加FOK、FAK使用）套利指令直接建立组合，实时优惠。 | I19: 1、每个交易日下午指定时间前（期货组合14:30前，期权组合14点前）向期货公司提交组合申请的持仓，结算时优惠； 2、备兑组合结算后自动优惠； 3、未通过套利指令建仓、未申请组合的持仓结算时不自动组合。 | J19: 1、跨品种：硅铁&锰硅、棉花&棉纱、纯碱&玻璃、PTA&短纤、PTA&瓶片、PTA&对二甲苯。
E20: 期货跨期 | F20: 在同一期货品种的不同月份合约上建立数量相等、方向相反的头寸
E21: 期货跨品种 | F21: 在不同期货品种合约上建立数量相等、方向相反的头寸
E22: 备兑组合 | F22: 卖出看涨期权，同时买入对应标的期货合约 | G22: 期货保证金+期权权利金
F23: 卖出看跌期权，同时卖出对应标的期货合约
E24: 期权跨式 | F24: 卖出相同标的期货合约相同执行价格的看涨期权和看跌期权 | G24: max(看涨期权保证金，看跌期权保证金)+另一腿权利金
E25: 期权宽跨式 | F25: 卖出相同标的期货合约低执行价格的看跌期权和高执行价格的看涨期权
B26: 中金所 | C26: 产品组单向大边保证金 （股指期货为权益组、国债期货为利率组） | D26: 符合优惠规则的双边持仓按照保证金较大的一边收取，保证金较少的一边予以优惠 | E26: 期货对锁 | F26: 在同一期货品种同一月份合约上建立数量相等、方向相反的头寸 | G26: 期货高腿保证金 | H26: 盘中实时优惠（产品组内的双边持仓只收取保证金较高的单边，保证金较少的单边免收） 委托时按照持仓和未成交委托综合判断保证金小的一边可开仓手数，如超过此手数则需补足保证金差额部分，可用资金需覆盖手续费。 | I26: 与盘中优惠规则一致 | J26: 1、国债期货合约在交割月前一交易日结算时取消优惠；股指期货无限制； 2、中金所股指期权无保证金优惠。
E27: 期货跨期 | F27: 在同一期货品种的不同月份合约上建立数量相等、方向相反的头寸
E28: 期货跨品种 | F28: 在不同期货品种合约上建立数量相等、方向相反的头寸
B29: 上期所 能源中心 | C29: 产品单向大边保证金 | D29: 符合优惠规则的双边持仓按照保证金较大的一边收取，保证金较少的一边予以优惠 | E29: 期货对锁 | F29: 在同一期货品种同一月份合约上建立数量相等、方向相反的头寸 | G29: 期货高腿保证金 | H29: 盘中实时优惠（品种内的双边持仓只收取保证金较高的单边，保证金较少的单边免收） 委托时按照持仓和未成交委托综合判断保证金小的一边可开仓手数，如超过此手数则需补足保证金差额部分，可用资金需覆盖手续费。 | I29: 与盘中优惠规则一致 | J29: 1、集运指数（欧线）品种无保证金优惠； 2、其余品种合约进入最后交易日前五个交易日闭市后取消优惠； 3、上期所、能源中心期权无保证金优惠。
E30: 期货跨期 | F30: 在同一期货品种的不同月份合约上建立数量相等、方向相反的头寸
B31: 上交所 深交所 | C31: 组合策略保证金 | D31: 符合优惠规则的双边持仓按照规定比例组成持仓组合，组合中的持仓按照交易所规定的组合保证金收取 | E31: 跨式空头 | F31: 由一个认购期权义务仓与一个相同合约标的、相同到期日、相同合约单位、相同行权价格的认沽期权义务仓组成 | G31: max(认购期权保证金，认沽期权保证金)+另一腿权利金 | H31: 盘中单腿开仓，再通过交易端申请组合可以实时享受优惠，也可以申请组合解除实时拆散组合，解除优惠。 | I31: 盘中未申请组合的，结算时交易所不会自动组合。 | J31: 1、到期月份的认购牛市价差策略、认沽熊市价差策略、认购熊市价差策略、认沽牛市价差策略组合于期权到期日前倒数第二个交易日收市后自动解除； 2、期权合约未被组合占用的双边持仓，于每个交易日收市后自动进行对冲了结； 3、除备兑策略外的期权组合，进行单腿平仓时，需要先解除组合，否则不能平仓； 4、通过交易端申请的方式，深交所支持备兑仓与普通认购义务仓互相转化；上交所仅支持普通认购义务仓转为备兑仓，不支持备兑仓转为普通认购义务仓。
E32: 宽跨式空头 | F32: 由一个较高行权价格的认购期权义务仓，与一个相同合约标的、相同到期日、相同合约单位、较低行权价格的认沽期权义务仓组成
E33: 认购牛市价差策略 | F33: 由一个认购期权权利仓与一个相同合约标的、相同到期日、相同合约单位的认购期权义务仓组成，其中义务仓的行权价格高于权利仓的行权价格 | G33: 零
E34: 认沽熊市价差策略 | F34: 由一个认沽期权权利仓与一个相同合约标的、相同到期日、相同合约单位的认沽期权义务仓组成，其中义务仓的行权价格低于权利仓的行权价格
E35: 认购熊市价差策略 | F35: 由一个认购期权权利仓与一个相同合约标的、相同到期日、相同合约单位的认购期权义务仓组成，其中义务仓的行权价格低于权利仓的行权价格 | G35: 行权价之差*合约单位
E36: 认沽牛市价差策略 | F36: 由一个认沽期权权利仓与一个相同合约标的、相同到期日、相同合约单位的认沽期权义务仓组成，其中义务仓的行权价格高于权利仓的行权价格
E37: 备兑策略 | F37: 持有现货ETF，同时卖出标的为该ETF的备兑性质认购期权 | G37: 零 | H37: 备兑开仓不收取保证金，普通仓转备兑仓盘中实时优惠。

Sheet 期权行权规则
A1: 点此返回目录
B2: 各交易所期权行权及自对冲规则对比表
B3: 交易所 | D3: 上期所 | E3: 能源中心 | F3: 广期所 | G3: 大商所 | H3: 郑商所 | I3: 中金所
B4: 自动行权条件 | D4: 1、相较于当日结算价为实值； 2、账户可用资金满足行权要求 | I4: 实值额大于行权手续费
B5: 支持自对冲类型 | D5: 期权自对冲 行权后期货自对冲 履约后期货自对冲 | F5: 期权自对冲，会员服务系统端申请，一次申请，长期有效；交易端申请，当日有效； 行权后期货自对冲，当日有效； 履约后期货自对冲，一次申请，长期有效 | G5: 期权自对冲；行权后期货自对冲；履约后期货自对冲；期货自对冲 | H5: 期权自对冲 行权后期货自对冲 履约后期货自对冲 | I5: 仅做市商可申请期权每日自对冲，其他客户不支持； 到期日所有客户自动对冲，以净头寸行权履约
B6: 自对冲申请有效期 | D6: 当日有效 | G6: 会员服务系统端申请，一次申请，长期有效； 交易端申请，当日有效 | H6: 一次申请，长期有效 | I6: 做市商开通自对冲之后，长期有效
B7: 自对冲申请途径 | D7: 交易端与期货公司会员服务系统均支持提交 | H7: 仅期货公司会员服务系统支持提交 | I7: 做市商日常对冲需通过期货公司会员服务系统申请 所有客户到期日自动对冲无需额外申请
B8: 行权手续费 | D8: 收取行权手续费，免收期货开仓手续费 | I8: 收取行权手续费，不涉及期货建仓
B9: 自对冲手续费 | C9: 期权自对冲 | D9: 收取双边期权自对冲手续费 | F9: 收取双边期权平仓手续费 | I9: 免收
C10: 期货自对冲 | D10: 免收 | F10: 收取双边期货平仓手续费 | I10: 不涉及

Sheet 交易指令
A1: 点此返回目录
B2: 交易指令
B4: 交易所 | C4: 产品类型 | D4: 限价指令 | F4: 市价指令 | H4: 套利 | J4: 互换 | L4: 止损（盈）指令
D5: 是否支持 | E5: 备注 | F5: 是否支持 | G5: 备注 | H5: 是否支持 | I5: 描述 | J5: 是否支持 | K5: 描述 | L5: 是否支持 | M5: 描述
B6: 上期所、 能源中心 | C6: 期货 | D6: 支持 | E6: 可附加FOK、FAK | F6: 支持 | G6: 须输入保护价；指按当时市场上可执行的最优价格（报价）成交的指令；不参与集合竞价；未成交的市价指令自动撤销或转换为限价指令；可附加FAK、FOK | H6: 不支持 | J6: 不支持 | L6: 不支持
C7: 期权
B8: 大商所 | C8: 期货 | D8: 支持 | E8: 可附加FOK、FAK、GIS | F8: 支持 | G8: 任意价，指交易所计算机撮合系统执行指令时以涨（跌）停板价格参与交易的买（卖）指令，可附加FAK、FOK | H8: 支持 | I8: 跨期套利，跨品种套利，具体支持情况由交易所公布 | J8: 支持 | K8: 跨期套利，跨品种套利，具体支持情况由交易所公布 | L8: 支持 | M8: 市价/限价止损（盈）指令：当市场价格触及客户预先设定触发价格时，立即转为市价/限价指令的指令，限价止损（盈）指令可附加GIS
C9: 期权 | F9: 不支持 | H9: 不支持 | J9: 不支持
B10: 广期所 | C10: 期货 | D10: 支持 | E10: 可附加FOK、FAK | F10: 支持 | G10: 任意价，指交易所计算机撮合系统执行指令时以涨（跌）停板价格参与交易的买（卖）指令，可附加FAK、FOK | H10: 支持 | I10: 跨期套利，具体支持情况由交易所公布 | J10: 支持 | K10: 跨期套利，具体支持情况由交易所公布 | L10: 支持 | M10: 市价/限价止损（盈）指令：当市场价格触及客户预先设定触发价格时，立即转为市价/限价指令的指令
C11: 期权 | F11: 不支持 | H11: 不支持 | J11: 不支持
B12: 郑商所 | C12: 期货 | D12: 支持 | E12: 可附加FAK | F12: 支持 | G12: 最优价，按市场最优价格成交，可附加FAK | H12: 支持 | I12: 跨期套利，跨品种套利 | J12: 支持 | K12: 跨期套利，跨品种套利 | L12: 不支持
C13: 期权 | E13: 可附加FOK、FAK | G13: 可附加FOK、FAK | I13: 期权跨式套利，期权宽跨式套利(必须附加FOK或FAK) | J13: 不支持
B14: 中金所 | C14: 期货 | D14: 支持 | E14: 可附加FOK、FAK | F14: 部分合约支持 | G14: 仅适用股指期货的当月、下月合约，国债期货最近的季月合约； 最优价，按市场最优价格成交（需附加五档价，最优价，最优价转限价，五档市价转现价等属性） | H14: 不支持 | J14: 不支持 | L14: 不支持
C15: 期权 | E15: 可附加FOK、FAK | F15: 不支持
B16: 上交所 | C16: 期权 | D16: 支持 | E16: 包括普通限价委托、全额即时限价委托等 | F16: 支持 | G16: 包括市价剩余转限价委托、市价剩余撤销委托、全额即时市价委托等 | H16: 不支持 | J16: 不支持 | L16: 不支持
B17: 深交所 | C17: 期权 | D17: 支持 | E17: 包括普通限价申报、全额成交或撤销限价申报等 | F17: 支持 | G17: 包括对手方最优价格市价申报、本方最优价格市价申报、最优五档即时成交剩余撤销市价申报、即时成交剩余撤销市价申报。全额成交或撤销市价申报等 | H17: 不支持 | J17: 不支持 | L17: 不支持
B18: 备注： （1）限价指令是指按照限定价格或者更优价格成交的指令； （2）大商所、广期所市价指令是指交易所计算机撮合系统执行指令时以涨（跌）停板价格参与交易的买（卖）指令；中金所、郑商所市价指令是指不限定价格、按照当时市场上可执行的报价成交的指令；市价指令只能和限价指令撮合成交； （3）FOK指令是指限价指令中所有数量必须同时成交，否则该指令自动撤销； （4）FAK指令是指限价指令中无法立即成交部分自动撤销。FOK指令是指限价指令中所有数量必须同时成交，否则该指令自动撤销； （5）GIS指令是指该指令只在本交易小节有效，本小节结束后，未成交部分立即撤销的指令属性。

Sheet 申报费规则
B1: 点此返回目录
B2: 期货交易所申报费规则对比表
B3: 交易所 | C3: 具体收取标准（元/笔） | G3: 共同之处 | H3: 备注
B4: 上期所& 能源中心 | C4: 品种 | D4: 信息量 | E4: OTR≤2 | F4: OTR＞2 | G4: 1、境内商品期货交易所对信息量笔数超过4000笔的客户收费； 2、按照合约计算信息量； 3、同一客户在不同期货公司开户的，对其所有信息量合并计算收取； 4、做市商做市交易，免收申报费； 5、对于具有实控关系的客户，交易所对其所有信息量合并计算； 6、自2026年6月1日交易时起，境内期货交易所上市的期货及期权品种均将全部实施梯度申报费规则。 | H4: 1、TAS指令的信息量和标的合约信息量合并计算； 2、有成交的报单笔数为0时，视其为1来计算OTR； 3、期权合约申报费按合约月份统计。
C5: A组【期货】包括白银、不锈钢、黄金、螺纹钢、铝、镍、铅、热轧卷板、燃料油、石油沥青、铜、天然橡胶、锌、锡、纸浆、低硫燃料油、20号胶、原油 | D5: 信息量≤4000笔 | E5: 0 | F5: 0
D6: 4000笔＜信息量≤8000笔 | E6: 1.5 | F6: 3
D7: 8000笔＜信息量≤40000笔 | E7: 7.5 | F7: 15
D8: 信息量＞40000笔 | E8: 25 | F8: 50
C9: B组【期权】包括原油期权、白银期权、黄金期权、螺纹钢期权、铝期权、铜期权、天然橡胶期权、锌期权、丁二烯橡胶期权、铅期权、镍期权、锡期权、氧化铝期权、铸造铝合金期权、石油沥青期权、纸浆期权、燃料油期权、胶版印刷纸期权、20号胶期权、国际铜期权 | D9: 信息量≤4000笔 | E9: 0 | F9: 0
D10: 4000笔＜信息量≤8000笔 | E10: 0.5 | F10: 1
D11: 8000笔＜信息量≤40000笔 | E11: 2.5 | F11: 5
D12: 信息量＞40000笔 | E12: 5 | F12: 10
C13: C组【期货】包括丁二烯橡胶、线材、氧化铝、国际铜、集运指数（欧线）、铸造铝合金、胶版印刷纸 | D13: 信息量≤4000笔 | E13: 0 | F13: 0
D14: 4000笔＜信息量≤8000笔 | E14: 0.1 | F14: 0.2
D15: 8000笔＜信息量≤40000笔 | E15: 0.5 | F15: 1
D16: 信息量＞40000笔 | E16: 2 | F16: 5
B17: 大商所 | C17: 品种 | D17: 信息量 | E17: OTR≤2 | F17: OTR＞2 | H17: 1、有成交的报单笔数为0时，OTR为极大值； 2、期权合约申报费按合约月份统计。
C18: 棕榈油期货、豆粕期货、 鸡蛋期货、苯乙烯期货、乙二醇期货、液化石油气期货、聚丙烯期货、聚丙烯月均价期货、聚氯乙烯期货、聚氯乙烯月均价期货 | D18: 信息量≤4000笔 | E18: 0 | F18: 0
D19: 4000笔＜信息量≤8000笔 | E19: 0 | F19: 3
D20: 信息量＞8000笔 | E20: 6 | F20: 15
C21: 玉米期货、线型低密度聚乙烯期货、线型低密度聚乙烯月均价期货、纯苯期货 | D21: 信息量≤4000笔 | E21: 0 | F21: 0
D22: 4000笔＜信息量≤8000笔 | E22: 0 | F22: 2
D23: 信息量＞8000笔 | E23: 4 | F23: 10
C24: 豆油期货、黄大豆1号期货、黄大豆2号期货、纤维板期货、粳米期货、玉米淀粉期货、原木期货 | D24: 信息量≤4000笔 | E24: 0 | F24: 0
D25: 4000笔＜信息量≤8000笔 | E25: 0 | F25: 1
D26: 信息量＞8000笔 | E26: 2 | F26: 5
C27: 全部期权 | D27: 信息量≤4000笔 | E27: 0 | F27: 0
D28: 4000笔＜信息量≤8000笔 | E28: 0 | F28: 1
D29: 信息量＞8000笔 | E29: 2 | F29: 5
C30: 生猪期货、铁矿石期货、 焦煤期货、焦炭期货、胶合板期货 | D30: 信息量≤4000笔 | E30: 0 | F30: 0
D31: 4000笔＜信息量≤8000笔 | E31: 0 | F31: 0.1
D32: 信息量＞8000笔 | E32: 0.2 | F32: 0.5
B33: 郑商所 | C33: 品种 | D33: 信息量 | E33: OTR≤2 | F33: OTR＞2 | H33: 1、有成交的报单笔数为0时，按OTR大于2来计算； 2、期权合约申报费按合约月份统计。
C34: PTA期货 | D34: 信息量≤4000笔 | E34: 0 | F34: 0
D35: 4000笔＜信息量≤8000笔 | E35: 0 | F35: 2
D36: 8000笔＜信息量≤20000笔 | E36: 5 | F36: 10
D37: 信息量＞20000笔 | E37: 10 | F37: 40
C38: 甲醇期货、白糖期货、菜油期货、菜粕期货、 棉花期货、玻璃期货、纯碱期货、硅铁期货、锰硅期货、红枣期货、苹果期货、对二甲苯期货、烧碱期货、尿素期货 | D38: 信息量≤4000笔 | E38: 0 | F38: 0
D39: 4000笔＜信息量≤8000笔 | E39: 0 | F39: 3
D40: 信息量＞8000笔 | E40: 7.5 | F40: 15
C41: 短纤期货、花生期货、 普通小麦期货、优质强筋小麦期货、早籼稻期货、晚籼稻期货、粳稻期货、动力煤期货、棉纱期货、油菜籽期货、瓶片期货、丙烯期货 | D41: 信息量≤4000笔 | E41: 0 | F41: 0
D42: 4000笔＜信息量≤8000笔 | E42: 0 | F42: 1
D43: 信息量＞8000笔 | E43: 2.5 | F43: 5
C44: 全部期权 | D44: 信息量≤4000笔 | E44: 0 | F44: 0
D45: 4000笔＜信息量≤8000笔 | E45: 0 | F45: 1
D46: 信息量＞8000笔 | E46: 2.5 | F46: 5
